Workbook
Name lst_Canal: Inicio!$E$5:$E$13
Name lst_StatusPago: Inicio!$F$5:$F$9
Name lst_EstadoCliente: Inicio!$G$5:$G$8
Name lst_Frecuencia: Inicio!$K$5:$K$7
Name rng_PDV: Clientes_PDV!$A$2:$A$250
Name rng_SKU: Maestro_SKU!$A$2:$A$500
Name cfg_IVA: Inicio!$B$13
Name cfg_VentaRecienteDias: Inicio!$B$14
Name cfg_VentaBaja: Inicio!$B$15
Name cfg_StockCritico: Inicio!$B$16
Name cfg_StockObservar: Inicio!$B$17
Name cfg_MontoPendiente: Inicio!$B$18
Name cfg_DiasVencer: Inicio!$B$19
Name cfg_AnioResumen: Resumen!$B$3
Name cfg_DiasCobertura: Inicio!$B$29
Name cfg_PctSeguridad: Inicio!$B$30
Name cfg_VentanaDemanda: Inicio!$B$31
Name cfg_VentaAlta: Inicio!$B$34

Sheet Inicio
A1: NUVA OXI | Control comercial simple
A2: GUÍA — cómo funciona, se edita, se alimenta y crece (clic aquí)
A3: Cómo se usa en simple | E3: Listas editables para desplegables
A4: 1 | B4: Dashboard: mirar cada lunes qué está en rojo o prioridad alta. | E4: Canal | F4: Status pago | G4: Estado cliente | H4: Condición pago | I4: Prioridad | J4: Estado stock | K4: Frecuencia
A5: 2 | B5: Cobertura: revisar el detalle por punto de venta, visita, venta, pago y stock. | E5: Retail | F5: Pendiente | G5: Activo | H5: Contado | I5: Alta | J5: Crítico | K5: Semanal
A6: 3 | B6: Clientes_PDV: agregar nuevos clientes o salas. Esa hoja alimenta Cobertura. | E6: Conveniencia | F6: Pagada | G6: Pausado | H6: Crédito 15 días | I6: Media | J6: Observar | K6: Quincenal
A7: 4 | B7: Ventas_SellIn: ingresar facturas reales. No usar PVP; solo precio neto facturado. | E7: Farmacias | F7: Parcial | G7: Prospecto | H7: Crédito 30 días | I7: Baja | J7: OK | K7: Mensual
A8: 5 | B8: Margen_Frontal: simular precio/margen aparte, sin afectar ventas ni cobertura. | E8: Especializadas | F8: Vencida | G8: Inactivo | H8: Crédito 45 días
A9: 6 | B9: SellOut_Jumbo: pegar exportaciones futuras de Cencosud/Jumbo cuando existan. | E9: HORECA | F9: Nota crédito | H9: Crédito 60 días
E10: Tradicional
A11: Condiciones editables | E11: Ecommerce
A12: Condición | B12: Valor editable | C12: Qué significa | E12: Corporativo
A13: IVA | B13: 0.19 | C13: Se usa para pasar neto a bruto y viceversa. | E13: Distribuidor
A14: Venta reciente últimos días | B14: 30 | C14: Período usado en cobertura y dashboard.
A15: Venta baja si es menor a | B15: 50000 | C15: Si venta neta 30d queda bajo este monto, se marca baja. | E15: Leyenda
A16: Stock crítico PDV barras | B16: 8 | C16: Barras equivalentes en sala bajo este nivel = crítico. | E16: Amarillo | F16: Dato editable
A17: Stock en observación PDV barras | B17: 20 | C17: Barras equivalentes en sala bajo este nivel = observar. | E17: Gris | F17: Fórmula; no tocar
A18: Monto pendiente relevante | B18: 100000 | C18: Deuda sobre este monto eleva prioridad. | E18: Morado | F18: Título/encabezado
A19: Factura próxima a vencer días | B19: 7 | C19: Días hacia adelante para marcar próxima a vencer.
A22: Frecuencia de visita
A23: Frecuencia | B23: Días máximos | C23: Regla
A24: Semanal | B24: 7 | C24: Atrasado desde 8 días
A25: Quincenal | B25: 15 | C25: Atrasado desde 16 días
A26: Mensual | B26: 30 | C26: Atrasado desde 31 días
A28: Parámetros de inventario (editable)
A29: Días de cobertura objetivo | B29: 30 | C29: Cuántos días de venta quieres tener en stock
A30: % stock de seguridad | B30: 0.2 | C30: Colchón sobre el objetivo ante quiebres
A31: Ventana de demanda (días) | B31: 30 | C31: Período de sell-in para el promedio (30/60/90)
A33: Reglas de rotación (editable)
A34: Rotación ALTA: venta 30d ≥ | B34: 150000 | C34: Sobre este monto, el PDV rota bien
A35: Rotación BAJA: venta 30d < | B35: =B15 | C35: Usa el mismo umbral de 'Venta baja' (B15)
A36: Rotación MEDIA: | B36: entre ambos | C36: Entre el monto de BAJA y el de ALTA

Sheet Guia_Ana
A1: Guía rápida para Ana | Cómo leer y cargar el archivo
A3: Objetivo del archivo
A4: Ayudar a decidir cada lunes qué puntos de venta visitar, cuáles están vendiendo, cuáles tienen facturas pendientes y dónde falta stock. No busca reemplazar ERP ni contabilidad.
A6: Qué mirar primero
A7: • | B7: 1. Abrir Dashboard y revisar prioridad alta.
A8: • | B8: 2. Ir a Cobertura para ver la razón: visita atrasada, sin venta, deuda o stock crítico.
A9: • | B9: 3. Filtrar por Canal o Cliente si se saldrá a terreno por zona/cuenta.
A11: Dónde cargar información
A12: • | B12: Clientes nuevos o nuevas salas: Clientes_PDV.
A13: • | B13: Facturas/sell-in: Ventas_SellIn. Ingresar fecha, factura, PDV_ID, SKU, cantidad, precio neto facturado y status de pago.
A14: • | B14: Stock observado en terreno: Stock_PDV.
A15: • | B15: Sell-out de Jumbo/Cencosud: SellOut_Jumbo, cuando exista exportación.
A16: • | B16: Simulación de precio y margen: Margen_Frontal.
A18: Regla de colores
A19: • | B19: Amarillo = se puede editar.
A20: • | B20: Gris = fórmula, mejor no tocar.
A21: • | B21: Morado = encabezado o título.
A22: • | B22: Si algo sale raro, revisar primero si falta PDV_ID, SKU o fecha.
A24: Conceptos simples
A25: • | B25: Sell-in: venta facturada al cliente o punto de venta.
A26: • | B26: Sell-out: venta desde la sala hacia consumidor final, cuando el retailer la informe.
A27: • | B27: Margen frontal: margen que el cliente obtiene entre el PVP neto y el precio neto que le facturamos.
A28: • | B28: Barras equivalentes: convierte unidades, estuches y cajas master a barras para comparar stock y venta.
A30: Cómo se edita, se alimenta y crece
A31: 1. | B31: Editar: solo celdas AMARILLAS. Las grises son fórmulas (se calculan solas).
A32: 2. | B32: Alimentar ventas: Ventas_SellIn, una fila por factura (usa los desplegables).
A33: 3. | B33: Terreno: registra visitas y stock de sala en Clientes_PDV y Stock_PDV.
A34: 4. | B34: Producto nuevo: agrégalo en Maestro_SKU; aparece solo en el plan y en las listas.
A35: 5. | B35: Cliente/sala nueva: agrégala en Clientes_PDV; aparece sola en Cobertura.
A36: 6. | B36: Inventario: escribe tu bodega en Plan_Inventario; te dice cuánto reponer.
A37: 7. | B37: Ajustes: cambia umbrales (venta, stock, cobertura, rotación) en Inicio, sin tocar fórmulas.
A38: 8. | B38: Crece hasta: 250 clientes/PDV y 800 facturas. Para más, se estiran los rangos.

Sheet Dashboard
A1: Dashboard semanal | Revisión lunes
A3: Indicador | B3: Valor | D3: Condiciones activas | E3: Valor
A4: Fecha control | B4: =TODAY() | D4: Venta reciente días | E4: =Inicio!B14
A5: PDV activos | B5: =COUNTIF(Clientes_PDV!$I$2:$I$250,"Activo") | D5: Venta baja menor a | E5: =Inicio!B15
A6: PDV prioridad alta | B6: =COUNTIF(Cobertura!$Q$2:$Q$250,"Alta") | D6: Semanal días | E6: =Inicio!B24
A7: Venta sell-in 30d neta | B7: =SUM(Cobertura!$I$2:$I$250) | D7: Quincenal días | E7: =Inicio!B25
A8: Monto pendiente | B8: =SUM(Cobertura!$M$2:$M$250) | D8: Mensual días | E8: =Inicio!B26
A9: PDV stock crítico | B9: =COUNTIF(Cobertura!$P$2:$P$250,"Crítico") | D9: Factura próxima a vencer | E9: =Inicio!B19
A11: ⚙ Ir a Configuración (hoja Inicio)
A12: Lista de gestión sugerida (filtrar en Cobertura si necesitas detalle)
A13: PDV | B13: Cliente | C13: Canal | D13: Estado visita | E13: Estado venta | F13: Estado pago | G13: Estado stock | H13: Prioridad
A14: =Cobertura!D2 | B14: =Cobertura!B2 | C14: =Cobertura!C2 | D14: =Cobertura!H2 | E14: =Cobertura!K2 | F14: =Cobertura!N2 | G14: =Cobertura!P2 | H14: =Cobertura!Q2
A15: =Cobertura!D3 | B15: =Cobertura!B3 | C15: =Cobertura!C3 | D15: =Cobertura!H3 | E15: =Cobertura!K3 | F15: =Cobertura!N3 | G15: =Cobertura!P3 | H15: =Cobertura!Q3
A16: =Cobertura!D4 | B16: =Cobertura!B4 | C16: =Cobertura!C4 | D16: =Cobertura!H4 | E16: =Cobertura!K4 | F16: =Cobertura!N4 | G16: =Cobertura!P4 | H16: =Cobertura!Q4
A17: =Cobertura!D5 | B17: =Cobertura!B5 | C17: =Cobertura!C5 | D17: =Cobertura!H5 | E17: =Cobertura!K5 | F17: =Cobertura!N5 | G17: =Cobertura!P5 | H17: =Cobertura!Q5
A18: =Cobertura!D6 | B18: =Cobertura!B6 | C18: =Cobertura!C6 | D18: =Cobertura!H6 | E18: =Cobertura!K6 | F18: =Cobertura!N6 | G18: =Cobertura!P6 | H18: =Cobertura!Q6
A19: =Cobertura!D7 | B19: =Cobertura!B7 | C19: =Cobertura!C7 | D19: =Cobertura!H7 | E19: =Cobertura!K7 | F19: =Cobertura!N7 | G19: =Cobertura!P7 | H19: =Cobertura!Q7
A20: =Cobertura!D8 | B20: =Cobertura!B8 | C20: =Cobertura!C8 | D20: =Cobertura!H8 | E20: =Cobertura!K8 | F20: =Cobertura!N8 | G20: =Cobertura!P8 | H20: =Cobertura!Q8
A21: =Cobertura!D9 | B21: =Cobertura!B9 | C21: =Cobertura!C9 | D21: =Cobertura!H9 | E21: =Cobertura!K9 | F21: =Cobertura!N9 | G21: =Cobertura!P9 | H21: =Cobertura!Q9
A22: =Cobertura!D10 | B22: =Cobertura!B10 | C22: =Cobertura!C10 | D22: =Cobertura!H10 | E22: =Cobertura!K10 | F22: =Cobertura!N10 | G22: =Cobertura!P10 | H22: =Cobertura!Q10
A23: =Cobertura!D11 | B23: =Cobertura!B11 | C23: =Cobertura!C11 | D23: =Cobertura!H11 | E23: =Cobertura!K11 | F23: =Cobertura!N11 | G23: =Cobertura!P11 | H23: =Cobertura!Q11
A24: =Cobertura!D12 | B24: =Cobertura!B12 | C24: =Cobertura!C12 | D24: =Cobertura!H12 | E24: =Cobertura!K12 | F24: =Cobertura!N12 | G24: =Cobertura!P12 | H24: =Cobertura!Q12
A25: =Cobertura!D13 | B25: =Cobertura!B13 | C25: =Cobertura!C13 | D25: =Cobertura!H13 | E25: =Cobertura!K13 | F25: =Cobertura!N13 | G25: =Cobertura!P13 | H25: =Cobertura!Q13

Sheet Resumen
A1: RESUMEN | Nuva Oxi
A3: Año de análisis: | B3: 2026 | D3: ⚙ Configuración
A5: Seguimiento — terreno vs escritorio | D5: Venta por mes (año en B3)
A6: Indicador | B6: Valor | D6: Periodo | E6: Venta neta | F6: Unidades | G6: Monto pend.
A7: PDV activos | B7: =COUNTIF(Clientes_PDV!$I$2:$I$250,"Activo") | D7: =$B$3&"-"&TEXT(1,"00") | E7: =SUMIFS(Ventas_SellIn!$L$2:$L$800,Ventas_SellIn!$X$2:$X$800,$D7) | F7: =SUMIFS(Ventas_SellIn!$J$2:$J$800,Ventas_SellIn!$X$2:$X$800,$D7) | G7: =SUMIFS(Ventas_SellIn!$R$2:$R$800,Ventas_SellIn!$X$2:$X$800,$D7)
A8: Visita vigente | B8: =COUNTIF(Cobertura!$H$2:$H$250,"Vigente") | D8: =$B$3&"-"&TEXT(2,"00") | E8: =SUMIFS(Ventas_SellIn!$L$2:$L$800,Ventas_SellIn!$X$2:$X$800,$D8) | F8: =SUMIFS(Ventas_SellIn!$J$2:$J$800,Ventas_SellIn!$X$2:$X$800,$D8) | G8: =SUMIFS(Ventas_SellIn!$R$2:$R$800,Ventas_SellIn!$X$2:$X$800,$D8)
A9: Visita atrasada | B9: =COUNTIF(Cobertura!$H$2:$H$250,"Atrasado") | D9: =$B$3&"-"&TEXT(3,"00") | E9: =SUMIFS(Ventas_SellIn!$L$2:$L$800,Ventas_SellIn!$X$2:$X$800,$D9) | F9: =SUMIFS(Ventas_SellIn!$J$2:$J$800,Ventas_SellIn!$X$2:$X$800,$D9) | G9: =SUMIFS(Ventas_SellIn!$R$2:$R$800,Ventas_SellIn!$X$2:$X$800,$D9)
A10: Sin visita | B10: =COUNTIF(Cobertura!$H$2:$H$250,"Sin visita") | D10: =$B$3&"-"&TEXT(4,"00") | E10: =SUMIFS(Ventas_SellIn!$L$2:$L$800,Ventas_SellIn!$X$2:$X$800,$D10) | F10: =SUMIFS(Ventas_SellIn!$J$2:$J$800,Ventas_SellIn!$X$2:$X$800,$D10) | G10: =SUMIFS(Ventas_SellIn!$R$2:$R$800,Ventas_SellIn!$X$2:$X$800,$D10)
A11: PDV con venta OK | B11: =COUNTIF(Cobertura!$K$2:$K$250,"Venta OK") | D11: =$B$3&"-"&TEXT(5,"00") | E11: =SUMIFS(Ventas_SellIn!$L$2:$L$800,Ventas_SellIn!$X$2:$X$800,$D11) | F11: =SUMIFS(Ventas_SellIn!$J$2:$J$800,Ventas_SellIn!$X$2:$X$800,$D11) | G11: =SUMIFS(Ventas_SellIn!$R$2:$R$800,Ventas_SellIn!$X$2:$X$800,$D11)
A12: PDV venta baja | B12: =COUNTIF(Cobertura!$K$2:$K$250,"Venta baja") | D12: =$B$3&"-"&TEXT(6,"00") | E12: =SUMIFS(Ventas_SellIn!$L$2:$L$800,Ventas_SellIn!$X$2:$X$800,$D12) | F12: =SUMIFS(Ventas_SellIn!$J$2:$J$800,Ventas_SellIn!$X$2:$X$800,$D12) | G12: =SUMIFS(Ventas_SellIn!$R$2:$R$800,Ventas_SellIn!$X$2:$X$800,$D12)
A13: PDV sin venta | B13: =COUNTIF(Cobertura!$K$2:$K$250,"Sin venta") | D13: =$B$3&"-"&TEXT(7,"00") | E13: =SUMIFS(Ventas_SellIn!$L$2:$L$800,Ventas_SellIn!$X$2:$X$800,$D13) | F13: =SUMIFS(Ventas_SellIn!$J$2:$J$800,Ventas_SellIn!$X$2:$X$800,$D13) | G13: =SUMIFS(Ventas_SellIn!$R$2:$R$800,Ventas_SellIn!$X$2:$X$800,$D13)
A14: Prioridad Alta (lunes) | B14: =COUNTIF(Cobertura!$Q$2:$Q$250,"Alta") | D14: =$B$3&"-"&TEXT(8,"00") | E14: =SUMIFS(Ventas_SellIn!$L$2:$L$800,Ventas_SellIn!$X$2:$X$800,$D14) | F14: =SUMIFS(Ventas_SellIn!$J$2:$J$800,Ventas_SellIn!$X$2:$X$800,$D14) | G14: =SUMIFS(Ventas_SellIn!$R$2:$R$800,Ventas_SellIn!$X$2:$X$800,$D14)
A15: Monto pendiente total | B15: =SUM(Cobertura!$M$2:$M$250) | D15: =$B$3&"-"&TEXT(9,"00") | E15: =SUMIFS(Ventas_SellIn!$L$2:$L$800,Ventas_SellIn!$X$2:$X$800,$D15) | F15: =SUMIFS(Ventas_SellIn!$J$2:$J$800,Ventas_SellIn!$X$2:$X$800,$D15) | G15: =SUMIFS(Ventas_SellIn!$R$2:$R$800,Ventas_SellIn!$X$2:$X$800,$D15)
D16: =$B$3&"-"&TEXT(10,"00") | E16: =SUMIFS(Ventas_SellIn!$L$2:$L$800,Ventas_SellIn!$X$2:$X$800,$D16) | F16: =SUMIFS(Ventas_SellIn!$J$2:$J$800,Ventas_SellIn!$X$2:$X$800,$D16) | G16: =SUMIFS(Ventas_SellIn!$R$2:$R$800,Ventas_SellIn!$X$2:$X$800,$D16)
D17: =$B$3&"-"&TEXT(11,"00") | E17: =SUMIFS(Ventas_SellIn!$L$2:$L$800,Ventas_SellIn!$X$2:$X$800,$D17) | F17: =SUMIFS(Ventas_SellIn!$J$2:$J$800,Ventas_SellIn!$X$2:$X$800,$D17) | G17: =SUMIFS(Ventas_SellIn!$R$2:$R$800,Ventas_SellIn!$X$2:$X$800,$D17)
D18: =$B$3&"-"&TEXT(12,"00") | E18: =SUMIFS(Ventas_SellIn!$L$2:$L$800,Ventas_SellIn!$X$2:$X$800,$D18) | F18: =SUMIFS(Ventas_SellIn!$J$2:$J$800,Ventas_SellIn!$X$2:$X$800,$D18) | G18: =SUMIFS(Ventas_SellIn!$R$2:$R$800,Ventas_SellIn!$X$2:$X$800,$D18)
A19: Nota: se llena solo desde Ventas_SellIn y Cobertura. Cambia el año en B3. | D19: TOTAL | E19: =SUM(E7:E18) | F19: =SUM(F7:F18) | G19: =SUM(G7:G18)
A21: Venta por canal
A22: Canal | B22: Venta neta | C22: Unidades
A23: =Inicio!$E$5 | B23: =IF($A23="","",SUMIFS(Ventas_SellIn!$L$2:$L$800,Ventas_SellIn!$F$2:$F$800,$A23)) | C23: =IF($A23="","",SUMIFS(Ventas_SellIn!$J$2:$J$800,Ventas_SellIn!$F$2:$F$800,$A23))
A24: =Inicio!$E$6 | B24: =IF($A24="","",SUMIFS(Ventas_SellIn!$L$2:$L$800,Ventas_SellIn!$F$2:$F$800,$A24)) | C24: =IF($A24="","",SUMIFS(Ventas_SellIn!$J$2:$J$800,Ventas_SellIn!$F$2:$F$800,$A24))
A25: =Inicio!$E$7 | B25: =IF($A25="","",SUMIFS(Ventas_SellIn!$L$2:$L$800,Ventas_SellIn!$F$2:$F$800,$A25)) | C25: =IF($A25="","",SUMIFS(Ventas_SellIn!$J$2:$J$800,Ventas_SellIn!$F$2:$F$800,$A25))
A26: =Inicio!$E$8 | B26: =IF($A26="","",SUMIFS(Ventas_SellIn!$L$2:$L$800,Ventas_SellIn!$F$2:$F$800,$A26)) | C26: =IF($A26="","",SUMIFS(Ventas_SellIn!$J$2:$J$800,Ventas_SellIn!$F$2:$F$800,$A26))
A27: =Inicio!$E$9 | B27: =IF($A27="","",SUMIFS(Ventas_SellIn!$L$2:$L$800,Ventas_SellIn!$F$2:$F$800,$A27)) | C27: =IF($A27="","",SUMIFS(Ventas_SellIn!$J$2:$J$800,Ventas_SellIn!$F$2:$F$800,$A27))
A28: =Inicio!$E$10 | B28: =IF($A28="","",SUMIFS(Ventas_SellIn!$L$2:$L$800,Ventas_SellIn!$F$2:$F$800,$A28)) | C28: =IF($A28="","",SUMIFS(Ventas_SellIn!$J$2:$J$800,Ventas_SellIn!$F$2:$F$800,$A28))
A29: =Inicio!$E$11 | B29: =IF($A29="","",SUMIFS(Ventas_SellIn!$L$2:$L$800,Ventas_SellIn!$F$2:$F$800,$A29)) | C29: =IF($A29="","",SUMIFS(Ventas_SellIn!$J$2:$J$800,Ventas_SellIn!$F$2:$F$800,$A29))
A30: =Inicio!$E$12 | B30: =IF($A30="","",SUMIFS(Ventas_SellIn!$L$2:$L$800,Ventas_SellIn!$F$2:$F$800,$A30)) | C30: =IF($A30="","",SUMIFS(Ventas_SellIn!$J$2:$J$800,Ventas_SellIn!$F$2:$F$800,$A30))
A31: =Inicio!$E$13 | B31: =IF($A31="","",SUMIFS(Ventas_SellIn!$L$2:$L$800,Ventas_SellIn!$F$2:$F$800,$A31)) | C31: =IF($A31="","",SUMIFS(Ventas_SellIn!$J$2:$J$800,Ventas_SellIn!$F$2:$F$800,$A31))
A32: Tip: en Ventas_SellIn filtra la columna Fecha → Filtros de fecha → Entre… para ver el detalle.
A33: Reporte de ventas por rango de fechas
A34: Desde: | B34: 46023 | C34: Hasta: | D34: 46387
A35: Métrica | B35: Valor
A36: Venta neta (rango) | B36: =SUMIFS(Ventas_SellIn!$L$2:$L$800,Ventas_SellIn!$B$2:$B$800,">="&$B$34,Ventas_SellIn!$B$2:$B$800,"<="&$D$34)
A37: Unidades (rango) | B37: =SUMIFS(Ventas_SellIn!$J$2:$J$800,Ventas_SellIn!$B$2:$B$800,">="&$B$34,Ventas_SellIn!$B$2:$B$800,"<="&$D$34)
A38: N° facturas/líneas | B38: =COUNTIFS(Ventas_SellIn!$B$2:$B$800,">="&$B$34,Ventas_SellIn!$B$2:$B$800,"<="&$D$34,Ventas_SellIn!$A$2:$A$800,"<>")
A39: Monto pendiente (rango) | B39: =SUMIFS(Ventas_SellIn!$R$2:$R$800,Ventas_SellIn!$B$2:$B$800,">="&$B$34,Ventas_SellIn!$B$2:$B$800,"<="&$D$34)
A41: Venta por canal en el rango
A42: Canal | B42: Venta neta | C42: Unidades
A43: =Inicio!$E$5 | B43: =IF($A43="","",SUMIFS(Ventas_SellIn!$L$2:$L$800,Ventas_SellIn!$F$2:$F$800,$A43,Ventas_SellIn!$B$2:$B$800,">="&$B$34,Ventas_SellIn!$B$2:$B$800,"<="&$D$34)) | C43: =IF($A43="","",SUMIFS(Ventas_SellIn!$J$2:$J$800,Ventas_SellIn!$F$2:$F$800,$A43,Ventas_SellIn!$B$2:$B$800,">="&$B$34,Ventas_SellIn!$B$2:$B$800,"<="&$D$34))
A44: =Inicio!$E$6 | B44: =IF($A44="","",SUMIFS(Ventas_SellIn!$L$2:$L$800,Ventas_SellIn!$F$2:$F$800,$A44,Ventas_SellIn!$B$2:$B$800,">="&$B$34,Ventas_SellIn!$B$2:$B$800,"<="&$D$34)) | C44: =IF($A44="","",SUMIFS(Ventas_SellIn!$J$2:$J$800,Ventas_SellIn!$F$2:$F$800,$A44,Ventas_SellIn!$B$2:$B$800,">="&$B$34,Ventas_SellIn!$B$2:$B$800,"<="&$D$34))
A45: =Inicio!$E$7 | B45: =IF($A45="","",SUMIFS(Ventas_SellIn!$L$2:$L$800,Ventas_SellIn!$F$2:$F$800,$A45,Ventas_SellIn!$B$2:$B$800,">="&$B$34,Ventas_SellIn!$B$2:$B$800,"<="&$D$34)) | C45: =IF($A45="","",SUMIFS(Ventas_SellIn!$J$2:$J$800,Ventas_SellIn!$F$2:$F$800,$A45,Ventas_SellIn!$B$2:$B$800,">="&$B$34,Ventas_SellIn!$B$2:$B$800,"<="&$D$34))
A46: =Inicio!$E$8 | B46: =IF($A46="","",SUMIFS(Ventas_SellIn!$L$2:$L$800,Ventas_SellIn!$F$2:$F$800,$A46,Ventas_SellIn!$B$2:$B$800,">="&$B$34,Ventas_SellIn!$B$2:$B$800,"<="&$D$34)) | C46: =IF($A46="","",SUMIFS(Ventas_SellIn!$J$2:$J$800,Ventas_SellIn!$F$2:$F$800,$A46,Ventas_SellIn!$B$2:$B$800,">="&$B$34,Ventas_SellIn!$B$2:$B$800,"<="&$D$34))
A47: =Inicio!$E$9 | B47: =IF($A47="","",SUMIFS(Ventas_SellIn!$L$2:$L$800,Ventas_SellIn!$F$2:$F$800,$A47,Ventas_SellIn!$B$2:$B$800,">="&$B$34,Ventas_SellIn!$B$2:$B$800,"<="&$D$34)) | C47: =IF($A47="","",SUMIFS(Ventas_SellIn!$J$2:$J$800,Ventas_SellIn!$F$2:$F$800,$A47,Ventas_SellIn!$B$2:$B$800,">="&$B$34,Ventas_SellIn!$B$2:$B$800,"<="&$D$34))
A48: =Inicio!$E$10 | B48: =IF($A48="","",SUMIFS(Ventas_SellIn!$L$2:$L$800,Ventas_SellIn!$F$2:$F$800,$A48,Ventas_SellIn!$B$2:$B$800,">="&$B$34,Ventas_SellIn!$B$2:$B$800,"<="&$D$34)) | C48: =IF($A48="","",SUMIFS(Ventas_SellIn!$J$2:$J$800,Ventas_SellIn!$F$2:$F$800,$A48,Ventas_SellIn!$B$2:$B$800,">="&$B$34,Ventas_SellIn!$B$2:$B$800,"<="&$D$34))
A49: =Inicio!$E$11 | B49: =IF($A49="","",SUMIFS(Ventas_SellIn!$L$2:$L$800,Ventas_SellIn!$F$2:$F$800,$A49,Ventas_SellIn!$B$2:$B$800,">="&$B$34,Ventas_SellIn!$B$2:$B$800,"<="&$D$34)) | C49: =IF($A49="","",SUMIFS(Ventas_SellIn!$J$2:$J$800,Ventas_SellIn!$F$2:$F$800,$A49,Ventas_SellIn!$B$2:$B$800,">="&$B$34,Ventas_SellIn!$B$2:$B$800,"<="&$D$34))
A50: =Inicio!$E$12 | B50: =IF($A50="","",SUMIFS(Ventas_SellIn!$L$2:$L$800,Ventas_SellIn!$F$2:$F$800,$A50,Ventas_SellIn!$B$2:$B$800,">="&$B$34,Ventas_SellIn!$B$2:$B$800,"<="&$D$34)) | C50: =IF($A50="","",SUMIFS(Ventas_SellIn!$J$2:$J$800,Ventas_SellIn!$F$2:$F$800,$A50,Ventas_SellIn!$B$2:$B$800,">="&$B$34,Ventas_SellIn!$B$2:$B$800,"<="&$D$34))
A51: =Inicio!$E$13 | B51: =IF($A51="","",SUMIFS(Ventas_SellIn!$L$2:$L$800,Ventas_SellIn!$F$2:$F$800,$A51,Ventas_SellIn!$B$2:$B$800,">="&$B$34,Ventas_SellIn!$B$2:$B$800,"<="&$D$34)) | C51: =IF($A51="","",SUMIFS(Ventas_SellIn!$J$2:$J$800,Ventas_SellIn!$F$2:$F$800,$A51,Ventas_SellIn!$B$2:$B$800,">="&$B$34,Ventas_SellIn!$B$2:$B$800,"<="&$D$34))

Sheet Plan_Inventario
A1: Producto (SKU) | B1: Descripción | C1: Sell-in ventana | D1: Venta/día | E1: Stock objetivo | F1: Bodega (unid.) | G1: Bodega barras | H1: Reponer (barras) | I1: Estado | K1: ⚙ Configuración
A2: =IF(Maestro_SKU!A2="","",Maestro_SKU!A2) | B2: =IF(A2="","",IFERROR(VLOOKUP(A2,Maestro_SKU!$A$2:$P$500,2,FALSE),"")) | C2: =IF(A2="","",SUMIFS(Ventas_SellIn!$Y$2:$Y$800,Ventas_SellIn!$H$2:$H$800,A2,Ventas_SellIn!$B$2:$B$800,">="&TODAY()-cfg_VentanaDemanda)) | D2: =IF(A2="","",C2/cfg_VentanaDemanda) | E2: =IF(A2="","",ROUND(D2*cfg_DiasCobertura*(1+cfg_PctSeguridad),0)) | G2: =IF(A2="","",IF(F2="",0,F2*IFERROR(VLOOKUP(A2,Maestro_SKU!$A$2:$P$500,12,FALSE),1))) | H2: =IF(A2="","",MAX(E2-G2,0)) | I2: =IF(A2="","",IF(F2="","Falta bodega",IF(G2>=E2,"OK",IF(G2>=E2*0.6,"Ajustado","Reponer"))))
A3: =IF(Maestro_SKU!A3="","",Maestro_SKU!A3) | B3: =IF(A3="","",IFERROR(VLOOKUP(A3,Maestro_SKU!$A$2:$P$500,2,FALSE),"")) | C3: =IF(A3="","",SUMIFS(Ventas_SellIn!$Y$2:$Y$800,Ventas_SellIn!$H$2:$H$800,A3,Ventas_SellIn!$B$2:$B$800,">="&TODAY()-cfg_VentanaDemanda)) | D3: =IF(A3="","",C3/cfg_VentanaDemanda) | E3: =IF(A3="","",ROUND(D3*cfg_DiasCobertura*(1+cfg_PctSeguridad),0)) | G3: =IF(A3="","",IF(F3="",0,F3*IFERROR(VLOOKUP(A3,Maestro_SKU!$A$2:$P$500,12,FALSE),1))) | H3: =IF(A3="","",MAX(E3-G3,0)) | I3: =IF(A3="","",IF(F3="","Falta bodega",IF(G3>=E3,"OK",IF(G3>=E3*0.6,"Ajustado","Reponer"))))
A4: =IF(Maestro_SKU!A4="","",Maestro_SKU!A4) | B4: =IF(A4="","",IFERROR(VLOOKUP(A4,Maestro_SKU!$A$2:$P$500,2,FALSE),"")) | C4: =IF(A4="","",SUMIFS(Ventas_SellIn!$Y$2:$Y$800,Ventas_SellIn!$H$2:$H$800,A4,Ventas_SellIn!$B$2:$B$800,">="&TODAY()-cfg_VentanaDemanda)) | D4: =IF(A4="","",C4/cfg_VentanaDemanda) | E4: =IF(A4="","",ROUND(D4*cfg_DiasCobertura*(1+cfg_PctSeguridad),0)) | G4: =IF(A4="","",IF(F4="",0,F4*IFERROR(VLOOKUP(A4,Maestro_SKU!$A$2:$P$500,12,FALSE),1))) | H4: =IF(A4="","",MAX(E4-G4,0)) | I4: =IF(A4="","",IF(F4="","Falta bodega",IF(G4>=E4,"OK",IF(G4>=E4*0.6,"Ajustado","Reponer"))))
A5: =IF(Maestro_SKU!A5="","",Maestro_SKU!A5) | B5: =IF(A5="","",IFERROR(VLOOKUP(A5,Maestro_SKU!$A$2:$P$500,2,FALSE),"")) | C5: =IF(A5="","",SUMIFS(Ventas_SellIn!$Y$2:$Y$800,Ventas_SellIn!$H$2:$H$800,A5,Ventas_SellIn!$B$2:$B$800,">="&TODAY()-cfg_VentanaDemanda)) | D5: =IF(A5="","",C5/cfg_VentanaDemanda) | E5: =IF(A5="","",ROUND(D5*cfg_DiasCobertura*(1+cfg_PctSeguridad),0)) | G5: =IF(A5="","",IF(F5="",0,F5*IFERROR(VLOOKUP(A5,Maestro_SKU!$A$2:$P$500,12,FALSE),1))) | H5: =IF(A5="","",MAX(E5-G5,0)) | I5: =IF(A5="","",IF(F5="","Falta bodega",IF(G5>=E5,"OK",IF(G5>=E5*0.6,"Ajustado","Reponer"))))
A6: =IF(Maestro_SKU!A6="","",Maestro_SKU!A6) | B6: =IF(A6="","",IFERROR(VLOOKUP(A6,Maestro_SKU!$A$2:$P$500,2,FALSE),"")) | C6: =IF(A6="","",SUMIFS(Ventas_SellIn!$Y$2:$Y$800,Ventas_SellIn!$H$2:$H$800,A6,Ventas_SellIn!$B$2:$B$800,">="&TODAY()-cfg_VentanaDemanda)) | D6: =IF(A6="","",C6/cfg_VentanaDemanda) | E6: =IF(A6="","",ROUND(D6*cfg_DiasCobertura*(1+cfg_PctSeguridad),0)) | G6: =IF(A6="","",IF(F6="",0,F6*IFERROR(VLOOKUP(A6,Maestro_SKU!$A$2:$P$500,12,FALSE),1))) | H6: =IF(A6="","",MAX(E6-G6,0)) | I6: =IF(A6="","",IF(F6="","Falta bodega",IF(G6>=E6,"OK",IF(G6>=E6*0.6,"Ajustado","Reponer"))))
A7: =IF(Maestro_SKU!A7="","",Maestro_SKU!A7) | B7: =IF(A7="","",IFERROR(VLOOKUP(A7,Maestro_SKU!$A$2:$P$500,2,FALSE),"")) | C7: =IF(A7="","",SUMIFS(Ventas_SellIn!$Y$2:$Y$800,Ventas_SellIn!$H$2:$H$800,A7,Ventas_SellIn!$B$2:$B$800,">="&TODAY()-cfg_VentanaDemanda)) | D7: =IF(A7="","",C7/cfg_VentanaDemanda) | E7: =IF(A7="","",ROUND(D7*cfg_DiasCobertura*(1+cfg_PctSeguridad),0)) | G7: =IF(A7="","",IF(F7="",0,F7*IFERROR(VLOOKUP(A7,Maestro_SKU!$A$2:$P$500,12,FALSE),1))) | H7: =IF(A7="","",MAX(E7-G7,0)) | I7: =IF(A7="","",IF(F7="","Falta bodega",IF(G7>=E7,"OK",IF(G7>=E7*0.6,"Ajustado","Reponer"))))
A8: =IF(Maestro_SKU!A8="","",Maestro_SKU!A8) | B8: =IF(A8="","",IFERROR(VLOOKUP(A8,Maestro_SKU!$A$2:$P$500,2,FALSE),"")) | C8: =IF(A8="","",SUMIFS(Ventas_SellIn!$Y$2:$Y$800,Ventas_SellIn!$H$2:$H$800,A8,Ventas_SellIn!$B$2:$B$800,">="&TODAY()-cfg_VentanaDemanda)) | D8: =IF(A8="","",C8/cfg_VentanaDemanda) | E8: =IF(A8="","",ROUND(D8*cfg_DiasCobertura*(1+cfg_PctSeguridad),0)) | G8: =IF(A8="","",IF(F8="",0,F8*IFERROR(VLOOKUP(A8,Maestro_SKU!$A$2:$P$500,12,FALSE),1))) | H8: =IF(A8="","",MAX(E8-G8,0)) | I8: =IF(A8="","",IF(F8="","Falta bodega",IF(G8>=E8,"OK",IF(G8>=E8*0.6,"Ajustado","Reponer"))))
A9: =IF(Maestro_SKU!A9="","",Maestro_SKU!A9) | B9: =IF(A9="","",IFERROR(VLOOKUP(A9,Maestro_SKU!$A$2:$P$500,2,FALSE),"")) | C9: =IF(A9="","",SUMIFS(Ventas_SellIn!$Y$2:$Y$800,Ventas_SellIn!$H$2:$H$800,A9,Ventas_SellIn!$B$2:$B$800,">="&TODAY()-cfg_VentanaDemanda)) | D9: =IF(A9="","",C9/cfg_VentanaDemanda) | E9: =IF(A9="","",ROUND(D9*cfg_DiasCobertura*(1+cfg_PctSeguridad),0)) | G9: =IF(A9="","",IF(F9="",0,F9*IFERROR(VLOOKUP(A9,Maestro_SKU!$A$2:$P$500,12,FALSE),1))) | H9: =IF(A9="","",MAX(E9-G9,0)) | I9: =IF(A9="","",IF(F9="","Falta bodega",IF(G9>=E9,"OK",IF(G9>=E9*0.6,"Ajustado","Reponer"))))
A10: =IF(Maestro_SKU!A10="","",Maestro_SKU!A10) | B10: =IF(A10="","",IFERROR(VLOOKUP(A10,Maestro_SKU!$A$2:$P$500,2,FALSE),"")) | C10: =IF(A10="","",SUMIFS(Ventas_SellIn!$Y$2:$Y$800,Ventas_SellIn!$H$2:$H$800,A10,Ventas_SellIn!$B$2:$B$800,">="&TODAY()-cfg_VentanaDemanda)) | D10: =IF(A10="","",C10/cfg_VentanaDemanda) | E10: =IF(A10="","",ROUND(D10*cfg_DiasCobertura*(1+cfg_PctSeguridad),0)) | G10: =IF(A10="","",IF(F10="",0,F10*IFERROR(VLOOKUP(A10,Maestro_SKU!$A$2:$P$500,12,FALSE),1))) | H10: =IF(A10="","",MAX(E10-G10,0)) | I10: =IF(A10="","",IF(F10="","Falta bodega",IF(G10>=E10,"OK",IF(G10>=E10*0.6,"Ajustado","Reponer"))))
A11: =IF(Maestro_SKU!A11="","",Maestro_SKU!A11) | B11: =IF(A11="","",IFERROR(VLOOKUP(A11,Maestro_SKU!$A$2:$P$500,2,FALSE),"")) | C11: =IF(A11="","",SUMIFS(Ventas_SellIn!$Y$2:$Y$800,Ventas_SellIn!$H$2:$H$800,A11,Ventas_SellIn!$B$2:$B$800,">="&TODAY()-cfg_VentanaDemanda)) | D11: =IF(A11="","",C11/cfg_VentanaDemanda) | E11: =IF(A11="","",ROUND(D11*cfg_DiasCobertura*(1+cfg_PctSeguridad),0)) | G11: =IF(A11="","",IF(F11="",0,F11*IFERROR(VLOOKUP(A11,Maestro_SKU!$A$2:$P$500,12,FALSE),1))) | H11: =IF(A11="","",MAX(E11-G11,0)) | I11: =IF(A11="","",IF(F11="","Falta bodega",IF(G11>=E11,"OK",IF(G11>=E11*0.6,"Ajustado","Reponer"))))
A12: =IF(Maestro_SKU!A12="","",Maestro_SKU!A12) | B12: =IF(A12="","",IFERROR(VLOOKUP(A12,Maestro_SKU!$A$2:$P$500,2,FALSE),"")) | C12: =IF(A12="","",SUMIFS(Ventas_SellIn!$Y$2:$Y$800,Ventas_SellIn!$H$2:$H$800,A12,Ventas_SellIn!$B$2:$B$800,">="&TODAY()-cfg_VentanaDemanda)) | D12: =IF(A12="","",C12/cfg_VentanaDemanda) | E12: =IF(A12="","",ROUND(D12*cfg_DiasCobertura*(1+cfg_PctSeguridad),0)) | G12: =IF(A12="","",IF(F12="",0,F12*IFERROR(VLOOKUP(A12,Maestro_SKU!$A$2:$P$500,12,FALSE),1))) | H12: =IF(A12="","",MAX(E12-G12,0)) | I12: =IF(A12="","",IF(F12="","Falta bodega",IF(G12>=E12,"OK",IF(G12>=E12*0.6,"Ajustado","Reponer"))))
A13: =IF(Maestro_SKU!A13="","",Maestro_SKU!A13) | B13: =IF(A13="","",IFERROR(VLOOKUP(A13,Maestro_SKU!$A$2:$P$500,2,FALSE),"")) | C13: =IF(A13="","",SUMIFS(Ventas_SellIn!$Y$2:$Y$800,Ventas_SellIn!$H$2:$H$800,A13,Ventas_SellIn!$B$2:$B$800,">="&TODAY()-cfg_VentanaDemanda)) | D13: =IF(A13="","",C13/cfg_VentanaDemanda) | E13: =IF(A13="","",ROUND(D13*cfg_DiasCobertura*(1+cfg_PctSeguridad),0)) | G13: =IF(A13="","",IF(F13="",0,F13*IFERROR(VLOOKUP(A13,Maestro_SKU!$A$2:$P$500,12,FALSE),1))) | H13: =IF(A13="","",MAX(E13-G13,0)) | I13: =IF(A13="","",IF(F13="","Falta bodega",IF(G13>=E13,"OK",IF(G13>=E13*0.6,"Ajustado","Reponer"))))
... A81: =IF(Maestro_SKU!A81="","",Maestro_SKU!A81) | B81: =IF(A81="","",IFERROR(VLOOKUP(A81,Maestro_SKU!$A$2:$P$500,2,FALSE),"")) | C81: =IF(A81="","",SUMIFS(Ventas_SellIn!$Y$2:$Y$800,Ventas_SellIn!$H$2:$H$800,A81,Ventas_SellIn!$B$2:$B$800,">="&TODAY()-cfg_VentanaDemanda)) | D81: =IF(A81="","",C81/cfg_VentanaDemanda) | E81: =IF(A81="","",ROUND(D81*cfg_DiasCobertura*(1+cfg_PctSeguridad),0)) | G81: =IF(A81="","",IF(F81="",0,F81*IFERROR(VLOOKUP(A81,Maestro_SKU!$A$2:$P$500,12,FALSE),1))) | H81: =IF(A81="","",MAX(E81-G81,0)) | I81: =IF(A81="","",IF(F81="","Falta bodega",IF(G81>=E81,"OK",IF(G81>=E81*0.6,"Ajustado","Reponer"))))

Sheet Cobertura
A1: PDV_ID | B1: Cliente | C1: Canal | D1: Punto de venta | E1: Frecuencia | F1: Última visita | G1: Días sin visita | H1: Estado visita | I1: Venta sell-in 30d neta | J1: Sell-out 30d unid. opcional | K1: Estado venta | L1: Facturas pendientes | M1: Monto pendiente | N1: Estado pago | O1: Stock PDV barras | P1: Estado stock | Q1: Prioridad lunes | R1: Acción sugerida | S1: Rotación | T1: ⚙ Configuración
A2: =IF(Clientes_PDV!A2="","",Clientes_PDV!A2) | B2: =IF(A2="","",IFERROR(VLOOKUP(A2,Clientes_PDV!$A$2:$J$250,2,FALSE),"")) | C2: =IF(A2="","",IFERROR(VLOOKUP(A2,Clientes_PDV!$A$2:$J$250,3,FALSE),"")) | D2: =IF(A2="","",IFERROR(VLOOKUP(A2,Clientes_PDV!$A$2:$J$250,4,FALSE),"")) | E2: =IF(A2="","",IFERROR(VLOOKUP(A2,Clientes_PDV!$A$2:$J$250,7,FALSE),"")) | F2: =IF(A2="","",IFERROR(VLOOKUP(A2,Clientes_PDV!$A$2:$J$250,8,FALSE),"")) | G2: =IF(F2="","",TODAY()-F2) | H2: =IF(A2="","",IF(F2="","Sin visita",IF(G2<=IFERROR(VLOOKUP(E2,Inicio!$A$24:$B$26,2,FALSE),0),"Vigente","Atrasado"))) | I2: =IF(A2="","",SUMIFS(Ventas_SellIn!$L$2:$L$800,Ventas_SellIn!$D$2:$D$800,A2,Ventas_SellIn!$B$2:$B$800,">="&TODAY()-Inicio!$B$14)) | J2: =IF(A2="","",SUMIFS(SellOut_Jumbo!$F$2:$F$800,SellOut_Jumbo!$C$2:$C$800,D2,SellOut_Jumbo!$A$2:$A$800,">="&TODAY()-Inicio!$B$14)) | K2: =IF(A2="","",IF(I2=0,"Sin venta",IF(I2<Inicio!$B$15,"Venta baja","Venta OK"))) | L2: =IF(A2="","",COUNTIFS(Ventas_SellIn!$D$2:$D$800,A2,Ventas_SellIn!$R$2:$R$800,">0")) | M2: =IF(A2="","",SUMIFS(Ventas_SellIn!$R$2:$R$800,Ventas_SellIn!$D$2:$D$800,A2)) | N2: =IF(A2="","",IF(M2>=Inicio!$B$18,"Pendiente relevante",IF(M2>0,"Pendiente menor","Sin deuda"))) | O2: =IF(A2="","",SUMIFS(Stock_PDV!$H$2:$H$800,Stock_PDV!$A$2:$A$800,A2)) | P2: =IF(A2="","",IF(O2<=Inicio!$B$16,"Crítico",IF(O2<=Inicio!$B$17,"Observar","OK"))) | Q2: =IF(A2="","",IF(OR(H2="Atrasado",K2="Sin venta",N2="Pendiente relevante",P2="Crítico"),"Alta",IF(OR(K2="Venta baja",N2="Pendiente menor",P2="Observar"),"Media","Baja"))) | R2: =IF(A2="","",IF(Q2="Alta","Gestionar esta semana",IF(Q2="Media","Hacer seguimiento","Mantener"))) | S2: =IF(A2="","",IF(I2=0,"Sin venta",IF(I2>=cfg_VentaAlta,"Alta",IF(I2<cfg_VentaBaja,"Baja","Media"))))
A3: =IF(Clientes_PDV!A3="","",Clientes_PDV!A3) | B3: =IF(A3="","",IFERROR(VLOOKUP(A3,Clientes_PDV!$A$2:$J$250,2,FALSE),"")) | C3: =IF(A3="","",IFERROR(VLOOKUP(A3,Clientes_PDV!$A$2:$J$250,3,FALSE),"")) | D3: =IF(A3="","",IFERROR(VLOOKUP(A3,Clientes_PDV!$A$2:$J$250,4,FALSE),"")) | E3: =IF(A3="","",IFERROR(VLOOKUP(A3,Clientes_PDV!$A$2:$J$250,7,FALSE),"")) | F3: =IF(A3="","",IFERROR(VLOOKUP(A3,Clientes_PDV!$A$2:$J$250,8,FALSE),"")) | G3: =IF(F3="","",TODAY()-F3) | H3: =IF(A3="","",IF(F3="","Sin visita",IF(G3<=IFERROR(VLOOKUP(E3,Inicio!$A$24:$B$26,2,FALSE),0),"Vigente","Atrasado"))) | I3: =IF(A3="","",SUMIFS(Ventas_SellIn!$L$2:$L$800,Ventas_SellIn!$D$2:$D$800,A3,Ventas_SellIn!$B$2:$B$800,">="&TODAY()-Inicio!$B$14)) | J3: =IF(A3="","",SUMIFS(SellOut_Jumbo!$F$2:$F$800,SellOut_Jumbo!$C$2:$C$800,D3,SellOut_Jumbo!$A$2:$A$800,">="&TODAY()-Inicio!$B$14)) | K3: =IF(A3="","",IF(I3=0,"Sin venta",IF(I3<Inicio!$B$15,"Venta baja","Venta OK"))) | L3: =IF(A3="","",COUNTIFS(Ventas_SellIn!$D$2:$D$800,A3,Ventas_SellIn!$R$2:$R$800,">0")) | M3: =IF(A3="","",SUMIFS(Ventas_SellIn!$R$2:$R$800,Ventas_SellIn!$D$2:$D$800,A3)) | N3: =IF(A3="","",IF(M3>=Inicio!$B$18,"Pendiente relevante",IF(M3>0,"Pendiente menor","Sin deuda"))) | O3: =IF(A3="","",SUMIFS(Stock_PDV!$H$2:$H$800,Stock_PDV!$A$2:$A$800,A3)) | P3: =IF(A3="","",IF(O3<=Inicio!$B$16,"Crítico",IF(O3<=Inicio!$B$17,"Observar","OK"))) | Q3: =IF(A3="","",IF(OR(H3="Atrasado",K3="Sin venta",N3="Pendiente relevante",P3="Crítico"),"Alta",IF(OR(K3="Venta baja",N3="Pendiente menor",P3="Observar"),"Media","Baja"))) | R3: =IF(A3="","",IF(Q3="Alta","Gestionar esta semana",IF(Q3="Media","Hacer seguimiento","Mantener"))) | S3: =IF(A3="","",IF(I3=0,"Sin venta",IF(I3>=cfg_VentaAlta,"Alta",IF(I3<cfg_VentaBaja,"Baja","Media"))))
A4: =IF(Clientes_PDV!A4="","",Clientes_PDV!A4) | B4: =IF(A4="","",IFERROR(VLOOKUP(A4,Clientes_PDV!$A$2:$J$250,2,FALSE),"")) | C4: =IF(A4="","",IFERROR(VLOOKUP(A4,Clientes_PDV!$A$2:$J$250,3,FALSE),"")) | D4: =IF(A4="","",IFERROR(VLOOKUP(A4,Clientes_PDV!$A$2:$J$250,4,FALSE),"")) | E4: =IF(A4="","",IFERROR(VLOOKUP(A4,Clientes_PDV!$A$2:$J$250,7,FALSE),"")) | F4: =IF(A4="","",IFERROR(VLOOKUP(A4,Clientes_PDV!$A$2:$J$250,8,FALSE),"")) | G4: =IF(F4="","",TODAY()-F4) | H4: =IF(A4="","",IF(F4="","Sin visita",IF(G4<=IFERROR(VLOOKUP(E4,Inicio!$A$24:$B$26,2,FALSE),0),"Vigente","Atrasado"))) | I4: =IF(A4="","",SUMIFS(Ventas_SellIn!$L$2:$L$800,Ventas_SellIn!$D$2:$D$800,A4,Ventas_SellIn!$B$2:$B$800,">="&TODAY()-Inicio!$B$14)) | J4: =IF(A4="","",SUMIFS(SellOut_Jumbo!$F$2:$F$800,SellOut_Jumbo!$C$2:$C$800,D4,SellOut_Jumbo!$A$2:$A$800,">="&TODAY()-Inicio!$B$14)) | K4: =IF(A4="","",IF(I4=0,"Sin venta",IF(I4<Inicio!$B$15,"Venta baja","Venta OK"))) | L4: =IF(A4="","",COUNTIFS(Ventas_SellIn!$D$2:$D$800,A4,Ventas_SellIn!$R$2:$R$800,">0")) | M4: =IF(A4="","",SUMIFS(Ventas_SellIn!$R$2:$R$800,Ventas_SellIn!$D$2:$D$800,A4)) | N4: =IF(A4="","",IF(M4>=Inicio!$B$18,"Pendiente relevante",IF(M4>0,"Pendiente menor","Sin deuda"))) | O4: =IF(A4="","",SUMIFS(Stock_PDV!$H$2:$H$800,Stock_PDV!$A$2:$A$800,A4)) | P4: =IF(A4="","",IF(O4<=Inicio!$B$16,"Crítico",IF(O4<=Inicio!$B$17,"Observar","OK"))) | Q4: =IF(A4="","",IF(OR(H4="Atrasado",K4="Sin venta",N4="Pendiente relevante",P4="Crítico"),"Alta",IF(OR(K4="Venta baja",N4="Pendiente menor",P4="Observar"),"Media","Baja"))) | R4: =IF(A4="","",IF(Q4="Alta","Gestionar esta semana",IF(Q4="Media","Hacer seguimiento","Mantener"))) | S4: =IF(A4="","",IF(I4=0,"Sin venta",IF(I4>=cfg_VentaAlta,"Alta",IF(I4<cfg_VentaBaja,"Baja","Media"))))
A5: =IF(Clientes_PDV!A5="","",Clientes_PDV!A5) | B5: =IF(A5="","",IFERROR(VLOOKUP(A5,Clientes_PDV!$A$2:$J$250,2,FALSE),"")) | C5: =IF(A5="","",IFERROR(VLOOKUP(A5,Clientes_PDV!$A$2:$J$250,3,FALSE),"")) | D5: =IF(A5="","",IFERROR(VLOOKUP(A5,Clientes_PDV!$A$2:$J$250,4,FALSE),"")) | E5: =IF(A5="","",IFERROR(VLOOKUP(A5,Clientes_PDV!$A$2:$J$250,7,FALSE),"")) | F5: =IF(A5="","",IFERROR(VLOOKUP(A5,Clientes_PDV!$A$2:$J$250,8,FALSE),"")) | G5: =IF(F5="","",TODAY()-F5) | H5: =IF(A5="","",IF(F5="","Sin visita",IF(G5<=IFERROR(VLOOKUP(E5,Inicio!$A$24:$B$26,2,FALSE),0),"Vigente","Atrasado"))) | I5: =IF(A5="","",SUMIFS(Ventas_SellIn!$L$2:$L$800,Ventas_SellIn!$D$2:$D$800,A5,Ventas_SellIn!$B$2:$B$800,">="&TODAY()-Inicio!$B$14)) | J5: =IF(A5="","",SUMIFS(SellOut_Jumbo!$F$2:$F$800,SellOut_Jumbo!$C$2:$C$800,D5,SellOut_Jumbo!$A$2:$A$800,">="&TODAY()-Inicio!$B$14)) | K5: =IF(A5="","",IF(I5=0,"Sin venta",IF(I5<Inicio!$B$15,"Venta baja","Venta OK"))) | L5: =IF(A5="","",COUNTIFS(Ventas_SellIn!$D$2:$D$800,A5,Ventas_SellIn!$R$2:$R$800,">0")) | M5: =IF(A5="","",SUMIFS(Ventas_SellIn!$R$2:$R$800,Ventas_SellIn!$D$2:$D$800,A5)) | N5: =IF(A5="","",IF(M5>=Inicio!$B$18,"Pendiente relevante",IF(M5>0,"Pendiente menor","Sin deuda"))) | O5: =IF(A5="","",SUMIFS(Stock_PDV!$H$2:$H$800,Stock_PDV!$A$2:$A$800,A5)) | P5: =IF(A5="","",IF(O5<=Inicio!$B$16,"Crítico",IF(O5<=Inicio!$B$17,"Observar","OK"))) | Q5: =IF(A5="","",IF(OR(H5="Atrasado",K5="Sin venta",N5="Pendiente relevante",P5="Crítico"),"Alta",IF(OR(K5="Venta baja",N5="Pendiente menor",P5="Observar"),"Media","Baja"))) | R5: =IF(A5="","",IF(Q5="Alta","Gestionar esta semana",IF(Q5="Media","Hacer seguimiento","Mantener"))) | S5: =IF(A5="","",IF(I5=0,"Sin venta",IF(I5>=cfg_VentaAlta,"Alta",IF(I5<cfg_VentaBaja,"Baja","Media"))))
A6: =IF(Clientes_PDV!A6="","",Clientes_PDV!A6) | B6: =IF(A6="","",IFERROR(VLOOKUP(A6,Clientes_PDV!$A$2:$J$250,2,FALSE),"")) | C6: =IF(A6="","",IFERROR(VLOOKUP(A6,Clientes_PDV!$A$2:$J$250,3,FALSE),"")) | D6: =IF(A6="","",IFERROR(VLOOKUP(A6,Clientes_PDV!$A$2:$J$250,4,FALSE),"")) | E6: =IF(A6="","",IFERROR(VLOOKUP(A6,Clientes_PDV!$A$2:$J$250,7,FALSE),"")) | F6: =IF(A6="","",IFERROR(VLOOKUP(A6,Clientes_PDV!$A$2:$J$250,8,FALSE),"")) | G6: =IF(F6="","",TODAY()-F6) | H6: =IF(A6="","",IF(F6="","Sin visita",IF(G6<=IFERROR(VLOOKUP(E6,Inicio!$A$24:$B$26,2,FALSE),0),"Vigente","Atrasado"))) | I6: =IF(A6="","",SUMIFS(Ventas_SellIn!$L$2:$L$800,Ventas_SellIn!$D$2:$D$800,A6,Ventas_SellIn!$B$2:$B$800,">="&TODAY()-Inicio!$B$14)) | J6: =IF(A6="","",SUMIFS(SellOut_Jumbo!$F$2:$F$800,SellOut_Jumbo!$C$2:$C$800,D6,SellOut_Jumbo!$A$2:$A$800,">="&TODAY()-Inicio!$B$14)) | K6: =IF(A6="","",IF(I6=0,"Sin venta",IF(I6<Inicio!$B$15,"Venta baja","Venta OK"))) | L6: =IF(A6="","",COUNTIFS(Ventas_SellIn!$D$2:$D$800,A6,Ventas_SellIn!$R$2:$R$800,">0")) | M6: =IF(A6="","",SUMIFS(Ventas_SellIn!$R$2:$R$800,Ventas_SellIn!$D$2:$D$800,A6)) | N6: =IF(A6="","",IF(M6>=Inicio!$B$18,"Pendiente relevante",IF(M6>0,"Pendiente menor","Sin deuda"))) | O6: =IF(A6="","",SUMIFS(Stock_PDV!$H$2:$H$800,Stock_PDV!$A$2:$A$800,A6)) | P6: =IF(A6="","",IF(O6<=Inicio!$B$16,"Crítico",IF(O6<=Inicio!$B$17,"Observar","OK"))) | Q6: =IF(A6="","",IF(OR(H6="Atrasado",K6="Sin venta",N6="Pendiente relevante",P6="Crítico"),"Alta",IF(OR(K6="Venta baja",N6="Pendiente menor",P6="Observar"),"Media","Baja"))) | R6: =IF(A6="","",IF(Q6="Alta","Gestionar esta semana",IF(Q6="Media","Hacer seguimiento","Mantener"))) | S6: =IF(A6="","",IF(I6=0,"Sin venta",IF(I6>=cfg_VentaAlta,"Alta",IF(I6<cfg_VentaBaja,"Baja","Media"))))
A7: =IF(Clientes_PDV!A7="","",Clientes_PDV!A7) | B7: =IF(A7="","",IFERROR(VLOOKUP(A7,Clientes_PDV!$A$2:$J$250,2,FALSE),"")) | C7: =IF(A7="","",IFERROR(VLOOKUP(A7,Clientes_PDV!$A$2:$J$250,3,FALSE),"")) | D7: =IF(A7="","",IFERROR(VLOOKUP(A7,Clientes_PDV!$A$2:$J$250,4,FALSE),"")) | E7: =IF(A7="","",IFERROR(VLOOKUP(A7,Clientes_PDV!$A$2:$J$250,7,FALSE),"")) | F7: =IF(A7="","",IFERROR(VLOOKUP(A7,Clientes_PDV!$A$2:$J$250,8,FALSE),"")) | G7: =IF(F7="","",TODAY()-F7) | H7: =IF(A7="","",IF(F7="","Sin visita",IF(G7<=IFERROR(VLOOKUP(E7,Inicio!$A$24:$B$26,2,FALSE),0),"Vigente","Atrasado"))) | I7: =IF(A7="","",SUMIFS(Ventas_SellIn!$L$2:$L$800,Ventas_SellIn!$D$2:$D$800,A7,Ventas_SellIn!$B$2:$B$800,">="&TODAY()-Inicio!$B$14)) | J7: =IF(A7="","",SUMIFS(SellOut_Jumbo!$F$2:$F$800,SellOut_Jumbo!$C$2:$C$800,D7,SellOut_Jumbo!$A$2:$A$800,">="&TODAY()-Inicio!$B$14)) | K7: =IF(A7="","",IF(I7=0,"Sin venta",IF(I7<Inicio!$B$15,"Venta baja","Venta OK"))) | L7: =IF(A7="","",COUNTIFS(Ventas_SellIn!$D$2:$D$800,A7,Ventas_SellIn!$R$2:$R$800,">0")) | M7: =IF(A7="","",SUMIFS(Ventas_SellIn!$R$2:$R$800,Ventas_SellIn!$D$2:$D$800,A7)) | N7: =IF(A7="","",IF(M7>=Inicio!$B$18,"Pendiente relevante",IF(M7>0,"Pendiente menor","Sin deuda"))) | O7: =IF(A7="","",SUMIFS(Stock_PDV!$H$2:$H$800,Stock_PDV!$A$2:$A$800,A7)) | P7: =IF(A7="","",IF(O7<=Inicio!$B$16,"Crítico",IF(O7<=Inicio!$B$17,"Observar","OK"))) | Q7: =IF(A7="","",IF(OR(H7="Atrasado",K7="Sin venta",N7="Pendiente relevante",P7="Crítico"),"Alta",IF(OR(K7="Venta baja",N7="Pendiente menor",P7="Observar"),"Media","Baja"))) | R7: =IF(A7="","",IF(Q7="Alta","Gestionar esta semana",IF(Q7="Media","Hacer seguimiento","Mantener"))) | S7: =IF(A7="","",IF(I7=0,"Sin venta",IF(I7>=cfg_VentaAlta,"Alta",IF(I7<cfg_VentaBaja,"Baja","Media"))))
A8: =IF(Clientes_PDV!A8="","",Clientes_PDV!A8) | B8: =IF(A8="","",IFERROR(VLOOKUP(A8,Clientes_PDV!$A$2:$J$250,2,FALSE),"")) | C8: =IF(A8="","",IFERROR(VLOOKUP(A8,Clientes_PDV!$A$2:$J$250,3,FALSE),"")) | D8: =IF(A8="","",IFERROR(VLOOKUP(A8,Clientes_PDV!$A$2:$J$250,4,FALSE),"")) | E8: =IF(A8="","",IFERROR(VLOOKUP(A8,Clientes_PDV!$A$2:$J$250,7,FALSE),"")) | F8: =IF(A8="","",IFERROR(VLOOKUP(A8,Clientes_PDV!$A$2:$J$250,8,FALSE),"")) | G8: =IF(F8="","",TODAY()-F8) | H8: =IF(A8="","",IF(F8="","Sin visita",IF(G8<=IFERROR(VLOOKUP(E8,Inicio!$A$24:$B$26,2,FALSE),0),"Vigente","Atrasado"))) | I8: =IF(A8="","",SUMIFS(Ventas_SellIn!$L$2:$L$800,Ventas_SellIn!$D$2:$D$800,A8,Ventas_SellIn!$B$2:$B$800,">="&TODAY()-Inicio!$B$14)) | J8: =IF(A8="","",SUMIFS(SellOut_Jumbo!$F$2:$F$800,SellOut_Jumbo!$C$2:$C$800,D8,SellOut_Jumbo!$A$2:$A$800,">="&TODAY()-Inicio!$B$14)) | K8: =IF(A8="","",IF(I8=0,"Sin venta",IF(I8<Inicio!$B$15,"Venta baja","Venta OK"))) | L8: =IF(A8="","",COUNTIFS(Ventas_SellIn!$D$2:$D$800,A8,Ventas_SellIn!$R$2:$R$800,">0")) | M8: =IF(A8="","",SUMIFS(Ventas_SellIn!$R$2:$R$800,Ventas_SellIn!$D$2:$D$800,A8)) | N8: =IF(A8="","",IF(M8>=Inicio!$B$18,"Pendiente relevante",IF(M8>0,"Pendiente menor","Sin deuda"))) | O8: =IF(A8="","",SUMIFS(Stock_PDV!$H$2:$H$800,Stock_PDV!$A$2:$A$800,A8)) | P8: =IF(A8="","",IF(O8<=Inicio!$B$16,"Crítico",IF(O8<=Inicio!$B$17,"Observar","OK"))) | Q8: =IF(A8="","",IF(OR(H8="Atrasado",K8="Sin venta",N8="Pendiente relevante",P8="Crítico"),"Alta",IF(OR(K8="Venta baja",N8="Pendiente menor",P8="Observar"),"Media","Baja"))) | R8: =IF(A8="","",IF(Q8="Alta","Gestionar esta semana",IF(Q8="Media","Hacer seguimiento","Mantener"))) | S8: =IF(A8="","",IF(I8=0,"Sin venta",IF(I8>=cfg_VentaAlta,"Alta",IF(I8<cfg_VentaBaja,"Baja","Media"))))
A9: =IF(Clientes_PDV!A9="","",Clientes_PDV!A9) | B9: =IF(A9="","",IFERROR(VLOOKUP(A9,Clientes_PDV!$A$2:$J$250,2,FALSE),"")) | C9: =IF(A9="","",IFERROR(VLOOKUP(A9,Clientes_PDV!$A$2:$J$250,3,FALSE),"")) | D9: =IF(A9="","",IFERROR(VLOOKUP(A9,Clientes_PDV!$A$2:$J$250,4,FALSE),"")) | E9: =IF(A9="","",IFERROR(VLOOKUP(A9,Clientes_PDV!$A$2:$J$250,7,FALSE),"")) | F9: =IF(A9="","",IFERROR(VLOOKUP(A9,Clientes_PDV!$A$2:$J$250,8,FALSE),"")) | G9: =IF(F9="","",TODAY()-F9) | H9: =IF(A9="","",IF(F9="","Sin visita",IF(G9<=IFERROR(VLOOKUP(E9,Inicio!$A$24:$B$26,2,FALSE),0),"Vigente","Atrasado"))) | I9: =IF(A9="","",SUMIFS(Ventas_SellIn!$L$2:$L$800,Ventas_SellIn!$D$2:$D$800,A9,Ventas_SellIn!$B$2:$B$800,">="&TODAY()-Inicio!$B$14)) | J9: =IF(A9="","",SUMIFS(SellOut_Jumbo!$F$2:$F$800,SellOut_Jumbo!$C$2:$C$800,D9,SellOut_Jumbo!$A$2:$A$800,">="&TODAY()-Inicio!$B$14)) | K9: =IF(A9="","",IF(I9=0,"Sin venta",IF(I9<Inicio!$B$15,"Venta baja","Venta OK"))) | L9: =IF(A9="","",COUNTIFS(Ventas_SellIn!$D$2:$D$800,A9,Ventas_SellIn!$R$2:$R$800,">0")) | M9: =IF(A9="","",SUMIFS(Ventas_SellIn!$R$2:$R$800,Ventas_SellIn!$D$2:$D$800,A9)) | N9: =IF(A9="","",IF(M9>=Inicio!$B$18,"Pendiente relevante",IF(M9>0,"Pendiente menor","Sin deuda"))) | O9: =IF(A9="","",SUMIFS(Stock_PDV!$H$2:$H$800,Stock_PDV!$A$2:$A$800,A9)) | P9: =IF(A9="","",IF(O9<=Inicio!$B$16,"Crítico",IF(O9<=Inicio!$B$17,"Observar","OK"))) | Q9: =IF(A9="","",IF(OR(H9="Atrasado",K9="Sin venta",N9="Pendiente relevante",P9="Crítico"),"Alta",IF(OR(K9="Venta baja",N9="Pendiente menor",P9="Observar"),"Media","Baja"))) | R9: =IF(A9="","",IF(Q9="Alta","Gestionar esta semana",IF(Q9="Media","Hacer seguimiento","Mantener"))) | S9: =IF(A9="","",IF(I9=0,"Sin venta",IF(I9>=cfg_VentaAlta,"Alta",IF(I9<cfg_VentaBaja,"Baja","Media"))))
A10: =IF(Clientes_PDV!A10="","",Clientes_PDV!A10) | B10: =IF(A10="","",IFERROR(VLOOKUP(A10,Clientes_PDV!$A$2:$J$250,2,FALSE),"")) | C10: =IF(A10="","",IFERROR(VLOOKUP(A10,Clientes_PDV!$A$2:$J$250,3,FALSE),"")) | D10: =IF(A10="","",IFERROR(VLOOKUP(A10,Clientes_PDV!$A$2:$J$250,4,FALSE),"")) | E10: =IF(A10="","",IFERROR(VLOOKUP(A10,Clientes_PDV!$A$2:$J$250,7,FALSE),"")) | F10: =IF(A10="","",IFERROR(VLOOKUP(A10,Clientes_PDV!$A$2:$J$250,8,FALSE),"")) | G10: =IF(F10="","",TODAY()-F10) | H10: =IF(A10="","",IF(F10="","Sin visita",IF(G10<=IFERROR(VLOOKUP(E10,Inicio!$A$24:$B$26,2,FALSE),0),"Vigente","Atrasado"))) | I10: =IF(A10="","",SUMIFS(Ventas_SellIn!$L$2:$L$800,Ventas_SellIn!$D$2:$D$800,A10,Ventas_SellIn!$B$2:$B$800,">="&TODAY()-Inicio!$B$14)) | J10: =IF(A10="","",SUMIFS(SellOut_Jumbo!$F$2:$F$800,SellOut_Jumbo!$C$2:$C$800,D10,SellOut_Jumbo!$A$2:$A$800,">="&TODAY()-Inicio!$B$14)) | K10: =IF(A10="","",IF(I10=0,"Sin venta",IF(I10<Inicio!$B$15,"Venta baja","Venta OK"))) | L10: =IF(A10="","",COUNTIFS(Ventas_SellIn!$D$2:$D$800,A10,Ventas_SellIn!$R$2:$R$800,">0")) | M10: =IF(A10="","",SUMIFS(Ventas_SellIn!$R$2:$R$800,Ventas_SellIn!$D$2:$D$800,A10)) | N10: =IF(A10="","",IF(M10>=Inicio!$B$18,"Pendiente relevante",IF(M10>0,"Pendiente menor","Sin deuda"))) | O10: =IF(A10="","",SUMIFS(Stock_PDV!$H$2:$H$800,Stock_PDV!$A$2:$A$800,A10)) | P10: =IF(A10="","",IF(O10<=Inicio!$B$16,"Crítico",IF(O10<=Inicio!$B$17,"Observar","OK"))) | Q10: =IF(A10="","",IF(OR(H10="Atrasado",K10="Sin venta",N10="Pendiente relevante",P10="Crítico"),"Alta",IF(OR(K10="Venta baja",N10="Pendiente menor",P10="Observar"),"Media","Baja"))) | R10: =IF(A10="","",IF(Q10="Alta","Gestionar esta semana",IF(Q10="Media","Hacer seguimiento","Mantener"))) | S10: =IF(A10="","",IF(I10=0,"Sin venta",IF(I10>=cfg_VentaAlta,"Alta",IF(I10<cfg_VentaBaja,"Baja","Media"))))
A11: =IF(Clientes_PDV!A11="","",Clientes_PDV!A11) | B11: =IF(A11="","",IFERROR(VLOOKUP(A11,Clientes_PDV!$A$2:$J$250,2,FALSE),"")) | C11: =IF(A11="","",IFERROR(VLOOKUP(A11,Clientes_PDV!$A$2:$J$250,3,FALSE),"")) | D11: =IF(A11="","",IFERROR(VLOOKUP(A11,Clientes_PDV!$A$2:$J$250,4,FALSE),"")) | E11: =IF(A11="","",IFERROR(VLOOKUP(A11,Clientes_PDV!$A$2:$J$250,7,FALSE),"")) | F11: =IF(A11="","",IFERROR(VLOOKUP(A11,Clientes_PDV!$A$2:$J$250,8,FALSE),"")) | G11: =IF(F11="","",TODAY()-F11) | H11: =IF(A11="","",IF(F11="","Sin visita",IF(G11<=IFERROR(VLOOKUP(E11,Inicio!$A$24:$B$26,2,FALSE),0),"Vigente","Atrasado"))) | I11: =IF(A11="","",SUMIFS(Ventas_SellIn!$L$2:$L$800,Ventas_SellIn!$D$2:$D$800,A11,Ventas_SellIn!$B$2:$B$800,">="&TODAY()-Inicio!$B$14)) | J11: =IF(A11="","",SUMIFS(SellOut_Jumbo!$F$2:$F$800,SellOut_Jumbo!$C$2:$C$800,D11,SellOut_Jumbo!$A$2:$A$800,">="&TODAY()-Inicio!$B$14)) | K11: =IF(A11="","",IF(I11=0,"Sin venta",IF(I11<Inicio!$B$15,"Venta baja","Venta OK"))) | L11: =IF(A11="","",COUNTIFS(Ventas_SellIn!$D$2:$D$800,A11,Ventas_SellIn!$R$2:$R$800,">0")) | M11: =IF(A11="","",SUMIFS(Ventas_SellIn!$R$2:$R$800,Ventas_SellIn!$D$2:$D$800,A11)) | N11: =IF(A11="","",IF(M11>=Inicio!$B$18,"Pendiente relevante",IF(M11>0,"Pendiente menor","Sin deuda"))) | O11: =IF(A11="","",SUMIFS(Stock_PDV!$H$2:$H$800,Stock_PDV!$A$2:$A$800,A11)) | P11: =IF(A11="","",IF(O11<=Inicio!$B$16,"Crítico",IF(O11<=Inicio!$B$17,"Observar","OK"))) | Q11: =IF(A11="","",IF(OR(H11="Atrasado",K11="Sin venta",N11="Pendiente relevante",P11="Crítico"),"Alta",IF(OR(K11="Venta baja",N11="Pendiente menor",P11="Observar"),"Media","Baja"))) | R11: =IF(A11="","",IF(Q11="Alta","Gestionar esta semana",IF(Q11="Media","Hacer seguimiento","Mantener"))) | S11: =IF(A11="","",IF(I11=0,"Sin venta",IF(I11>=cfg_VentaAlta,"Alta",IF(I11<cfg_VentaBaja,"Baja","Media"))))
A12: =IF(Clientes_PDV!A12="","",Clientes_PDV!A12) | B12: =IF(A12="","",IFERROR(VLOOKUP(A12,Clientes_PDV!$A$2:$J$250,2,FALSE),"")) | C12: =IF(A12="","",IFERROR(VLOOKUP(A12,Clientes_PDV!$A$2:$J$250,3,FALSE),"")) | D12: =IF(A12="","",IFERROR(VLOOKUP(A12,Clientes_PDV!$A$2:$J$250,4,FALSE),"")) | E12: =IF(A12="","",IFERROR(VLOOKUP(A12,Clientes_PDV!$A$2:$J$250,7,FALSE),"")) | F12: =IF(A12="","",IFERROR(VLOOKUP(A12,Clientes_PDV!$A$2:$J$250,8,FALSE),"")) | G12: =IF(F12="","",TODAY()-F12) | H12: =IF(A12="","",IF(F12="","Sin visita",IF(G12<=IFERROR(VLOOKUP(E12,Inicio!$A$24:$B$26,2,FALSE),0),"Vigente","Atrasado"))) | I12: =IF(A12="","",SUMIFS(Ventas_SellIn!$L$2:$L$800,Ventas_SellIn!$D$2:$D$800,A12,Ventas_SellIn!$B$2:$B$800,">="&TODAY()-Inicio!$B$14)) | J12: =IF(A12="","",SUMIFS(SellOut_Jumbo!$F$2:$F$800,SellOut_Jumbo!$C$2:$C$800,D12,SellOut_Jumbo!$A$2:$A$800,">="&TODAY()-Inicio!$B$14)) | K12: =IF(A12="","",IF(I12=0,"Sin venta",IF(I12<Inicio!$B$15,"Venta baja","Venta OK"))) | L12: =IF(A12="","",COUNTIFS(Ventas_SellIn!$D$2:$D$800,A12,Ventas_SellIn!$R$2:$R$800,">0")) | M12: =IF(A12="","",SUMIFS(Ventas_SellIn!$R$2:$R$800,Ventas_SellIn!$D$2:$D$800,A12)) | N12: =IF(A12="","",IF(M12>=Inicio!$B$18,"Pendiente relevante",IF(M12>0,"Pendiente menor","Sin deuda"))) | O12: =IF(A12="","",SUMIFS(Stock_PDV!$H$2:$H$800,Stock_PDV!$A$2:$A$800,A12)) | P12: =IF(A12="","",IF(O12<=Inicio!$B$16,"Crítico",IF(O12<=Inicio!$B$17,"Observar","OK"))) | Q12: =IF(A12="","",IF(OR(H12="Atrasado",K12="Sin venta",N12="Pendiente relevante",P12="Crítico"),"Alta",IF(OR(K12="Venta baja",N12="Pendiente menor",P12="Observar"),"Media","Baja"))) | R12: =IF(A12="","",IF(Q12="Alta","Gestionar esta semana",IF(Q12="Media","Hacer seguimiento","Mantener"))) | S12: =IF(A12="","",IF(I12=0,"Sin venta",IF(I12>=cfg_VentaAlta,"Alta",IF(I12<cfg_VentaBaja,"Baja","Media"))))
A13: =IF(Clientes_PDV!A13="","",Clientes_PDV!A13) | B13: =IF(A13="","",IFERROR(VLOOKUP(A13,Clientes_PDV!$A$2:$J$250,2,FALSE),"")) | C13: =IF(A13="","",IFERROR(VLOOKUP(A13,Clientes_PDV!$A$2:$J$250,3,FALSE),"")) | D13: =IF(A13="","",IFERROR(VLOOKUP(A13,Clientes_PDV!$A$2:$J$250,4,FALSE),"")) | E13: =IF(A13="","",IFERROR(VLOOKUP(A13,Clientes_PDV!$A$2:$J$250,7,FALSE),"")) | F13: =IF(A13="","",IFERROR(VLOOKUP(A13,Clientes_PDV!$A$2:$J$250,8,FALSE),"")) | G13: =IF(F13="","",TODAY()-F13) | H13: =IF(A13="","",IF(F13="","Sin visita",IF(G13<=IFERROR(VLOOKUP(E13,Inicio!$A$24:$B$26,2,FALSE),0),"Vigente","Atrasado"))) | I13: =IF(A13="","",SUMIFS(Ventas_SellIn!$L$2:$L$800,Ventas_SellIn!$D$2:$D$800,A13,Ventas_SellIn!$B$2:$B$800,">="&TODAY()-Inicio!$B$14)) | J13: =IF(A13="","",SUMIFS(SellOut_Jumbo!$F$2:$F$800,SellOut_Jumbo!$C$2:$C$800,D13,SellOut_Jumbo!$A$2:$A$800,">="&TODAY()-Inicio!$B$14)) | K13: =IF(A13="","",IF(I13=0,"Sin venta",IF(I13<Inicio!$B$15,"Venta baja","Venta OK"))) | L13: =IF(A13="","",COUNTIFS(Ventas_SellIn!$D$2:$D$800,A13,Ventas_SellIn!$R$2:$R$800,">0")) | M13: =IF(A13="","",SUMIFS(Ventas_SellIn!$R$2:$R$800,Ventas_SellIn!$D$2:$D$800,A13)) | N13: =IF(A13="","",IF(M13>=Inicio!$B$18,"Pendiente relevante",IF(M13>0,"Pendiente menor","Sin deuda"))) | O13: =IF(A13="","",SUMIFS(Stock_PDV!$H$2:$H$800,Stock_PDV!$A$2:$A$800,A13)) | P13: =IF(A13="","",IF(O13<=Inicio!$B$16,"Crítico",IF(O13<=Inicio!$B$17,"Observar","OK"))) | Q13: =IF(A13="","",IF(OR(H13="Atrasado",K13="Sin venta",N13="Pendiente relevante",P13="Crítico"),"Alta",IF(OR(K13="Venta baja",N13="Pendiente menor",P13="Observar"),"Media","Baja"))) | R13: =IF(A13="","",IF(Q13="Alta","Gestionar esta semana",IF(Q13="Media","Hacer seguimiento","Mantener"))) | S13: =IF(A13="","",IF(I13=0,"Sin venta",IF(I13>=cfg_VentaAlta,"Alta",IF(I13<cfg_VentaBaja,"Baja","Media"))))
... A250: =IF(Clientes_PDV!A250="","",Clientes_PDV!A250) | B250: =IF(A250="","",IFERROR(VLOOKUP(A250,Clientes_PDV!$A$2:$J$250,2,FALSE),"")) | C250: =IF(A250="","",IFERROR(VLOOKUP(A250,Clientes_PDV!$A$2:$J$250,3,FALSE),"")) | D250: =IF(A250="","",IFERROR(VLOOKUP(A250,Clientes_PDV!$A$2:$J$250,4,FALSE),"")) | E250: =IF(A250="","",IFERROR(VLOOKUP(A250,Clientes_PDV!$A$2:$J$250,7,FALSE),"")) | F250: =IF(A250="","",IFERROR(VLOOKUP(A250,Clientes_PDV!$A$2:$J$250,8,FALSE),"")) | G250: =IF(F250="","",TODAY()-F250) | H250: =IF(A250="","",IF(F250="","Sin visita",IF(G250<=IFERROR(VLOOKUP(E250,Inicio!$A$24:$B$26,2,FALSE),0),"Vigente","Atrasado"))) | I250: =IF(A250="","",SUMIFS(Ventas_SellIn!$L$2:$L$800,Ventas_SellIn!$D$2:$D$800,A250,Ventas_SellIn!$B$2:$B$800,">="&TODAY()-Inicio!$B$14)) | J250: =IF(A250="","",SUMIFS(SellOut_Jumbo!$F$2:$F$800,SellOut_Jumbo!$C$2:$C$800,D250,SellOut_Jumbo!$A$2:$A$800,">="&TODAY()-Inicio!$B$14)) | K250: =IF(A250="","",IF(I250=0,"Sin venta",IF(I250<Inicio!$B$15,"Venta baja","Venta OK"))) | L250: =IF(A250="","",COUNTIFS(Ventas_SellIn!$D$2:$D$800,A250,Ventas_SellIn!$R$2:$R$800,">0")) | M250: =IF(A250="","",SUMIFS(Ventas_SellIn!$R$2:$R$800,Ventas_SellIn!$D$2:$D$800,A250)) | N250: =IF(A250="","",IF(M250>=Inicio!$B$18,"Pendiente relevante",IF(M250>0,"Pendiente menor","Sin deuda"))) | O250: =IF(A250="","",SUMIFS(Stock_PDV!$H$2:$H$800,Stock_PDV!$A$2:$A$800,A250)) | P250: =IF(A250="","",IF(O250<=Inicio!$B$16,"Crítico",IF(O250<=Inicio!$B$17,"Observar","OK"))) | Q250: =IF(A250="","",IF(OR(H250="Atrasado",K250="Sin venta",N250="Pendiente relevante",P250="Crítico"),"Alta",IF(OR(K250="Venta baja",N250="Pendiente menor",P250="Observar"),"Media","Baja"))) | R250: =IF(A250="","",IF(Q250="Alta","Gestionar esta semana",IF(Q250="Media","Hacer seguimiento","Mantener"))) | S250: =IF(A250="","",IF(I250=0,"Sin venta",IF(I250>=cfg_VentaAlta,"Alta",IF(I250<cfg_VentaBaja,"Baja","Media"))))

Sheet Clientes_PDV
A1: PDV_ID | B1: Cliente | C1: Canal | D1: Punto de venta | E1: Comuna | F1: Región | G1: Frecuencia visita | H1: Última visita | I1: Estado cliente | J1: Observaciones | L1: ⚙ Configuración
A2: PDV-001 | B2: Jumbo | C2: Retail | D2: Jumbo Bilbao | E2: Las Condes | F2: RM | G2: Semanal | H2: 46209 | I2: Activo | J2: Sala prioritaria
A3: PDV-002 | B3: Jumbo | C3: Retail | D3: Jumbo Kennedy | E3: Vitacura | F3: RM | G3: Semanal | H3: 46201 | I3: Activo | J3: Revisar reposición
A4: PDV-003 | B4: Jumbo | C4: Retail | D4: Jumbo La Reina | E4: La Reina | F4: RM | G4: Quincenal | H4: 46197 | I4: Activo
A5: PDV-004 | B5: Get It | C5: Conveniencia | D5: Get It Apoquindo | E5: Las Condes | F5: RM | G5: Semanal | H5: 46206 | I5: Activo
A6: PDV-005 | B6: Get It | C6: Conveniencia | D6: Get It Vitacura | E6: Vitacura | F6: RM | G6: Quincenal | H6: 46191 | I6: Activo
A7: PDV-006 | B7: Aldea Nativa | C7: Especializadas | D7: Aldea Nativa Providencia | E7: Providencia | F7: RM | G7: Mensual | H7: 46182 | I7: Activo
A8: PDV-007 | B8: All Nutrition | C8: Especializadas | D8: All Nutrition La Reina | E8: La Reina | F8: RM | G8: Mensual | H8: 46167 | I8: Activo | J8: Sin venta reciente
A9: PDV-008 | B9: Farmacia Ahumada | C9: Farmacias | D9: Ahumada Los Dominicos | E9: Las Condes | F9: RM | G9: Quincenal | H9: 46203 | I9: Prospecto
A10: PDV-009 | B10: Cruz Verde | C10: Farmacias | D10: Cruz Verde Vitacura | E10: Vitacura | F10: RM | G10: Quincenal | H10: 46194 | I10: Activo
A11: PDV-010 | B11: Sodexo | C11: Corporativo | D11: Sodexo Casa Matriz | E11: Providencia | F11: RM | G11: Mensual | H11: 46185 | I11: Activo
A12: PDV-011 | B12: Tres Toques | C12: HORECA | D12: Tres Toques Vitacura | E12: Vitacura | F12: RM | G12: Mensual | H12: 46204 | I12: Activo
A13: PDV-012 | B13: Mundo del Vino | C13: Especializadas | D13: Mundo del Vino Escuela Militar | E13: Las Condes | F13: RM | G13: Quincenal | H13: 46207 | I13: Activo

Sheet Ventas_SellIn
A1: ID_venta | B1: Fecha factura | C1: N° factura | D1: PDV_ID | E1: Cliente | F1: Canal | G1: Punto de venta | H1: SKU | I1: Descripción SKU | J1: Cantidad facturada | K1: Precio neto unit. facturado | L1: Venta neta | M1: IVA | N1: Venta bruta | O1: Fecha vencimiento | P1: Status pago | Q1: Monto pagado | R1: Monto pendiente | S1: Estado factura | T1: Observaciones | U1: Año | V1: Mes | W1: Día | X1: Periodo | Y1: Barras equiv | Z1: ⚙ Configuración
A2: V-0001 | B2: 46199 | C2: F-202607001 | D2: PDV-010 | E2: =IFERROR(VLOOKUP(D2,Clientes_PDV!$A$2:$J$250,2,FALSE),"") | F2: =IFERROR(VLOOKUP(D2,Clientes_PDV!$A$2:$J$250,3,FALSE),"") | G2: =IFERROR(VLOOKUP(D2,Clientes_PDV!$A$2:$J$250,4,FALSE),"") | H2: NUVA-BAR-BM-U-01 | I2: =IFERROR(VLOOKUP(H2,Maestro_SKU!$A$2:$P$500,2,FALSE),"") | J2: 20 | K2: 911 | L2: =IF(OR(J2="",K2=""),"",J2*K2) | M2: =IF(L2="","",L2*Inicio!$B$13) | N2: =IF(L2="","",L2+M2) | O2: 46244 | P2: Parcial | Q2: 14349 | R2: =IF(N2="","",MAX(N2-Q2,0)) | S2: =IF(A2="","",IF(OR(P2="Pagada",R2=0),"Pagada",IF(O2<TODAY(),"Vencida",IF(O2<=TODAY()+Inicio!$B$19,"Próxima a vencer","Vigente")))) | U2: =IF($B2="","",YEAR($B2)) | V2: =IF($B2="","",MONTH($B2)) | W2: =IF($B2="","",DAY($B2)) | X2: =IF($B2="","",YEAR($B2)&"-"&TEXT(MONTH($B2),"00")) | Y2: =IF(OR($H2="",$J2=""),"",$J2*IFERROR(VLOOKUP($H2,Maestro_SKU!$A$2:$P$500,12,FALSE),1))
A3: V-0002 | B3: 46208 | C3: F-202607002 | D3: PDV-011 | E3: =IFERROR(VLOOKUP(D3,Clientes_PDV!$A$2:$J$250,2,FALSE),"") | F3: =IFERROR(VLOOKUP(D3,Clientes_PDV!$A$2:$J$250,3,FALSE),"") | G3: =IFERROR(VLOOKUP(D3,Clientes_PDV!$A$2:$J$250,4,FALSE),"") | H3: NUVA-BAR-CC-U-01 | I3: =IFERROR(VLOOKUP(H3,Maestro_SKU!$A$2:$P$500,2,FALSE),"") | J3: 4 | K3: 948 | L3: =IF(OR(J3="",K3=""),"",J3*K3) | M3: =IF(L3="","",L3*Inicio!$B$13) | N3: =IF(L3="","",L3+M3) | O3: 46223 | P3: Vencida | Q3: 0 | R3: =IF(N3="","",MAX(N3-Q3,0)) | S3: =IF(A3="","",IF(OR(P3="Pagada",R3=0),"Pagada",IF(O3<TODAY(),"Vencida",IF(O3<=TODAY()+Inicio!$B$19,"Próxima a vencer","Vigente")))) | U3: =IF($B3="","",YEAR($B3)) | V3: =IF($B3="","",MONTH($B3)) | W3: =IF($B3="","",DAY($B3)) | X3: =IF($B3="","",YEAR($B3)&"-"&TEXT(MONTH($B3),"00")) | Y3: =IF(OR($H3="",$J3=""),"",$J3*IFERROR(VLOOKUP($H3,Maestro_SKU!$A$2:$P$500,12,FALSE),1))
A4: V-0003 | B4: 46174 | C4: F-202607003 | D4: PDV-012 | E4: =IFERROR(VLOOKUP(D4,Clientes_PDV!$A$2:$J$250,2,FALSE),"") | F4: =IFERROR(VLOOKUP(D4,Clientes_PDV!$A$2:$J$250,3,FALSE),"") | G4: =IFERROR(VLOOKUP(D4,Clientes_PDV!$A$2:$J$250,4,FALSE),"") | H4: NUVA-BAR-CC-BX-04 | I4: =IFERROR(VLOOKUP(H4,Maestro_SKU!$A$2:$P$500,2,FALSE),"") | J4: 4 | K4: 3807 | L4: =IF(OR(J4="",K4=""),"",J4*K4) | M4: =IF(L4="","",L4*Inicio!$B$13) | N4: =IF(L4="","",L4+M4) | O4: 46204 | P4: Pagada | Q4: 18121.32 | R4: =IF(N4="","",MAX(N4-Q4,0)) | S4: =IF(A4="","",IF(OR(P4="Pagada",R4=0),"Pagada",IF(O4<TODAY(),"Vencida",IF(O4<=TODAY()+Inicio!$B$19,"Próxima a vencer","Vigente")))) | U4: =IF($B4="","",YEAR($B4)) | V4: =IF($B4="","",MONTH($B4)) | W4: =IF($B4="","",DAY($B4)) | X4: =IF($B4="","",YEAR($B4)&"-"&TEXT(MONTH($B4),"00")) | Y4: =IF(OR($H4="",$J4=""),"",$J4*IFERROR(VLOOKUP($H4,Maestro_SKU!$A$2:$P$500,12,FALSE),1))
A5: V-0004 | B5: 46170 | C5: F-202607004 | D5: PDV-005 | E5: =IFERROR(VLOOKUP(D5,Clientes_PDV!$A$2:$J$250,2,FALSE),"") | F5: =IFERROR(VLOOKUP(D5,Clientes_PDV!$A$2:$J$250,3,FALSE),"") | G5: =IFERROR(VLOOKUP(D5,Clientes_PDV!$A$2:$J$250,4,FALSE),"") | H5: NUVA-BAR-PB-BX-04 | I5: =IFERROR(VLOOKUP(H5,Maestro_SKU!$A$2:$P$500,2,FALSE),"") | J5: 24 | K5: 3130 | L5: =IF(OR(J5="",K5=""),"",J5*K5) | M5: =IF(L5="","",L5*Inicio!$B$13) | N5: =IF(L5="","",L5+M5) | O5: 46200 | P5: Pagada | Q5: 89392.8 | R5: =IF(N5="","",MAX(N5-Q5,0)) | S5: =IF(A5="","",IF(OR(P5="Pagada",R5=0),"Pagada",IF(O5<TODAY(),"Vencida",IF(O5<=TODAY()+Inicio!$B$19,"Próxima a vencer","Vigente")))) | U5: =IF($B5="","",YEAR($B5)) | V5: =IF($B5="","",MONTH($B5)) | W5: =IF($B5="","",DAY($B5)) | X5: =IF($B5="","",YEAR($B5)&"-"&TEXT(MONTH($B5),"00")) | Y5: =IF(OR($H5="",$J5=""),"",$J5*IFERROR(VLOOKUP($H5,Maestro_SKU!$A$2:$P$500,12,FALSE),1))
A6: V-0005 | B6: 46197 | C6: F-202607005 | D6: PDV-004 | E6: =IFERROR(VLOOKUP(D6,Clientes_PDV!$A$2:$J$250,2,FALSE),"") | F6: =IFERROR(VLOOKUP(D6,Clientes_PDV!$A$2:$J$250,3,FALSE),"") | G6: =IFERROR(VLOOKUP(D6,Clientes_PDV!$A$2:$J$250,4,FALSE),"") | H6: NUVA-BAR-PB-CS-24 | I6: =IFERROR(VLOOKUP(H6,Maestro_SKU!$A$2:$P$500,2,FALSE),"") | J6: 20 | K6: 17022 | L6: =IF(OR(J6="",K6=""),"",J6*K6) | M6: =IF(L6="","",L6*Inicio!$B$13) | N6: =IF(L6="","",L6+M6) | O6: 46212 | P6: Pagada | Q6: 405123.6 | R6: =IF(N6="","",MAX(N6-Q6,0)) | S6: =IF(A6="","",IF(OR(P6="Pagada",R6=0),"Pagada",IF(O6<TODAY(),"Vencida",IF(O6<=TODAY()+Inicio!$B$19,"Próxima a vencer","Vigente")))) | U6: =IF($B6="","",YEAR($B6)) | V6: =IF($B6="","",MONTH($B6)) | W6: =IF($B6="","",DAY($B6)) | X6: =IF($B6="","",YEAR($B6)&"-"&TEXT(MONTH($B6),"00")) | Y6: =IF(OR($H6="",$J6=""),"",$J6*IFERROR(VLOOKUP($H6,Maestro_SKU!$A$2:$P$500,12,FALSE),1))
A7: V-0006 | B7: 46177 | C7: F-202607006 | D7: PDV-005 | E7: =IFERROR(VLOOKUP(D7,Clientes_PDV!$A$2:$J$250,2,FALSE),"") | F7: =IFERROR(VLOOKUP(D7,Clientes_PDV!$A$2:$J$250,3,FALSE),"") | G7: =IFERROR(VLOOKUP(D7,Clientes_PDV!$A$2:$J$250,4,FALSE),"") | H7: NUVA-BAR-CC-CS-24 | I7: =IFERROR(VLOOKUP(H7,Maestro_SKU!$A$2:$P$500,2,FALSE),"") | J7: 15 | K7: 17698 | L7: =IF(OR(J7="",K7=""),"",J7*K7) | M7: =IF(L7="","",L7*Inicio!$B$13) | N7: =IF(L7="","",L7+M7) | O7: 46222 | P7: Pagada | Q7: 315909.3 | R7: =IF(N7="","",MAX(N7-Q7,0)) | S7: =IF(A7="","",IF(OR(P7="Pagada",R7=0),"Pagada",IF(O7<TODAY(),"Vencida",IF(O7<=TODAY()+Inicio!$B$19,"Próxima a vencer","Vigente")))) | U7: =IF($B7="","",YEAR($B7)) | V7: =IF($B7="","",MONTH($B7)) | W7: =IF($B7="","",DAY($B7)) | X7: =IF($B7="","",YEAR($B7)&"-"&TEXT(MONTH($B7),"00")) | Y7: =IF(OR($H7="",$J7=""),"",$J7*IFERROR(VLOOKUP($H7,Maestro_SKU!$A$2:$P$500,12,FALSE),1))
A8: V-0007 | B8: 46197 | C8: F-202607007 | D8: PDV-002 | E8: =IFERROR(VLOOKUP(D8,Clientes_PDV!$A$2:$J$250,2,FALSE),"") | F8: =IFERROR(VLOOKUP(D8,Clientes_PDV!$A$2:$J$250,3,FALSE),"") | G8: =IFERROR(VLOOKUP(D8,Clientes_PDV!$A$2:$J$250,4,FALSE),"") | H8: NUVA-BAR-CC-BX-04 | I8: =IFERROR(VLOOKUP(H8,Maestro_SKU!$A$2:$P$500,2,FALSE),"") | J8: 8 | K8: 3268 | L8: =IF(OR(J8="",K8=""),"",J8*K8) | M8: =IF(L8="","",L8*Inicio!$B$13) | N8: =IF(L8="","",L8+M8) | O8: 46197 | P8: Pagada | Q8: 31111.36 | R8: =IF(N8="","",MAX(N8-Q8,0)) | S8: =IF(A8="","",IF(OR(P8="Pagada",R8=0),"Pagada",IF(O8<TODAY(),"Vencida",IF(O8<=TODAY()+Inicio!$B$19,"Próxima a vencer","Vigente")))) | U8: =IF($B8="","",YEAR($B8)) | V8: =IF($B8="","",MONTH($B8)) | W8: =IF($B8="","",DAY($B8)) | X8: =IF($B8="","",YEAR($B8)&"-"&TEXT(MONTH($B8),"00")) | Y8: =IF(OR($H8="",$J8=""),"",$J8*IFERROR(VLOOKUP($H8,Maestro_SKU!$A$2:$P$500,12,FALSE),1))
A9: V-0008 | B9: 46152 | C9: F-202607008 | D9: PDV-005 | E9: =IFERROR(VLOOKUP(D9,Clientes_PDV!$A$2:$J$250,2,FALSE),"") | F9: =IFERROR(VLOOKUP(D9,Clientes_PDV!$A$2:$J$250,3,FALSE),"") | G9: =IFERROR(VLOOKUP(D9,Clientes_PDV!$A$2:$J$250,4,FALSE),"") | H9: NUVA-BAR-PB-U-01 | I9: =IFERROR(VLOOKUP(H9,Maestro_SKU!$A$2:$P$500,2,FALSE),"") | J9: 6 | K9: 745 | L9: =IF(OR(J9="",K9=""),"",J9*K9) | M9: =IF(L9="","",L9*Inicio!$B$13) | N9: =IF(L9="","",L9+M9) | O9: 46182 | P9: Vencida | Q9: 0 | R9: =IF(N9="","",MAX(N9-Q9,0)) | S9: =IF(A9="","",IF(OR(P9="Pagada",R9=0),"Pagada",IF(O9<TODAY(),"Vencida",IF(O9<=TODAY()+Inicio!$B$19,"Próxima a vencer","Vigente")))) | U9: =IF($B9="","",YEAR($B9)) | V9: =IF($B9="","",MONTH($B9)) | W9: =IF($B9="","",DAY($B9)) | X9: =IF($B9="","",YEAR($B9)&"-"&TEXT(MONTH($B9),"00")) | Y9: =IF(OR($H9="",$J9=""),"",$J9*IFERROR(VLOOKUP($H9,Maestro_SKU!$A$2:$P$500,12,FALSE),1))
A10: V-0009 | B10: 46161 | C10: F-202607009 | D10: PDV-003 | E10: =IFERROR(VLOOKUP(D10,Clientes_PDV!$A$2:$J$250,2,FALSE),"") | F10: =IFERROR(VLOOKUP(D10,Clientes_PDV!$A$2:$J$250,3,FALSE),"") | G10: =IFERROR(VLOOKUP(D10,Clientes_PDV!$A$2:$J$250,4,FALSE),"") | H10: NUVA-BAR-PB-U-01 | I10: =IFERROR(VLOOKUP(H10,Maestro_SKU!$A$2:$P$500,2,FALSE),"") | J10: 6 | K10: 851 | L10: =IF(OR(J10="",K10=""),"",J10*K10) | M10: =IF(L10="","",L10*Inicio!$B$13) | N10: =IF(L10="","",L10+M10) | O10: 46176 | P10: Vencida | Q10: 0 | R10: =IF(N10="","",MAX(N10-Q10,0)) | S10: =IF(A10="","",IF(OR(P10="Pagada",R10=0),"Pagada",IF(O10<TODAY(),"Vencida",IF(O10<=TODAY()+Inicio!$B$19,"Próxima a vencer","Vigente")))) | U10: =IF($B10="","",YEAR($B10)) | V10: =IF($B10="","",MONTH($B10)) | W10: =IF($B10="","",DAY($B10)) | X10: =IF($B10="","",YEAR($B10)&"-"&TEXT(MONTH($B10),"00")) | Y10: =IF(OR($H10="",$J10=""),"",$J10*IFERROR(VLOOKUP($H10,Maestro_SKU!$A$2:$P$500,12,FALSE),1))
A11: V-0010 | B11: 46203 | C11: F-202607010 | D11: PDV-007 | E11: =IFERROR(VLOOKUP(D11,Clientes_PDV!$A$2:$J$250,2,FALSE),"") | F11: =IFERROR(VLOOKUP(D11,Clientes_PDV!$A$2:$J$250,3,FALSE),"") | G11: =IFERROR(VLOOKUP(D11,Clientes_PDV!$A$2:$J$250,4,FALSE),"") | H11: NUVA-BAR-BM-CS-24 | I11: =IFERROR(VLOOKUP(H11,Maestro_SKU!$A$2:$P$500,2,FALSE),"") | J11: 24 | K11: 18767 | L11: =IF(OR(J11="",K11=""),"",J11*K11) | M11: =IF(L11="","",L11*Inicio!$B$13) | N11: =IF(L11="","",L11+M11) | O11: 46218 | P11: Parcial | Q11: 205558 | R11: =IF(N11="","",MAX(N11-Q11,0)) | S11: =IF(A11="","",IF(OR(P11="Pagada",R11=0),"Pagada",IF(O11<TODAY(),"Vencida",IF(O11<=TODAY()+Inicio!$B$19,"Próxima a vencer","Vigente")))) | U11: =IF($B11="","",YEAR($B11)) | V11: =IF($B11="","",MONTH($B11)) | W11: =IF($B11="","",DAY($B11)) | X11: =IF($B11="","",YEAR($B11)&"-"&TEXT(MONTH($B11),"00")) | Y11: =IF(OR($H11="",$J11=""),"",$J11*IFERROR(VLOOKUP($H11,Maestro_SKU!$A$2:$P$500,12,FALSE),1))
A12: V-0011 | B12: 46190 | C12: F-202607011 | D12: PDV-005 | E12: =IFERROR(VLOOKUP(D12,Clientes_PDV!$A$2:$J$250,2,FALSE),"") | F12: =IFERROR(VLOOKUP(D12,Clientes_PDV!$A$2:$J$250,3,FALSE),"") | G12: =IFERROR(VLOOKUP(D12,Clientes_PDV!$A$2:$J$250,4,FALSE),"") | H12: NUVA-BAR-CC-U-01 | I12: =IFERROR(VLOOKUP(H12,Maestro_SKU!$A$2:$P$500,2,FALSE),"") | J12: 8 | K12: 757 | L12: =IF(OR(J12="",K12=""),"",J12*K12) | M12: =IF(L12="","",L12*Inicio!$B$13) | N12: =IF(L12="","",L12+M12) | O12: 46220 | P12: Pagada | Q12: 7206.64 | R12: =IF(N12="","",MAX(N12-Q12,0)) | S12: =IF(A12="","",IF(OR(P12="Pagada",R12=0),"Pagada",IF(O12<TODAY(),"Vencida",IF(O12<=TODAY()+Inicio!$B$19,"Próxima a vencer","Vigente")))) | U12: =IF($B12="","",YEAR($B12)) | V12: =IF($B12="","",MONTH($B12)) | W12: =IF($B12="","",DAY($B12)) | X12: =IF($B12="","",YEAR($B12)&"-"&TEXT(MONTH($B12),"00")) | Y12: =IF(OR($H12="",$J12=""),"",$J12*IFERROR(VLOOKUP($H12,Maestro_SKU!$A$2:$P$500,12,FALSE),1))
A13: V-0012 | B13: 46197 | C13: F-202607012 | D13: PDV-001 | E13: =IFERROR(VLOOKUP(D13,Clientes_PDV!$A$2:$J$250,2,FALSE),"") | F13: =IFERROR(VLOOKUP(D13,Clientes_PDV!$A$2:$J$250,3,FALSE),"") | G13: =IFERROR(VLOOKUP(D13,Clientes_PDV!$A$2:$J$250,4,FALSE),"") | H13: NUVA-BAR-CC-CS-24 | I13: =IFERROR(VLOOKUP(H13,Maestro_SKU!$A$2:$P$500,2,FALSE),"") | J13: 4 | K13: 20929 | L13: =IF(OR(J13="",K13=""),"",J13*K13) | M13: =IF(L13="","",L13*Inicio!$B$13) | N13: =IF(L13="","",L13+M13) | O13: 46197 | P13: Pagada | Q13: 99622.04 | R13: =IF(N13="","",MAX(N13-Q13,0)) | S13: =IF(A13="","",IF(OR(P13="Pagada",R13=0),"Pagada",IF(O13<TODAY(),"Vencida",IF(O13<=TODAY()+Inicio!$B$19,"Próxima a vencer","Vigente")))) | U13: =IF($B13="","",YEAR($B13)) | V13: =IF($B13="","",MONTH($B13)) | W13: =IF($B13="","",DAY($B13)) | X13: =IF($B13="","",YEAR($B13)&"-"&TEXT(MONTH($B13),"00")) | Y13: =IF(OR($H13="",$J13=""),"",$J13*IFERROR(VLOOKUP($H13,Maestro_SKU!$A$2:$P$500,12,FALSE),1))
... A46: V-0045 | B46: 46170 | C46: F-202607045 | D46: PDV-009 | E46: =IFERROR(VLOOKUP(D46,Clientes_PDV!$A$2:$J$250,2,FALSE),"") | F46: =IFERROR(VLOOKUP(D46,Clientes_PDV!$A$2:$J$250,3,FALSE),"") | G46: =IFERROR(VLOOKUP(D46,Clientes_PDV!$A$2:$J$250,4,FALSE),"") | H46: NUVA-BAR-PB-CS-24 | I46: =IFERROR(VLOOKUP(H46,Maestro_SKU!$A$2:$P$500,2,FALSE),"") | J46: 10 | K46: 22036 | L46: =IF(OR(J46="",K46=""),"",J46*K46) | M46: =IF(L46="","",L46*Inicio!$B$13) | N46: =IF(L46="","",L46+M46) | O46: 46185 | P46: Vencida | Q46: 0 | R46: =IF(N46="","",MAX(N46-Q46,0)) | S46: =IF(A46="","",IF(OR(P46="Pagada",R46=0),"Pagada",IF(O46<TODAY(),"Vencida",IF(O46<=TODAY()+Inicio!$B$19,"Próxima a vencer","Vigente")))) | U46: =IF($B46="","",YEAR($B46)) | V46: =IF($B46="","",MONTH($B46)) | W46: =IF($B46="","",DAY($B46)) | X46: =IF($B46="","",YEAR($B46)&"-"&TEXT(MONTH($B46),"00")) | Y46: =IF(OR($H46="",$J46=""),"",$J46*IFERROR(VLOOKUP($H46,Maestro_SKU!$A$2:$P$500,12,FALSE),1))
E47: =IFERROR(VLOOKUP(D47,Clientes_PDV!$A$2:$J$250,2,FALSE),"") | F47: =IFERROR(VLOOKUP(D47,Clientes_PDV!$A$2:$J$250,3,FALSE),"") | G47: =IFERROR(VLOOKUP(D47,Clientes_PDV!$A$2:$J$250,4,FALSE),"") | I47: =IFERROR(VLOOKUP(H47,Maestro_SKU!$A$2:$P$500,2,FALSE),"") | L47: =IF(OR(J47="",K47=""),"",J47*K47) | M47: =IF(L47="","",L47*Inicio!$B$13) | N47: =IF(L47="","",L47+M47) | R47: =IF(N47="","",MAX(N47-Q47,0)) | S47: =IF(A47="","",IF(OR(P47="Pagada",R47=0),"Pagada",IF(O47<TODAY(),"Vencida",IF(O47<=TODAY()+Inicio!$B$19,"Próxima a vencer","Vigente")))) | U47: =IF($B47="","",YEAR($B47)) | V47: =IF($B47="","",MONTH($B47)) | W47: =IF($B47="","",DAY($B47)) | X47: =IF($B47="","",YEAR($B47)&"-"&TEXT(MONTH($B47),"00")) | Y47: =IF(OR($H47="",$J47=""),"",$J47*IFERROR(VLOOKUP($H47,Maestro_SKU!$A$2:$P$500,12,FALSE),1))
E48: =IFERROR(VLOOKUP(D48,Clientes_PDV!$A$2:$J$250,2,FALSE),"") | F48: =IFERROR(VLOOKUP(D48,Clientes_PDV!$A$2:$J$250,3,FALSE),"") | G48: =IFERROR(VLOOKUP(D48,Clientes_PDV!$A$2:$J$250,4,FALSE),"") | I48: =IFERROR(VLOOKUP(H48,Maestro_SKU!$A$2:$P$500,2,FALSE),"") | L48: =IF(OR(J48="",K48=""),"",J48*K48) | M48: =IF(L48="","",L48*Inicio!$B$13) | N48: =IF(L48="","",L48+M48) | R48: =IF(N48="","",MAX(N48-Q48,0)) | S48: =IF(A48="","",IF(OR(P48="Pagada",R48=0),"Pagada",IF(O48<TODAY(),"Vencida",IF(O48<=TODAY()+Inicio!$B$19,"Próxima a vencer","Vigente")))) | U48: =IF($B48="","",YEAR($B48)) | V48: =IF($B48="","",MONTH($B48)) | W48: =IF($B48="","",DAY($B48)) | X48: =IF($B48="","",YEAR($B48)&"-"&TEXT(MONTH($B48),"00")) | Y48: =IF(OR($H48="",$J48=""),"",$J48*IFERROR(VLOOKUP($H48,Maestro_SKU!$A$2:$P$500,12,FALSE),1))
E49: =IFERROR(VLOOKUP(D49,Clientes_PDV!$A$2:$J$250,2,FALSE),"") | F49: =IFERROR(VLOOKUP(D49,Clientes_PDV!$A$2:$J$250,3,FALSE),"") | G49: =IFERROR(VLOOKUP(D49,Clientes_PDV!$A$2:$J$250,4,FALSE),"") | I49: =IFERROR(VLOOKUP(H49,Maestro_SKU!$A$2:$P$500,2,FALSE),"") | L49: =IF(OR(J49="",K49=""),"",J49*K49) | M49: =IF(L49="","",L49*Inicio!$B$13) | N49: =IF(L49="","",L49+M49) | R49: =IF(N49="","",MAX(N49-Q49,0)) | S49: =IF(A49="","",IF(OR(P49="Pagada",R49=0),"Pagada",IF(O49<TODAY(),"Vencida",IF(O49<=TODAY()+Inicio!$B$19,"Próxima a vencer","Vigente")))) | U49: =IF($B49="","",YEAR($B49)) | V49: =IF($B49="","",MONTH($B49)) | W49: =IF($B49="","",DAY($B49)) | X49: =IF($B49="","",YEAR($B49)&"-"&TEXT(MONTH($B49),"00")) | Y49: =IF(OR($H49="",$J49=""),"",$J49*IFERROR(VLOOKUP($H49,Maestro_SKU!$A$2:$P$500,12,FALSE),1))
E50: =IFERROR(VLOOKUP(D50,Clientes_PDV!$A$2:$J$250,2,FALSE),"") | F50: =IFERROR(VLOOKUP(D50,Clientes_PDV!$A$2:$J$250,3,FALSE),"") | G50: =IFERROR(VLOOKUP(D50,Clientes_PDV!$A$2:$J$250,4,FALSE),"") | I50: =IFERROR(VLOOKUP(H50,Maestro_SKU!$A$2:$P$500,2,FALSE),"") | L50: =IF(OR(J50="",K50=""),"",J50*K50) | M50: =IF(L50="","",L50*Inicio!$B$13) | N50: =IF(L50="","",L50+M50) | R50: =IF(N50="","",MAX(N50-Q50,0)) | S50: =IF(A50="","",IF(OR(P50="Pagada",R50=0),"Pagada",IF(O50<TODAY(),"Vencida",IF(O50<=TODAY()+Inicio!$B$19,"Próxima a vencer","Vigente")))) | U50: =IF($B50="","",YEAR($B50)) | V50: =IF($B50="","",MONTH($B50)) | W50: =IF($B50="","",DAY($B50)) | X50: =IF($B50="","",YEAR($B50)&"-"&TEXT(MONTH($B50),"00")) | Y50: =IF(OR($H50="",$J50=""),"",$J50*IFERROR(VLOOKUP($H50,Maestro_SKU!$A$2:$P$500,12,FALSE),1))
E51: =IFERROR(VLOOKUP(D51,Clientes_PDV!$A$2:$J$250,2,FALSE),"") | F51: =IFERROR(VLOOKUP(D51,Clientes_PDV!$A$2:$J$250,3,FALSE),"") | G51: =IFERROR(VLOOKUP(D51,Clientes_PDV!$A$2:$J$250,4,FALSE),"") | I51: =IFERROR(VLOOKUP(H51,Maestro_SKU!$A$2:$P$500,2,FALSE),"") | L51: =IF(OR(J51="",K51=""),"",J51*K51) | M51: =IF(L51="","",L51*Inicio!$B$13) | N51: =IF(L51="","",L51+M51) | R51: =IF(N51="","",MAX(N51-Q51,0)) | S51: =IF(A51="","",IF(OR(P51="Pagada",R51=0),"Pagada",IF(O51<TODAY(),"Vencida",IF(O51<=TODAY()+Inicio!$B$19,"Próxima a vencer","Vigente")))) | U51: =IF($B51="","",YEAR($B51)) | V51: =IF($B51="","",MONTH($B51)) | W51: =IF($B51="","",DAY($B51)) | X51: =IF($B51="","",YEAR($B51)&"-"&TEXT(MONTH($B51),"00")) | Y51: =IF(OR($H51="",$J51=""),"",$J51*IFERROR(VLOOKUP($H51,Maestro_SKU!$A$2:$P$500,12,FALSE),1))
E52: =IFERROR(VLOOKUP(D52,Clientes_PDV!$A$2:$J$250,2,FALSE),"") | F52: =IFERROR(VLOOKUP(D52,Clientes_PDV!$A$2:$J$250,3,FALSE),"") | G52: =IFERROR(VLOOKUP(D52,Clientes_PDV!$A$2:$J$250,4,FALSE),"") | I52: =IFERROR(VLOOKUP(H52,Maestro_SKU!$A$2:$P$500,2,FALSE),"") | L52: =IF(OR(J52="",K52=""),"",J52*K52) | M52: =IF(L52="","",L52*Inicio!$B$13) | N52: =IF(L52="","",L52+M52) | R52: =IF(N52="","",MAX(N52-Q52,0)) | S52: =IF(A52="","",IF(OR(P52="Pagada",R52=0),"Pagada",IF(O52<TODAY(),"Vencida",IF(O52<=TODAY()+Inicio!$B$19,"Próxima a vencer","Vigente")))) | U52: =IF($B52="","",YEAR($B52)) | V52: =IF($B52="","",MONTH($B52)) | W52: =IF($B52="","",DAY($B52)) | X52: =IF($B52="","",YEAR($B52)&"-"&TEXT(MONTH($B52),"00")) | Y52: =IF(OR($H52="",$J52=""),"",$J52*IFERROR(VLOOKUP($H52,Maestro_SKU!$A$2:$P$500,12,FALSE),1))
E53: =IFERROR(VLOOKUP(D53,Clientes_PDV!$A$2:$J$250,2,FALSE),"") | F53: =IFERROR(VLOOKUP(D53,Clientes_PDV!$A$2:$J$250,3,FALSE),"") | G53: =IFERROR(VLOOKUP(D53,Clientes_PDV!$A$2:$J$250,4,FALSE),"") | I53: =IFERROR(VLOOKUP(H53,Maestro_SKU!$A$2:$P$500,2,FALSE),"") | L53: =IF(OR(J53="",K53=""),"",J53*K53) | M53: =IF(L53="","",L53*Inicio!$B$13) | N53: =IF(L53="","",L53+M53) | R53: =IF(N53="","",MAX(N53-Q53,0)) | S53: =IF(A53="","",IF(OR(P53="Pagada",R53=0),"Pagada",IF(O53<TODAY(),"Vencida",IF(O53<=TODAY()+Inicio!$B$19,"Próxima a vencer","Vigente")))) | U53: =IF($B53="","",YEAR($B53)) | V53: =IF($B53="","",MONTH($B53)) | W53: =IF($B53="","",DAY($B53)) | X53: =IF($B53="","",YEAR($B53)&"-"&TEXT(MONTH($B53),"00")) | Y53: =IF(OR($H53="",$J53=""),"",$J53*IFERROR(VLOOKUP($H53,Maestro_SKU!$A$2:$P$500,12,FALSE),1))
E54: =IFERROR(VLOOKUP(D54,Clientes_PDV!$A$2:$J$250,2,FALSE),"") | F54: =IFERROR(VLOOKUP(D54,Clientes_PDV!$A$2:$J$250,3,FALSE),"") | G54: =IFERROR(VLOOKUP(D54,Clientes_PDV!$A$2:$J$250,4,FALSE),"") | I54: =IFERROR(VLOOKUP(H54,Maestro_SKU!$A$2:$P$500,2,FALSE),"") | L54: =IF(OR(J54="",K54=""),"",J54*K54) | M54: =IF(L54="","",L54*Inicio!$B$13) | N54: =IF(L54="","",L54+M54) | R54: =IF(N54="","",MAX(N54-Q54,0)) | S54: =IF(A54="","",IF(OR(P54="Pagada",R54=0),"Pagada",IF(O54<TODAY(),"Vencida",IF(O54<=TODAY()+Inicio!$B$19,"Próxima a vencer","Vigente")))) | U54: =IF($B54="","",YEAR($B54)) | V54: =IF($B54="","",MONTH($B54)) | W54: =IF($B54="","",DAY($B54)) | X54: =IF($B54="","",YEAR($B54)&"-"&TEXT(MONTH($B54),"00")) | Y54: =IF(OR($H54="",$J54=""),"",$J54*IFERROR(VLOOKUP($H54,Maestro_SKU!$A$2:$P$500,12,FALSE),1))
E55: =IFERROR(VLOOKUP(D55,Clientes_PDV!$A$2:$J$250,2,FALSE),"") | F55: =IFERROR(VLOOKUP(D55,Clientes_PDV!$A$2:$J$250,3,FALSE),"") | G55: =IFERROR(VLOOKUP(D55,Clientes_PDV!$A$2:$J$250,4,FALSE),"") | I55: =IFERROR(VLOOKUP(H55,Maestro_SKU!$A$2:$P$500,2,FALSE),"") | L55: =IF(OR(J55="",K55=""),"",J55*K55) | M55: =IF(L55="","",L55*Inicio!$B$13) | N55: =IF(L55="","",L55+M55) | R55: =IF(N55="","",MAX(N55-Q55,0)) | S55: =IF(A55="","",IF(OR(P55="Pagada",R55=0),"Pagada",IF(O55<TODAY(),"Vencida",IF(O55<=TODAY()+Inicio!$B$19,"Próxima a vencer","Vigente")))) | U55: =IF($B55="","",YEAR($B55)) | V55: =IF($B55="","",MONTH($B55)) | W55: =IF($B55="","",DAY($B55)) | X55: =IF($B55="","",YEAR($B55)&"-"&TEXT(MONTH($B55),"00")) | Y55: =IF(OR($H55="",$J55=""),"",$J55*IFERROR(VLOOKUP($H55,Maestro_SKU!$A$2:$P$500,12,FALSE),1))
E56: =IFERROR(VLOOKUP(D56,Clientes_PDV!$A$2:$J$250,2,FALSE),"") | F56: =IFERROR(VLOOKUP(D56,Clientes_PDV!$A$2:$J$250,3,FALSE),"") | G56: =IFERROR(VLOOKUP(D56,Clientes_PDV!$A$2:$J$250,4,FALSE),"") | I56: =IFERROR(VLOOKUP(H56,Maestro_SKU!$A$2:$P$500,2,FALSE),"") | L56: =IF(OR(J56="",K56=""),"",J56*K56) | M56: =IF(L56="","",L56*Inicio!$B$13) | N56: =IF(L56="","",L56+M56) | R56: =IF(N56="","",MAX(N56-Q56,0)) | S56: =IF(A56="","",IF(OR(P56="Pagada",R56=0),"Pagada",IF(O56<TODAY(),"Vencida",IF(O56<=TODAY()+Inicio!$B$19,"Próxima a vencer","Vigente")))) | U56: =IF($B56="","",YEAR($B56)) | V56: =IF($B56="","",MONTH($B56)) | W56: =IF($B56="","",DAY($B56)) | X56: =IF($B56="","",YEAR($B56)&"-"&TEXT(MONTH($B56),"00")) | Y56: =IF(OR($H56="",$J56=""),"",$J56*IFERROR(VLOOKUP($H56,Maestro_SKU!$A$2:$P$500,12,FALSE),1))
E57: =IFERROR(VLOOKUP(D57,Clientes_PDV!$A$2:$J$250,2,FALSE),"") | F57: =IFERROR(VLOOKUP(D57,Clientes_PDV!$A$2:$J$250,3,FALSE),"") | G57: =IFERROR(VLOOKUP(D57,Clientes_PDV!$A$2:$J$250,4,FALSE),"") | I57: =IFERROR(VLOOKUP(H57,Maestro_SKU!$A$2:$P$500,2,FALSE),"") | L57: =IF(OR(J57="",K57=""),"",J57*K57) | M57: =IF(L57="","",L57*Inicio!$B$13) | N57: =IF(L57="","",L57+M57) | R57: =IF(N57="","",MAX(N57-Q57,0)) | S57: =IF(A57="","",IF(OR(P57="Pagada",R57=0),"Pagada",IF(O57<TODAY(),"Vencida",IF(O57<=TODAY()+Inicio!$B$19,"Próxima a vencer","Vigente")))) | U57: =IF($B57="","",YEAR($B57)) | V57: =IF($B57="","",MONTH($B57)) | W57: =IF($B57="","",DAY($B57)) | X57: =IF($B57="","",YEAR($B57)&"-"&TEXT(MONTH($B57),"00")) | Y57: =IF(OR($H57="",$J57=""),"",$J57*IFERROR(VLOOKUP($H57,Maestro_SKU!$A$2:$P$500,12,FALSE),1))
E58: =IFERROR(VLOOKUP(D58,Clientes_PDV!$A$2:$J$250,2,FALSE),"") | F58: =IFERROR(VLOOKUP(D58,Clientes_PDV!$A$2:$J$250,3,FALSE),"") | G58: =IFERROR(VLOOKUP(D58,Clientes_PDV!$A$2:$J$250,4,FALSE),"") | I58: =IFERROR(VLOOKUP(H58,Maestro_SKU!$A$2:$P$500,2,FALSE),"") | L58: =IF(OR(J58="",K58=""),"",J58*K58) | M58: =IF(L58="","",L58*Inicio!$B$13) | N58: =IF(L58="","",L58+M58) | R58: =IF(N58="","",MAX(N58-Q58,0)) | S58: =IF(A58="","",IF(OR(P58="Pagada",R58=0),"Pagada",IF(O58<TODAY(),"Vencida",IF(O58<=TODAY()+Inicio!$B$19,"Próxima a vencer","Vigente")))) | U58: =IF($B58="","",YEAR($B58)) | V58: =IF($B58="","",MONTH($B58)) | W58: =IF($B58="","",DAY($B58)) | X58: =IF($B58="","",YEAR($B58)&"-"&TEXT(MONTH($B58),"00")) | Y58: =IF(OR($H58="",$J58=""),"",$J58*IFERROR(VLOOKUP($H58,Maestro_SKU!$A$2:$P$500,12,FALSE),1))
... E800: =IFERROR(VLOOKUP(D800,Clientes_PDV!$A$2:$J$250,2,FALSE),"") | F800: =IFERROR(VLOOKUP(D800,Clientes_PDV!$A$2:$J$250,3,FALSE),"") | G800: =IFERROR(VLOOKUP(D800,Clientes_PDV!$A$2:$J$250,4,FALSE),"") | I800: =IFERROR(VLOOKUP(H800,Maestro_SKU!$A$2:$P$500,2,FALSE),"") | L800: =IF(OR(J800="",K800=""),"",J800*K800) | M800: =IF(L800="","",L800*Inicio!$B$13) | N800: =IF(L800="","",L800+M800) | R800: =IF(N800="","",MAX(N800-Q800,0)) | S800: =IF(A800="","",IF(OR(P800="Pagada",R800=0),"Pagada",IF(O800<TODAY(),"Vencida",IF(O800<=TODAY()+Inicio!$B$19,"Próxima a vencer","Vigente")))) | U800: =IF($B800="","",YEAR($B800)) | V800: =IF($B800="","",MONTH($B800)) | W800: =IF($B800="","",DAY($B800)) | X800: =IF($B800="","",YEAR($B800)&"-"&TEXT(MONTH($B800),"00")) | Y800: =IF(OR($H800="",$J800=""),"",$J800*IFERROR(VLOOKUP($H800,Maestro_SKU!$A$2:$P$500,12,FALSE),1))

Sheet Margen_Frontal
A1: Margen frontal | Simulador separado de ventas | L1: ⚙ Configuración
A2: Esta hoja NO modifica Ventas_SellIn ni Cobertura. Sirve para preparar negociación de precio antes de facturar.
A4: 1) Calcular precio sugerido desde PVP pensado y margen objetivo
A5: Cliente | B5: Canal | C5: SKU opcional | D5: PVP bruto pensado | E5: Margen frontal objetivo | F5: PVP neto calculado | G5: Precio neto sugerido | H5: Precio bruto equivalente | I5: Margen calculado | J5: Comentario
A6: Get It | B6: Conveniencia | C6: NUVA-BAR-CC-U-01 | D6: 1990 | E6: 0.4 | F6: =IF(D6="","",D6/(1+Inicio!$B$13)) | G6: =IF(OR(F6="",E6=""),"",F6*(1-E6)) | H6: =IF(G6="","",G6*(1+Inicio!$B$13)) | I6: =IF(OR(F6="",G6=""),"",(F6-G6)/F6) | J6: Ejemplo: si Get It pide 40% de margen frontal
A7: Jumbo | B7: Retail | C7: NUVA-BAR-BM-BX-04 | D7: 5990 | E7: 0.45 | F7: =IF(D7="","",D7/(1+Inicio!$B$13)) | G7: =IF(OR(F7="",E7=""),"",F7*(1-E7)) | H7: =IF(G7="","",G7*(1+Inicio!$B$13)) | I7: =IF(OR(F7="",G7=""),"",(F7-G7)/F7) | J7: Ejemplo retail estuche x4
A8: Farmacia Ahumada | B8: Farmacias | C8: NUVA-BAR-PB-U-01 | D8: 1990 | E8: 0.4 | F8: =IF(D8="","",D8/(1+Inicio!$B$13)) | G8: =IF(OR(F8="",E8=""),"",F8*(1-E8)) | H8: =IF(G8="","",G8*(1+Inicio!$B$13)) | I8: =IF(OR(F8="",G8=""),"",(F8-G8)/F8) | J8: Ejemplo farmacias
F9: =IF(D9="","",D9/(1+Inicio!$B$13)) | G9: =IF(OR(F9="",E9=""),"",F9*(1-E9)) | H9: =IF(G9="","",G9*(1+Inicio!$B$13)) | I9: =IF(OR(F9="",G9=""),"",(F9-G9)/F9)
F10: =IF(D10="","",D10/(1+Inicio!$B$13)) | G10: =IF(OR(F10="",E10=""),"",F10*(1-E10)) | H10: =IF(G10="","",G10*(1+Inicio!$B$13)) | I10: =IF(OR(F10="",G10=""),"",(F10-G10)/F10)
F11: =IF(D11="","",D11/(1+Inicio!$B$13)) | G11: =IF(OR(F11="",E11=""),"",F11*(1-E11)) | H11: =IF(G11="","",G11*(1+Inicio!$B$13)) | I11: =IF(OR(F11="",G11=""),"",(F11-G11)/F11)
F12: =IF(D12="","",D12/(1+Inicio!$B$13)) | G12: =IF(OR(F12="",E12=""),"",F12*(1-E12)) | H12: =IF(G12="","",G12*(1+Inicio!$B$13)) | I12: =IF(OR(F12="",G12=""),"",(F12-G12)/F12)
F13: =IF(D13="","",D13/(1+Inicio!$B$13)) | G13: =IF(OR(F13="",E13=""),"",F13*(1-E13)) | H13: =IF(G13="","",G13*(1+Inicio!$B$13)) | I13: =IF(OR(F13="",G13=""),"",(F13-G13)/F13)
F14: =IF(D14="","",D14/(1+Inicio!$B$13)) | G14: =IF(OR(F14="",E14=""),"",F14*(1-E14)) | H14: =IF(G14="","",G14*(1+Inicio!$B$13)) | I14: =IF(OR(F14="",G14=""),"",(F14-G14)/F14)
F15: =IF(D15="","",D15/(1+Inicio!$B$13)) | G15: =IF(OR(F15="",E15=""),"",F15*(1-E15)) | H15: =IF(G15="","",G15*(1+Inicio!$B$13)) | I15: =IF(OR(F15="",G15=""),"",(F15-G15)/F15)
F16: =IF(D16="","",D16/(1+Inicio!$B$13)) | G16: =IF(OR(F16="",E16=""),"",F16*(1-E16)) | H16: =IF(G16="","",G16*(1+Inicio!$B$13)) | I16: =IF(OR(F16="",G16=""),"",(F16-G16)/F16)
F17: =IF(D17="","",D17/(1+Inicio!$B$13)) | G17: =IF(OR(F17="",E17=""),"",F17*(1-E17)) | H17: =IF(G17="","",G17*(1+Inicio!$B$13)) | I17: =IF(OR(F17="",G17=""),"",(F17-G17)/F17)
F18: =IF(D18="","",D18/(1+Inicio!$B$13)) | G18: =IF(OR(F18="",E18=""),"",F18*(1-E18)) | H18: =IF(G18="","",G18*(1+Inicio!$B$13)) | I18: =IF(OR(F18="",G18=""),"",(F18-G18)/F18)
F19: =IF(D19="","",D19/(1+Inicio!$B$13)) | G19: =IF(OR(F19="",E19=""),"",F19*(1-E19)) | H19: =IF(G19="","",G19*(1+Inicio!$B$13)) | I19: =IF(OR(F19="",G19=""),"",(F19-G19)/F19)
F20: =IF(D20="","",D20/(1+Inicio!$B$13)) | G20: =IF(OR(F20="",E20=""),"",F20*(1-E20)) | H20: =IF(G20="","",G20*(1+Inicio!$B$13)) | I20: =IF(OR(F20="",G20=""),"",(F20-G20)/F20)
... F55: =IF(D55="","",D55/(1+Inicio!$B$13)) | G55: =IF(OR(F55="",E55=""),"",F55*(1-E55)) | H55: =IF(G55="","",G55*(1+Inicio!$B$13)) | I55: =IF(OR(F55="",G55=""),"",(F55-G55)/F55)
A60: 2) Evaluar margen real desde un precio neto que tú decidas ofrecer
A61: Cliente | B61: Canal | C61: SKU opcional | D61: PVP bruto pensado | E61: Precio neto ofrecido | F61: Precio bruto equivalente | G61: PVP neto calculado | H61: Margen frontal real | I61: Margen objetivo referencial | J61: Resultado
A62: Get It | B62: Conveniencia | C62: NUVA-BAR-CC-U-01 | D62: 1990 | E62: 1000 | F62: =IF(E62="","",E62*(1+Inicio!$B$13)) | G62: =IF(D62="","",D62/(1+Inicio!$B$13)) | H62: =IF(OR(G62="",E62=""),"",(G62-E62)/G62) | I62: 0.4 | J62: =IF(OR(H62="",I62=""),"",IF(H62>=I62,"Cumple","Bajo objetivo"))
A63: Jumbo | B63: Retail | C63: NUVA-BAR-BM-BX-04 | D63: 5990 | E63: 2800 | F63: =IF(E63="","",E63*(1+Inicio!$B$13)) | G63: =IF(D63="","",D63/(1+Inicio!$B$13)) | H63: =IF(OR(G63="",E63=""),"",(G63-E63)/G63) | I63: 0.45 | J63: =IF(OR(H63="",I63=""),"",IF(H63>=I63,"Cumple","Bajo objetivo"))
F64: =IF(E64="","",E64*(1+Inicio!$B$13)) | G64: =IF(D64="","",D64/(1+Inicio!$B$13)) | H64: =IF(OR(G64="",E64=""),"",(G64-E64)/G64) | J64: =IF(OR(H64="",I64=""),"",IF(H64>=I64,"Cumple","Bajo objetivo"))
F65: =IF(E65="","",E65*(1+Inicio!$B$13)) | G65: =IF(D65="","",D65/(1+Inicio!$B$13)) | H65: =IF(OR(G65="",E65=""),"",(G65-E65)/G65) | J65: =IF(OR(H65="",I65=""),"",IF(H65>=I65,"Cumple","Bajo objetivo"))
F66: =IF(E66="","",E66*(1+Inicio!$B$13)) | G66: =IF(D66="","",D66/(1+Inicio!$B$13)) | H66: =IF(OR(G66="",E66=""),"",(G66-E66)/G66) | J66: =IF(OR(H66="",I66=""),"",IF(H66>=I66,"Cumple","Bajo objetivo"))
F67: =IF(E67="","",E67*(1+Inicio!$B$13)) | G67: =IF(D67="","",D67/(1+Inicio!$B$13)) | H67: =IF(OR(G67="",E67=""),"",(G67-E67)/G67) | J67: =IF(OR(H67="",I67=""),"",IF(H67>=I67,"Cumple","Bajo objetivo"))
F68: =IF(E68="","",E68*(1+Inicio!$B$13)) | G68: =IF(D68="","",D68/(1+Inicio!$B$13)) | H68: =IF(OR(G68="",E68=""),"",(G68-E68)/G68) | J68: =IF(OR(H68="",I68=""),"",IF(H68>=I68,"Cumple","Bajo objetivo"))
F69: =IF(E69="","",E69*(1+Inicio!$B$13)) | G69: =IF(D69="","",D69/(1+Inicio!$B$13)) | H69: =IF(OR(G69="",E69=""),"",(G69-E69)/G69) | J69: =IF(OR(H69="",I69=""),"",IF(H69>=I69,"Cumple","Bajo objetivo"))
F70: =IF(E70="","",E70*(1+Inicio!$B$13)) | G70: =IF(D70="","",D70/(1+Inicio!$B$13)) | H70: =IF(OR(G70="",E70=""),"",(G70-E70)/G70) | J70: =IF(OR(H70="",I70=""),"",IF(H70>=I70,"Cumple","Bajo objetivo"))
F71: =IF(E71="","",E71*(1+Inicio!$B$13)) | G71: =IF(D71="","",D71/(1+Inicio!$B$13)) | H71: =IF(OR(G71="",E71=""),"",(G71-E71)/G71) | J71: =IF(OR(H71="",I71=""),"",IF(H71>=I71,"Cumple","Bajo objetivo"))
F72: =IF(E72="","",E72*(1+Inicio!$B$13)) | G72: =IF(D72="","",D72/(1+Inicio!$B$13)) | H72: =IF(OR(G72="",E72=""),"",(G72-E72)/G72) | J72: =IF(OR(H72="",I72=""),"",IF(H72>=I72,"Cumple","Bajo objetivo"))
F73: =IF(E73="","",E73*(1+Inicio!$B$13)) | G73: =IF(D73="","",D73/(1+Inicio!$B$13)) | H73: =IF(OR(G73="",E73=""),"",(G73-E73)/G73) | J73: =IF(OR(H73="",I73=""),"",IF(H73>=I73,"Cumple","Bajo objetivo"))
F74: =IF(E74="","",E74*(1+Inicio!$B$13)) | G74: =IF(D74="","",D74/(1+Inicio!$B$13)) | H74: =IF(OR(G74="",E74=""),"",(G74-E74)/G74) | J74: =IF(OR(H74="",I74=""),"",IF(H74>=I74,"Cumple","Bajo objetivo"))
F75: =IF(E75="","",E75*(1+Inicio!$B$13)) | G75: =IF(D75="","",D75/(1+Inicio!$B$13)) | H75: =IF(OR(G75="",E75=""),"",(G75-E75)/G75) | J75: =IF(OR(H75="",I75=""),"",IF(H75>=I75,"Cumple","Bajo objetivo"))
... F111: =IF(E111="","",E111*(1+Inicio!$B$13)) | G111: =IF(D111="","",D111/(1+Inicio!$B$13)) | H111: =IF(OR(G111="",E111=""),"",(G111-E111)/G111) | J111: =IF(OR(H111="",I111=""),"",IF(H111>=I111,"Cumple","Bajo objetivo"))

Sheet SellOut_Jumbo
A1: Fecha | B1: Cliente | C1: PDV | D1: SKU | E1: Descripción SKU | F1: Unidades sell-out | G1: Venta pública bruta | H1: Stock informado | I1: Fuente/archivo | J1: Observaciones | K1: Año | L1: Mes | M1: Día | N1: Periodo | P1: ⚙ Configuración
A2: 46200 | B2: Jumbo | C2: Jumbo La Reina | D2: NUVA-BAR-PB-U-01 | E2: =IFERROR(VLOOKUP(D2,Maestro_SKU!$A$2:$P$500,2,FALSE),"") | F2: 2 | G2: 35940 | H2: 16 | I2: Ejemplo exportación Cencosud | K2: =IF($A2="","",YEAR($A2)) | L2: =IF($A2="","",MONTH($A2)) | M2: =IF($A2="","",DAY($A2)) | N2: =IF($A2="","",YEAR($A2)&"-"&TEXT(MONTH($A2),"00"))
A3: 46209 | B3: Jumbo | C3: Jumbo La Reina | D3: NUVA-BAR-BM-BX-04 | E3: =IFERROR(VLOOKUP(D3,Maestro_SKU!$A$2:$P$500,2,FALSE),"") | F3: 12 | G3: 11980 | H3: 8 | I3: Ejemplo exportación Cencosud | K3: =IF($A3="","",YEAR($A3)) | L3: =IF($A3="","",MONTH($A3)) | M3: =IF($A3="","",DAY($A3)) | N3: =IF($A3="","",YEAR($A3)&"-"&TEXT(MONTH($A3),"00"))
A4: 46201 | B4: Jumbo | C4: Jumbo Bilbao | D4: NUVA-BAR-PB-U-01 | E4: =IFERROR(VLOOKUP(D4,Maestro_SKU!$A$2:$P$500,2,FALSE),"") | F4: 12 | G4: 35940 | H4: 32 | I4: Ejemplo exportación Cencosud | K4: =IF($A4="","",YEAR($A4)) | L4: =IF($A4="","",MONTH($A4)) | M4: =IF($A4="","",DAY($A4)) | N4: =IF($A4="","",YEAR($A4)&"-"&TEXT(MONTH($A4),"00"))
A5: 46212 | B5: Jumbo | C5: Jumbo Bilbao | D5: NUVA-BAR-BM-BX-04 | E5: =IFERROR(VLOOKUP(D5,Maestro_SKU!$A$2:$P$500,2,FALSE),"") | F5: 2 | G5: 5990 | H5: 16 | I5: Ejemplo exportación Cencosud | K5: =IF($A5="","",YEAR($A5)) | L5: =IF($A5="","",MONTH($A5)) | M5: =IF($A5="","",DAY($A5)) | N5: =IF($A5="","",YEAR($A5)&"-"&TEXT(MONTH($A5),"00"))
A6: 46202 | B6: Jumbo | C6: Jumbo Bilbao | D6: NUVA-BAR-CC-BX-04 | E6: =IFERROR(VLOOKUP(D6,Maestro_SKU!$A$2:$P$500,2,FALSE),"") | F6: 2 | G6: 17970 | H6: 8 | I6: Ejemplo exportación Cencosud | K6: =IF($A6="","",YEAR($A6)) | L6: =IF($A6="","",MONTH($A6)) | M6: =IF($A6="","",DAY($A6)) | N6: =IF($A6="","",YEAR($A6)&"-"&TEXT(MONTH($A6),"00"))
A7: 46192 | B7: Jumbo | C7: Jumbo Kennedy | D7: NUVA-BAR-PB-U-01 | E7: =IFERROR(VLOOKUP(D7,Maestro_SKU!$A$2:$P$500,2,FALSE),"") | F7: 2 | G7: 11980 | H7: 4 | I7: Ejemplo exportación Cencosud | K7: =IF($A7="","",YEAR($A7)) | L7: =IF($A7="","",MONTH($A7)) | M7: =IF($A7="","",DAY($A7)) | N7: =IF($A7="","",YEAR($A7)&"-"&TEXT(MONTH($A7),"00"))
A8: 46203 | B8: Jumbo | C8: Jumbo Bilbao | D8: NUVA-BAR-PB-U-01 | E8: =IFERROR(VLOOKUP(D8,Maestro_SKU!$A$2:$P$500,2,FALSE),"") | F8: 4 | G8: 23960 | H8: 32 | I8: Ejemplo exportación Cencosud | K8: =IF($A8="","",YEAR($A8)) | L8: =IF($A8="","",MONTH($A8)) | M8: =IF($A8="","",DAY($A8)) | N8: =IF($A8="","",YEAR($A8)&"-"&TEXT(MONTH($A8),"00"))
A9: 46195 | B9: Jumbo | C9: Jumbo La Reina | D9: NUVA-BAR-PB-BX-04 | E9: =IFERROR(VLOOKUP(D9,Maestro_SKU!$A$2:$P$500,2,FALSE),"") | F9: 8 | G9: 35940 | H9: 0 | I9: Ejemplo exportación Cencosud | K9: =IF($A9="","",YEAR($A9)) | L9: =IF($A9="","",MONTH($A9)) | M9: =IF($A9="","",DAY($A9)) | N9: =IF($A9="","",YEAR($A9)&"-"&TEXT(MONTH($A9),"00"))
A10: 46208 | B10: Jumbo | C10: Jumbo Bilbao | D10: NUVA-BAR-BM-U-01 | E10: =IFERROR(VLOOKUP(D10,Maestro_SKU!$A$2:$P$500,2,FALSE),"") | F10: 2 | G10: 5990 | H10: 4 | I10: Ejemplo exportación Cencosud | K10: =IF($A10="","",YEAR($A10)) | L10: =IF($A10="","",MONTH($A10)) | M10: =IF($A10="","",DAY($A10)) | N10: =IF($A10="","",YEAR($A10)&"-"&TEXT(MONTH($A10),"00"))
A11: 46209 | B11: Jumbo | C11: Jumbo La Reina | D11: NUVA-BAR-BM-BX-04 | E11: =IFERROR(VLOOKUP(D11,Maestro_SKU!$A$2:$P$500,2,FALSE),"") | F11: 2 | G11: 5990 | H11: 16 | I11: Ejemplo exportación Cencosud | K11: =IF($A11="","",YEAR($A11)) | L11: =IF($A11="","",MONTH($A11)) | M11: =IF($A11="","",DAY($A11)) | N11: =IF($A11="","",YEAR($A11)&"-"&TEXT(MONTH($A11),"00"))
A12: 46189 | B12: Jumbo | C12: Jumbo La Reina | D12: NUVA-BAR-PB-U-01 | E12: =IFERROR(VLOOKUP(D12,Maestro_SKU!$A$2:$P$500,2,FALSE),"") | F12: 12 | G12: 23960 | H12: 0 | I12: Ejemplo exportación Cencosud | K12: =IF($A12="","",YEAR($A12)) | L12: =IF($A12="","",MONTH($A12)) | M12: =IF($A12="","",DAY($A12)) | N12: =IF($A12="","",YEAR($A12)&"-"&TEXT(MONTH($A12),"00"))
A13: 46195 | B13: Jumbo | C13: Jumbo Bilbao | D13: NUVA-BAR-BM-U-01 | E13: =IFERROR(VLOOKUP(D13,Maestro_SKU!$A$2:$P$500,2,FALSE),"") | F13: 15 | G13: 23960 | H13: 32 | I13: Ejemplo exportación Cencosud | K13: =IF($A13="","",YEAR($A13)) | L13: =IF($A13="","",MONTH($A13)) | M13: =IF($A13="","",DAY($A13)) | N13: =IF($A13="","",YEAR($A13)&"-"&TEXT(MONTH($A13),"00"))
... A19: 46187 | B19: Jumbo | C19: Jumbo Kennedy | D19: NUVA-BAR-BM-U-01 | E19: =IFERROR(VLOOKUP(D19,Maestro_SKU!$A$2:$P$500,2,FALSE),"") | F19: 12 | G19: 17970 | H19: 32 | I19: Ejemplo exportación Cencosud | K19: =IF($A19="","",YEAR($A19)) | L19: =IF($A19="","",MONTH($A19)) | M19: =IF($A19="","",DAY($A19)) | N19: =IF($A19="","",YEAR($A19)&"-"&TEXT(MONTH($A19),"00"))
E20: =IFERROR(VLOOKUP(D20,Maestro_SKU!$A$2:$P$500,2,FALSE),"") | K20: =IF($A20="","",YEAR($A20)) | L20: =IF($A20="","",MONTH($A20)) | M20: =IF($A20="","",DAY($A20)) | N20: =IF($A20="","",YEAR($A20)&"-"&TEXT(MONTH($A20),"00"))
E21: =IFERROR(VLOOKUP(D21,Maestro_SKU!$A$2:$P$500,2,FALSE),"") | K21: =IF($A21="","",YEAR($A21)) | L21: =IF($A21="","",MONTH($A21)) | M21: =IF($A21="","",DAY($A21)) | N21: =IF($A21="","",YEAR($A21)&"-"&TEXT(MONTH($A21),"00"))
E22: =IFERROR(VLOOKUP(D22,Maestro_SKU!$A$2:$P$500,2,FALSE),"") | K22: =IF($A22="","",YEAR($A22)) | L22: =IF($A22="","",MONTH($A22)) | M22: =IF($A22="","",DAY($A22)) | N22: =IF($A22="","",YEAR($A22)&"-"&TEXT(MONTH($A22),"00"))
E23: =IFERROR(VLOOKUP(D23,Maestro_SKU!$A$2:$P$500,2,FALSE),"") | K23: =IF($A23="","",YEAR($A23)) | L23: =IF($A23="","",MONTH($A23)) | M23: =IF($A23="","",DAY($A23)) | N23: =IF($A23="","",YEAR($A23)&"-"&TEXT(MONTH($A23),"00"))
E24: =IFERROR(VLOOKUP(D24,Maestro_SKU!$A$2:$P$500,2,FALSE),"") | K24: =IF($A24="","",YEAR($A24)) | L24: =IF($A24="","",MONTH($A24)) | M24: =IF($A24="","",DAY($A24)) | N24: =IF($A24="","",YEAR($A24)&"-"&TEXT(MONTH($A24),"00"))
E25: =IFERROR(VLOOKUP(D25,Maestro_SKU!$A$2:$P$500,2,FALSE),"") | K25: =IF($A25="","",YEAR($A25)) | L25: =IF($A25="","",MONTH($A25)) | M25: =IF($A25="","",DAY($A25)) | N25: =IF($A25="","",YEAR($A25)&"-"&TEXT(MONTH($A25),"00"))
E26: =IFERROR(VLOOKUP(D26,Maestro_SKU!$A$2:$P$500,2,FALSE),"") | K26: =IF($A26="","",YEAR($A26)) | L26: =IF($A26="","",MONTH($A26)) | M26: =IF($A26="","",DAY($A26)) | N26: =IF($A26="","",YEAR($A26)&"-"&TEXT(MONTH($A26),"00"))
E27: =IFERROR(VLOOKUP(D27,Maestro_SKU!$A$2:$P$500,2,FALSE),"") | K27: =IF($A27="","",YEAR($A27)) | L27: =IF($A27="","",MONTH($A27)) | M27: =IF($A27="","",DAY($A27)) | N27: =IF($A27="","",YEAR($A27)&"-"&TEXT(MONTH($A27),"00"))
E28: =IFERROR(VLOOKUP(D28,Maestro_SKU!$A$2:$P$500,2,FALSE),"") | K28: =IF($A28="","",YEAR($A28)) | L28: =IF($A28="","",MONTH($A28)) | M28: =IF($A28="","",DAY($A28)) | N28: =IF($A28="","",YEAR($A28)&"-"&TEXT(MONTH($A28),"00"))
E29: =IFERROR(VLOOKUP(D29,Maestro_SKU!$A$2:$P$500,2,FALSE),"") | K29: =IF($A29="","",YEAR($A29)) | L29: =IF($A29="","",MONTH($A29)) | M29: =IF($A29="","",DAY($A29)) | N29: =IF($A29="","",YEAR($A29)&"-"&TEXT(MONTH($A29),"00"))
E30: =IFERROR(VLOOKUP(D30,Maestro_SKU!$A$2:$P$500,2,FALSE),"") | K30: =IF($A30="","",YEAR($A30)) | L30: =IF($A30="","",MONTH($A30)) | M30: =IF($A30="","",DAY($A30)) | N30: =IF($A30="","",YEAR($A30)&"-"&TEXT(MONTH($A30),"00"))
E31: =IFERROR(VLOOKUP(D31,Maestro_SKU!$A$2:$P$500,2,FALSE),"") | K31: =IF($A31="","",YEAR($A31)) | L31: =IF($A31="","",MONTH($A31)) | M31: =IF($A31="","",DAY($A31)) | N31: =IF($A31="","",YEAR($A31)&"-"&TEXT(MONTH($A31),"00"))
... E800: =IFERROR(VLOOKUP(D800,Maestro_SKU!$A$2:$P$500,2,FALSE),"") | K800: =IF($A800="","",YEAR($A800)) | L800: =IF($A800="","",MONTH($A800)) | M800: =IF($A800="","",DAY($A800)) | N800: =IF($A800="","",YEAR($A800)&"-"&TEXT(MONTH($A800),"00"))

Sheet Stock_PDV
A1: PDV_ID | B1: Cliente | C1: Canal | D1: Punto de venta | E1: SKU | F1: Descripción SKU | G1: Stock unidades | H1: Barras equivalentes | I1: Fecha conteo | J1: Estado stock | K1: Observaciones | M1: ⚙ Configuración
A2: PDV-001 | B2: =IFERROR(VLOOKUP(A2,Clientes_PDV!$A$2:$J$250,2,FALSE),"") | C2: =IFERROR(VLOOKUP(A2,Clientes_PDV!$A$2:$J$250,3,FALSE),"") | D2: =IFERROR(VLOOKUP(A2,Clientes_PDV!$A$2:$J$250,4,FALSE),"") | E2: NUVA-BAR-BM-U-01 | F2: =IFERROR(VLOOKUP(E2,Maestro_SKU!$A$2:$P$500,2,FALSE),"") | G2: 5 | H2: =IF(OR(G2="",E2=""),"",G2*IFERROR(VLOOKUP(E2,Maestro_SKU!$A$2:$P$500,12,FALSE),1)) | I2: 46201 | J2: =IF(A2="","",IF(H2<=Inicio!$B$16,"Crítico",IF(H2<=Inicio!$B$17,"Observar","OK")))
A3: PDV-001 | B3: =IFERROR(VLOOKUP(A3,Clientes_PDV!$A$2:$J$250,2,FALSE),"") | C3: =IFERROR(VLOOKUP(A3,Clientes_PDV!$A$2:$J$250,3,FALSE),"") | D3: =IFERROR(VLOOKUP(A3,Clientes_PDV!$A$2:$J$250,4,FALSE),"") | E3: NUVA-BAR-PB-U-01 | F3: =IFERROR(VLOOKUP(E3,Maestro_SKU!$A$2:$P$500,2,FALSE),"") | G3: 0 | H3: =IF(OR(G3="",E3=""),"",G3*IFERROR(VLOOKUP(E3,Maestro_SKU!$A$2:$P$500,12,FALSE),1)) | I3: 46203 | J3: =IF(A3="","",IF(H3<=Inicio!$B$16,"Crítico",IF(H3<=Inicio!$B$17,"Observar","OK")))
A4: PDV-001 | B4: =IFERROR(VLOOKUP(A4,Clientes_PDV!$A$2:$J$250,2,FALSE),"") | C4: =IFERROR(VLOOKUP(A4,Clientes_PDV!$A$2:$J$250,3,FALSE),"") | D4: =IFERROR(VLOOKUP(A4,Clientes_PDV!$A$2:$J$250,4,FALSE),"") | E4: NUVA-BAR-CC-U-01 | F4: =IFERROR(VLOOKUP(E4,Maestro_SKU!$A$2:$P$500,2,FALSE),"") | G4: 8 | H4: =IF(OR(G4="",E4=""),"",G4*IFERROR(VLOOKUP(E4,Maestro_SKU!$A$2:$P$500,12,FALSE),1)) | I4: 46204 | J4: =IF(A4="","",IF(H4<=Inicio!$B$16,"Crítico",IF(H4<=Inicio!$B$17,"Observar","OK")))
A5: PDV-001 | B5: =IFERROR(VLOOKUP(A5,Clientes_PDV!$A$2:$J$250,2,FALSE),"") | C5: =IFERROR(VLOOKUP(A5,Clientes_PDV!$A$2:$J$250,3,FALSE),"") | D5: =IFERROR(VLOOKUP(A5,Clientes_PDV!$A$2:$J$250,4,FALSE),"") | E5: NUVA-BAR-BM-BX-04 | F5: =IFERROR(VLOOKUP(E5,Maestro_SKU!$A$2:$P$500,2,FALSE),"") | G5: 5 | H5: =IF(OR(G5="",E5=""),"",G5*IFERROR(VLOOKUP(E5,Maestro_SKU!$A$2:$P$500,12,FALSE),1)) | I5: 46208 | J5: =IF(A5="","",IF(H5<=Inicio!$B$16,"Crítico",IF(H5<=Inicio!$B$17,"Observar","OK")))
A6: PDV-002 | B6: =IFERROR(VLOOKUP(A6,Clientes_PDV!$A$2:$J$250,2,FALSE),"") | C6: =IFERROR(VLOOKUP(A6,Clientes_PDV!$A$2:$J$250,3,FALSE),"") | D6: =IFERROR(VLOOKUP(A6,Clientes_PDV!$A$2:$J$250,4,FALSE),"") | E6: NUVA-BAR-BM-U-01 | F6: =IFERROR(VLOOKUP(E6,Maestro_SKU!$A$2:$P$500,2,FALSE),"") | G6: 0 | H6: =IF(OR(G6="",E6=""),"",G6*IFERROR(VLOOKUP(E6,Maestro_SKU!$A$2:$P$500,12,FALSE),1)) | I6: 46207 | J6: =IF(A6="","",IF(H6<=Inicio!$B$16,"Crítico",IF(H6<=Inicio!$B$17,"Observar","OK")))
A7: PDV-003 | B7: =IFERROR(VLOOKUP(A7,Clientes_PDV!$A$2:$J$250,2,FALSE),"") | C7: =IFERROR(VLOOKUP(A7,Clientes_PDV!$A$2:$J$250,3,FALSE),"") | D7: =IFERROR(VLOOKUP(A7,Clientes_PDV!$A$2:$J$250,4,FALSE),"") | E7: NUVA-BAR-PB-U-01 | F7: =IFERROR(VLOOKUP(E7,Maestro_SKU!$A$2:$P$500,2,FALSE),"") | G7: 30 | H7: =IF(OR(G7="",E7=""),"",G7*IFERROR(VLOOKUP(E7,Maestro_SKU!$A$2:$P$500,12,FALSE),1)) | I7: 46203 | J7: =IF(A7="","",IF(H7<=Inicio!$B$16,"Crítico",IF(H7<=Inicio!$B$17,"Observar","OK")))
A8: PDV-003 | B8: =IFERROR(VLOOKUP(A8,Clientes_PDV!$A$2:$J$250,2,FALSE),"") | C8: =IFERROR(VLOOKUP(A8,Clientes_PDV!$A$2:$J$250,3,FALSE),"") | D8: =IFERROR(VLOOKUP(A8,Clientes_PDV!$A$2:$J$250,4,FALSE),"") | E8: NUVA-BAR-CC-U-01 | F8: =IFERROR(VLOOKUP(E8,Maestro_SKU!$A$2:$P$500,2,FALSE),"") | G8: 5 | H8: =IF(OR(G8="",E8=""),"",G8*IFERROR(VLOOKUP(E8,Maestro_SKU!$A$2:$P$500,12,FALSE),1)) | I8: 46207 | J8: =IF(A8="","",IF(H8<=Inicio!$B$16,"Crítico",IF(H8<=Inicio!$B$17,"Observar","OK")))
A9: PDV-003 | B9: =IFERROR(VLOOKUP(A9,Clientes_PDV!$A$2:$J$250,2,FALSE),"") | C9: =IFERROR(VLOOKUP(A9,Clientes_PDV!$A$2:$J$250,3,FALSE),"") | D9: =IFERROR(VLOOKUP(A9,Clientes_PDV!$A$2:$J$250,4,FALSE),"") | E9: NUVA-BAR-CC-BX-04 | F9: =IFERROR(VLOOKUP(E9,Maestro_SKU!$A$2:$P$500,2,FALSE),"") | G9: 30 | H9: =IF(OR(G9="",E9=""),"",G9*IFERROR(VLOOKUP(E9,Maestro_SKU!$A$2:$P$500,12,FALSE),1)) | I9: 46210 | J9: =IF(A9="","",IF(H9<=Inicio!$B$16,"Crítico",IF(H9<=Inicio!$B$17,"Observar","OK")))
A10: PDV-004 | B10: =IFERROR(VLOOKUP(A10,Clientes_PDV!$A$2:$J$250,2,FALSE),"") | C10: =IFERROR(VLOOKUP(A10,Clientes_PDV!$A$2:$J$250,3,FALSE),"") | D10: =IFERROR(VLOOKUP(A10,Clientes_PDV!$A$2:$J$250,4,FALSE),"") | E10: NUVA-BAR-PB-U-01 | F10: =IFERROR(VLOOKUP(E10,Maestro_SKU!$A$2:$P$500,2,FALSE),"") | G10: 8 | H10: =IF(OR(G10="",E10=""),"",G10*IFERROR(VLOOKUP(E10,Maestro_SKU!$A$2:$P$500,12,FALSE),1)) | I10: 46205 | J10: =IF(A10="","",IF(H10<=Inicio!$B$16,"Crítico",IF(H10<=Inicio!$B$17,"Observar","OK")))
A11: PDV-005 | B11: =IFERROR(VLOOKUP(A11,Clientes_PDV!$A$2:$J$250,2,FALSE),"") | C11: =IFERROR(VLOOKUP(A11,Clientes_PDV!$A$2:$J$250,3,FALSE),"") | D11: =IFERROR(VLOOKUP(A11,Clientes_PDV!$A$2:$J$250,4,FALSE),"") | E11: NUVA-BAR-PB-U-01 | F11: =IFERROR(VLOOKUP(E11,Maestro_SKU!$A$2:$P$500,2,FALSE),"") | G11: 20 | H11: =IF(OR(G11="",E11=""),"",G11*IFERROR(VLOOKUP(E11,Maestro_SKU!$A$2:$P$500,12,FALSE),1)) | I11: 46201 | J11: =IF(A11="","",IF(H11<=Inicio!$B$16,"Crítico",IF(H11<=Inicio!$B$17,"Observar","OK")))
A12: PDV-005 | B12: =IFERROR(VLOOKUP(A12,Clientes_PDV!$A$2:$J$250,2,FALSE),"") | C12: =IFERROR(VLOOKUP(A12,Clientes_PDV!$A$2:$J$250,3,FALSE),"") | D12: =IFERROR(VLOOKUP(A12,Clientes_PDV!$A$2:$J$250,4,FALSE),"") | E12: NUVA-BAR-BM-BX-04 | F12: =IFERROR(VLOOKUP(E12,Maestro_SKU!$A$2:$P$500,2,FALSE),"") | G12: 45 | H12: =IF(OR(G12="",E12=""),"",G12*IFERROR(VLOOKUP(E12,Maestro_SKU!$A$2:$P$500,12,FALSE),1)) | I12: 46212 | J12: =IF(A12="","",IF(H12<=Inicio!$B$16,"Crítico",IF(H12<=Inicio!$B$17,"Observar","OK")))
A13: PDV-006 | B13: =IFERROR(VLOOKUP(A13,Clientes_PDV!$A$2:$J$250,2,FALSE),"") | C13: =IFERROR(VLOOKUP(A13,Clientes_PDV!$A$2:$J$250,3,FALSE),"") | D13: =IFERROR(VLOOKUP(A13,Clientes_PDV!$A$2:$J$250,4,FALSE),"") | E13: NUVA-BAR-PB-U-01 | F13: =IFERROR(VLOOKUP(E13,Maestro_SKU!$A$2:$P$500,2,FALSE),"") | G13: 3 | H13: =IF(OR(G13="",E13=""),"",G13*IFERROR(VLOOKUP(E13,Maestro_SKU!$A$2:$P$500,12,FALSE),1)) | I13: 46198 | J13: =IF(A13="","",IF(H13<=Inicio!$B$16,"Crítico",IF(H13<=Inicio!$B$17,"Observar","OK")))
... A29: PDV-012 | B29: =IFERROR(VLOOKUP(A29,Clientes_PDV!$A$2:$J$250,2,FALSE),"") | C29: =IFERROR(VLOOKUP(A29,Clientes_PDV!$A$2:$J$250,3,FALSE),"") | D29: =IFERROR(VLOOKUP(A29,Clientes_PDV!$A$2:$J$250,4,FALSE),"") | E29: NUVA-BAR-CC-BX-04 | F29: =IFERROR(VLOOKUP(E29,Maestro_SKU!$A$2:$P$500,2,FALSE),"") | G29: 5 | H29: =IF(OR(G29="",E29=""),"",G29*IFERROR(VLOOKUP(E29,Maestro_SKU!$A$2:$P$500,12,FALSE),1)) | I29: 46198 | J29: =IF(A29="","",IF(H29<=Inicio!$B$16,"Crítico",IF(H29<=Inicio!$B$17,"Observar","OK")))
B30: =IFERROR(VLOOKUP(A30,Clientes_PDV!$A$2:$J$250,2,FALSE),"") | C30: =IFERROR(VLOOKUP(A30,Clientes_PDV!$A$2:$J$250,3,FALSE),"") | D30: =IFERROR(VLOOKUP(A30,Clientes_PDV!$A$2:$J$250,4,FALSE),"") | F30: =IFERROR(VLOOKUP(E30,Maestro_SKU!$A$2:$P$500,2,FALSE),"") | H30: =IF(OR(G30="",E30=""),"",G30*IFERROR(VLOOKUP(E30,Maestro_SKU!$A$2:$P$500,12,FALSE),1)) | J30: =IF(A30="","",IF(H30<=Inicio!$B$16,"Crítico",IF(H30<=Inicio!$B$17,"Observar","OK")))
B31: =IFERROR(VLOOKUP(A31,Clientes_PDV!$A$2:$J$250,2,FALSE),"") | C31: =IFERROR(VLOOKUP(A31,Clientes_PDV!$A$2:$J$250,3,FALSE),"") | D31: =IFERROR(VLOOKUP(A31,Clientes_PDV!$A$2:$J$250,4,FALSE),"") | F31: =IFERROR(VLOOKUP(E31,Maestro_SKU!$A$2:$P$500,2,FALSE),"") | H31: =IF(OR(G31="",E31=""),"",G31*IFERROR(VLOOKUP(E31,Maestro_SKU!$A$2:$P$500,12,FALSE),1)) | J31: =IF(A31="","",IF(H31<=Inicio!$B$16,"Crítico",IF(H31<=Inicio!$B$17,"Observar","OK")))
B32: =IFERROR(VLOOKUP(A32,Clientes_PDV!$A$2:$J$250,2,FALSE),"") | C32: =IFERROR(VLOOKUP(A32,Clientes_PDV!$A$2:$J$250,3,FALSE),"") | D32: =IFERROR(VLOOKUP(A32,Clientes_PDV!$A$2:$J$250,4,FALSE),"") | F32: =IFERROR(VLOOKUP(E32,Maestro_SKU!$A$2:$P$500,2,FALSE),"") | H32: =IF(OR(G32="",E32=""),"",G32*IFERROR(VLOOKUP(E32,Maestro_SKU!$A$2:$P$500,12,FALSE),1)) | J32: =IF(A32="","",IF(H32<=Inicio!$B$16,"Crítico",IF(H32<=Inicio!$B$17,"Observar","OK")))
B33: =IFERROR(VLOOKUP(A33,Clientes_PDV!$A$2:$J$250,2,FALSE),"") | C33: =IFERROR(VLOOKUP(A33,Clientes_PDV!$A$2:$J$250,3,FALSE),"") | D33: =IFERROR(VLOOKUP(A33,Clientes_PDV!$A$2:$J$250,4,FALSE),"") | F33: =IFERROR(VLOOKUP(E33,Maestro_SKU!$A$2:$P$500,2,FALSE),"") | H33: =IF(OR(G33="",E33=""),"",G33*IFERROR(VLOOKUP(E33,Maestro_SKU!$A$2:$P$500,12,FALSE),1)) | J33: =IF(A33="","",IF(H33<=Inicio!$B$16,"Crítico",IF(H33<=Inicio!$B$17,"Observar","OK")))
B34: =IFERROR(VLOOKUP(A34,Clientes_PDV!$A$2:$J$250,2,FALSE),"") | C34: =IFERROR(VLOOKUP(A34,Clientes_PDV!$A$2:$J$250,3,FALSE),"") | D34: =IFERROR(VLOOKUP(A34,Clientes_PDV!$A$2:$J$250,4,FALSE),"") | F34: =IFERROR(VLOOKUP(E34,Maestro_SKU!$A$2:$P$500,2,FALSE),"") | H34: =IF(OR(G34="",E34=""),"",G34*IFERROR(VLOOKUP(E34,Maestro_SKU!$A$2:$P$500,12,FALSE),1)) | J34: =IF(A34="","",IF(H34<=Inicio!$B$16,"Crítico",IF(H34<=Inicio!$B$17,"Observar","OK")))
B35: =IFERROR(VLOOKUP(A35,Clientes_PDV!$A$2:$J$250,2,FALSE),"") | C35: =IFERROR(VLOOKUP(A35,Clientes_PDV!$A$2:$J$250,3,FALSE),"") | D35: =IFERROR(VLOOKUP(A35,Clientes_PDV!$A$2:$J$250,4,FALSE),"") | F35: =IFERROR(VLOOKUP(E35,Maestro_SKU!$A$2:$P$500,2,FALSE),"") | H35: =IF(OR(G35="",E35=""),"",G35*IFERROR(VLOOKUP(E35,Maestro_SKU!$A$2:$P$500,12,FALSE),1)) | J35: =IF(A35="","",IF(H35<=Inicio!$B$16,"Crítico",IF(H35<=Inicio!$B$17,"Observar","OK")))
B36: =IFERROR(VLOOKUP(A36,Clientes_PDV!$A$2:$J$250,2,FALSE),"") | C36: =IFERROR(VLOOKUP(A36,Clientes_PDV!$A$2:$J$250,3,FALSE),"") | D36: =IFERROR(VLOOKUP(A36,Clientes_PDV!$A$2:$J$250,4,FALSE),"") | F36: =IFERROR(VLOOKUP(E36,Maestro_SKU!$A$2:$P$500,2,FALSE),"") | H36: =IF(OR(G36="",E36=""),"",G36*IFERROR(VLOOKUP(E36,Maestro_SKU!$A$2:$P$500,12,FALSE),1)) | J36: =IF(A36="","",IF(H36<=Inicio!$B$16,"Crítico",IF(H36<=Inicio!$B$17,"Observar","OK")))
B37: =IFERROR(VLOOKUP(A37,Clientes_PDV!$A$2:$J$250,2,FALSE),"") | C37: =IFERROR(VLOOKUP(A37,Clientes_PDV!$A$2:$J$250,3,FALSE),"") | D37: =IFERROR(VLOOKUP(A37,Clientes_PDV!$A$2:$J$250,4,FALSE),"") | F37: =IFERROR(VLOOKUP(E37,Maestro_SKU!$A$2:$P$500,2,FALSE),"") | H37: =IF(OR(G37="",E37=""),"",G37*IFERROR(VLOOKUP(E37,Maestro_SKU!$A$2:$P$500,12,FALSE),1)) | J37: =IF(A37="","",IF(H37<=Inicio!$B$16,"Crítico",IF(H37<=Inicio!$B$17,"Observar","OK")))
B38: =IFERROR(VLOOKUP(A38,Clientes_PDV!$A$2:$J$250,2,FALSE),"") | C38: =IFERROR(VLOOKUP(A38,Clientes_PDV!$A$2:$J$250,3,FALSE),"") | D38: =IFERROR(VLOOKUP(A38,Clientes_PDV!$A$2:$J$250,4,FALSE),"") | F38: =IFERROR(VLOOKUP(E38,Maestro_SKU!$A$2:$P$500,2,FALSE),"") | H38: =IF(OR(G38="",E38=""),"",G38*IFERROR(VLOOKUP(E38,Maestro_SKU!$A$2:$P$500,12,FALSE),1)) | J38: =IF(A38="","",IF(H38<=Inicio!$B$16,"Crítico",IF(H38<=Inicio!$B$17,"Observar","OK")))
B39: =IFERROR(VLOOKUP(A39,Clientes_PDV!$A$2:$J$250,2,FALSE),"") | C39: =IFERROR(VLOOKUP(A39,Clientes_PDV!$A$2:$J$250,3,FALSE),"") | D39: =IFERROR(VLOOKUP(A39,Clientes_PDV!$A$2:$J$250,4,FALSE),"") | F39: =IFERROR(VLOOKUP(E39,Maestro_SKU!$A$2:$P$500,2,FALSE),"") | H39: =IF(OR(G39="",E39=""),"",G39*IFERROR(VLOOKUP(E39,Maestro_SKU!$A$2:$P$500,12,FALSE),1)) | J39: =IF(A39="","",IF(H39<=Inicio!$B$16,"Crítico",IF(H39<=Inicio!$B$17,"Observar","OK")))
B40: =IFERROR(VLOOKUP(A40,Clientes_PDV!$A$2:$J$250,2,FALSE),"") | C40: =IFERROR(VLOOKUP(A40,Clientes_PDV!$A$2:$J$250,3,FALSE),"") | D40: =IFERROR(VLOOKUP(A40,Clientes_PDV!$A$2:$J$250,4,FALSE),"") | F40: =IFERROR(VLOOKUP(E40,Maestro_SKU!$A$2:$P$500,2,FALSE),"") | H40: =IF(OR(G40="",E40=""),"",G40*IFERROR(VLOOKUP(E40,Maestro_SKU!$A$2:$P$500,12,FALSE),1)) | J40: =IF(A40="","",IF(H40<=Inicio!$B$16,"Crítico",IF(H40<=Inicio!$B$17,"Observar","OK")))
B41: =IFERROR(VLOOKUP(A41,Clientes_PDV!$A$2:$J$250,2,FALSE),"") | C41: =IFERROR(VLOOKUP(A41,Clientes_PDV!$A$2:$J$250,3,FALSE),"") | D41: =IFERROR(VLOOKUP(A41,Clientes_PDV!$A$2:$J$250,4,FALSE),"") | F41: =IFERROR(VLOOKUP(E41,Maestro_SKU!$A$2:$P$500,2,FALSE),"") | H41: =IF(OR(G41="",E41=""),"",G41*IFERROR(VLOOKUP(E41,Maestro_SKU!$A$2:$P$500,12,FALSE),1)) | J41: =IF(A41="","",IF(H41<=Inicio!$B$16,"Crítico",IF(H41<=Inicio!$B$17,"Observar","OK")))
... B800: =IFERROR(VLOOKUP(A800,Clientes_PDV!$A$2:$J$250,2,FALSE),"") | C800: =IFERROR(VLOOKUP(A800,Clientes_PDV!$A$2:$J$250,3,FALSE),"") | D800: =IFERROR(VLOOKUP(A800,Clientes_PDV!$A$2:$J$250,4,FALSE),"") | F800: =IFERROR(VLOOKUP(E800,Maestro_SKU!$A$2:$P$500,2,FALSE),"") | H800: =IF(OR(G800="",E800=""),"",G800*IFERROR(VLOOKUP(E800,Maestro_SKU!$A$2:$P$500,12,FALSE),1)) | J800: =IF(A800="","",IF(H800<=Inicio!$B$16,"Crítico",IF(H800<=Inicio!$B$17,"Observar","OK")))

Sheet Maestro_SKU
A1: SKU | B1: Descripción SKU | C1: Cód. barra | D1: Marca | E1: Categoría | F1: Código Categoría | G1: Subcategoría | H1: Sabor | I1: Código sabor | J1: Nivel logístico | K1: Formato | L1: Unidades por pack | M1: Mercado | N1: UM venta | O1: Estado | P1: Observación
A2: NUVA-BAR-BM-U-01 | B2: Barra Berry Mix unidad | D2: NUVA | E2: Barritas | F2: BAR | G2: Funcionales | H2: Berry Mix | I2: BM | J2: Unitario | K2: U | L2: 1 | M2: CL | N2: un | O2: Activo | P2: SKU de venta unitario
A3: NUVA-BAR-PB-U-01 | B3: Barra Peanut Boost unidad | D3: NUVA | E3: Barritas | F3: BAR | G3: Funcionales | H3: Peanut Boost | I3: PB | J3: Unitario | K3: U | L3: 1 | M3: CL | N3: un | O3: Activo | P3: SKU de venta unitario
A4: NUVA-BAR-CC-U-01 | B4: Barra Cacao Crispy unidad | D4: NUVA | E4: Barritas | F4: BAR | G4: Funcionales | H4: Cacao Crispy | I4: CC | J4: Unitario | K4: U | L4: 1 | M4: CL | N4: un | O4: Activo | P4: SKU de venta unitario
A5: NUVA-BAR-BM-BX-04 | B5: Estuche Berry Mix 4 unidades | D5: NUVA | E5: Barritas | F5: BAR | G5: Funcionales | H5: Berry Mix | I5: BM | J5: Estuche | K5: BX | L5: 4 | M5: CL | N5: un | O5: Activo | P5: SKU pack comercial
A6: NUVA-BAR-PB-BX-04 | B6: Estuche Peanut Boost 4 unidades | D6: NUVA | E6: Barritas | F6: BAR | G6: Funcionales | H6: Peanut Boost | I6: PB | J6: Estuche | K6: BX | L6: 4 | M6: CL | N6: un | O6: Activo | P6: SKU pack comercial
A7: NUVA-BAR-CC-BX-04 | B7: Estuche Cacao Crispy 4 unidades | D7: NUVA | E7: Barritas | F7: BAR | G7: Funcionales | H7: Cacao Crispy | I7: CC | J7: Estuche | K7: BX | L7: 4 | M7: CL | N7: un | O7: Activo | P7: SKU pack comercial
A8: NUVA-BAR-BM-CS-24 | B8: Caja master Berry Mix 24 unidades | D8: NUVA | E8: Barritas | F8: BAR | G8: Funcionales | H8: Berry Mix | I8: BM | J8: Caja master | K8: CS | L8: 24 | M8: CL | N8: un | O8: Activo | P8: SKU pack comercial
A9: NUVA-BAR-PB-CS-24 | B9: Caja master Peanut Boost 24 unidades | D9: NUVA | E9: Barritas | F9: BAR | G9: Funcionales | H9: Peanut Boost | I9: PB | J9: Caja master | K9: CS | L9: 24 | M9: CL | N9: un | O9: Activo | P9: SKU pack comercial
A10: NUVA-BAR-CC-CS-24 | B10: Caja master Cacao Crispy 24 unidades | D10: NUVA | E10: Barritas | F10: BAR | G10: Funcionales | H10: Cacao Crispy | I10: CC | J10: Caja master | K10: CS | L10: 24 | M10: CL | N10: un | O10: Activo | P10: SKU pack comercial
A11: NUVA-BAR-BM-CS-60 | B11: Caja master Berry Mix 15x4 unidades | D11: NUVA | E11: Barritas | F11: BAR | G11: Funcionales | H11: Berry Mix | I11: BM | J11: Caja master | K11: CS | L11: 60 | M11: CL | N11: un | O11: Activo | P11: SKU logístico
A12: NUVA-BAR-PB-CS-60 | B12: Caja master Peanut Boost 15x4 unidades | D12: NUVA | E12: Barritas | F12: BAR | G12: Funcionales | H12: Peanut Boost | I12: PB | J12: Caja master | K12: CS | L12: 60 | M12: CL | N12: un | O12: Activo | P12: SKU logístico
A13: NUVA-BAR-CC-CS-60 | B13: Caja master Cacao Crispy 15x4 unidades | D13: NUVA | E13: Barritas | F13: BAR | G13: Funcionales | H13: Cacao Crispy | I13: CC | J13: Caja master | K13: CS | L13: 60 | M13: CL | N13: un | O13: Activo | P13: SKU logístico
