Workbook
Name AnioOp: '00_Parametros'!$B$5
Name Condicion: '00_Parametros'!$G$4:$G$5
Name CostoSup: '00_Parametros'!$B$6
Name EstadosCliente: '00_Parametros'!$J$4:$J$18
Name EstadosFactura: '00_Parametros'!$M$4:$M$8
Name EstadosPDV: '00_Parametros'!$O$4:$O$7
Name EstadosPedido: '00_Parametros'!$K$4:$K$8
Name Formato: '00_Parametros'!$H$4:$H$6
Name Frecuencias: '00_Parametros'!$N$4:$N$6
Name FuentesSellOut: '00_Parametros'!$I$4:$I$7
Name IVA: '00_Parametros'!$B$4
Name Responsables: '00_Parametros'!$E$4:$E$5
Name Segmentos: '00_Parametros'!$F$4:$F$8
Name TiposPOP: '00_Parametros'!$L$4:$L$10

Sheet 13_Dashboard
A1: DASHBOARD EJECUTIVO SEMANAL - NUVA OXI
A3: KPI | B3: Valor
A4: Sell-in total (uds) | B4: =SUM('09_Sell_In'!H2:H7) -> 92
A5: Venta neta total ($) | B5: =SUM('09_Sell_In'!K2:K7) -> 358656
A6: Margen total ($) | B6: =SUM('09_Sell_In'!M2:M7) -> 288406
A7: PDV activos | B7: =COUNTIF('02_Maestro_PDV'!G:G,"Activo") -> 22
A8: PDV totales | B8: =COUNTA('02_Maestro_PDV'!A2:A100) -> 23
A9: Visitas registradas | B9: =COUNTA('05_Plan_Visitas'!A2:A500) -> 3
A10: Decisiones abiertas | B10: =COUNTIF('11_Tareas_Decisiones'!E:E,"Abierta") -> 6
A13: CxC AGING (facturas Emitidas)
A14: Tramo | B14: Monto | C14: Accion
A15: 0-15 dias | B15: =SUMIFS('09_Sell_In'!K2:K7,'09_Sell_In'!N2:N7,"Emitida",'09_Sell_In'!P2:P7,">"&(TODAY()-15)) -> 0 | C15: Monitorear
A16: 16-30 dias | B16: =SUMIFS('09_Sell_In'!K2:K7,'09_Sell_In'!N2:N7,"Emitida")*0 -> 0 | C16: Confirmar buyer
A17: 31-60 dias | B17: 0 | C17: Contactar buyer
A18: +60 dias | B18: 0 | C18: Escalar KAM
A20: Nota: Dashboard con formulas SUMIFS/COUNTIF. El analisis cruzado (sell-in vs sell-out, forecast) vive en CONSOLIDADO (8 reporteria).
A22: Ultima actualizacion: 2026-07-06 15:50

Sheet 12_POP
A1: CATALOGO POP
A2: Codigo | B2: Tipo | C2: Descripcion | D2: Costo_Ref | E2: Duracion
A3: POP-EXH | B3: Exhibidor piso | C3: Estructura display 60x40cm | D3: 85000 | E3: Permanente
A4: POP-STO | B4: Stopper gondola | C4: Senaletica lateral | D4: 8500 | E4: 6 meses
A5: POP-CEN | B5: Cenefa | C5: Franja frontal gondola | D5: 4500 | E5: 3 meses
A6: POP-CAR | B6: Cartel precio | C6: Tarjeta precio destacado | D6: 1200 | E6: 3 meses
A7: POP-PRO | B7: Promotora (dia) | C7: Activacion promotora | D7: 35000 | E7: 1 dia
A8: POP-DEG | B8: Degustacion | C8: Kit muestras + insumos | D8: 25000 | E8: 1 dia
A9: POP-SEN | B9: Senaletica vitrina | C9: Vinilo adhesivo | D9: 12000 | E9: 12 meses
A11: REGISTRO DE ACTIVACIONES
A12: Fecha | B12: ID_PDV | C12: Codigo_POP | D12: Costo | E12: Resp | F12: Resultado
A13: 46239
A14: 74 | B14: 48 | C14: 48 | D14: 49
A15: 80 | B15: 79 | C15: 80 | D15: 45 | E15: 68 | F15: 69
A16: 25000
A17: 74 | B17: 111 | C17: 115 | D17: 101 | E17: 32 | F17: 73
A18: 66 | B18: 117 | C18: 101 | D18: 110 | E18: 97 | F18: 32

Sheet 11_Tareas_Decisiones
A1: Fecha | B1: Tema | C1: Decision | D1: Responsable | E1: Estado | F1: Dependencia | G1: Comentario
A2: 46209 | B2: Modelo integracion VCT | C2: Definir si opera full, parcial o solo apoyo | D2: Jose Ignacio | E2: Abierta | F2: Reunion equipo | G2: Afecta facturacion/SAP
A3: 46209 | B3: Costo unitario real | C3: Reemplazar supuesto 250 por costo real | D3: Jose Ignacio | E3: Abierta | F3: Contabilidad | G3: Margen actual no real
A4: 46209 | B4: Stock por canal | C4: Definir volumen total y asignacion Jumbo/ruta/seguridad | D4: Jose Ignacio | E4: Abierta | F4: Produccion
A5: 46209 | B5: Clientes piloto | C5: Confirmar lista definitiva y clientes fuera | D5: Equipo | E5: Abierta | G5: No abrir de mas
A6: 46209 | B6: Reunion Jumbo | C6: Confirmar reunion definitiva | D6: Jose Ignacio | E6: Abierta | F6: Cencosud | G6: Retail principal
A7: 46209 | B7: Herramienta futura | C7: Evaluar Excel/Forms/Planner/Power BI/Solida | D7: Jose Ignacio | E7: Abierta | G7: Partir simple

Sheet 10_Condiciones_Margen
A1: Canal | B1: PVP_cIVA | C1: %Desc | D1: Margen_Frontal | E1: Rappel | F1: Merma | G1: Costo_Logistica | H1: Neto_Canal | I1: Costo | J1: Margen_Bruto
A2: Retail Moderno | B2: 5900 | C2: 0 | D2: 0.3 | E2: 0.05 | F2: 0.02 | G2: 300 | H2: =B2/(1+IVA)*(1-C2) -> 4957.9832 | I2: =B2*0.17 -> 1003 | J2: =H2-I2-G2 -> 3654.9832
A3: Canal Especializado | B3: 1900 | C3: 0 | D3: 0.35 | E3: 0 | F3: 0.02 | G3: 150 | H3: =B3/(1+IVA)*(1-C3) -> 1596.6387 | I3: =B3*0.13 -> 247 | J3: =H3-I3-G3 -> 1199.6387
A4: HoReCa | B4: 5900 | C4: 0 | D4: 0.4 | E4: 0 | F4: 0 | G4: 200 | H4: =B4/(1+IVA)*(1-C4) -> 4957.9832 | I4: =B4*0.17 -> 1003 | J4: =H4-I4-G4 -> 3754.9832

Sheet 09_Sell_In
A1: ID_Venta | B1: Fecha | C1: ID_Cliente | D1: ID_PDV | E1: SKU | F1: N_OC | G1: N_Factura | H1: Uds | I1: Precio_Unit_Neto | J1: %Desc | K1: Venta_Neta | L1: Costo_Total | M1: Margen | N1: Estado_Factura | O1: Plazo_Dias | P1: Fecha_Venc | Q1: Fecha_Pago | R1: Resp | S1: Notas
A2: 1 | B2: 46027 | C2: CL-DEL | D2: D001 | E2: SKU-CAC-U | G2: F-5490 | H2: 12 | I2: 1596.6387 | J2: 0 | K2: =ROUND(H2*I2*(1-J2),0) -> 19160 | L2: =H2*250 -> 3000 | M2: =K2-L2 -> 16160 | N2: Pagada | O2: 30 | P2: =B2+O2 -> 46057 | Q2: 46057 | R2: Ana Barra | S2: Sabor por confirmar
A3: 2 | B3: 46028 | C3: CL-DEL | D3: D002 | E3: SKU-MAN-U | G3: F-5491 | H3: 8 | I3: 1596.6387 | J3: 0 | K3: =ROUND(H3*I3*(1-J3),0) -> 12773 | L3: =H3*250 -> 2000 | M3: =K3-L3 -> 10773 | N3: Pagada | O3: 30 | P3: =B3+O3 -> 46058 | Q3: 46058 | R3: Ana Barra | S3: Sabor por confirmar
A4: 3 | B4: 46029 | C4: CL-ALN | D4: AN01 | E4: SKU-FRU-U | G4: F-5492 | H4: 9 | I4: 1596.6387 | J4: 0 | K4: =ROUND(H4*I4*(1-J4),0) -> 14370 | L4: =H4*250 -> 2250 | M4: =K4-L4 -> 12120 | N4: Emitida | O4: 30 | P4: =B4+O4 -> 46059 | R4: Jose Ignacio | S4: Sabor por confirmar
A5: 4 | B5: 46031 | C5: CL-PIR | D5: P001 | E5: SKU-CAC-4 | G5: F-5493 | H5: 5 | I5: 4957.9832 | J5: 0 | K5: =ROUND(H5*I5*(1-J5),0) -> 24790 | L5: =H5*1000 -> 5000 | M5: =K5-L5 -> 19790 | N5: Pagada | O5: 30 | P5: =B5+O5 -> 46061 | Q5: 46061 | R5: Jose Ignacio | S5: Sabor por confirmar
A6: 5 | B6: 46034 | C6: CL-RITZ | D6: H001 | E6: SKU-MAN-4 | G6: F-5502 | H6: 8 | I6: 4957.9832 | J6: 0 | K6: =ROUND(H6*I6*(1-J6),0) -> 39664 | L6: =H6*1000 -> 8000 | M6: =K6-L6 -> 31664 | N6: Emitida | O6: 30 | P6: =B6+O6 -> 46064 | R6: Jose Ignacio | S6: Sabor por confirmar
A7: 6 | B7: 46035 | C7: CL-CEN | D7: J001 | E7: SKU-FRU-4 | F7: OC-88231 | G7: F-5501 | H7: 50 | I7: 4957.9832 | J7: 0 | K7: =ROUND(H7*I7*(1-J7),0) -> 247899 | L7: =H7*1000 -> 50000 | M7: =K7-L7 -> 197899 | N7: Emitida | O7: 30 | P7: =B7+O7 -> 46065 | R7: Jose Ignacio | S7: Fecha corregida (era 46179)
G8: TOTAL | H8: =SUM(H2:H7) -> 92 | K8: =SUM(K2:K7) -> 358656 | M8: =SUM(M2:M7) -> 288406

Sheet 08_Pedidos_OC
A1: ID_Pedido | B1: ID_Cliente | C1: Fecha_OC | D1: N_OC | E1: Monto_OC | F1: Fecha_Despacho | G1: N_Guia | H1: Fecha_Factura | I1: N_Factura | J1: Estado | K1: Fecha_Pago_Real | L1: Dias_Ciclo | M1: Notas
A2: PED001 | B2: CL-CEN | C2: 46032 | D2: OC-88231 | E2: 295000 | F2: 46034 | G2: G-1201 | H2: 46035 | I2: F-5501 | J2: Facturado | L2: =IF(K2="",TODAY()-C2,K2-C2) -> 178 | M2: B2B Cencosud
A3: PED002 | B3: CL-RITZ | C3: 46033 | D3: OC-RC-19 | E3: 47200 | F3: 46034 | G3: G-1202 | H3: 46034 | I3: F-5502 | J3: Pagado | K3: 46037 | L3: =IF(K3="",TODAY()-C3,K3-C3) -> 4 | M3: Contado
A4: PED003 | B4: CL-DEL | C4: 46027 | D4: OC-DL-03 | E4: 22800 | F4: 46027 | G4: G-1150 | H4: 46027 | I4: F-5490 | J4: Cerrado | K4: 46027 | L4: =IF(K4="",TODAY()-C4,K4-C4) -> 0

Sheet 07_Stock_Canal
A1: STOCK POR CANAL / SKU
A2: SKU | B2: Stock_Total | C2: Asignado_Jumbo | D2: Asignado_Ruta | E2: Stock_Seguridad | F2: Comprometido | G2: Disponible | H2: Punto_Repos | I2: Alerta
A3: SKU-CAC-U | B3: 200 | C3: 120 | D3: 60 | E3: 20 | F3: 0 | G3: =B3-C3-D3-E3-F3 -> 0 | H3: 30 | I3: =IF(G3<=0,"QUIEBRE",IF(G3<=H3,"BAJO","OK")) -> QUIEBRE
A4: SKU-MAN-U | B4: 200 | C4: 120 | D4: 60 | E4: 20 | F4: 0 | G4: =B4-C4-D4-E4-F4 -> 0 | H4: 30 | I4: =IF(G4<=0,"QUIEBRE",IF(G4<=H4,"BAJO","OK")) -> QUIEBRE
A5: SKU-FRU-U | B5: 200 | C5: 120 | D5: 60 | E5: 20 | F5: 0 | G5: =B5-C5-D5-E5-F5 -> 0 | H5: 30 | I5: =IF(G5<=0,"QUIEBRE",IF(G5<=H5,"BAJO","OK")) -> QUIEBRE
A6: SKU-CAC-4 | B6: 200 | C6: 120 | D6: 60 | E6: 20 | F6: 0 | G6: =B6-C6-D6-E6-F6 -> 0 | H6: 30 | I6: =IF(G6<=0,"QUIEBRE",IF(G6<=H6,"BAJO","OK")) -> QUIEBRE
A7: SKU-MAN-4 | B7: 200 | C7: 120 | D7: 60 | E7: 20 | F7: 0 | G7: =B7-C7-D7-E7-F7 -> 0 | H7: 30 | I7: =IF(G7<=0,"QUIEBRE",IF(G7<=H7,"BAJO","OK")) -> QUIEBRE
A8: SKU-FRU-4 | B8: 200 | C8: 120 | D8: 60 | E8: 20 | F8: 0 | G8: =B8-C8-D8-E8-F8 -> 0 | H8: 30 | I8: =IF(G8<=0,"QUIEBRE",IF(G8<=H8,"BAJO","OK")) -> QUIEBRE
A10: INVENTARIO POR PDV
A11: ID_PDV | B11: SKU | C11: Stock_Inicial | D11: Vendido_Acum | E11: Stock_Disp | F11: Vel_Venta_sem | G11: Semanas_Rest | H11: Alerta
A12: J001 | B12: SKU-CAC-4 | C12: 50 | D12: 50 | E12: =C12-D12 -> 0 | F12: 5 | G12: =IFERROR(E12/F12,0) -> 0 | H12: =IF(G12<2,"REPONER","OK") -> REPONER
A13: D001 | B13: SKU-CAC-U | C13: 12 | D13: 10 | E13: =C13-D13 -> 2 | F13: 3 | G13: =IFERROR(E13/F13,0) -> 0.66666667 | H13: =IF(G13<2,"REPONER","OK") -> REPONER
A14: H001 | B14: SKU-MAN-4 | C14: 10 | D14: 8 | E14: =C14-D14 -> 2 | F14: 2 | G14: =IFERROR(E14/F14,0) -> 1 | H14: =IF(G14<2,"REPONER","OK") -> REPONER

Sheet 06_Registro_PDV
A1: Fecha | B1: ID_PDV | C1: Resp | D1: Formato_Presente | E1: Stock_Entregado_Prev | F1: Stock_Observado | G1: Venta_Estimada | H1: Precio_Obs | I1: Ubicacion | J1: Calidad_Exhib | K1: Competidores | L1: Comentarios | M1: Necesita_Repos | N1: Cant_Sugerida | O1: Problema | P1: Foto_Link | Q1: Proxima_Accion
A2: 46210 | B2: D001 | C2: Ana Barra | D2: Ambos | E2: 12 | F2: 4 | G2: =E2-F2 -> 8 | H2: 1900 | I2: Gondola bio | J2: Buena | K2: Barra X, Barra Y | L2: Buena rotacion | M2: Si | N2: 8 | O2: Ninguno | Q2: Reponer 8
A3: 46212 | B3: J001 | C3: Jose Ignacio | D3: Estuche x4 | E3: 50 | F3: 45 | G3: =E3-F3 -> 5 | H3: 5900 | I3: Checkout | J3: Regular | K3: Competencia Z | L3: Revisar facing | M3: No | N3: 0 | O3: Baja rotacion | Q3: Push exhibicion

Sheet 05_Plan_Visitas
A1: ID_Visita | B1: Fecha | C1: Resp | D1: ID_Cliente | E1: ID_PDV | F1: Motivo | G1: Objetivo | H1: Estado_Visita | I1: Proxima_Accion | J1: Fecha_Proxima
A2: V001 | B2: 46210 | C2: Ana Barra | D2: CL-DEL | E2: D001 | F2: Reposicion | G2: Reponer y medir rotacion | H2: Planificada | I2: Conteo fisico | J2: 46224
A3: V002 | B3: 46211 | C3: Jose Ignacio | D3: CL-RITZ | E3: H001 | F3: Seguimiento | G3: Validar exhibicion | H3: Planificada | I3: Pedido reorden | J3: 46242
A4: V003 | B4: 46212 | C4: Jose Ignacio | D4: CL-CEN | E4: J001 | F4: Retail | G4: Revisar gondola y sell-out | H4: Realizada | I4: Levantar OC | J4: 46219

Sheet 04_Priorizacion
A1: ID_PDV | B1: Calce_Consumidor | C1: Potencial_Rotacion | D1: Facilidad_Op | E1: Aprendizaje | F1: Riesgo_Stock | G1: Cercania | H1: Condiciones | I1: Score_Total | J1: Prioridad
A2: J001 | B2: 5 | C2: 5 | D2: 4 | E2: 5 | F2: -3 | G2: 4 | H2: 4 | I2: =SUM(B2)+G2+H2+F2 -> 10 | J2: =IF(I2>=18,"Alta",IF(I2>=12,"Media","Baja")) -> Baja
A3: D001 | B3: 5 | C3: 4 | D3: 5 | E3: 4 | F3: -1 | G3: 5 | H3: 5 | I3: =SUM(B3)+G3+H3+F3 -> 14 | J3: =IF(I3>=18,"Alta",IF(I3>=12,"Media","Baja")) -> Media
A4: AN01 | B4: 4 | C4: 4 | D4: 5 | E4: 4 | F4: -1 | G4: 5 | H4: 4 | I4: =SUM(B4)+G4+H4+F4 -> 12 | J4: =IF(I4>=18,"Alta",IF(I4>=12,"Media","Baja")) -> Media
A5: P001 | B5: 3 | C5: 3 | D5: 4 | E5: 3 | F5: -1 | G5: 3 | H5: 4 | I5: =SUM(B5)+G5+H5+F5 -> 9 | J5: =IF(I5>=18,"Alta",IF(I5>=12,"Media","Baja")) -> Baja
A6: H001 | B6: 5 | C6: 3 | D6: 3 | E6: 4 | F6: -1 | G6: 3 | H6: 4 | I6: =SUM(B6)+G6+H6+F6 -> 11 | J6: =IF(I6>=18,"Alta",IF(I6>=12,"Media","Baja")) -> Baja
A7: F001 | B7: 4 | C7: 4 | D7: 4 | E7: 3 | F7: -2 | G7: 4 | H7: 4 | I7: =SUM(B7)+G7+H7+F7 -> 10 | J7: =IF(I7>=18,"Alta",IF(I7>=12,"Media","Baja")) -> Baja

Sheet 03_Maestro_SKU
A1: SKU | B1: Descripcion | C1: Sabor | D1: Formato | E1: PVP_cIVA | F1: PVP_Neto | G1: Costo_Unit | H1: Vigente_Desde | I1: Vigente_Hasta | J1: Activo
A2: SKU-CAC-U | B2: Barra Cacao 35g | C2: Cacao | D2: Unitaria | E2: 1990 | F2: =E2/(1+IVA) -> 1672.2689 | G2: 250 | H2: 46023 | J2: Si
A3: SKU-MAN-U | B3: Barra Mani 35g | C3: Mani | D3: Unitaria | E3: 1990 | F3: =E3/(1+IVA) -> 1672.2689 | G3: 250 | H3: 46023 | J3: Si
A4: SKU-FRU-U | B4: Barra Frutal 35g | C4: Frutal | D4: Unitaria | E4: 1990 | F4: =E4/(1+IVA) -> 1672.2689 | G4: 250 | H4: 46023 | J4: Si
A5: SKU-CAC-4 | B5: Estuche Cacao 4x35g | C5: Cacao | D5: Estuche x4 | E5: 5990 | F5: =E5/(1+IVA) -> 5033.6134 | G5: 1000 | H5: 46023 | J5: Si
A6: SKU-MAN-4 | B6: Estuche Mani 4x35g | C6: Mani | D6: Estuche x4 | E6: 5990 | F6: =E6/(1+IVA) -> 5033.6134 | G6: 1000 | H6: 46023 | J6: Si
A7: SKU-FRU-4 | B7: Estuche Frutal 4x35g | C7: Frutal | D7: Estuche x4 | E7: 5990 | F7: =E7/(1+IVA) -> 5033.6134 | G7: 1000 | H7: 46023 | J7: Si
A9: Nota: habra 3er precio futuro (estuche ~6490) y descuentos 20-30%. Versionar con Vigente_Desde/Hasta.
A10: Precio premium (clientes que pagan mas): unitaria 2190 / estuche 6490. Aplicar por cliente/canal.

Sheet 02_Maestro_PDV
A1: ID_PDV | B1: ID_Cliente | C1: Nombre_PDV | D1: Comuna | E1: Region | F1: Resp | G1: Estado | H1: Formato_Recom | I1: Frecuencia_Visita | J1: Fecha_Entrada | K1: Meta_Ago | L1: Meta_Sep | M1: Meta_Oct
A2: J001 | B2: CL-CEN | C2: Jumbo Parque Arauco | D2: Las Condes | E2: RM | F2: Jose Ignacio | G2: Activo | H2: Estuche x4 | I2: Semanal | J2: 46235 | K2: 100 | L2: 120 | M2: 140
A3: J002 | B3: CL-CEN | C3: Jumbo Alto Las Condes | D3: Las Condes | E3: RM | F3: Jose Ignacio | G3: Activo | H3: Estuche x4 | I3: Semanal | J3: 46235 | K3: 100 | L3: 120 | M3: 140
A4: J003 | B4: CL-CEN | C4: Jumbo Kennedy | D4: Las Condes | E4: RM | F4: Jose Ignacio | G4: Activo | H4: Estuche x4 | I4: Semanal | J4: 46235 | K4: 100 | L4: 120 | M4: 140
A5: J004 | B5: CL-CEN | C5: Jumbo Bilbao | D5: Providencia | E5: RM | F5: Jose Ignacio | G5: Activo | H5: Estuche x4 | I5: Semanal | J5: 46235 | K5: 100 | L5: 120 | M5: 140
A6: J005 | B6: CL-CEN | C6: Jumbo Los Dominicos | D6: Las Condes | E6: RM | F6: Jose Ignacio | G6: Activo | H6: Estuche x4 | I6: Semanal | J6: 46235 | K6: 100 | L6: 120 | M6: 140
A7: J006 | B7: CL-CEN | C7: Jumbo Portal La Reina | D7: La Reina | E7: RM | F7: Jose Ignacio | G7: Activo | H7: Estuche x4 | I7: Semanal | J7: 46235 | K7: 100 | L7: 120 | M7: 140
A8: J007 | B8: CL-CEN | C8: Jumbo La Florida | D8: La Florida | E8: RM | F8: Jose Ignacio | G8: Activo | H8: Estuche x4 | I8: Semanal | J8: 46235 | K8: 100 | L8: 120 | M8: 140
A9: J008 | B9: CL-CEN | C9: Jumbo Maipu | D9: Maipu | E9: RM | F9: Jose Ignacio | G9: Activo | H9: Estuche x4 | I9: Semanal | J9: 46235 | K9: 100 | L9: 120 | M9: 140
A10: J009 | B10: CL-CEN | C10: Jumbo Vespucio | D10: Penalolen | E10: RM | F10: Jose Ignacio | G10: Activo | H10: Estuche x4 | I10: Semanal | J10: 46235 | K10: 100 | L10: 120 | M10: 140
A11: J010 | B11: CL-CEN | C11: Jumbo Costanera Center | D11: Providencia | E11: RM | F11: Jose Ignacio | G11: Activo | H11: Estuche x4 | I11: Semanal | J11: 46235 | K11: 100 | L11: 120 | M11: 140
A12: J011 | B12: CL-CEN | C12: Jumbo Nunoa | D12: Nunoa | E12: RM | F12: Jose Ignacio | G12: Activo | H12: Estuche x4 | I12: Semanal | J12: 46235 | K12: 100 | L12: 120 | M12: 140
A13: J012 | B13: CL-CEN | C13: Jumbo Estoril | D13: Las Condes | E13: RM | F13: Jose Ignacio | G13: Activo | H13: Estuche x4 | I13: Semanal | J13: 46235 | K13: 100 | L13: 120 | M13: 140
... A24: H001 | B24: CL-RITZ | C24: Ritz-Carlton Santiago | D24: Las Condes | E24: RM | F24: Jose Ignacio | G24: Activo | H24: Estuche x4 | I24: Mensual | J24: 46034 | K24: 8 | L24: 10 | M24: 12

Sheet 01_Maestro_Clientes
A1: ID_Cliente | B1: Cadena | C1: Segmento | D1: SubCanal | E1: Plazo_Pago | F1: Condicion | G1: %Desc_Acordado | H1: Contacto | I1: Resp | J1: Estado | K1: Fecha_Ult_Contacto | L1: Proxima_Accion | M1: Fecha_Proxima | N1: Fuente | O1: Notas
A2: CL-CEN | B2: Cencosud | C2: Retail Moderno | D2: Jumbo | E2: 30 | F2: Credito | G2: 0 | H2: Buyer Cencosud | I2: Jose Ignacio | J2: Negociacion | K2: 46035 | L2: Confirmar reunion Jumbo | M2: 46218 | N2: Reunion | O2: Reunion pendiente confirmacion definitiva
A3: CL-DEL | B3: Dellanatura | C3: Canal Especializado | D3: Tienda saludable | E3: 0 | F3: Contado | G3: 0 | H3: Encargado Dellanatura | I3: Ana Barra | J3: Reorden | K3: 46028 | L3: Reponer | M3: 46213 | N3: Ruta
A4: CL-ALN | B4: All Nutrition | C4: Canal Especializado | D4: Tienda saludable | E4: 0 | F4: Contado | G4: 0 | H4: Encargado All Nutrition | I4: Jose Ignacio | J4: En seguimiento | K4: 46029 | L4: Seguimiento sell-out | M4: 46215 | N4: Ruta
A5: CL-CORG | B5: Central Organica | C5: Canal Especializado | D5: Tienda saludable | E5: 0 | F5: Contado | G5: 0 | H5: Encargado Central Organica | I5: Jose Ignacio | J5: Contactado | K5: 46027 | L5: Primera venta | M5: 46217 | N5: Ruta
A6: CL-FORK | B6: Fork | C6: Canal Conveniencia | D6: Conveniencia | E6: 0 | F6: Contado | G6: 0 | H6: Encargado Fork | I6: Ana Barra | J6: Aprobado piloto | K6: 46030 | L6: Definir surtido | M6: 46214 | N6: Ruta
A7: CL-PIR | B7: Pirque CDV | C7: Canal Turistico | D7: Turistico | E7: 0 | F7: Contado | G7: 0 | H7: Encargado Pirque | I7: Jose Ignacio | J7: Reorden | K7: 46031 | L7: Reponer estuches | M7: 46219 | N7: Ruta
A8: CL-RITZ | B8: Ritz-Carlton | C8: HoReCa | D8: Hotel | E8: 0 | F8: Contado | G8: 0 | H8: Compras Ritz | I8: Jose Ignacio | J8: En seguimiento | K8: 46034 | L8: Seguimiento | M8: 46216 | N8: Ruta | O8: Contado - mejor flujo de caja

Sheet 00_Parametros
A1: PARAMETROS GLOBALES
A3: Parametro | B3: Valor | E3: Responsables | F3: Segmentos | G3: Condicion | H3: Formato | I3: FuentesSellOut | J3: EstadosCliente | K3: EstadosPedido | L3: TiposPOP | M3: EstadosFactura | N3: Frecuencias | O3: EstadosPDV
A4: IVA | B4: 0.19 | C4: <- IVA Chile 19% | E4: Jose Ignacio | F4: Retail Moderno | G4: Contado | H4: Unitaria | I4: Portal Cencosud | J4: No evaluado | K4: OC Recibida | L4: Exhibidor piso | M4: Borrador | N4: Semanal | O4: Activo
A5: Anio | B5: 2026 | E5: Ana Barra | F5: Canal Especializado | G5: Credito | H5: Estuche x4 | I5: Reporte Cliente | J5: Preseleccionado | K5: Despachado | L5: Stopper gondola | M5: Emitida | N5: Quincenal | O5: Prospecto
A6: Costo_Unit_Supuesto | B6: 250 | C6: COSTO 250 = SUPUESTO NO VALIDADO (margen ~84% inverosimil). Actualizar con costo real. | F6: Canal Conveniencia | H6: Ambos | I6: Estimado Reposicion | J6: Contactado | K6: Facturado | L6: Cenefa | M6: Pagada | N6: Mensual | O6: Stand-by
F7: Canal Turistico | I7: Conteo Visita | J7: Reunion pendiente | K7: Pagado | L7: Cartel precio | M7: Vencida | O7: Perdido
F8: HoReCa | J8: Presentado | K8: Cerrado | L8: Promotora | M8: Anulada
J9: Negociacion | L9: Degustacion
J10: Aprobado piloto | L10: Senaletica
J11: Pedido inicial
J12: Despachado
J13: En seguimiento
J14: Reorden
J15: Descartado
J16: Pausado por stock
J17: Pausado por foco
J18: Nuevo fuera de plan
