Workbook
Name cfg_AnioResumen: Resumen!$B$3
Name cfg_DiasCobertura: Inicio!$B$29
Name cfg_DiasVencer: Inicio!$B$19
Name cfg_IVA: Inicio!$B$13
Name cfg_MontoPendiente: Inicio!$B$18
Name cfg_PctSeguridad: Inicio!$B$30
Name cfg_StockCritico: Inicio!$B$16
Name cfg_StockObservar: Inicio!$B$17
Name cfg_VentaAlta: Inicio!$B$34
Name cfg_VentaBaja: Inicio!$B$15
Name cfg_VentanaDemanda: Inicio!$B$31
Name cfg_VentaRecienteDias: Inicio!$B$14
Name lst_Bodega: Bodegas!$A$2:$A$50
Name lst_Canal: Inicio!$E$5:$E$13
Name lst_CondPago: Inicio!$H$5:$H$9
Name lst_EstadoCliente: Inicio!$G$5:$G$8
Name lst_Frecuencia: Inicio!$K$5:$K$7
Name lst_StatusPago: Inicio!$F$5:$F$9
Name rng_PDV: Clientes_PDV!$A$2:$A$250
Name rng_SKU: Maestro_SKU!$A$2:$A$500

Sheet Inicio
A1: NUVA OXI · Control Comercial — CONFIDENCIAL Y RESTRINGIDO (uso interno)
A2: GUÍA — cómo funciona, se edita, se alimenta y crece (clic aquí)
A3: Cómo se usa en simple | E3: Listas editables para desplegables
A4: 1 | B4: Dashboard: mirar cada lunes qué está en rojo o prioridad alta. | E4: Canal | F4: Status pago | G4: Estado cliente | H4: Condición pago | I4: Prioridad | J4: Estado stock | K4: Frecuencia
A5: 2 | B5: Cobertura: revisar el detalle por punto de venta, visita, venta, pago y stock. | E5: Retail | F5: Pendiente | G5: Activo | H5: Contado | I5: Alta | J5: Crítico | K5: Semanal
A6: 3 | B6: Clientes_PDV: agregar nuevos clientes o salas. Esa hoja alimenta Cobertura. | E6: Conveniencia | F6: Pagada | G6: Pausado | H6: Crédito 15 días | I6: Media | J6: Observar | K6: Quincenal
A7: 4 | B7: Ventas_SellIn: ingresar facturas reales. No usar PVP; solo precio neto facturado. | E7: Farmacias | F7: Parcial | G7: Prospecto | H7: Crédito 30 días | I7: Baja | J7: OK | K7: Mensual
A8: 5 | B8: Margen_Frontal: simular precio/margen aparte, sin afectar ventas ni cobertura. | E8: Especializadas | F8: Vencida | G8: Inactivo | H8: Crédito 45 días
A9: 6 | B9: SellOut_Jumbo: pegar exportaciones futuras de Cencosud/Jumbo cuando existan. | E9: HORECA | F9: Nota crédito | H9: Crédito 60 días
E10: Tradicional
A11: Condiciones editables | E11: Ecommerce
A12: Condición | B12: Valor editable | C12: Qué significa | E12: Corporativo
A13: IVA | B13: 0.19 | C13: Se usa para pasar neto a bruto y viceversa. | E13: Distribuidor
A14: Venta reciente últimos días | B14: 30 | C14: Período usado en cobertura y dashboard.
A15: Venta baja si es menor a | B15: 500000 | C15: Si venta neta 30d queda bajo este monto, se marca baja. | E15: Leyenda
A16: Stock crítico PDV barras | B16: 8 | C16: Barras equivalentes en sala bajo este nivel = crítico. | E16: Amarillo | F16: Dato editable
A17: Stock en observación PDV barras | B17: 20 | C17: Barras equivalentes en sala bajo este nivel = observar. | E17: Gris | F17: Fórmula; no tocar
A18: Monto pendiente relevante | B18: 100000 | C18: Deuda sobre este monto eleva prioridad. | E18: Morado | F18: Título/encabezado
A19: Factura próxima a vencer días | B19: 7 | C19: Días hacia adelante para marcar próxima a vencer.
A21: Regla: NETO = sin IVA (lo que facturas y analizas). Con IVA = lo que se paga y cobra.
A22: Frecuencia de visita
A23: Frecuencia | B23: Días máximos | C23: Regla
A24: Semanal | B24: 7 | C24: Atrasado desde 8 días
A25: Quincenal | B25: 15 | C25: Atrasado desde 16 días
A26: Mensual | B26: 30 | C26: Atrasado desde 31 días
A28: Parámetros de inventario (editable)
A29: Días de cobertura objetivo | B29: 30 | C29: Cuántos días de venta quieres tener en stock
A30: % stock de seguridad | B30: 0.2 | C30: Colchón sobre el objetivo ante quiebres
A31: Ventana de demanda (días) | B31: 30 | C31: Período de sell-in para el promedio (30/60/90)
A33: Reglas de rotación (editable)
A34: Rotación ALTA: venta 30d ≥ | B34: 1000000 | C34: Sobre este monto, el PDV rota bien
A35: Rotación BAJA: venta 30d < | B35: =B15 -> 500000 | C35: Usa el mismo umbral de 'Venta baja' (B15)
A36: Rotación MEDIA: | B36: entre ambos | C36: Entre el monto de BAJA y el de ALTA
A38: Qué define cada estado (los valores se editan arriba)
A39: Stock CRÍTICO: barras ≤ | B39: =B16 -> 8
A40: Stock OBSERVAR: barras ≤ | B40: =B17 -> 20
A41: Venta BAJA: venta 30d < | B41: =B15 -> 500000
A42: Deuda RELEVANTE: monto ≥ | B42: =B18 -> 100000
A43: Rotación ALTA: venta 30d ≥ | B43: =B34 -> 1000000
A44: Factura POR VENCER: días ≤ | B44: =B19 -> 7
A45: Visita ATRASADA: cuando pasan más días que su frecuencia (ver tabla arriba).

Sheet Guia
A1: Guía rápida para Ana | Cómo leer y cargar el archivo
A3: Objetivo del archivo
A4: Ayudar a decidir cada lunes qué puntos de venta visitar, cuáles están vendiendo, cuáles tienen facturas pendientes y dónde falta stock. No busca reemplazar ERP ni contabilidad.
A6: Qué mirar primero
A7: • | B7: 1. Abrir Dashboard y revisar prioridad alta.
A8: • | B8: 2. Ir a Cobertura para ver la razón: visita atrasada, sin venta, deuda o stock crítico y *Revisar en Clientes_PDV la ultima visita.
A9: • | B9: 3. Filtrar por Canal o Cliente si se saldrá a terreno por zona/cuenta.
A11: Dónde cargar información
A12: • | B12: Clientes nuevos o nuevas salas: Clientes_PDV.
A13: • | B13: Facturas/sell-in: Ventas_SellIn. Ingresar fecha, factura, PDV_ID, SKU, cantidad, precio neto facturado y status de pago.
A14: • | B14: Stock observado en terreno: Stock_PDV.
A15: • | B15: Sell-out de Jumbo/Cencosud: SellOut_Jumbo, cuando exista exportación.
A16: • | B16: Simulación de precio y margen: Margen_Frontal.
A18: Regla de colores
A19: • | B19: Amarillo = se puede editar.
A20: • | B20: Gris = fórmula, mejor no tocar.
A21: • | B21: Morado = encabezado o título.
A22: • | B22: Si algo sale raro, revisar primero si falta PDV_ID, SKU o fecha.
A24: Conceptos simples
A25: • | B25: Sell-in: venta facturada al cliente o punto de venta.
A26: • | B26: Sell-out: venta desde la sala hacia consumidor final, cuando el retailer la informe.
A27: • | B27: Margen frontal: margen que el cliente obtiene entre el PVP neto y el precio neto que le facturamos.
A28: • | B28: Barras equivalentes: convierte unidades, estuches y cajas master a barras para comparar stock y venta.
A29: Regla de dinero: NETO = sin IVA (ventas y análisis). Con IVA = pagos, deuda y facturas.
A30: Cómo se edita, se alimenta y crece
A31: 1. | B31: Editar: solo celdas AMARILLAS. Las grises son fórmulas (se calculan solas).
A32: 2. | B32: Alimentar ventas: Ventas_SellIn, una fila por factura (usa los desplegables).
A33: 3. | B33: Terreno: registra visitas y stock de sala en Clientes_PDV y Stock_PDV.
A34: 4. | B34: Producto nuevo: agrégalo en Maestro_SKU; aparece solo en el plan y en las listas.
A35: 5. | B35: Cliente/sala nueva: agrégala en Clientes_PDV; aparece sola en Cobertura.
A36: 6. | B36: Inventario: escribe tu bodega en Plan_Inventario; te dice cuánto reponer.
A37: 7. | B37: Ajustes: cambia umbrales (venta, stock, cobertura, rotación) en Inicio, sin tocar fórmulas.
A38: 8. | B38: Crece hasta: 250 clientes/PDV y 800 facturas. Para más, se estiran los rangos.

Sheet Dashboard
A1: Dashboard semanal · Revisión del lunes — CONFIDENCIAL
B3: Indicador | C3: Valor | E3: Parámetros activos (se leen desde Inicio) | F3: Valor
B4: Fecha control | C4: =TODAY() -> 46213 | E4: Venta reciente días | F4: =Inicio!B14 -> 30
B5: PDV activos | C5: =COUNTIF(Clientes_PDV!$I$2:$I$250,"Activo") -> 11 | E5: Venta baja menor a | F5: =Inicio!B15 -> 500000
B6: PDV prioridad alta | C6: =COUNTIF(Cobertura!$Q$2:$Q$250,"Alta") -> 10 | E6: Semanal días | F6: =Inicio!B24 -> 7
B7: Venta sell-in 30d NETA (sin IVA) | C7: =SUM(Cobertura!$I$2:$I$250) -> 2871252 | E7: Quincenal días | F7: =Inicio!B25 -> 15
B8: Deuda total (con IVA) | C8: =SUM(Cobertura!$M$2:$M$250) -> 2688041.9 | E8: Mensual días | F8: =Inicio!B26 -> 30
B9: PDV stock crítico | C9: =COUNTIF(Cobertura!$P$2:$P$250,"Crítico") -> 4 | E9: Factura próxima a vencer | F9: =Inicio!B19 -> 7
B11: ⚙ Ir a Configuración (hoja Inicio)
B12: Puntos de venta a gestionar esta semana
A13: ID | B13: Punto de venta | C13: Cliente | D13: Canal | E13: Estado visita | F13: Estado venta | G13: Estado pago | H13: Estado stock | I13: Prioridad
A14: =Cobertura!A2 -> PDV-001 | B14: =Cobertura!D2 -> Jumbo Bilbao | C14: =Cobertura!B2 -> Jumbo | D14: =Cobertura!C2 -> Retail | E14: =Cobertura!H2 -> Vigente | F14: =Cobertura!K2 -> Venta baja | G14: =Cobertura!N2 -> Pendiente menor | H14: =Cobertura!P2 -> OK | I14: =Cobertura!Q2 -> Media
A15: =Cobertura!A3 -> PDV-002 | B15: =Cobertura!D3 -> Jumbo Kennedy | C15: =Cobertura!B3 -> Jumbo | D15: =Cobertura!C3 -> Retail | E15: =Cobertura!H3 -> Atrasado | F15: =Cobertura!K3 -> Venta baja | G15: =Cobertura!N3 -> Sin deuda | H15: =Cobertura!P3 -> Crítico | I15: =Cobertura!Q3 -> Alta
A16: =Cobertura!A4 -> PDV-003 | B16: =Cobertura!D4 -> Jumbo La Reina | C16: =Cobertura!B4 -> Jumbo | D16: =Cobertura!C4 -> Retail | E16: =Cobertura!H4 -> Atrasado | F16: =Cobertura!K4 -> Venta baja | G16: =Cobertura!N4 -> Pendiente menor | H16: =Cobertura!P4 -> OK | I16: =Cobertura!Q4 -> Alta
A17: =Cobertura!A5 -> PDV-004 | B17: =Cobertura!D5 -> Get It Apoquindo | C17: =Cobertura!B5 -> Get It | D17: =Cobertura!C5 -> Conveniencia | E17: =Cobertura!H5 -> Vigente | F17: =Cobertura!K5 -> Venta baja | G17: =Cobertura!N5 -> Pendiente menor | H17: =Cobertura!P5 -> Crítico | I17: =Cobertura!Q5 -> Alta
A18: =Cobertura!A6 -> PDV-005 | B18: =Cobertura!D6 -> Get It Vitacura | C18: =Cobertura!B6 -> Get It | D18: =Cobertura!C6 -> Conveniencia | E18: =Cobertura!H6 -> Atrasado | F18: =Cobertura!K6 -> Venta OK | G18: =Cobertura!N6 -> Pendiente relevante | H18: =Cobertura!P6 -> OK | I18: =Cobertura!Q6 -> Alta
A19: =Cobertura!A7 -> PDV-006 | B19: =Cobertura!D7 -> Aldea Nativa Providencia | C19: =Cobertura!B7 -> Aldea Nativa | D19: =Cobertura!C7 -> Especializadas | E19: =Cobertura!H7 -> Atrasado | F19: =Cobertura!K7 -> Venta baja | G19: =Cobertura!N7 -> Pendiente menor | H19: =Cobertura!P7 -> OK | I19: =Cobertura!Q7 -> Alta
A20: =Cobertura!A8 -> PDV-007 | B20: =Cobertura!D8 -> All Nutrition La Reina | C20: =Cobertura!B8 -> All Nutrition | D20: =Cobertura!C8 -> Especializadas | E20: =Cobertura!H8 -> Atrasado | F20: =Cobertura!K8 -> Venta baja | G20: =Cobertura!N8 -> Pendiente relevante | H20: =Cobertura!P8 -> OK | I20: =Cobertura!Q8 -> Alta
A21: =Cobertura!A9 -> PDV-008 | B21: =Cobertura!D9 -> Ahumada Los Dominicos | C21: =Cobertura!B9 -> Farmacia Ahumada | D21: =Cobertura!C9 -> Farmacias | E21: =Cobertura!H9 -> Vigente | F21: =Cobertura!K9 -> Venta baja | G21: =Cobertura!N9 -> Pendiente menor | H21: =Cobertura!P9 -> Crítico | I21: =Cobertura!Q9 -> Alta
A22: =Cobertura!A10 -> PDV-009 | B22: =Cobertura!D10 -> Cruz Verde Vitacura | C22: =Cobertura!B10 -> Cruz Verde | D22: =Cobertura!C10 -> Farmacias | E22: =Cobertura!H10 -> Atrasado | F22: =Cobertura!K10 -> Venta baja | G22: =Cobertura!N10 -> Pendiente relevante | H22: =Cobertura!P10 -> OK | I22: =Cobertura!Q10 -> Alta
A23: =Cobertura!A11 -> PDV-010 | B23: =Cobertura!D11 -> Sodexo Casa Matriz | C23: =Cobertura!B11 -> Sodexo | D23: =Cobertura!C11 -> Corporativo | E23: =Cobertura!H11 -> Vigente | F23: =Cobertura!K11 -> Venta baja | G23: =Cobertura!N11 -> Pendiente relevante | H23: =Cobertura!P11 -> Crítico | I23: =Cobertura!Q11 -> Alta
A24: =Cobertura!A12 -> PDV-011 | B24: =Cobertura!D12 -> Tres Toques Vitacura | C24: =Cobertura!B12 -> Tres Toques | D24: =Cobertura!C12 -> HORECA | E24: =Cobertura!H12 -> Vigente | F24: =Cobertura!K12 -> Venta baja | G24: =Cobertura!N12 -> Pendiente menor | H24: =Cobertura!P12 -> OK | I24: =Cobertura!Q12 -> Media
A25: =Cobertura!A13 -> PDV-012 | B25: =Cobertura!D13 -> Mundo del Vino Escuela Militar | C25: =Cobertura!B13 -> Mundo del Vino | D25: =Cobertura!C13 -> Especializadas | E25: =Cobertura!H13 -> Vigente | F25: =Cobertura!K13 -> Venta baja | G25: =Cobertura!N13 -> Pendiente relevante | H25: =Cobertura!P13 -> OK | I25: =Cobertura!Q13 -> Alta
A28: Venta acumulada NETA (sin IVA) | D28: Venta acumulada por punto de venta
A29: Desde: | B29: 46023 | C29: (hasta hoy) | D29: Punto de venta | E29: Cliente | F29: Canal | G29: Venta neta acum. | H29: Dirección
A30: Total acumulado: | B30: =SUMIFS(Ventas_SellIn!$L$2:$L$800,Ventas_SellIn!$B$2:$B$800,">="&$B$29) -> 5894865 | D30: =IF(Clientes_PDV!A2="","",Clientes_PDV!D2) -> Jumbo Bilbao | E30: =IF(Clientes_PDV!A2="","",Clientes_PDV!B2) -> Jumbo | F30: =IF(Clientes_PDV!A2="","",Clientes_PDV!C2) -> Retail | G30: =IF(Clientes_PDV!A2="","",SUMIFS(Ventas_SellIn!$L$2:$L$800,Ventas_SellIn!$D$2:$D$800,Clientes_PDV!A2,Ventas_SellIn!$B$2:$B$800,">="&$B$29)) -> 411396 | H30: =IF(Clientes_PDV!A2="","",Clientes_PDV!K2) -> 0
D31: =IF(Clientes_PDV!A3="","",Clientes_PDV!D3) -> Jumbo Kennedy | E31: =IF(Clientes_PDV!A3="","",Clientes_PDV!B3) -> Jumbo | F31: =IF(Clientes_PDV!A3="","",Clientes_PDV!C3) -> Retail | G31: =IF(Clientes_PDV!A3="","",SUMIFS(Ventas_SellIn!$L$2:$L$800,Ventas_SellIn!$D$2:$D$800,Clientes_PDV!A3,Ventas_SellIn!$B$2:$B$800,">="&$B$29)) -> 523920 | H31: =IF(Clientes_PDV!A3="","",Clientes_PDV!K3) -> 0
A32: Canal | B32: Venta neta acum. | D32: =IF(Clientes_PDV!A4="","",Clientes_PDV!D4) -> Jumbo La Reina | E32: =IF(Clientes_PDV!A4="","",Clientes_PDV!B4) -> Jumbo | F32: =IF(Clientes_PDV!A4="","",Clientes_PDV!C4) -> Retail | G32: =IF(Clientes_PDV!A4="","",SUMIFS(Ventas_SellIn!$L$2:$L$800,Ventas_SellIn!$D$2:$D$800,Clientes_PDV!A4,Ventas_SellIn!$B$2:$B$800,">="&$B$29)) -> 71326 | H32: =IF(Clientes_PDV!A4="","",Clientes_PDV!K4) -> 0
A33: =Inicio!$E$5 -> Retail | B33: =IF($A33="","",SUMIFS(Ventas_SellIn!$L$2:$L$800,Ventas_SellIn!$F$2:$F$800,$A33,Ventas_SellIn!$B$2:$B$800,">="&$B$29)) -> 1006642 | D33: =IF(Clientes_PDV!A5="","",Clientes_PDV!D5) -> Get It Apoquindo | E33: =IF(Clientes_PDV!A5="","",Clientes_PDV!B5) -> Get It | F33: =IF(Clientes_PDV!A5="","",Clientes_PDV!C5) -> Conveniencia | G33: =IF(Clientes_PDV!A5="","",SUMIFS(Ventas_SellIn!$L$2:$L$800,Ventas_SellIn!$D$2:$D$800,Clientes_PDV!A5,Ventas_SellIn!$B$2:$B$800,">="&$B$29)) -> 368880 | H33: =IF(Clientes_PDV!A5="","",Clientes_PDV!K5) -> 0
A34: =Inicio!$E$6 -> Conveniencia | B34: =IF($A34="","",SUMIFS(Ventas_SellIn!$L$2:$L$800,Ventas_SellIn!$F$2:$F$800,$A34,Ventas_SellIn!$B$2:$B$800,">="&$B$29)) -> 1713268 | D34: =IF(Clientes_PDV!A6="","",Clientes_PDV!D6) -> Get It Vitacura | E34: =IF(Clientes_PDV!A6="","",Clientes_PDV!B6) -> Get It | F34: =IF(Clientes_PDV!A6="","",Clientes_PDV!C6) -> Conveniencia | G34: =IF(Clientes_PDV!A6="","",SUMIFS(Ventas_SellIn!$L$2:$L$800,Ventas_SellIn!$D$2:$D$800,Clientes_PDV!A6,Ventas_SellIn!$B$2:$B$800,">="&$B$29)) -> 1344388 | H34: =IF(Clientes_PDV!A6="","",Clientes_PDV!K6) -> 0
A35: =Inicio!$E$7 -> Farmacias | B35: =IF($A35="","",SUMIFS(Ventas_SellIn!$L$2:$L$800,Ventas_SellIn!$F$2:$F$800,$A35,Ventas_SellIn!$B$2:$B$800,">="&$B$29)) -> 723604 | D35: =IF(Clientes_PDV!A7="","",Clientes_PDV!D7) -> Aldea Nativa Providencia | E35: =IF(Clientes_PDV!A7="","",Clientes_PDV!B7) -> Aldea Nativa | F35: =IF(Clientes_PDV!A7="","",Clientes_PDV!C7) -> Especializadas | G35: =IF(Clientes_PDV!A7="","",SUMIFS(Ventas_SellIn!$L$2:$L$800,Ventas_SellIn!$D$2:$D$800,Clientes_PDV!A7,Ventas_SellIn!$B$2:$B$800,">="&$B$29)) -> 552872 | H35: =IF(Clientes_PDV!A7="","",Clientes_PDV!K7) -> 0
A36: =Inicio!$E$8 -> Especializadas | B36: =IF($A36="","",SUMIFS(Ventas_SellIn!$L$2:$L$800,Ventas_SellIn!$F$2:$F$800,$A36,Ventas_SellIn!$B$2:$B$800,">="&$B$29)) -> 1735473 | D36: =IF(Clientes_PDV!A8="","",Clientes_PDV!D8) -> All Nutrition La Reina | E36: =IF(Clientes_PDV!A8="","",Clientes_PDV!B8) -> All Nutrition | F36: =IF(Clientes_PDV!A8="","",Clientes_PDV!C8) -> Especializadas | G36: =IF(Clientes_PDV!A8="","",SUMIFS(Ventas_SellIn!$L$2:$L$800,Ventas_SellIn!$D$2:$D$800,Clientes_PDV!A8,Ventas_SellIn!$B$2:$B$800,">="&$B$29)) -> 771763 | H36: =IF(Clientes_PDV!A8="","",Clientes_PDV!K8) -> 0
A37: =Inicio!$E$9 -> HORECA | B37: =IF($A37="","",SUMIFS(Ventas_SellIn!$L$2:$L$800,Ventas_SellIn!$F$2:$F$800,$A37,Ventas_SellIn!$B$2:$B$800,">="&$B$29)) -> 108624 | D37: =IF(Clientes_PDV!A9="","",Clientes_PDV!D9) -> Ahumada Los Dominicos | E37: =IF(Clientes_PDV!A9="","",Clientes_PDV!B9) -> Farmacia Ahumada | F37: =IF(Clientes_PDV!A9="","",Clientes_PDV!C9) -> Farmacias | G37: =IF(Clientes_PDV!A9="","",SUMIFS(Ventas_SellIn!$L$2:$L$800,Ventas_SellIn!$D$2:$D$800,Clientes_PDV!A9,Ventas_SellIn!$B$2:$B$800,">="&$B$29)) -> 12984 | H37: =IF(Clientes_PDV!A9="","",Clientes_PDV!K9) -> 0
A38: =Inicio!$E$10 -> Tradicional | B38: =IF($A38="","",SUMIFS(Ventas_SellIn!$L$2:$L$800,Ventas_SellIn!$F$2:$F$800,$A38,Ventas_SellIn!$B$2:$B$800,">="&$B$29)) -> 0 | D38: =IF(Clientes_PDV!A10="","",Clientes_PDV!D10) -> Cruz Verde Vitacura | E38: =IF(Clientes_PDV!A10="","",Clientes_PDV!B10) -> Cruz Verde | F38: =IF(Clientes_PDV!A10="","",Clientes_PDV!C10) -> Farmacias | G38: =IF(Clientes_PDV!A10="","",SUMIFS(Ventas_SellIn!$L$2:$L$800,Ventas_SellIn!$D$2:$D$800,Clientes_PDV!A10,Ventas_SellIn!$B$2:$B$800,">="&$B$29)) -> 710620 | H38: =IF(Clientes_PDV!A10="","",Clientes_PDV!K10) -> 0
A39: =Inicio!$E$11 -> Ecommerce | B39: =IF($A39="","",SUMIFS(Ventas_SellIn!$L$2:$L$800,Ventas_SellIn!$F$2:$F$800,$A39,Ventas_SellIn!$B$2:$B$800,">="&$B$29)) -> 0 | D39: =IF(Clientes_PDV!A11="","",Clientes_PDV!D11) -> Sodexo Casa Matriz | E39: =IF(Clientes_PDV!A11="","",Clientes_PDV!B11) -> Sodexo | F39: =IF(Clientes_PDV!A11="","",Clientes_PDV!C11) -> Corporativo | G39: =IF(Clientes_PDV!A11="","",SUMIFS(Ventas_SellIn!$L$2:$L$800,Ventas_SellIn!$D$2:$D$800,Clientes_PDV!A11,Ventas_SellIn!$B$2:$B$800,">="&$B$29)) -> 607254 | H39: =IF(Clientes_PDV!A11="","",Clientes_PDV!K11) -> 0
A40: =Inicio!$E$12 -> Corporativo | B40: =IF($A40="","",SUMIFS(Ventas_SellIn!$L$2:$L$800,Ventas_SellIn!$F$2:$F$800,$A40,Ventas_SellIn!$B$2:$B$800,">="&$B$29)) -> 607254 | D40: =IF(Clientes_PDV!A12="","",Clientes_PDV!D12) -> Tres Toques Vitacura | E40: =IF(Clientes_PDV!A12="","",Clientes_PDV!B12) -> Tres Toques | F40: =IF(Clientes_PDV!A12="","",Clientes_PDV!C12) -> HORECA | G40: =IF(Clientes_PDV!A12="","",SUMIFS(Ventas_SellIn!$L$2:$L$800,Ventas_SellIn!$D$2:$D$800,Clientes_PDV!A12,Ventas_SellIn!$B$2:$B$800,">="&$B$29)) -> 108624 | H40: =IF(Clientes_PDV!A12="","",Clientes_PDV!K12) -> 0
A41: =Inicio!$E$13 -> Distribuidor | B41: =IF($A41="","",SUMIFS(Ventas_SellIn!$L$2:$L$800,Ventas_SellIn!$F$2:$F$800,$A41,Ventas_SellIn!$B$2:$B$800,">="&$B$29)) -> 0 | D41: =IF(Clientes_PDV!A13="","",Clientes_PDV!D13) -> Mundo del Vino Escuela Militar | E41: =IF(Clientes_PDV!A13="","",Clientes_PDV!B13) -> Mundo del Vino | F41: =IF(Clientes_PDV!A13="","",Clientes_PDV!C13) -> Especializadas | G41: =IF(Clientes_PDV!A13="","",SUMIFS(Ventas_SellIn!$L$2:$L$800,Ventas_SellIn!$D$2:$D$800,Clientes_PDV!A13,Ventas_SellIn!$B$2:$B$800,">="&$B$29)) -> 410838 | H41: =IF(Clientes_PDV!A13="","",Clientes_PDV!K13) -> 0

Sheet Resumen
A1: RESUMEN | Nuva Oxi
A3: Año de análisis: | B3: 2026 | D3: ⚙ Configuración
A5: Seguimiento — terreno vs escritorio | D5: Venta por mes (año en B3)
A6: Indicador | B6: Valor | D6: Periodo | E6: Venta NETA | F6: Unidades | G6: Deuda (c/IVA)
A7: PDV activos | B7: =COUNTIF(Clientes_PDV!$I$2:$I$250,"Activo") -> 11 | D7: =$B$3&"-"&TEXT(1,"00") -> 2026-01 | E7: =SUMIFS(Ventas_SellIn!$L$2:$L$800,Ventas_SellIn!$X$2:$X$800,$D7) -> 0 | F7: =SUMIFS(Ventas_SellIn!$J$2:$J$800,Ventas_SellIn!$X$2:$X$800,$D7) -> 0 | G7: =SUMIFS(Ventas_SellIn!$R$2:$R$800,Ventas_SellIn!$X$2:$X$800,$D7) -> 0
A8: Visita vigente | B8: =COUNTIF(Cobertura!$H$2:$H$250,"Vigente") -> 6 | D8: =$B$3&"-"&TEXT(2,"00") -> 2026-02 | E8: =SUMIFS(Ventas_SellIn!$L$2:$L$800,Ventas_SellIn!$X$2:$X$800,$D8) -> 0 | F8: =SUMIFS(Ventas_SellIn!$J$2:$J$800,Ventas_SellIn!$X$2:$X$800,$D8) -> 0 | G8: =SUMIFS(Ventas_SellIn!$R$2:$R$800,Ventas_SellIn!$X$2:$X$800,$D8) -> 0
A9: Visita atrasada | B9: =COUNTIF(Cobertura!$H$2:$H$250,"Atrasado") -> 6 | D9: =$B$3&"-"&TEXT(3,"00") -> 2026-03 | E9: =SUMIFS(Ventas_SellIn!$L$2:$L$800,Ventas_SellIn!$X$2:$X$800,$D9) -> 0 | F9: =SUMIFS(Ventas_SellIn!$J$2:$J$800,Ventas_SellIn!$X$2:$X$800,$D9) -> 0 | G9: =SUMIFS(Ventas_SellIn!$R$2:$R$800,Ventas_SellIn!$X$2:$X$800,$D9) -> 0
A10: Sin visita | B10: =COUNTIF(Cobertura!$H$2:$H$250,"Sin visita") -> 0 | D10: =$B$3&"-"&TEXT(4,"00") -> 2026-04 | E10: =SUMIFS(Ventas_SellIn!$L$2:$L$800,Ventas_SellIn!$X$2:$X$800,$D10) -> 0 | F10: =SUMIFS(Ventas_SellIn!$J$2:$J$800,Ventas_SellIn!$X$2:$X$800,$D10) -> 0 | G10: =SUMIFS(Ventas_SellIn!$R$2:$R$800,Ventas_SellIn!$X$2:$X$800,$D10) -> 0
A11: PDV con venta OK | B11: =COUNTIF(Cobertura!$K$2:$K$250,"Venta OK") -> 1 | D11: =$B$3&"-"&TEXT(5,"00") -> 2026-05 | E11: =SUMIFS(Ventas_SellIn!$L$2:$L$800,Ventas_SellIn!$X$2:$X$800,$D11) -> 2511263 | F11: =SUMIFS(Ventas_SellIn!$J$2:$J$800,Ventas_SellIn!$X$2:$X$800,$D11) -> 220 | G11: =SUMIFS(Ventas_SellIn!$R$2:$R$800,Ventas_SellIn!$X$2:$X$800,$D11) -> 1427456.9
A12: PDV venta baja | B12: =COUNTIF(Cobertura!$K$2:$K$250,"Venta baja") -> 11 | D12: =$B$3&"-"&TEXT(6,"00") -> 2026-06 | E12: =SUMIFS(Ventas_SellIn!$L$2:$L$800,Ventas_SellIn!$X$2:$X$800,$D12) -> 3110100 | F12: =SUMIFS(Ventas_SellIn!$J$2:$J$800,Ventas_SellIn!$X$2:$X$800,$D12) -> 371 | G12: =SUMIFS(Ventas_SellIn!$R$2:$R$800,Ventas_SellIn!$X$2:$X$800,$D12) -> 1256072.6
A13: PDV sin venta | B13: =COUNTIF(Cobertura!$K$2:$K$250,"Sin venta") -> 0 | D13: =$B$3&"-"&TEXT(7,"00") -> 2026-07 | E13: =SUMIFS(Ventas_SellIn!$L$2:$L$800,Ventas_SellIn!$X$2:$X$800,$D13) -> 273502 | F13: =SUMIFS(Ventas_SellIn!$J$2:$J$800,Ventas_SellIn!$X$2:$X$800,$D13) -> 38 | G13: =SUMIFS(Ventas_SellIn!$R$2:$R$800,Ventas_SellIn!$X$2:$X$800,$D13) -> 4512.48
A14: Prioridad Alta (lunes) | B14: =COUNTIF(Cobertura!$Q$2:$Q$250,"Alta") -> 10 | D14: =$B$3&"-"&TEXT(8,"00") -> 2026-08 | E14: =SUMIFS(Ventas_SellIn!$L$2:$L$800,Ventas_SellIn!$X$2:$X$800,$D14) -> 0 | F14: =SUMIFS(Ventas_SellIn!$J$2:$J$800,Ventas_SellIn!$X$2:$X$800,$D14) -> 0 | G14: =SUMIFS(Ventas_SellIn!$R$2:$R$800,Ventas_SellIn!$X$2:$X$800,$D14) -> 0
A15: Deuda total (con IVA) | B15: =SUM(Cobertura!$M$2:$M$250) -> 2688041.9 | D15: =$B$3&"-"&TEXT(9,"00") -> 2026-09 | E15: =SUMIFS(Ventas_SellIn!$L$2:$L$800,Ventas_SellIn!$X$2:$X$800,$D15) -> 0 | F15: =SUMIFS(Ventas_SellIn!$J$2:$J$800,Ventas_SellIn!$X$2:$X$800,$D15) -> 0 | G15: =SUMIFS(Ventas_SellIn!$R$2:$R$800,Ventas_SellIn!$X$2:$X$800,$D15) -> 0
D16: =$B$3&"-"&TEXT(10,"00") -> 2026-10 | E16: =SUMIFS(Ventas_SellIn!$L$2:$L$800,Ventas_SellIn!$X$2:$X$800,$D16) -> 0 | F16: =SUMIFS(Ventas_SellIn!$J$2:$J$800,Ventas_SellIn!$X$2:$X$800,$D16) -> 0 | G16: =SUMIFS(Ventas_SellIn!$R$2:$R$800,Ventas_SellIn!$X$2:$X$800,$D16) -> 0
D17: =$B$3&"-"&TEXT(11,"00") -> 2026-11 | E17: =SUMIFS(Ventas_SellIn!$L$2:$L$800,Ventas_SellIn!$X$2:$X$800,$D17) -> 0 | F17: =SUMIFS(Ventas_SellIn!$J$2:$J$800,Ventas_SellIn!$X$2:$X$800,$D17) -> 0 | G17: =SUMIFS(Ventas_SellIn!$R$2:$R$800,Ventas_SellIn!$X$2:$X$800,$D17) -> 0
D18: =$B$3&"-"&TEXT(12,"00") -> 2026-12 | E18: =SUMIFS(Ventas_SellIn!$L$2:$L$800,Ventas_SellIn!$X$2:$X$800,$D18) -> 0 | F18: =SUMIFS(Ventas_SellIn!$J$2:$J$800,Ventas_SellIn!$X$2:$X$800,$D18) -> 0 | G18: =SUMIFS(Ventas_SellIn!$R$2:$R$800,Ventas_SellIn!$X$2:$X$800,$D18) -> 0
A19: Nota: se llena solo desde Ventas_SellIn y Cobertura. Cambia el año en B3. | D19: TOTAL | E19: =SUM(E7:E18) -> 5894865 | F19: =SUM(F7:F18) -> 629 | G19: =SUM(G7:G18) -> 2688041.9
A21: Venta por canal
A22: Canal | B22: Venta neta | C22: Unidades
A23: =Inicio!$E$5 -> Retail | B23: =IF($A23="","",SUMIFS(Ventas_SellIn!$L$2:$L$800,Ventas_SellIn!$F$2:$F$800,$A23)) -> 1006642 | C23: =IF($A23="","",SUMIFS(Ventas_SellIn!$J$2:$J$800,Ventas_SellIn!$F$2:$F$800,$A23)) -> 102
A24: =Inicio!$E$6 -> Conveniencia | B24: =IF($A24="","",SUMIFS(Ventas_SellIn!$L$2:$L$800,Ventas_SellIn!$F$2:$F$800,$A24)) -> 1713268 | C24: =IF($A24="","",SUMIFS(Ventas_SellIn!$J$2:$J$800,Ventas_SellIn!$F$2:$F$800,$A24)) -> 143
A25: =Inicio!$E$7 -> Farmacias | B25: =IF($A25="","",SUMIFS(Ventas_SellIn!$L$2:$L$800,Ventas_SellIn!$F$2:$F$800,$A25)) -> 723604 | C25: =IF($A25="","",SUMIFS(Ventas_SellIn!$J$2:$J$800,Ventas_SellIn!$F$2:$F$800,$A25)) -> 86
A26: =Inicio!$E$8 -> Especializadas | B26: =IF($A26="","",SUMIFS(Ventas_SellIn!$L$2:$L$800,Ventas_SellIn!$F$2:$F$800,$A26)) -> 1735473 | C26: =IF($A26="","",SUMIFS(Ventas_SellIn!$J$2:$J$800,Ventas_SellIn!$F$2:$F$800,$A26)) -> 224
A27: =Inicio!$E$9 -> HORECA | B27: =IF($A27="","",SUMIFS(Ventas_SellIn!$L$2:$L$800,Ventas_SellIn!$F$2:$F$800,$A27)) -> 108624 | C27: =IF($A27="","",SUMIFS(Ventas_SellIn!$J$2:$J$800,Ventas_SellIn!$F$2:$F$800,$A27)) -> 28
A28: =Inicio!$E$10 -> Tradicional | B28: =IF($A28="","",SUMIFS(Ventas_SellIn!$L$2:$L$800,Ventas_SellIn!$F$2:$F$800,$A28)) -> 0 | C28: =IF($A28="","",SUMIFS(Ventas_SellIn!$J$2:$J$800,Ventas_SellIn!$F$2:$F$800,$A28)) -> 0
A29: =Inicio!$E$11 -> Ecommerce | B29: =IF($A29="","",SUMIFS(Ventas_SellIn!$L$2:$L$800,Ventas_SellIn!$F$2:$F$800,$A29)) -> 0 | C29: =IF($A29="","",SUMIFS(Ventas_SellIn!$J$2:$J$800,Ventas_SellIn!$F$2:$F$800,$A29)) -> 0
A30: =Inicio!$E$12 -> Corporativo | B30: =IF($A30="","",SUMIFS(Ventas_SellIn!$L$2:$L$800,Ventas_SellIn!$F$2:$F$800,$A30)) -> 607254 | C30: =IF($A30="","",SUMIFS(Ventas_SellIn!$J$2:$J$800,Ventas_SellIn!$F$2:$F$800,$A30)) -> 46
A31: =Inicio!$E$13 -> Distribuidor | B31: =IF($A31="","",SUMIFS(Ventas_SellIn!$L$2:$L$800,Ventas_SellIn!$F$2:$F$800,$A31)) -> 0 | C31: =IF($A31="","",SUMIFS(Ventas_SellIn!$J$2:$J$800,Ventas_SellIn!$F$2:$F$800,$A31)) -> 0
A32: Tip: en Ventas_SellIn filtra la columna Fecha → Filtros de fecha → Entre… para ver el detalle.
A33: Reporte de ventas por rango de fechas
A34: Desde: | B34: 46023 | C34: Hasta: | D34: 46387
A35: Métrica | B35: Valor
A36: Venta NETA del rango (sin IVA) | B36: =SUMIFS(Ventas_SellIn!$L$2:$L$800,Ventas_SellIn!$B$2:$B$800,">="&$B$34,Ventas_SellIn!$B$2:$B$800,"<="&$D$34) -> 5894865
A37: Unidades (rango) | B37: =SUMIFS(Ventas_SellIn!$J$2:$J$800,Ventas_SellIn!$B$2:$B$800,">="&$B$34,Ventas_SellIn!$B$2:$B$800,"<="&$D$34) -> 629
A38: N° facturas/líneas | B38: =COUNTIFS(Ventas_SellIn!$B$2:$B$800,">="&$B$34,Ventas_SellIn!$B$2:$B$800,"<="&$D$34,Ventas_SellIn!$A$2:$A$800,"<>") -> 45
A39: Deuda del rango (con IVA) | B39: =SUMIFS(Ventas_SellIn!$R$2:$R$800,Ventas_SellIn!$B$2:$B$800,">="&$B$34,Ventas_SellIn!$B$2:$B$800,"<="&$D$34) -> 2688041.9
A41: Venta por canal en el rango
A42: Canal | B42: Venta neta | C42: Unidades
A43: =Inicio!$E$5 -> Retail | B43: =IF($A43="","",SUMIFS(Ventas_SellIn!$L$2:$L$800,Ventas_SellIn!$F$2:$F$800,$A43,Ventas_SellIn!$B$2:$B$800,">="&$B$34,Ventas_SellIn!$B$2:$B$800,"<="&$D$34)) -> 1006642 | C43: =IF($A43="","",SUMIFS(Ventas_SellIn!$J$2:$J$800,Ventas_SellIn!$F$2:$F$800,$A43,Ventas_SellIn!$B$2:$B$800,">="&$B$34,Ventas_SellIn!$B$2:$B$800,"<="&$D$34)) -> 102
A44: =Inicio!$E$6 -> Conveniencia | B44: =IF($A44="","",SUMIFS(Ventas_SellIn!$L$2:$L$800,Ventas_SellIn!$F$2:$F$800,$A44,Ventas_SellIn!$B$2:$B$800,">="&$B$34,Ventas_SellIn!$B$2:$B$800,"<="&$D$34)) -> 1713268 | C44: =IF($A44="","",SUMIFS(Ventas_SellIn!$J$2:$J$800,Ventas_SellIn!$F$2:$F$800,$A44,Ventas_SellIn!$B$2:$B$800,">="&$B$34,Ventas_SellIn!$B$2:$B$800,"<="&$D$34)) -> 143
A45: =Inicio!$E$7 -> Farmacias | B45: =IF($A45="","",SUMIFS(Ventas_SellIn!$L$2:$L$800,Ventas_SellIn!$F$2:$F$800,$A45,Ventas_SellIn!$B$2:$B$800,">="&$B$34,Ventas_SellIn!$B$2:$B$800,"<="&$D$34)) -> 723604 | C45: =IF($A45="","",SUMIFS(Ventas_SellIn!$J$2:$J$800,Ventas_SellIn!$F$2:$F$800,$A45,Ventas_SellIn!$B$2:$B$800,">="&$B$34,Ventas_SellIn!$B$2:$B$800,"<="&$D$34)) -> 86
A46: =Inicio!$E$8 -> Especializadas | B46: =IF($A46="","",SUMIFS(Ventas_SellIn!$L$2:$L$800,Ventas_SellIn!$F$2:$F$800,$A46,Ventas_SellIn!$B$2:$B$800,">="&$B$34,Ventas_SellIn!$B$2:$B$800,"<="&$D$34)) -> 1735473 | C46: =IF($A46="","",SUMIFS(Ventas_SellIn!$J$2:$J$800,Ventas_SellIn!$F$2:$F$800,$A46,Ventas_SellIn!$B$2:$B$800,">="&$B$34,Ventas_SellIn!$B$2:$B$800,"<="&$D$34)) -> 224
A47: =Inicio!$E$9 -> HORECA | B47: =IF($A47="","",SUMIFS(Ventas_SellIn!$L$2:$L$800,Ventas_SellIn!$F$2:$F$800,$A47,Ventas_SellIn!$B$2:$B$800,">="&$B$34,Ventas_SellIn!$B$2:$B$800,"<="&$D$34)) -> 108624 | C47: =IF($A47="","",SUMIFS(Ventas_SellIn!$J$2:$J$800,Ventas_SellIn!$F$2:$F$800,$A47,Ventas_SellIn!$B$2:$B$800,">="&$B$34,Ventas_SellIn!$B$2:$B$800,"<="&$D$34)) -> 28
A48: =Inicio!$E$10 -> Tradicional | B48: =IF($A48="","",SUMIFS(Ventas_SellIn!$L$2:$L$800,Ventas_SellIn!$F$2:$F$800,$A48,Ventas_SellIn!$B$2:$B$800,">="&$B$34,Ventas_SellIn!$B$2:$B$800,"<="&$D$34)) -> 0 | C48: =IF($A48="","",SUMIFS(Ventas_SellIn!$J$2:$J$800,Ventas_SellIn!$F$2:$F$800,$A48,Ventas_SellIn!$B$2:$B$800,">="&$B$34,Ventas_SellIn!$B$2:$B$800,"<="&$D$34)) -> 0
A49: =Inicio!$E$11 -> Ecommerce | B49: =IF($A49="","",SUMIFS(Ventas_SellIn!$L$2:$L$800,Ventas_SellIn!$F$2:$F$800,$A49,Ventas_SellIn!$B$2:$B$800,">="&$B$34,Ventas_SellIn!$B$2:$B$800,"<="&$D$34)) -> 0 | C49: =IF($A49="","",SUMIFS(Ventas_SellIn!$J$2:$J$800,Ventas_SellIn!$F$2:$F$800,$A49,Ventas_SellIn!$B$2:$B$800,">="&$B$34,Ventas_SellIn!$B$2:$B$800,"<="&$D$34)) -> 0
A50: =Inicio!$E$12 -> Corporativo | B50: =IF($A50="","",SUMIFS(Ventas_SellIn!$L$2:$L$800,Ventas_SellIn!$F$2:$F$800,$A50,Ventas_SellIn!$B$2:$B$800,">="&$B$34,Ventas_SellIn!$B$2:$B$800,"<="&$D$34)) -> 607254 | C50: =IF($A50="","",SUMIFS(Ventas_SellIn!$J$2:$J$800,Ventas_SellIn!$F$2:$F$800,$A50,Ventas_SellIn!$B$2:$B$800,">="&$B$34,Ventas_SellIn!$B$2:$B$800,"<="&$D$34)) -> 46
A51: =Inicio!$E$13 -> Distribuidor | B51: =IF($A51="","",SUMIFS(Ventas_SellIn!$L$2:$L$800,Ventas_SellIn!$F$2:$F$800,$A51,Ventas_SellIn!$B$2:$B$800,">="&$B$34,Ventas_SellIn!$B$2:$B$800,"<="&$D$34)) -> 0 | C51: =IF($A51="","",SUMIFS(Ventas_SellIn!$J$2:$J$800,Ventas_SellIn!$F$2:$F$800,$A51,Ventas_SellIn!$B$2:$B$800,">="&$B$34,Ventas_SellIn!$B$2:$B$800,"<="&$D$34)) -> 0

Sheet Plan_Inventario
A1: Producto (SKU) | B1: Descripción | C1: Sell-in ventana | D1: Venta/día | E1: Stock objetivo | F1: Bodega (unid.) | G1: Bodega barras | H1: Reponer (barras) | I1: Estado | K1: ⚙ Configuración
A2: =IF(Maestro_SKU!A2="","",Maestro_SKU!A2) -> NUVA-BAR-BM-U-01 | B2: =IF(A2="","",IFERROR(VLOOKUP(A2,Maestro_SKU!$A$2:$P$500,2,FALSE),"")) -> Barra Berry Mix unidad | C2: =IF(A2="","",SUMIFS(Ventas_SellIn!$Y$2:$Y$800,Ventas_SellIn!$H$2:$H$800,A2,Ventas_SellIn!$B$2:$B$800,">="&TODAY()-cfg_VentanaDemanda)) -> 32 | D2: =IF(A2="","",C2/cfg_VentanaDemanda) -> 1.0666667 | E2: =IF(A2="","",ROUND(D2*cfg_DiasCobertura*(1+cfg_PctSeguridad),0)) -> 38 | F2: 20 | G2: =IF(A2="","",IF(F2="",0,F2*IFERROR(VLOOKUP(A2,Maestro_SKU!$A$2:$P$500,12,FALSE),1))) -> 20 | H2: =IF(A2="","",MAX(E2-G2,0)) -> 18 | I2: =IF(A2="","",IF(F2="","Falta bodega",IF(G2>=E2,"OK",IF(G2>=E2*0.6,"Ajustado","Reponer")))) -> Reponer
A3: =IF(Maestro_SKU!A3="","",Maestro_SKU!A3) -> NUVA-BAR-PB-U-01 | B3: =IF(A3="","",IFERROR(VLOOKUP(A3,Maestro_SKU!$A$2:$P$500,2,FALSE),"")) -> Barra Peanut Boost unidad | C3: =IF(A3="","",SUMIFS(Ventas_SellIn!$Y$2:$Y$800,Ventas_SellIn!$H$2:$H$800,A3,Ventas_SellIn!$B$2:$B$800,">="&TODAY()-cfg_VentanaDemanda)) -> 32 | D3: =IF(A3="","",C3/cfg_VentanaDemanda) -> 1.0666667 | E3: =IF(A3="","",ROUND(D3*cfg_DiasCobertura*(1+cfg_PctSeguridad),0)) -> 38 | F3: 20 | G3: =IF(A3="","",IF(F3="",0,F3*IFERROR(VLOOKUP(A3,Maestro_SKU!$A$2:$P$500,12,FALSE),1))) -> 20 | H3: =IF(A3="","",MAX(E3-G3,0)) -> 18 | I3: =IF(A3="","",IF(F3="","Falta bodega",IF(G3>=E3,"OK",IF(G3>=E3*0.6,"Ajustado","Reponer")))) -> Reponer
A4: =IF(Maestro_SKU!A4="","",Maestro_SKU!A4) -> NUVA-BAR-CC-U-01 | B4: =IF(A4="","",IFERROR(VLOOKUP(A4,Maestro_SKU!$A$2:$P$500,2,FALSE),"")) -> Barra Cacao Crispy unidad | C4: =IF(A4="","",SUMIFS(Ventas_SellIn!$Y$2:$Y$800,Ventas_SellIn!$H$2:$H$800,A4,Ventas_SellIn!$B$2:$B$800,">="&TODAY()-cfg_VentanaDemanda)) -> 32 | D4: =IF(A4="","",C4/cfg_VentanaDemanda) -> 1.0666667 | E4: =IF(A4="","",ROUND(D4*cfg_DiasCobertura*(1+cfg_PctSeguridad),0)) -> 38 | F4: 20 | G4: =IF(A4="","",IF(F4="",0,F4*IFERROR(VLOOKUP(A4,Maestro_SKU!$A$2:$P$500,12,FALSE),1))) -> 20 | H4: =IF(A4="","",MAX(E4-G4,0)) -> 18 | I4: =IF(A4="","",IF(F4="","Falta bodega",IF(G4>=E4,"OK",IF(G4>=E4*0.6,"Ajustado","Reponer")))) -> Reponer
A5: =IF(Maestro_SKU!A5="","",Maestro_SKU!A5) -> NUVA-BAR-BM-BX-04 | B5: =IF(A5="","",IFERROR(VLOOKUP(A5,Maestro_SKU!$A$2:$P$500,2,FALSE),"")) -> Estuche Berry Mix 4 unidades | C5: =IF(A5="","",SUMIFS(Ventas_SellIn!$Y$2:$Y$800,Ventas_SellIn!$H$2:$H$800,A5,Ventas_SellIn!$B$2:$B$800,">="&TODAY()-cfg_VentanaDemanda)) -> 80 | D5: =IF(A5="","",C5/cfg_VentanaDemanda) -> 2.6666667 | E5: =IF(A5="","",ROUND(D5*cfg_DiasCobertura*(1+cfg_PctSeguridad),0)) -> 96 | F5: 20 | G5: =IF(A5="","",IF(F5="",0,F5*IFERROR(VLOOKUP(A5,Maestro_SKU!$A$2:$P$500,12,FALSE),1))) -> 80 | H5: =IF(A5="","",MAX(E5-G5,0)) -> 16 | I5: =IF(A5="","",IF(F5="","Falta bodega",IF(G5>=E5,"OK",IF(G5>=E5*0.6,"Ajustado","Reponer")))) -> Ajustado
A6: =IF(Maestro_SKU!A6="","",Maestro_SKU!A6) -> NUVA-BAR-PB-BX-04 | B6: =IF(A6="","",IFERROR(VLOOKUP(A6,Maestro_SKU!$A$2:$P$500,2,FALSE),"")) -> Estuche Peanut Boost 4 unidades | C6: =IF(A6="","",SUMIFS(Ventas_SellIn!$Y$2:$Y$800,Ventas_SellIn!$H$2:$H$800,A6,Ventas_SellIn!$B$2:$B$800,">="&TODAY()-cfg_VentanaDemanda)) -> 76 | D6: =IF(A6="","",C6/cfg_VentanaDemanda) -> 2.5333333 | E6: =IF(A6="","",ROUND(D6*cfg_DiasCobertura*(1+cfg_PctSeguridad),0)) -> 91 | F6: 20 | G6: =IF(A6="","",IF(F6="",0,F6*IFERROR(VLOOKUP(A6,Maestro_SKU!$A$2:$P$500,12,FALSE),1))) -> 80 | H6: =IF(A6="","",MAX(E6-G6,0)) -> 11 | I6: =IF(A6="","",IF(F6="","Falta bodega",IF(G6>=E6,"OK",IF(G6>=E6*0.6,"Ajustado","Reponer")))) -> Ajustado
A7: =IF(Maestro_SKU!A7="","",Maestro_SKU!A7) -> NUVA-BAR-CC-BX-04 | B7: =IF(A7="","",IFERROR(VLOOKUP(A7,Maestro_SKU!$A$2:$P$500,2,FALSE),"")) -> Estuche Cacao Crispy 4 unidades | C7: =IF(A7="","",SUMIFS(Ventas_SellIn!$Y$2:$Y$800,Ventas_SellIn!$H$2:$H$800,A7,Ventas_SellIn!$B$2:$B$800,">="&TODAY()-cfg_VentanaDemanda)) -> 160 | D7: =IF(A7="","",C7/cfg_VentanaDemanda) -> 5.3333333 | E7: =IF(A7="","",ROUND(D7*cfg_DiasCobertura*(1+cfg_PctSeguridad),0)) -> 192 | F7: 100 | G7: =IF(A7="","",IF(F7="",0,F7*IFERROR(VLOOKUP(A7,Maestro_SKU!$A$2:$P$500,12,FALSE),1))) -> 400 | H7: =IF(A7="","",MAX(E7-G7,0)) -> 0 | I7: =IF(A7="","",IF(F7="","Falta bodega",IF(G7>=E7,"OK",IF(G7>=E7*0.6,"Ajustado","Reponer")))) -> OK
A8: =IF(Maestro_SKU!A8="","",Maestro_SKU!A8) -> NUVA-BAR-BM-CS-24 | B8: =IF(A8="","",IFERROR(VLOOKUP(A8,Maestro_SKU!$A$2:$P$500,2,FALSE),"")) -> Caja master Berry Mix 24 unidades | C8: =IF(A8="","",SUMIFS(Ventas_SellIn!$Y$2:$Y$800,Ventas_SellIn!$H$2:$H$800,A8,Ventas_SellIn!$B$2:$B$800,">="&TODAY()-cfg_VentanaDemanda)) -> 1056 | D8: =IF(A8="","",C8/cfg_VentanaDemanda) -> 35.2 | E8: =IF(A8="","",ROUND(D8*cfg_DiasCobertura*(1+cfg_PctSeguridad),0)) -> 1267 | F8: 50 | G8: =IF(A8="","",IF(F8="",0,F8*IFERROR(VLOOKUP(A8,Maestro_SKU!$A$2:$P$500,12,FALSE),1))) -> 1200 | H8: =IF(A8="","",MAX(E8-G8,0)) -> 67 | I8: =IF(A8="","",IF(F8="","Falta bodega",IF(G8>=E8,"OK",IF(G8>=E8*0.6,"Ajustado","Reponer")))) -> Ajustado
A9: =IF(Maestro_SKU!A9="","",Maestro_SKU!A9) -> NUVA-BAR-PB-CS-24 | B9: =IF(A9="","",IFERROR(VLOOKUP(A9,Maestro_SKU!$A$2:$P$500,2,FALSE),"")) -> Caja master Peanut Boost 24 unidades | C9: =IF(A9="","",SUMIFS(Ventas_SellIn!$Y$2:$Y$800,Ventas_SellIn!$H$2:$H$800,A9,Ventas_SellIn!$B$2:$B$800,">="&TODAY()-cfg_VentanaDemanda)) -> 1200 | D9: =IF(A9="","",C9/cfg_VentanaDemanda) -> 40 | E9: =IF(A9="","",ROUND(D9*cfg_DiasCobertura*(1+cfg_PctSeguridad),0)) -> 1440 | F9: 20 | G9: =IF(A9="","",IF(F9="",0,F9*IFERROR(VLOOKUP(A9,Maestro_SKU!$A$2:$P$500,12,FALSE),1))) -> 480 | H9: =IF(A9="","",MAX(E9-G9,0)) -> 960 | I9: =IF(A9="","",IF(F9="","Falta bodega",IF(G9>=E9,"OK",IF(G9>=E9*0.6,"Ajustado","Reponer")))) -> Reponer
A10: =IF(Maestro_SKU!A10="","",Maestro_SKU!A10) -> NUVA-BAR-CC-CS-24 | B10: =IF(A10="","",IFERROR(VLOOKUP(A10,Maestro_SKU!$A$2:$P$500,2,FALSE),"")) -> Caja master Cacao Crispy 24 unidades | C10: =IF(A10="","",SUMIFS(Ventas_SellIn!$Y$2:$Y$800,Ventas_SellIn!$H$2:$H$800,A10,Ventas_SellIn!$B$2:$B$800,">="&TODAY()-cfg_VentanaDemanda)) -> 912 | D10: =IF(A10="","",C10/cfg_VentanaDemanda) -> 30.4 | E10: =IF(A10="","",ROUND(D10*cfg_DiasCobertura*(1+cfg_PctSeguridad),0)) -> 1094 | F10: 20 | G10: =IF(A10="","",IF(F10="",0,F10*IFERROR(VLOOKUP(A10,Maestro_SKU!$A$2:$P$500,12,FALSE),1))) -> 480 | H10: =IF(A10="","",MAX(E10-G10,0)) -> 614 | I10: =IF(A10="","",IF(F10="","Falta bodega",IF(G10>=E10,"OK",IF(G10>=E10*0.6,"Ajustado","Reponer")))) -> Reponer
A11: =IF(Maestro_SKU!A11="","",Maestro_SKU!A11) -> NUVA-BAR-BM-CS-60 | B11: =IF(A11="","",IFERROR(VLOOKUP(A11,Maestro_SKU!$A$2:$P$500,2,FALSE),"")) -> Caja master Berry Mix 15x4 unidades | C11: =IF(A11="","",SUMIFS(Ventas_SellIn!$Y$2:$Y$800,Ventas_SellIn!$H$2:$H$800,A11,Ventas_SellIn!$B$2:$B$800,">="&TODAY()-cfg_VentanaDemanda)) -> 0 | D11: =IF(A11="","",C11/cfg_VentanaDemanda) -> 0 | E11: =IF(A11="","",ROUND(D11*cfg_DiasCobertura*(1+cfg_PctSeguridad),0)) -> 0 | F11: 20 | G11: =IF(A11="","",IF(F11="",0,F11*IFERROR(VLOOKUP(A11,Maestro_SKU!$A$2:$P$500,12,FALSE),1))) -> 1200 | H11: =IF(A11="","",MAX(E11-G11,0)) -> 0 | I11: =IF(A11="","",IF(F11="","Falta bodega",IF(G11>=E11,"OK",IF(G11>=E11*0.6,"Ajustado","Reponer")))) -> OK
A12: =IF(Maestro_SKU!A12="","",Maestro_SKU!A12) -> NUVA-BAR-PB-CS-60 | B12: =IF(A12="","",IFERROR(VLOOKUP(A12,Maestro_SKU!$A$2:$P$500,2,FALSE),"")) -> Caja master Peanut Boost 15x4 unidades | C12: =IF(A12="","",SUMIFS(Ventas_SellIn!$Y$2:$Y$800,Ventas_SellIn!$H$2:$H$800,A12,Ventas_SellIn!$B$2:$B$800,">="&TODAY()-cfg_VentanaDemanda)) -> 0 | D12: =IF(A12="","",C12/cfg_VentanaDemanda) -> 0 | E12: =IF(A12="","",ROUND(D12*cfg_DiasCobertura*(1+cfg_PctSeguridad),0)) -> 0 | F12: 20 | G12: =IF(A12="","",IF(F12="",0,F12*IFERROR(VLOOKUP(A12,Maestro_SKU!$A$2:$P$500,12,FALSE),1))) -> 1200 | H12: =IF(A12="","",MAX(E12-G12,0)) -> 0 | I12: =IF(A12="","",IF(F12="","Falta bodega",IF(G12>=E12,"OK",IF(G12>=E12*0.6,"Ajustado","Reponer")))) -> OK
A13: =IF(Maestro_SKU!A13="","",Maestro_SKU!A13) -> NUVA-BAR-CC-CS-60 | B13: =IF(A13="","",IFERROR(VLOOKUP(A13,Maestro_SKU!$A$2:$P$500,2,FALSE),"")) -> Caja master Cacao Crispy 15x4 unidades | C13: =IF(A13="","",SUMIFS(Ventas_SellIn!$Y$2:$Y$800,Ventas_SellIn!$H$2:$H$800,A13,Ventas_SellIn!$B$2:$B$800,">="&TODAY()-cfg_VentanaDemanda)) -> 0 | D13: =IF(A13="","",C13/cfg_VentanaDemanda) -> 0 | E13: =IF(A13="","",ROUND(D13*cfg_DiasCobertura*(1+cfg_PctSeguridad),0)) -> 0 | F13: 20 | G13: =IF(A13="","",IF(F13="",0,F13*IFERROR(VLOOKUP(A13,Maestro_SKU!$A$2:$P$500,12,FALSE),1))) -> 1200 | H13: =IF(A13="","",MAX(E13-G13,0)) -> 0 | I13: =IF(A13="","",IF(F13="","Falta bodega",IF(G13>=E13,"OK",IF(G13>=E13*0.6,"Ajustado","Reponer")))) -> OK
A14: =IF(Maestro_SKU!A14="","",Maestro_SKU!A14) | B14: =IF(A14="","",IFERROR(VLOOKUP(A14,Maestro_SKU!$A$2:$P$500,2,FALSE),"")) | C14: =IF(A14="","",SUMIFS(Ventas_SellIn!$Y$2:$Y$800,Ventas_SellIn!$H$2:$H$800,A14,Ventas_SellIn!$B$2:$B$800,">="&TODAY()-cfg_VentanaDemanda)) | D14: =IF(A14="","",C14/cfg_VentanaDemanda) | E14: =IF(A14="","",ROUND(D14*cfg_DiasCobertura*(1+cfg_PctSeguridad),0)) | G14: =IF(A14="","",IF(F14="",0,F14*IFERROR(VLOOKUP(A14,Maestro_SKU!$A$2:$P$500,12,FALSE),1))) | H14: =IF(A14="","",MAX(E14-G14,0)) | I14: =IF(A14="","",IF(F14="","Falta bodega",IF(G14>=E14,"OK",IF(G14>=E14*0.6,"Ajustado","Reponer"))))
A15: =IF(Maestro_SKU!A15="","",Maestro_SKU!A15) | B15: =IF(A15="","",IFERROR(VLOOKUP(A15,Maestro_SKU!$A$2:$P$500,2,FALSE),"")) | C15: =IF(A15="","",SUMIFS(Ventas_SellIn!$Y$2:$Y$800,Ventas_SellIn!$H$2:$H$800,A15,Ventas_SellIn!$B$2:$B$800,">="&TODAY()-cfg_VentanaDemanda)) | D15: =IF(A15="","",C15/cfg_VentanaDemanda) | E15: =IF(A15="","",ROUND(D15*cfg_DiasCobertura*(1+cfg_PctSeguridad),0)) | G15: =IF(A15="","",IF(F15="",0,F15*IFERROR(VLOOKUP(A15,Maestro_SKU!$A$2:$P$500,12,FALSE),1))) | H15: =IF(A15="","",MAX(E15-G15,0)) | I15: =IF(A15="","",IF(F15="","Falta bodega",IF(G15>=E15,"OK",IF(G15>=E15*0.6,"Ajustado","Reponer"))))
A16: =IF(Maestro_SKU!A16="","",Maestro_SKU!A16) | B16: =IF(A16="","",IFERROR(VLOOKUP(A16,Maestro_SKU!$A$2:$P$500,2,FALSE),"")) | C16: =IF(A16="","",SUMIFS(Ventas_SellIn!$Y$2:$Y$800,Ventas_SellIn!$H$2:$H$800,A16,Ventas_SellIn!$B$2:$B$800,">="&TODAY()-cfg_VentanaDemanda)) | D16: =IF(A16="","",C16/cfg_VentanaDemanda) | E16: =IF(A16="","",ROUND(D16*cfg_DiasCobertura*(1+cfg_PctSeguridad),0)) | G16: =IF(A16="","",IF(F16="",0,F16*IFERROR(VLOOKUP(A16,Maestro_SKU!$A$2:$P$500,12,FALSE),1))) | H16: =IF(A16="","",MAX(E16-G16,0)) | I16: =IF(A16="","",IF(F16="","Falta bodega",IF(G16>=E16,"OK",IF(G16>=E16*0.6,"Ajustado","Reponer"))))
A17: =IF(Maestro_SKU!A17="","",Maestro_SKU!A17) | B17: =IF(A17="","",IFERROR(VLOOKUP(A17,Maestro_SKU!$A$2:$P$500,2,FALSE),"")) | C17: =IF(A17="","",SUMIFS(Ventas_SellIn!$Y$2:$Y$800,Ventas_SellIn!$H$2:$H$800,A17,Ventas_SellIn!$B$2:$B$800,">="&TODAY()-cfg_VentanaDemanda)) | D17: =IF(A17="","",C17/cfg_VentanaDemanda) | E17: =IF(A17="","",ROUND(D17*cfg_DiasCobertura*(1+cfg_PctSeguridad),0)) | G17: =IF(A17="","",IF(F17="",0,F17*IFERROR(VLOOKUP(A17,Maestro_SKU!$A$2:$P$500,12,FALSE),1))) | H17: =IF(A17="","",MAX(E17-G17,0)) | I17: =IF(A17="","",IF(F17="","Falta bodega",IF(G17>=E17,"OK",IF(G17>=E17*0.6,"Ajustado","Reponer"))))
A18: =IF(Maestro_SKU!A18="","",Maestro_SKU!A18) | B18: =IF(A18="","",IFERROR(VLOOKUP(A18,Maestro_SKU!$A$2:$P$500,2,FALSE),"")) | C18: =IF(A18="","",SUMIFS(Ventas_SellIn!$Y$2:$Y$800,Ventas_SellIn!$H$2:$H$800,A18,Ventas_SellIn!$B$2:$B$800,">="&TODAY()-cfg_VentanaDemanda)) | D18: =IF(A18="","",C18/cfg_VentanaDemanda) | E18: =IF(A18="","",ROUND(D18*cfg_DiasCobertura*(1+cfg_PctSeguridad),0)) | G18: =IF(A18="","",IF(F18="",0,F18*IFERROR(VLOOKUP(A18,Maestro_SKU!$A$2:$P$500,12,FALSE),1))) | H18: =IF(A18="","",MAX(E18-G18,0)) | I18: =IF(A18="","",IF(F18="","Falta bodega",IF(G18>=E18,"OK",IF(G18>=E18*0.6,"Ajustado","Reponer"))))
A19: =IF(Maestro_SKU!A19="","",Maestro_SKU!A19) | B19: =IF(A19="","",IFERROR(VLOOKUP(A19,Maestro_SKU!$A$2:$P$500,2,FALSE),"")) | C19: =IF(A19="","",SUMIFS(Ventas_SellIn!$Y$2:$Y$800,Ventas_SellIn!$H$2:$H$800,A19,Ventas_SellIn!$B$2:$B$800,">="&TODAY()-cfg_VentanaDemanda)) | D19: =IF(A19="","",C19/cfg_VentanaDemanda) | E19: =IF(A19="","",ROUND(D19*cfg_DiasCobertura*(1+cfg_PctSeguridad),0)) | G19: =IF(A19="","",IF(F19="",0,F19*IFERROR(VLOOKUP(A19,Maestro_SKU!$A$2:$P$500,12,FALSE),1))) | H19: =IF(A19="","",MAX(E19-G19,0)) | I19: =IF(A19="","",IF(F19="","Falta bodega",IF(G19>=E19,"OK",IF(G19>=E19*0.6,"Ajustado","Reponer"))))
A20: =IF(Maestro_SKU!A20="","",Maestro_SKU!A20) | B20: =IF(A20="","",IFERROR(VLOOKUP(A20,Maestro_SKU!$A$2:$P$500,2,FALSE),"")) | C20: =IF(A20="","",SUMIFS(Ventas_SellIn!$Y$2:$Y$800,Ventas_SellIn!$H$2:$H$800,A20,Ventas_SellIn!$B$2:$B$800,">="&TODAY()-cfg_VentanaDemanda)) | D20: =IF(A20="","",C20/cfg_VentanaDemanda) | E20: =IF(A20="","",ROUND(D20*cfg_DiasCobertura*(1+cfg_PctSeguridad),0)) | G20: =IF(A20="","",IF(F20="",0,F20*IFERROR(VLOOKUP(A20,Maestro_SKU!$A$2:$P$500,12,FALSE),1))) | H20: =IF(A20="","",MAX(E20-G20,0)) | I20: =IF(A20="","",IF(F20="","Falta bodega",IF(G20>=E20,"OK",IF(G20>=E20*0.6,"Ajustado","Reponer"))))
A21: =IF(Maestro_SKU!A21="","",Maestro_SKU!A21) | B21: =IF(A21="","",IFERROR(VLOOKUP(A21,Maestro_SKU!$A$2:$P$500,2,FALSE),"")) | C21: =IF(A21="","",SUMIFS(Ventas_SellIn!$Y$2:$Y$800,Ventas_SellIn!$H$2:$H$800,A21,Ventas_SellIn!$B$2:$B$800,">="&TODAY()-cfg_VentanaDemanda)) | D21: =IF(A21="","",C21/cfg_VentanaDemanda) | E21: =IF(A21="","",ROUND(D21*cfg_DiasCobertura*(1+cfg_PctSeguridad),0)) | G21: =IF(A21="","",IF(F21="",0,F21*IFERROR(VLOOKUP(A21,Maestro_SKU!$A$2:$P$500,12,FALSE),1))) | H21: =IF(A21="","",MAX(E21-G21,0)) | I21: =IF(A21="","",IF(F21="","Falta bodega",IF(G21>=E21,"OK",IF(G21>=E21*0.6,"Ajustado","Reponer"))))
A22: =IF(Maestro_SKU!A22="","",Maestro_SKU!A22) | B22: =IF(A22="","",IFERROR(VLOOKUP(A22,Maestro_SKU!$A$2:$P$500,2,FALSE),"")) | C22: =IF(A22="","",SUMIFS(Ventas_SellIn!$Y$2:$Y$800,Ventas_SellIn!$H$2:$H$800,A22,Ventas_SellIn!$B$2:$B$800,">="&TODAY()-cfg_VentanaDemanda)) | D22: =IF(A22="","",C22/cfg_VentanaDemanda) | E22: =IF(A22="","",ROUND(D22*cfg_DiasCobertura*(1+cfg_PctSeguridad),0)) | G22: =IF(A22="","",IF(F22="",0,F22*IFERROR(VLOOKUP(A22,Maestro_SKU!$A$2:$P$500,12,FALSE),1))) | H22: =IF(A22="","",MAX(E22-G22,0)) | I22: =IF(A22="","",IF(F22="","Falta bodega",IF(G22>=E22,"OK",IF(G22>=E22*0.6,"Ajustado","Reponer"))))
A23: =IF(Maestro_SKU!A23="","",Maestro_SKU!A23) | B23: =IF(A23="","",IFERROR(VLOOKUP(A23,Maestro_SKU!$A$2:$P$500,2,FALSE),"")) | C23: =IF(A23="","",SUMIFS(Ventas_SellIn!$Y$2:$Y$800,Ventas_SellIn!$H$2:$H$800,A23,Ventas_SellIn!$B$2:$B$800,">="&TODAY()-cfg_VentanaDemanda)) | D23: =IF(A23="","",C23/cfg_VentanaDemanda) | E23: =IF(A23="","",ROUND(D23*cfg_DiasCobertura*(1+cfg_PctSeguridad),0)) | G23: =IF(A23="","",IF(F23="",0,F23*IFERROR(VLOOKUP(A23,Maestro_SKU!$A$2:$P$500,12,FALSE),1))) | H23: =IF(A23="","",MAX(E23-G23,0)) | I23: =IF(A23="","",IF(F23="","Falta bodega",IF(G23>=E23,"OK",IF(G23>=E23*0.6,"Ajustado","Reponer"))))
A24: =IF(Maestro_SKU!A24="","",Maestro_SKU!A24) | B24: =IF(A24="","",IFERROR(VLOOKUP(A24,Maestro_SKU!$A$2:$P$500,2,FALSE),"")) | C24: =IF(A24="","",SUMIFS(Ventas_SellIn!$Y$2:$Y$800,Ventas_SellIn!$H$2:$H$800,A24,Ventas_SellIn!$B$2:$B$800,">="&TODAY()-cfg_VentanaDemanda)) | D24: =IF(A24="","",C24/cfg_VentanaDemanda) | E24: =IF(A24="","",ROUND(D24*cfg_DiasCobertura*(1+cfg_PctSeguridad),0)) | G24: =IF(A24="","",IF(F24="",0,F24*IFERROR(VLOOKUP(A24,Maestro_SKU!$A$2:$P$500,12,FALSE),1))) | H24: =IF(A24="","",MAX(E24-G24,0)) | I24: =IF(A24="","",IF(F24="","Falta bodega",IF(G24>=E24,"OK",IF(G24>=E24*0.6,"Ajustado","Reponer"))))
A25: =IF(Maestro_SKU!A25="","",Maestro_SKU!A25) | B25: =IF(A25="","",IFERROR(VLOOKUP(A25,Maestro_SKU!$A$2:$P$500,2,FALSE),"")) | C25: =IF(A25="","",SUMIFS(Ventas_SellIn!$Y$2:$Y$800,Ventas_SellIn!$H$2:$H$800,A25,Ventas_SellIn!$B$2:$B$800,">="&TODAY()-cfg_VentanaDemanda)) | D25: =IF(A25="","",C25/cfg_VentanaDemanda) | E25: =IF(A25="","",ROUND(D25*cfg_DiasCobertura*(1+cfg_PctSeguridad),0)) | G25: =IF(A25="","",IF(F25="",0,F25*IFERROR(VLOOKUP(A25,Maestro_SKU!$A$2:$P$500,12,FALSE),1))) | H25: =IF(A25="","",MAX(E25-G25,0)) | I25: =IF(A25="","",IF(F25="","Falta bodega",IF(G25>=E25,"OK",IF(G25>=E25*0.6,"Ajustado","Reponer"))))
... A81: =IF(Maestro_SKU!A81="","",Maestro_SKU!A81) | B81: =IF(A81="","",IFERROR(VLOOKUP(A81,Maestro_SKU!$A$2:$P$500,2,FALSE),"")) | C81: =IF(A81="","",SUMIFS(Ventas_SellIn!$Y$2:$Y$800,Ventas_SellIn!$H$2:$H$800,A81,Ventas_SellIn!$B$2:$B$800,">="&TODAY()-cfg_VentanaDemanda)) | D81: =IF(A81="","",C81/cfg_VentanaDemanda) | E81: =IF(A81="","",ROUND(D81*cfg_DiasCobertura*(1+cfg_PctSeguridad),0)) | G81: =IF(A81="","",IF(F81="",0,F81*IFERROR(VLOOKUP(A81,Maestro_SKU!$A$2:$P$500,12,FALSE),1))) | H81: =IF(A81="","",MAX(E81-G81,0)) | I81: =IF(A81="","",IF(F81="","Falta bodega",IF(G81>=E81,"OK",IF(G81>=E81*0.6,"Ajustado","Reponer"))))

Sheet Bodegas
A1: Bodega_ID | B1: Cliente | C1: Nombre bodega | D1: Dirección | E1: Sell-in acum. (barras) | F1: Sell-out acum. (barras) | G1: Stock en salas (barras) | H1: Estimado en bodega (barras)
A2: BOD-001 | B2: Jumbo | C2: Bodega Cencosud | E2: =IF($B2="","",SUMIFS(Ventas_SellIn!$Y$2:$Y$800,Ventas_SellIn!$E$2:$E$800,$B2)) -> 1350 | F2: =IF($B2="","",SUMIFS(SellOut_Jumbo!$O$2:$O$800,SellOut_Jumbo!$B$2:$B$800,$B2)) -> 243 | G2: =IF($B2="","",SUMIFS(Stock_PDV!$H$2:$H$800,Stock_PDV!$B$2:$B$800,$B2)) -> 188 | H2: =IF($B2="","",E2-F2-G2) -> 919
E3: =IF($B3="","",SUMIFS(Ventas_SellIn!$Y$2:$Y$800,Ventas_SellIn!$E$2:$E$800,$B3)) | F3: =IF($B3="","",SUMIFS(SellOut_Jumbo!$O$2:$O$800,SellOut_Jumbo!$B$2:$B$800,$B3)) | G3: =IF($B3="","",SUMIFS(Stock_PDV!$H$2:$H$800,Stock_PDV!$B$2:$B$800,$B3)) | H3: =IF($B3="","",E3-F3-G3)
E4: =IF($B4="","",SUMIFS(Ventas_SellIn!$Y$2:$Y$800,Ventas_SellIn!$E$2:$E$800,$B4)) | F4: =IF($B4="","",SUMIFS(SellOut_Jumbo!$O$2:$O$800,SellOut_Jumbo!$B$2:$B$800,$B4)) | G4: =IF($B4="","",SUMIFS(Stock_PDV!$H$2:$H$800,Stock_PDV!$B$2:$B$800,$B4)) | H4: =IF($B4="","",E4-F4-G4)
E5: =IF($B5="","",SUMIFS(Ventas_SellIn!$Y$2:$Y$800,Ventas_SellIn!$E$2:$E$800,$B5)) | F5: =IF($B5="","",SUMIFS(SellOut_Jumbo!$O$2:$O$800,SellOut_Jumbo!$B$2:$B$800,$B5)) | G5: =IF($B5="","",SUMIFS(Stock_PDV!$H$2:$H$800,Stock_PDV!$B$2:$B$800,$B5)) | H5: =IF($B5="","",E5-F5-G5)
E6: =IF($B6="","",SUMIFS(Ventas_SellIn!$Y$2:$Y$800,Ventas_SellIn!$E$2:$E$800,$B6)) | F6: =IF($B6="","",SUMIFS(SellOut_Jumbo!$O$2:$O$800,SellOut_Jumbo!$B$2:$B$800,$B6)) | G6: =IF($B6="","",SUMIFS(Stock_PDV!$H$2:$H$800,Stock_PDV!$B$2:$B$800,$B6)) | H6: =IF($B6="","",E6-F6-G6)
E7: =IF($B7="","",SUMIFS(Ventas_SellIn!$Y$2:$Y$800,Ventas_SellIn!$E$2:$E$800,$B7)) | F7: =IF($B7="","",SUMIFS(SellOut_Jumbo!$O$2:$O$800,SellOut_Jumbo!$B$2:$B$800,$B7)) | G7: =IF($B7="","",SUMIFS(Stock_PDV!$H$2:$H$800,Stock_PDV!$B$2:$B$800,$B7)) | H7: =IF($B7="","",E7-F7-G7)
E8: =IF($B8="","",SUMIFS(Ventas_SellIn!$Y$2:$Y$800,Ventas_SellIn!$E$2:$E$800,$B8)) | F8: =IF($B8="","",SUMIFS(SellOut_Jumbo!$O$2:$O$800,SellOut_Jumbo!$B$2:$B$800,$B8)) | G8: =IF($B8="","",SUMIFS(Stock_PDV!$H$2:$H$800,Stock_PDV!$B$2:$B$800,$B8)) | H8: =IF($B8="","",E8-F8-G8)
E9: =IF($B9="","",SUMIFS(Ventas_SellIn!$Y$2:$Y$800,Ventas_SellIn!$E$2:$E$800,$B9)) | F9: =IF($B9="","",SUMIFS(SellOut_Jumbo!$O$2:$O$800,SellOut_Jumbo!$B$2:$B$800,$B9)) | G9: =IF($B9="","",SUMIFS(Stock_PDV!$H$2:$H$800,Stock_PDV!$B$2:$B$800,$B9)) | H9: =IF($B9="","",E9-F9-G9)
E10: =IF($B10="","",SUMIFS(Ventas_SellIn!$Y$2:$Y$800,Ventas_SellIn!$E$2:$E$800,$B10)) | F10: =IF($B10="","",SUMIFS(SellOut_Jumbo!$O$2:$O$800,SellOut_Jumbo!$B$2:$B$800,$B10)) | G10: =IF($B10="","",SUMIFS(Stock_PDV!$H$2:$H$800,Stock_PDV!$B$2:$B$800,$B10)) | H10: =IF($B10="","",E10-F10-G10)
E11: =IF($B11="","",SUMIFS(Ventas_SellIn!$Y$2:$Y$800,Ventas_SellIn!$E$2:$E$800,$B11)) | F11: =IF($B11="","",SUMIFS(SellOut_Jumbo!$O$2:$O$800,SellOut_Jumbo!$B$2:$B$800,$B11)) | G11: =IF($B11="","",SUMIFS(Stock_PDV!$H$2:$H$800,Stock_PDV!$B$2:$B$800,$B11)) | H11: =IF($B11="","",E11-F11-G11)
E12: =IF($B12="","",SUMIFS(Ventas_SellIn!$Y$2:$Y$800,Ventas_SellIn!$E$2:$E$800,$B12)) | F12: =IF($B12="","",SUMIFS(SellOut_Jumbo!$O$2:$O$800,SellOut_Jumbo!$B$2:$B$800,$B12)) | G12: =IF($B12="","",SUMIFS(Stock_PDV!$H$2:$H$800,Stock_PDV!$B$2:$B$800,$B12)) | H12: =IF($B12="","",E12-F12-G12)
E13: =IF($B13="","",SUMIFS(Ventas_SellIn!$Y$2:$Y$800,Ventas_SellIn!$E$2:$E$800,$B13)) | F13: =IF($B13="","",SUMIFS(SellOut_Jumbo!$O$2:$O$800,SellOut_Jumbo!$B$2:$B$800,$B13)) | G13: =IF($B13="","",SUMIFS(Stock_PDV!$H$2:$H$800,Stock_PDV!$B$2:$B$800,$B13)) | H13: =IF($B13="","",E13-F13-G13)
E14: =IF($B14="","",SUMIFS(Ventas_SellIn!$Y$2:$Y$800,Ventas_SellIn!$E$2:$E$800,$B14)) | F14: =IF($B14="","",SUMIFS(SellOut_Jumbo!$O$2:$O$800,SellOut_Jumbo!$B$2:$B$800,$B14)) | G14: =IF($B14="","",SUMIFS(Stock_PDV!$H$2:$H$800,Stock_PDV!$B$2:$B$800,$B14)) | H14: =IF($B14="","",E14-F14-G14)
... E50: =IF($B50="","",SUMIFS(Ventas_SellIn!$Y$2:$Y$800,Ventas_SellIn!$E$2:$E$800,$B50)) | F50: =IF($B50="","",SUMIFS(SellOut_Jumbo!$O$2:$O$800,SellOut_Jumbo!$B$2:$B$800,$B50)) | G50: =IF($B50="","",SUMIFS(Stock_PDV!$H$2:$H$800,Stock_PDV!$B$2:$B$800,$B50)) | H50: =IF($B50="","",E50-F50-G50)

Sheet Cobertura
A1: PDV_ID | B1: Cliente | C1: Canal | D1: Punto de venta | E1: Frecuencia | F1: Última visita | G1: Días sin visita | H1: Estado visita | I1: Venta 30d NETA (sin IVA) | J1: Sell-out 30d unid. opcional | K1: Estado venta | L1: Facturas pendientes | M1: Deuda (con IVA) | N1: Estado pago | O1: Stock PDV barras | P1: Estado stock | Q1: Prioridad lunes | R1: Acción sugerida | S1: Rotación | T1: Dirección | V1: ⚙ Configuración
A2: =IF(Clientes_PDV!A2="","",Clientes_PDV!A2) -> PDV-001 | B2: =IF(A2="","",IFERROR(VLOOKUP(A2,Clientes_PDV!$A$2:$J$250,2,FALSE),"")) -> Jumbo | C2: =IF(A2="","",IFERROR(VLOOKUP(A2,Clientes_PDV!$A$2:$J$250,3,FALSE),"")) -> Retail | D2: =IF(A2="","",IFERROR(VLOOKUP(A2,Clientes_PDV!$A$2:$J$250,4,FALSE),"")) -> Jumbo Bilbao | E2: =IF(A2="","",IFERROR(VLOOKUP(A2,Clientes_PDV!$A$2:$J$250,7,FALSE),"")) -> Semanal | F2: =IF(A2="","",IFERROR(VLOOKUP(A2,Clientes_PDV!$A$2:$J$250,8,FALSE),"")) -> 46209 | G2: =IF(F2="","",TODAY()-F2) -> 4 | H2: =IF(A2="","",IF(F2="","Sin visita",IF(G2<=IFERROR(VLOOKUP(E2,Inicio!$A$24:$B$26,2,FALSE),0),"Vigente","Atrasado"))) -> Vigente | I2: =IF(A2="","",SUMIFS(Ventas_SellIn!$L$2:$L$800,Ventas_SellIn!$D$2:$D$800,A2,Ventas_SellIn!$B$2:$B$800,">="&TODAY()-Inicio!$B$14)) -> 411396 | J2: =IF(A2="","",SUMIFS(SellOut_Jumbo!$F$2:$F$800,SellOut_Jumbo!$C$2:$C$800,D2,SellOut_Jumbo!$A$2:$A$800,">="&TODAY()-Inicio!$B$14)) -> 41 | K2: =IF(A2="","",IF(I2=0,"Sin venta",IF(I2<Inicio!$B$15,"Venta baja","Venta OK"))) -> Venta baja | L2: =IF(A2="","",COUNTIFS(Ventas_SellIn!$D$2:$D$800,A2,Ventas_SellIn!$R$2:$R$800,">0")) -> 1 | M2: =IF(A2="","",SUMIFS(Ventas_SellIn!$R$2:$R$800,Ventas_SellIn!$D$2:$D$800,A2)) -> 1.4551915e-11 | N2: =IF(A2="","",IF(M2>=Inicio!$B$18,"Pendiente relevante",IF(M2>0,"Pendiente menor","Sin deuda"))) -> Pendiente menor | O2: =IF(A2="","",SUMIFS(Stock_PDV!$H$2:$H$800,Stock_PDV!$A$2:$A$800,A2)) -> 33 | P2: =IF(A2="","",IF(O2<=Inicio!$B$16,"Crítico",IF(O2<=Inicio!$B$17,"Observar","OK"))) -> OK | Q2: =IF(A2="","",IF(OR(H2="Atrasado",K2="Sin venta",N2="Pendiente relevante",P2="Crítico"),"Alta",IF(OR(K2="Venta baja",N2="Pendiente menor",P2="Observar"),"Media","Baja"))) -> Media | R2: =IF(A2="","",IF(Q2="Alta","Gestionar esta semana",IF(Q2="Media","Hacer seguimiento","Mantener"))) -> Hacer seguimiento | S2: =IF(A2="","",IF(I2=0,"Sin venta",IF(I2>=cfg_VentaAlta,"Alta",IF(I2<cfg_VentaBaja,"Baja","Media")))) -> Baja | T2: =IF(A2="","",IFERROR(VLOOKUP(A2,Clientes_PDV!$A$2:$K$250,11,FALSE),"")) -> 0
A3: =IF(Clientes_PDV!A3="","",Clientes_PDV!A3) -> PDV-002 | B3: =IF(A3="","",IFERROR(VLOOKUP(A3,Clientes_PDV!$A$2:$J$250,2,FALSE),"")) -> Jumbo | C3: =IF(A3="","",IFERROR(VLOOKUP(A3,Clientes_PDV!$A$2:$J$250,3,FALSE),"")) -> Retail | D3: =IF(A3="","",IFERROR(VLOOKUP(A3,Clientes_PDV!$A$2:$J$250,4,FALSE),"")) -> Jumbo Kennedy | E3: =IF(A3="","",IFERROR(VLOOKUP(A3,Clientes_PDV!$A$2:$J$250,7,FALSE),"")) -> Semanal | F3: =IF(A3="","",IFERROR(VLOOKUP(A3,Clientes_PDV!$A$2:$J$250,8,FALSE),"")) -> 46201 | G3: =IF(F3="","",TODAY()-F3) -> 12 | H3: =IF(A3="","",IF(F3="","Sin visita",IF(G3<=IFERROR(VLOOKUP(E3,Inicio!$A$24:$B$26,2,FALSE),0),"Vigente","Atrasado"))) -> Atrasado | I3: =IF(A3="","",SUMIFS(Ventas_SellIn!$L$2:$L$800,Ventas_SellIn!$D$2:$D$800,A3,Ventas_SellIn!$B$2:$B$800,">="&TODAY()-Inicio!$B$14)) -> 461000 | J3: =IF(A3="","",SUMIFS(SellOut_Jumbo!$F$2:$F$800,SellOut_Jumbo!$C$2:$C$800,D3,SellOut_Jumbo!$A$2:$A$800,">="&TODAY()-Inicio!$B$14)) -> 37 | K3: =IF(A3="","",IF(I3=0,"Sin venta",IF(I3<Inicio!$B$15,"Venta baja","Venta OK"))) -> Venta baja | L3: =IF(A3="","",COUNTIFS(Ventas_SellIn!$D$2:$D$800,A3,Ventas_SellIn!$R$2:$R$800,">0")) -> 0 | M3: =IF(A3="","",SUMIFS(Ventas_SellIn!$R$2:$R$800,Ventas_SellIn!$D$2:$D$800,A3)) -> 0 | N3: =IF(A3="","",IF(M3>=Inicio!$B$18,"Pendiente relevante",IF(M3>0,"Pendiente menor","Sin deuda"))) -> Sin deuda | O3: =IF(A3="","",SUMIFS(Stock_PDV!$H$2:$H$800,Stock_PDV!$A$2:$A$800,A3)) -> 0 | P3: =IF(A3="","",IF(O3<=Inicio!$B$16,"Crítico",IF(O3<=Inicio!$B$17,"Observar","OK"))) -> Crítico | Q3: =IF(A3="","",IF(OR(H3="Atrasado",K3="Sin venta",N3="Pendiente relevante",P3="Crítico"),"Alta",IF(OR(K3="Venta baja",N3="Pendiente menor",P3="Observar"),"Media","Baja"))) -> Alta | R3: =IF(A3="","",IF(Q3="Alta","Gestionar esta semana",IF(Q3="Media","Hacer seguimiento","Mantener"))) -> Gestionar esta semana | S3: =IF(A3="","",IF(I3=0,"Sin venta",IF(I3>=cfg_VentaAlta,"Alta",IF(I3<cfg_VentaBaja,"Baja","Media")))) -> Baja | T3: =IF(A3="","",IFERROR(VLOOKUP(A3,Clientes_PDV!$A$2:$K$250,11,FALSE),"")) -> 0
A4: =IF(Clientes_PDV!A4="","",Clientes_PDV!A4) -> PDV-003 | B4: =IF(A4="","",IFERROR(VLOOKUP(A4,Clientes_PDV!$A$2:$J$250,2,FALSE),"")) -> Jumbo | C4: =IF(A4="","",IFERROR(VLOOKUP(A4,Clientes_PDV!$A$2:$J$250,3,FALSE),"")) -> Retail | D4: =IF(A4="","",IFERROR(VLOOKUP(A4,Clientes_PDV!$A$2:$J$250,4,FALSE),"")) -> Jumbo La Reina | E4: =IF(A4="","",IFERROR(VLOOKUP(A4,Clientes_PDV!$A$2:$J$250,7,FALSE),"")) -> Quincenal | F4: =IF(A4="","",IFERROR(VLOOKUP(A4,Clientes_PDV!$A$2:$J$250,8,FALSE),"")) -> 46197 | G4: =IF(F4="","",TODAY()-F4) -> 16 | H4: =IF(A4="","",IF(F4="","Sin visita",IF(G4<=IFERROR(VLOOKUP(E4,Inicio!$A$24:$B$26,2,FALSE),0),"Vigente","Atrasado"))) -> Atrasado | I4: =IF(A4="","",SUMIFS(Ventas_SellIn!$L$2:$L$800,Ventas_SellIn!$D$2:$D$800,A4,Ventas_SellIn!$B$2:$B$800,">="&TODAY()-Inicio!$B$14)) -> 66220 | J4: =IF(A4="","",SUMIFS(SellOut_Jumbo!$F$2:$F$800,SellOut_Jumbo!$C$2:$C$800,D4,SellOut_Jumbo!$A$2:$A$800,">="&TODAY()-Inicio!$B$14)) -> 36 | K4: =IF(A4="","",IF(I4=0,"Sin venta",IF(I4<Inicio!$B$15,"Venta baja","Venta OK"))) -> Venta baja | L4: =IF(A4="","",COUNTIFS(Ventas_SellIn!$D$2:$D$800,A4,Ventas_SellIn!$R$2:$R$800,">0")) -> 1 | M4: =IF(A4="","",SUMIFS(Ventas_SellIn!$R$2:$R$800,Ventas_SellIn!$D$2:$D$800,A4)) -> 6076.14 | N4: =IF(A4="","",IF(M4>=Inicio!$B$18,"Pendiente relevante",IF(M4>0,"Pendiente menor","Sin deuda"))) -> Pendiente menor | O4: =IF(A4="","",SUMIFS(Stock_PDV!$H$2:$H$800,Stock_PDV!$A$2:$A$800,A4)) -> 155 | P4: =IF(A4="","",IF(O4<=Inicio!$B$16,"Crítico",IF(O4<=Inicio!$B$17,"Observar","OK"))) -> OK | Q4: =IF(A4="","",IF(OR(H4="Atrasado",K4="Sin venta",N4="Pendiente relevante",P4="Crítico"),"Alta",IF(OR(K4="Venta baja",N4="Pendiente menor",P4="Observar"),"Media","Baja"))) -> Alta | R4: =IF(A4="","",IF(Q4="Alta","Gestionar esta semana",IF(Q4="Media","Hacer seguimiento","Mantener"))) -> Gestionar esta semana | S4: =IF(A4="","",IF(I4=0,"Sin venta",IF(I4>=cfg_VentaAlta,"Alta",IF(I4<cfg_VentaBaja,"Baja","Media")))) -> Baja | T4: =IF(A4="","",IFERROR(VLOOKUP(A4,Clientes_PDV!$A$2:$K$250,11,FALSE),"")) -> 0
A5: =IF(Clientes_PDV!A5="","",Clientes_PDV!A5) -> PDV-004 | B5: =IF(A5="","",IFERROR(VLOOKUP(A5,Clientes_PDV!$A$2:$J$250,2,FALSE),"")) -> Get It | C5: =IF(A5="","",IFERROR(VLOOKUP(A5,Clientes_PDV!$A$2:$J$250,3,FALSE),"")) -> Conveniencia | D5: =IF(A5="","",IFERROR(VLOOKUP(A5,Clientes_PDV!$A$2:$J$250,4,FALSE),"")) -> Get It Apoquindo | E5: =IF(A5="","",IFERROR(VLOOKUP(A5,Clientes_PDV!$A$2:$J$250,7,FALSE),"")) -> Semanal | F5: =IF(A5="","",IFERROR(VLOOKUP(A5,Clientes_PDV!$A$2:$J$250,8,FALSE),"")) -> 46206 | G5: =IF(F5="","",TODAY()-F5) -> 7 | H5: =IF(A5="","",IF(F5="","Sin visita",IF(G5<=IFERROR(VLOOKUP(E5,Inicio!$A$24:$B$26,2,FALSE),0),"Vigente","Atrasado"))) -> Vigente | I5: =IF(A5="","",SUMIFS(Ventas_SellIn!$L$2:$L$800,Ventas_SellIn!$D$2:$D$800,A5,Ventas_SellIn!$B$2:$B$800,">="&TODAY()-Inicio!$B$14)) -> 368880 | J5: =IF(A5="","",SUMIFS(SellOut_Jumbo!$F$2:$F$800,SellOut_Jumbo!$C$2:$C$800,D5,SellOut_Jumbo!$A$2:$A$800,">="&TODAY()-Inicio!$B$14)) -> 0 | K5: =IF(A5="","",IF(I5=0,"Sin venta",IF(I5<Inicio!$B$15,"Venta baja","Venta OK"))) -> Venta baja | L5: =IF(A5="","",COUNTIFS(Ventas_SellIn!$D$2:$D$800,A5,Ventas_SellIn!$R$2:$R$800,">0")) -> 2 | M5: =IF(A5="","",SUMIFS(Ventas_SellIn!$R$2:$R$800,Ventas_SellIn!$D$2:$D$800,A5)) -> 27036.8 | N5: =IF(A5="","",IF(M5>=Inicio!$B$18,"Pendiente relevante",IF(M5>0,"Pendiente menor","Sin deuda"))) -> Pendiente menor | O5: =IF(A5="","",SUMIFS(Stock_PDV!$H$2:$H$800,Stock_PDV!$A$2:$A$800,A5)) -> 8 | P5: =IF(A5="","",IF(O5<=Inicio!$B$16,"Crítico",IF(O5<=Inicio!$B$17,"Observar","OK"))) -> Crítico | Q5: =IF(A5="","",IF(OR(H5="Atrasado",K5="Sin venta",N5="Pendiente relevante",P5="Crítico"),"Alta",IF(OR(K5="Venta baja",N5="Pendiente menor",P5="Observar"),"Media","Baja"))) -> Alta | R5: =IF(A5="","",IF(Q5="Alta","Gestionar esta semana",IF(Q5="Media","Hacer seguimiento","Mantener"))) -> Gestionar esta semana | S5: =IF(A5="","",IF(I5=0,"Sin venta",IF(I5>=cfg_VentaAlta,"Alta",IF(I5<cfg_VentaBaja,"Baja","Media")))) -> Baja | T5: =IF(A5="","",IFERROR(VLOOKUP(A5,Clientes_PDV!$A$2:$K$250,11,FALSE),"")) -> 0
A6: =IF(Clientes_PDV!A6="","",Clientes_PDV!A6) -> PDV-005 | B6: =IF(A6="","",IFERROR(VLOOKUP(A6,Clientes_PDV!$A$2:$J$250,2,FALSE),"")) -> Get It | C6: =IF(A6="","",IFERROR(VLOOKUP(A6,Clientes_PDV!$A$2:$J$250,3,FALSE),"")) -> Conveniencia | D6: =IF(A6="","",IFERROR(VLOOKUP(A6,Clientes_PDV!$A$2:$J$250,4,FALSE),"")) -> Get It Vitacura | E6: =IF(A6="","",IFERROR(VLOOKUP(A6,Clientes_PDV!$A$2:$J$250,7,FALSE),"")) -> Quincenal | F6: =IF(A6="","",IFERROR(VLOOKUP(A6,Clientes_PDV!$A$2:$J$250,8,FALSE),"")) -> 46191 | G6: =IF(F6="","",TODAY()-F6) -> 22 | H6: =IF(A6="","",IF(F6="","Sin visita",IF(G6<=IFERROR(VLOOKUP(E6,Inicio!$A$24:$B$26,2,FALSE),0),"Vigente","Atrasado"))) -> Atrasado | I6: =IF(A6="","",SUMIFS(Ventas_SellIn!$L$2:$L$800,Ventas_SellIn!$D$2:$D$800,A6,Ventas_SellIn!$B$2:$B$800,">="&TODAY()-Inicio!$B$14)) -> 588968 | J6: =IF(A6="","",SUMIFS(SellOut_Jumbo!$F$2:$F$800,SellOut_Jumbo!$C$2:$C$800,D6,SellOut_Jumbo!$A$2:$A$800,">="&TODAY()-Inicio!$B$14)) -> 0 | K6: =IF(A6="","",IF(I6=0,"Sin venta",IF(I6<Inicio!$B$15,"Venta baja","Venta OK"))) -> Venta OK | L6: =IF(A6="","",COUNTIFS(Ventas_SellIn!$D$2:$D$800,A6,Ventas_SellIn!$R$2:$R$800,">0")) -> 4 | M6: =IF(A6="","",SUMIFS(Ventas_SellIn!$R$2:$R$800,Ventas_SellIn!$D$2:$D$800,A6)) -> 1178554.6 | N6: =IF(A6="","",IF(M6>=Inicio!$B$18,"Pendiente relevante",IF(M6>0,"Pendiente menor","Sin deuda"))) -> Pendiente relevante | O6: =IF(A6="","",SUMIFS(Stock_PDV!$H$2:$H$800,Stock_PDV!$A$2:$A$800,A6)) -> 200 | P6: =IF(A6="","",IF(O6<=Inicio!$B$16,"Crítico",IF(O6<=Inicio!$B$17,"Observar","OK"))) -> OK | Q6: =IF(A6="","",IF(OR(H6="Atrasado",K6="Sin venta",N6="Pendiente relevante",P6="Crítico"),"Alta",IF(OR(K6="Venta baja",N6="Pendiente menor",P6="Observar"),"Media","Baja"))) -> Alta | R6: =IF(A6="","",IF(Q6="Alta","Gestionar esta semana",IF(Q6="Media","Hacer seguimiento","Mantener"))) -> Gestionar esta semana | S6: =IF(A6="","",IF(I6=0,"Sin venta",IF(I6>=cfg_VentaAlta,"Alta",IF(I6<cfg_VentaBaja,"Baja","Media")))) -> Media | T6: =IF(A6="","",IFERROR(VLOOKUP(A6,Clientes_PDV!$A$2:$K$250,11,FALSE),"")) -> 0
A7: =IF(Clientes_PDV!A7="","",Clientes_PDV!A7) -> PDV-006 | B7: =IF(A7="","",IFERROR(VLOOKUP(A7,Clientes_PDV!$A$2:$J$250,2,FALSE),"")) -> Aldea Nativa | C7: =IF(A7="","",IFERROR(VLOOKUP(A7,Clientes_PDV!$A$2:$J$250,3,FALSE),"")) -> Especializadas | D7: =IF(A7="","",IFERROR(VLOOKUP(A7,Clientes_PDV!$A$2:$J$250,4,FALSE),"")) -> Aldea Nativa Providencia | E7: =IF(A7="","",IFERROR(VLOOKUP(A7,Clientes_PDV!$A$2:$J$250,7,FALSE),"")) -> Mensual | F7: =IF(A7="","",IFERROR(VLOOKUP(A7,Clientes_PDV!$A$2:$J$250,8,FALSE),"")) -> 46182 | G7: =IF(F7="","",TODAY()-F7) -> 31 | H7: =IF(A7="","",IF(F7="","Sin visita",IF(G7<=IFERROR(VLOOKUP(E7,Inicio!$A$24:$B$26,2,FALSE),0),"Vigente","Atrasado"))) -> Atrasado | I7: =IF(A7="","",SUMIFS(Ventas_SellIn!$L$2:$L$800,Ventas_SellIn!$D$2:$D$800,A7,Ventas_SellIn!$B$2:$B$800,">="&TODAY()-Inicio!$B$14)) -> 53340 | J7: =IF(A7="","",SUMIFS(SellOut_Jumbo!$F$2:$F$800,SellOut_Jumbo!$C$2:$C$800,D7,SellOut_Jumbo!$A$2:$A$800,">="&TODAY()-Inicio!$B$14)) -> 0 | K7: =IF(A7="","",IF(I7=0,"Sin venta",IF(I7<Inicio!$B$15,"Venta baja","Venta OK"))) -> Venta baja | L7: =IF(A7="","",COUNTIFS(Ventas_SellIn!$D$2:$D$800,A7,Ventas_SellIn!$R$2:$R$800,">0")) -> 1 | M7: =IF(A7="","",SUMIFS(Ventas_SellIn!$R$2:$R$800,Ventas_SellIn!$D$2:$D$800,A7)) -> 63474.6 | N7: =IF(A7="","",IF(M7>=Inicio!$B$18,"Pendiente relevante",IF(M7>0,"Pendiente menor","Sin deuda"))) -> Pendiente menor | O7: =IF(A7="","",SUMIFS(Stock_PDV!$H$2:$H$800,Stock_PDV!$A$2:$A$800,A7)) -> 183 | P7: =IF(A7="","",IF(O7<=Inicio!$B$16,"Crítico",IF(O7<=Inicio!$B$17,"Observar","OK"))) -> OK | Q7: =IF(A7="","",IF(OR(H7="Atrasado",K7="Sin venta",N7="Pendiente relevante",P7="Crítico"),"Alta",IF(OR(K7="Venta baja",N7="Pendiente menor",P7="Observar"),"Media","Baja"))) -> Alta | R7: =IF(A7="","",IF(Q7="Alta","Gestionar esta semana",IF(Q7="Media","Hacer seguimiento","Mantener"))) -> Gestionar esta semana | S7: =IF(A7="","",IF(I7=0,"Sin venta",IF(I7>=cfg_VentaAlta,"Alta",IF(I7<cfg_VentaBaja,"Baja","Media")))) -> Baja | T7: =IF(A7="","",IFERROR(VLOOKUP(A7,Clientes_PDV!$A$2:$K$250,11,FALSE),"")) -> 0
A8: =IF(Clientes_PDV!A8="","",Clientes_PDV!A8) -> PDV-007 | B8: =IF(A8="","",IFERROR(VLOOKUP(A8,Clientes_PDV!$A$2:$J$250,2,FALSE),"")) -> All Nutrition | C8: =IF(A8="","",IFERROR(VLOOKUP(A8,Clientes_PDV!$A$2:$J$250,3,FALSE),"")) -> Especializadas | D8: =IF(A8="","",IFERROR(VLOOKUP(A8,Clientes_PDV!$A$2:$J$250,4,FALSE),"")) -> All Nutrition La Reina | E8: =IF(A8="","",IFERROR(VLOOKUP(A8,Clientes_PDV!$A$2:$J$250,7,FALSE),"")) -> Mensual | F8: =IF(A8="","",IFERROR(VLOOKUP(A8,Clientes_PDV!$A$2:$J$250,8,FALSE),"")) -> 46167 | G8: =IF(F8="","",TODAY()-F8) -> 46 | H8: =IF(A8="","",IF(F8="","Sin visita",IF(G8<=IFERROR(VLOOKUP(E8,Inicio!$A$24:$B$26,2,FALSE),0),"Vigente","Atrasado"))) -> Atrasado | I8: =IF(A8="","",SUMIFS(Ventas_SellIn!$L$2:$L$800,Ventas_SellIn!$D$2:$D$800,A8,Ventas_SellIn!$B$2:$B$800,">="&TODAY()-Inicio!$B$14)) -> 472508 | J8: =IF(A8="","",SUMIFS(SellOut_Jumbo!$F$2:$F$800,SellOut_Jumbo!$C$2:$C$800,D8,SellOut_Jumbo!$A$2:$A$800,">="&TODAY()-Inicio!$B$14)) -> 0 | K8: =IF(A8="","",IF(I8=0,"Sin venta",IF(I8<Inicio!$B$15,"Venta baja","Venta OK"))) -> Venta baja | L8: =IF(A8="","",COUNTIFS(Ventas_SellIn!$D$2:$D$800,A8,Ventas_SellIn!$R$2:$R$800,">0")) -> 3 | M8: =IF(A8="","",SUMIFS(Ventas_SellIn!$R$2:$R$800,Ventas_SellIn!$D$2:$D$800,A8)) -> 636608.57 | N8: =IF(A8="","",IF(M8>=Inicio!$B$18,"Pendiente relevante",IF(M8>0,"Pendiente menor","Sin deuda"))) -> Pendiente relevante | O8: =IF(A8="","",SUMIFS(Stock_PDV!$H$2:$H$800,Stock_PDV!$A$2:$A$800,A8)) -> 100 | P8: =IF(A8="","",IF(O8<=Inicio!$B$16,"Crítico",IF(O8<=Inicio!$B$17,"Observar","OK"))) -> OK | Q8: =IF(A8="","",IF(OR(H8="Atrasado",K8="Sin venta",N8="Pendiente relevante",P8="Crítico"),"Alta",IF(OR(K8="Venta baja",N8="Pendiente menor",P8="Observar"),"Media","Baja"))) -> Alta | R8: =IF(A8="","",IF(Q8="Alta","Gestionar esta semana",IF(Q8="Media","Hacer seguimiento","Mantener"))) -> Gestionar esta semana | S8: =IF(A8="","",IF(I8=0,"Sin venta",IF(I8>=cfg_VentaAlta,"Alta",IF(I8<cfg_VentaBaja,"Baja","Media")))) -> Baja | T8: =IF(A8="","",IFERROR(VLOOKUP(A8,Clientes_PDV!$A$2:$K$250,11,FALSE),"")) -> 0
A9: =IF(Clientes_PDV!A9="","",Clientes_PDV!A9) -> PDV-008 | B9: =IF(A9="","",IFERROR(VLOOKUP(A9,Clientes_PDV!$A$2:$J$250,2,FALSE),"")) -> Farmacia Ahumada | C9: =IF(A9="","",IFERROR(VLOOKUP(A9,Clientes_PDV!$A$2:$J$250,3,FALSE),"")) -> Farmacias | D9: =IF(A9="","",IFERROR(VLOOKUP(A9,Clientes_PDV!$A$2:$J$250,4,FALSE),"")) -> Ahumada Los Dominicos | E9: =IF(A9="","",IFERROR(VLOOKUP(A9,Clientes_PDV!$A$2:$J$250,7,FALSE),"")) -> Quincenal | F9: =IF(A9="","",IFERROR(VLOOKUP(A9,Clientes_PDV!$A$2:$J$250,8,FALSE),"")) -> 46203 | G9: =IF(F9="","",TODAY()-F9) -> 10 | H9: =IF(A9="","",IF(F9="","Sin visita",IF(G9<=IFERROR(VLOOKUP(E9,Inicio!$A$24:$B$26,2,FALSE),0),"Vigente","Atrasado"))) -> Vigente | I9: =IF(A9="","",SUMIFS(Ventas_SellIn!$L$2:$L$800,Ventas_SellIn!$D$2:$D$800,A9,Ventas_SellIn!$B$2:$B$800,">="&TODAY()-Inicio!$B$14)) -> 12984 | J9: =IF(A9="","",SUMIFS(SellOut_Jumbo!$F$2:$F$800,SellOut_Jumbo!$C$2:$C$800,D9,SellOut_Jumbo!$A$2:$A$800,">="&TODAY()-Inicio!$B$14)) -> 0 | K9: =IF(A9="","",IF(I9=0,"Sin venta",IF(I9<Inicio!$B$15,"Venta baja","Venta OK"))) -> Venta baja | L9: =IF(A9="","",COUNTIFS(Ventas_SellIn!$D$2:$D$800,A9,Ventas_SellIn!$R$2:$R$800,">0")) -> 1 | M9: =IF(A9="","",SUMIFS(Ventas_SellIn!$R$2:$R$800,Ventas_SellIn!$D$2:$D$800,A9)) -> 15450.96 | N9: =IF(A9="","",IF(M9>=Inicio!$B$18,"Pendiente relevante",IF(M9>0,"Pendiente menor","Sin deuda"))) -> Pendiente menor | O9: =IF(A9="","",SUMIFS(Stock_PDV!$H$2:$H$800,Stock_PDV!$A$2:$A$800,A9)) -> 0 | P9: =IF(A9="","",IF(O9<=Inicio!$B$16,"Crítico",IF(O9<=Inicio!$B$17,"Observar","OK"))) -> Crítico | Q9: =IF(A9="","",IF(OR(H9="Atrasado",K9="Sin venta",N9="Pendiente relevante",P9="Crítico"),"Alta",IF(OR(K9="Venta baja",N9="Pendiente menor",P9="Observar"),"Media","Baja"))) -> Alta | R9: =IF(A9="","",IF(Q9="Alta","Gestionar esta semana",IF(Q9="Media","Hacer seguimiento","Mantener"))) -> Gestionar esta semana | S9: =IF(A9="","",IF(I9=0,"Sin venta",IF(I9>=cfg_VentaAlta,"Alta",IF(I9<cfg_VentaBaja,"Baja","Media")))) -> Baja | T9: =IF(A9="","",IFERROR(VLOOKUP(A9,Clientes_PDV!$A$2:$K$250,11,FALSE),"")) -> 0
A10: =IF(Clientes_PDV!A10="","",Clientes_PDV!A10) -> PDV-009 | B10: =IF(A10="","",IFERROR(VLOOKUP(A10,Clientes_PDV!$A$2:$J$250,2,FALSE),"")) -> Cruz Verde | C10: =IF(A10="","",IFERROR(VLOOKUP(A10,Clientes_PDV!$A$2:$J$250,3,FALSE),"")) -> Farmacias | D10: =IF(A10="","",IFERROR(VLOOKUP(A10,Clientes_PDV!$A$2:$J$250,4,FALSE),"")) -> Cruz Verde Vitacura | E10: =IF(A10="","",IFERROR(VLOOKUP(A10,Clientes_PDV!$A$2:$J$250,7,FALSE),"")) -> Quincenal | F10: =IF(A10="","",IFERROR(VLOOKUP(A10,Clientes_PDV!$A$2:$J$250,8,FALSE),"")) -> 46194 | G10: =IF(F10="","",TODAY()-F10) -> 19 | H10: =IF(A10="","",IF(F10="","Sin visita",IF(G10<=IFERROR(VLOOKUP(E10,Inicio!$A$24:$B$26,2,FALSE),0),"Vigente","Atrasado"))) -> Atrasado | I10: =IF(A10="","",SUMIFS(Ventas_SellIn!$L$2:$L$800,Ventas_SellIn!$D$2:$D$800,A10,Ventas_SellIn!$B$2:$B$800,">="&TODAY()-Inicio!$B$14)) -> 74680 | J10: =IF(A10="","",SUMIFS(SellOut_Jumbo!$F$2:$F$800,SellOut_Jumbo!$C$2:$C$800,D10,SellOut_Jumbo!$A$2:$A$800,">="&TODAY()-Inicio!$B$14)) -> 0 | K10: =IF(A10="","",IF(I10=0,"Sin venta",IF(I10<Inicio!$B$15,"Venta baja","Venta OK"))) -> Venta baja | L10: =IF(A10="","",COUNTIFS(Ventas_SellIn!$D$2:$D$800,A10,Ventas_SellIn!$R$2:$R$800,">0")) -> 3 | M10: =IF(A10="","",SUMIFS(Ventas_SellIn!$R$2:$R$800,Ventas_SellIn!$D$2:$D$800,A10)) -> 351097.6 | N10: =IF(A10="","",IF(M10>=Inicio!$B$18,"Pendiente relevante",IF(M10>0,"Pendiente menor","Sin deuda"))) -> Pendiente relevante | O10: =IF(A10="","",SUMIFS(Stock_PDV!$H$2:$H$800,Stock_PDV!$A$2:$A$800,A10)) -> 57 | P10: =IF(A10="","",IF(O10<=Inicio!$B$16,"Crítico",IF(O10<=Inicio!$B$17,"Observar","OK"))) -> OK | Q10: =IF(A10="","",IF(OR(H10="Atrasado",K10="Sin venta",N10="Pendiente relevante",P10="Crítico"),"Alta",IF(OR(K10="Venta baja",N10="Pendiente menor",P10="Observar"),"Media","Baja"))) -> Alta | R10: =IF(A10="","",IF(Q10="Alta","Gestionar esta semana",IF(Q10="Media","Hacer seguimiento","Mantener"))) -> Gestionar esta semana | S10: =IF(A10="","",IF(I10=0,"Sin venta",IF(I10>=cfg_VentaAlta,"Alta",IF(I10<cfg_VentaBaja,"Baja","Media")))) -> Baja | T10: =IF(A10="","",IFERROR(VLOOKUP(A10,Clientes_PDV!$A$2:$K$250,11,FALSE),"")) -> 0
A11: =IF(Clientes_PDV!A11="","",Clientes_PDV!A11) -> PDV-010 | B11: =IF(A11="","",IFERROR(VLOOKUP(A11,Clientes_PDV!$A$2:$J$250,2,FALSE),"")) -> Sodexo | C11: =IF(A11="","",IFERROR(VLOOKUP(A11,Clientes_PDV!$A$2:$J$250,3,FALSE),"")) -> Corporativo | D11: =IF(A11="","",IFERROR(VLOOKUP(A11,Clientes_PDV!$A$2:$J$250,4,FALSE),"")) -> Sodexo Casa Matriz | E11: =IF(A11="","",IFERROR(VLOOKUP(A11,Clientes_PDV!$A$2:$J$250,7,FALSE),"")) -> Mensual | F11: =IF(A11="","",IFERROR(VLOOKUP(A11,Clientes_PDV!$A$2:$J$250,8,FALSE),"")) -> 46185 | G11: =IF(F11="","",TODAY()-F11) -> 28 | H11: =IF(A11="","",IF(F11="","Sin visita",IF(G11<=IFERROR(VLOOKUP(E11,Inicio!$A$24:$B$26,2,FALSE),0),"Vigente","Atrasado"))) -> Vigente | I11: =IF(A11="","",SUMIFS(Ventas_SellIn!$L$2:$L$800,Ventas_SellIn!$D$2:$D$800,A11,Ventas_SellIn!$B$2:$B$800,">="&TODAY()-Inicio!$B$14)) -> 127474 | J11: =IF(A11="","",SUMIFS(SellOut_Jumbo!$F$2:$F$800,SellOut_Jumbo!$C$2:$C$800,D11,SellOut_Jumbo!$A$2:$A$800,">="&TODAY()-Inicio!$B$14)) -> 0 | K11: =IF(A11="","",IF(I11=0,"Sin venta",IF(I11<Inicio!$B$15,"Venta baja","Venta OK"))) -> Venta baja | L11: =IF(A11="","",COUNTIFS(Ventas_SellIn!$D$2:$D$800,A11,Ventas_SellIn!$R$2:$R$800,">0")) -> 3 | M11: =IF(A11="","",SUMIFS(Ventas_SellIn!$R$2:$R$800,Ventas_SellIn!$D$2:$D$800,A11)) -> 200342 | N11: =IF(A11="","",IF(M11>=Inicio!$B$18,"Pendiente relevante",IF(M11>0,"Pendiente menor","Sin deuda"))) -> Pendiente relevante | O11: =IF(A11="","",SUMIFS(Stock_PDV!$H$2:$H$800,Stock_PDV!$A$2:$A$800,A11)) -> 5 | P11: =IF(A11="","",IF(O11<=Inicio!$B$16,"Crítico",IF(O11<=Inicio!$B$17,"Observar","OK"))) -> Crítico | Q11: =IF(A11="","",IF(OR(H11="Atrasado",K11="Sin venta",N11="Pendiente relevante",P11="Crítico"),"Alta",IF(OR(K11="Venta baja",N11="Pendiente menor",P11="Observar"),"Media","Baja"))) -> Alta | R11: =IF(A11="","",IF(Q11="Alta","Gestionar esta semana",IF(Q11="Media","Hacer seguimiento","Mantener"))) -> Gestionar esta semana | S11: =IF(A11="","",IF(I11=0,"Sin venta",IF(I11>=cfg_VentaAlta,"Alta",IF(I11<cfg_VentaBaja,"Baja","Media")))) -> Baja | T11: =IF(A11="","",IFERROR(VLOOKUP(A11,Clientes_PDV!$A$2:$K$250,11,FALSE),"")) -> 0
A12: =IF(Clientes_PDV!A12="","",Clientes_PDV!A12) -> PDV-011 | B12: =IF(A12="","",IFERROR(VLOOKUP(A12,Clientes_PDV!$A$2:$J$250,2,FALSE),"")) -> Tres Toques | C12: =IF(A12="","",IFERROR(VLOOKUP(A12,Clientes_PDV!$A$2:$J$250,3,FALSE),"")) -> HORECA | D12: =IF(A12="","",IFERROR(VLOOKUP(A12,Clientes_PDV!$A$2:$J$250,4,FALSE),"")) -> Tres Toques Vitacura | E12: =IF(A12="","",IFERROR(VLOOKUP(A12,Clientes_PDV!$A$2:$J$250,7,FALSE),"")) -> Mensual | F12: =IF(A12="","",IFERROR(VLOOKUP(A12,Clientes_PDV!$A$2:$J$250,8,FALSE),"")) -> 46204 | G12: =IF(F12="","",TODAY()-F12) -> 9 | H12: =IF(A12="","",IF(F12="","Sin visita",IF(G12<=IFERROR(VLOOKUP(E12,Inicio!$A$24:$B$26,2,FALSE),0),"Vigente","Atrasado"))) -> Vigente | I12: =IF(A12="","",SUMIFS(Ventas_SellIn!$L$2:$L$800,Ventas_SellIn!$D$2:$D$800,A12,Ventas_SellIn!$B$2:$B$800,">="&TODAY()-Inicio!$B$14)) -> 3792 | J12: =IF(A12="","",SUMIFS(SellOut_Jumbo!$F$2:$F$800,SellOut_Jumbo!$C$2:$C$800,D12,SellOut_Jumbo!$A$2:$A$800,">="&TODAY()-Inicio!$B$14)) -> 0 | K12: =IF(A12="","",IF(I12=0,"Sin venta",IF(I12<Inicio!$B$15,"Venta baja","Venta OK"))) -> Venta baja | L12: =IF(A12="","",COUNTIFS(Ventas_SellIn!$D$2:$D$800,A12,Ventas_SellIn!$R$2:$R$800,">0")) -> 1 | M12: =IF(A12="","",SUMIFS(Ventas_SellIn!$R$2:$R$800,Ventas_SellIn!$D$2:$D$800,A12)) -> 4512.48 | N12: =IF(A12="","",IF(M12>=Inicio!$B$18,"Pendiente relevante",IF(M12>0,"Pendiente menor","Sin deuda"))) -> Pendiente menor | O12: =IF(A12="","",SUMIFS(Stock_PDV!$H$2:$H$800,Stock_PDV!$A$2:$A$800,A12)) -> 225 | P12: =IF(A12="","",IF(O12<=Inicio!$B$16,"Crítico",IF(O12<=Inicio!$B$17,"Observar","OK"))) -> OK | Q12: =IF(A12="","",IF(OR(H12="Atrasado",K12="Sin venta",N12="Pendiente relevante",P12="Crítico"),"Alta",IF(OR(K12="Venta baja",N12="Pendiente menor",P12="Observar"),"Media","Baja"))) -> Media | R12: =IF(A12="","",IF(Q12="Alta","Gestionar esta semana",IF(Q12="Media","Hacer seguimiento","Mantener"))) -> Hacer seguimiento | S12: =IF(A12="","",IF(I12=0,"Sin venta",IF(I12>=cfg_VentaAlta,"Alta",IF(I12<cfg_VentaBaja,"Baja","Media")))) -> Baja | T12: =IF(A12="","",IFERROR(VLOOKUP(A12,Clientes_PDV!$A$2:$K$250,11,FALSE),"")) -> 0
A13: =IF(Clientes_PDV!A13="","",Clientes_PDV!A13) -> PDV-012 | B13: =IF(A13="","",IFERROR(VLOOKUP(A13,Clientes_PDV!$A$2:$J$250,2,FALSE),"")) -> Mundo del Vino | C13: =IF(A13="","",IFERROR(VLOOKUP(A13,Clientes_PDV!$A$2:$J$250,3,FALSE),"")) -> Especializadas | D13: =IF(A13="","",IFERROR(VLOOKUP(A13,Clientes_PDV!$A$2:$J$250,4,FALSE),"")) -> Mundo del Vino Escuela Militar | E13: =IF(A13="","",IFERROR(VLOOKUP(A13,Clientes_PDV!$A$2:$J$250,7,FALSE),"")) -> Quincenal | F13: =IF(A13="","",IFERROR(VLOOKUP(A13,Clientes_PDV!$A$2:$J$250,8,FALSE),"")) -> 46207 | G13: =IF(F13="","",TODAY()-F13) -> 6 | H13: =IF(A13="","",IF(F13="","Sin visita",IF(G13<=IFERROR(VLOOKUP(E13,Inicio!$A$24:$B$26,2,FALSE),0),"Vigente","Atrasado"))) -> Vigente | I13: =IF(A13="","",SUMIFS(Ventas_SellIn!$L$2:$L$800,Ventas_SellIn!$D$2:$D$800,A13,Ventas_SellIn!$B$2:$B$800,">="&TODAY()-Inicio!$B$14)) -> 230010 | J13: =IF(A13="","",SUMIFS(SellOut_Jumbo!$F$2:$F$800,SellOut_Jumbo!$C$2:$C$800,D13,SellOut_Jumbo!$A$2:$A$800,">="&TODAY()-Inicio!$B$14)) -> 0 | K13: =IF(A13="","",IF(I13=0,"Sin venta",IF(I13<Inicio!$B$15,"Venta baja","Venta OK"))) -> Venta baja | L13: =IF(A13="","",COUNTIFS(Ventas_SellIn!$D$2:$D$800,A13,Ventas_SellIn!$R$2:$R$800,">0")) -> 2 | M13: =IF(A13="","",SUMIFS(Ventas_SellIn!$R$2:$R$800,Ventas_SellIn!$D$2:$D$800,A13)) -> 204888.2 | N13: =IF(A13="","",IF(M13>=Inicio!$B$18,"Pendiente relevante",IF(M13>0,"Pendiente menor","Sin deuda"))) -> Pendiente relevante | O13: =IF(A13="","",SUMIFS(Stock_PDV!$H$2:$H$800,Stock_PDV!$A$2:$A$800,A13)) -> 140 | P13: =IF(A13="","",IF(O13<=Inicio!$B$16,"Crítico",IF(O13<=Inicio!$B$17,"Observar","OK"))) -> OK | Q13: =IF(A13="","",IF(OR(H13="Atrasado",K13="Sin venta",N13="Pendiente relevante",P13="Crítico"),"Alta",IF(OR(K13="Venta baja",N13="Pendiente menor",P13="Observar"),"Media","Baja"))) -> Alta | R13: =IF(A13="","",IF(Q13="Alta","Gestionar esta semana",IF(Q13="Media","Hacer seguimiento","Mantener"))) -> Gestionar esta semana | S13: =IF(A13="","",IF(I13=0,"Sin venta",IF(I13>=cfg_VentaAlta,"Alta",IF(I13<cfg_VentaBaja,"Baja","Media")))) -> Baja | T13: =IF(A13="","",IFERROR(VLOOKUP(A13,Clientes_PDV!$A$2:$K$250,11,FALSE),"")) -> 0
... A250: =IF(Clientes_PDV!A250="","",Clientes_PDV!A250) | B250: =IF(A250="","",IFERROR(VLOOKUP(A250,Clientes_PDV!$A$2:$J$250,2,FALSE),"")) | C250: =IF(A250="","",IFERROR(VLOOKUP(A250,Clientes_PDV!$A$2:$J$250,3,FALSE),"")) | D250: =IF(A250="","",IFERROR(VLOOKUP(A250,Clientes_PDV!$A$2:$J$250,4,FALSE),"")) | E250: =IF(A250="","",IFERROR(VLOOKUP(A250,Clientes_PDV!$A$2:$J$250,7,FALSE),"")) | F250: =IF(A250="","",IFERROR(VLOOKUP(A250,Clientes_PDV!$A$2:$J$250,8,FALSE),"")) | G250: =IF(F250="","",TODAY()-F250) | H250: =IF(A250="","",IF(F250="","Sin visita",IF(G250<=IFERROR(VLOOKUP(E250,Inicio!$A$24:$B$26,2,FALSE),0),"Vigente","Atrasado"))) | I250: =IF(A250="","",SUMIFS(Ventas_SellIn!$L$2:$L$800,Ventas_SellIn!$D$2:$D$800,A250,Ventas_SellIn!$B$2:$B$800,">="&TODAY()-Inicio!$B$14)) | J250: =IF(A250="","",SUMIFS(SellOut_Jumbo!$F$2:$F$800,SellOut_Jumbo!$C$2:$C$800,D250,SellOut_Jumbo!$A$2:$A$800,">="&TODAY()-Inicio!$B$14)) | K250: =IF(A250="","",IF(I250=0,"Sin venta",IF(I250<Inicio!$B$15,"Venta baja","Venta OK"))) | L250: =IF(A250="","",COUNTIFS(Ventas_SellIn!$D$2:$D$800,A250,Ventas_SellIn!$R$2:$R$800,">0")) | M250: =IF(A250="","",SUMIFS(Ventas_SellIn!$R$2:$R$800,Ventas_SellIn!$D$2:$D$800,A250)) | N250: =IF(A250="","",IF(M250>=Inicio!$B$18,"Pendiente relevante",IF(M250>0,"Pendiente menor","Sin deuda"))) | O250: =IF(A250="","",SUMIFS(Stock_PDV!$H$2:$H$800,Stock_PDV!$A$2:$A$800,A250)) | P250: =IF(A250="","",IF(O250<=Inicio!$B$16,"Crítico",IF(O250<=Inicio!$B$17,"Observar","OK"))) | Q250: =IF(A250="","",IF(OR(H250="Atrasado",K250="Sin venta",N250="Pendiente relevante",P250="Crítico"),"Alta",IF(OR(K250="Venta baja",N250="Pendiente menor",P250="Observar"),"Media","Baja"))) | R250: =IF(A250="","",IF(Q250="Alta","Gestionar esta semana",IF(Q250="Media","Hacer seguimiento","Mantener"))) | S250: =IF(A250="","",IF(I250=0,"Sin venta",IF(I250>=cfg_VentaAlta,"Alta",IF(I250<cfg_VentaBaja,"Baja","Media")))) | T250: =IF(A250="","",IFERROR(VLOOKUP(A250,Clientes_PDV!$A$2:$K$250,11,FALSE),""))

Sheet Clientes_PDV
A1: PDV_ID | B1: Cliente | C1: Canal | D1: Punto de venta | E1: Comuna | F1: Región | G1: Frecuencia visita | H1: Última visita | I1: Estado cliente | J1: Observaciones | K1: Dirección | L1: Bodega asignada | M1: Encargado | N1: Teléfono | O1: Email | P1: Condición de pago
A2: PDV-001 | B2: Jumbo | C2: Retail | D2: Jumbo Bilbao | E2: Las Condes | F2: RM | G2: Semanal | H2: 46209 | I2: Activo | J2: Sala prioritaria | L2: BOD-001
A3: PDV-002 | B3: Jumbo | C3: Retail | D3: Jumbo Kennedy | E3: Vitacura | F3: RM | G3: Semanal | H3: 46201 | I3: Activo | J3: Revisar reposición | L3: BOD-001
A4: PDV-003 | B4: Jumbo | C4: Retail | D4: Jumbo La Reina | E4: La Reina | F4: RM | G4: Quincenal | H4: 46197 | I4: Activo | L4: BOD-001
A5: PDV-004 | B5: Get It | C5: Conveniencia | D5: Get It Apoquindo | E5: Las Condes | F5: RM | G5: Semanal | H5: 46206 | I5: Activo
A6: PDV-005 | B6: Get It | C6: Conveniencia | D6: Get It Vitacura | E6: Vitacura | F6: RM | G6: Quincenal | H6: 46191 | I6: Activo
A7: PDV-006 | B7: Aldea Nativa | C7: Especializadas | D7: Aldea Nativa Providencia | E7: Providencia | F7: RM | G7: Mensual | H7: 46182 | I7: Activo
A8: PDV-007 | B8: All Nutrition | C8: Especializadas | D8: All Nutrition La Reina | E8: La Reina | F8: RM | G8: Mensual | H8: 46167 | I8: Activo | J8: Sin venta reciente
A9: PDV-008 | B9: Farmacia Ahumada | C9: Farmacias | D9: Ahumada Los Dominicos | E9: Las Condes | F9: RM | G9: Quincenal | H9: 46203 | I9: Prospecto
A10: PDV-009 | B10: Cruz Verde | C10: Farmacias | D10: Cruz Verde Vitacura | E10: Vitacura | F10: RM | G10: Quincenal | H10: 46194 | I10: Activo
A11: PDV-010 | B11: Sodexo | C11: Corporativo | D11: Sodexo Casa Matriz | E11: Providencia | F11: RM | G11: Mensual | H11: 46185 | I11: Activo
A12: PDV-011 | B12: Tres Toques | C12: HORECA | D12: Tres Toques Vitacura | E12: Vitacura | F12: RM | G12: Mensual | H12: 46204 | I12: Activo
A13: PDV-012 | B13: Mundo del Vino | C13: Especializadas | D13: Mundo del Vino Escuela Militar | E13: Las Condes | F13: RM | G13: Quincenal | H13: 46207 | I13: Activo

Sheet Ventas_SellIn
A1: ID_venta | B1: Fecha emisión (factura) | C1: N° factura | D1: PDV_ID | E1: Cliente | F1: Canal | G1: Punto de venta | H1: SKU | I1: Descripción SKU | J1: Cantidad facturada | K1: Precio unit. NETO (sin IVA) | L1: Venta NETA (sin IVA) | M1: IVA ($) | N1: Venta TOTAL (con IVA) | O1: Fecha vencimiento | P1: Status pago | Q1: Pagado (con IVA) | R1: Pendiente (con IVA) | S1: Estado factura (auto) | T1: Observaciones | U1: Año | V1: Mes | W1: Día | X1: Periodo | Y1: Barras equiv | Z1: Días para vencer | AB1: ⚙ Configuración
A2: V-0001 | B2: 46199 | C2: F-202607001 | D2: PDV-010 | E2: =IFERROR(VLOOKUP(D2,Clientes_PDV!$A$2:$J$250,2,FALSE),"") -> Sodexo | F2: =IFERROR(VLOOKUP(D2,Clientes_PDV!$A$2:$J$250,3,FALSE),"") -> Corporativo | G2: =IFERROR(VLOOKUP(D2,Clientes_PDV!$A$2:$J$250,4,FALSE),"") -> Sodexo Casa Matriz | H2: NUVA-BAR-BM-U-01 | I2: =IFERROR(VLOOKUP(H2,Maestro_SKU!$A$2:$P$500,2,FALSE),"") -> Barra Berry Mix unidad | J2: 20 | K2: 911 | L2: =IF(OR(J2="",K2=""),"",J2*K2) -> 18220 | M2: =IF(L2="","",L2*Inicio!$B$13) -> 3461.8 | N2: =IF(L2="","",L2+M2) -> 21681.8 | O2: 46244 | P2: Parcial | Q2: 14349 | R2: =IF(N2="","",MAX(N2-Q2,0)) -> 7332.8 | S2: =IF(A2="","",IF(OR(P2="Pagada",R2=0),"Pagada",IF(O2<TODAY(),"Vencida",IF(O2<=TODAY()+Inicio!$B$19,"Próxima a vencer","Vigente")))) -> Vigente | U2: =IF($B2="","",YEAR($B2)) -> 2026 | V2: =IF($B2="","",MONTH($B2)) -> 6 | W2: =IF($B2="","",DAY($B2)) -> 26 | X2: =IF($B2="","",YEAR($B2)&"-"&TEXT(MONTH($B2),"00")) -> 2026-06 | Y2: =IF(OR($H2="",$J2=""),"",$J2*IFERROR(VLOOKUP($H2,Maestro_SKU!$A$2:$P$500,12,FALSE),1)) -> 20 | Z2: =IF(OR($A2="",$O2="",$S2="Pagada"),"",$O2-TODAY()) -> 31
A3: V-0002 | B3: 46208 | C3: F-202607002 | D3: PDV-011 | E3: =IFERROR(VLOOKUP(D3,Clientes_PDV!$A$2:$J$250,2,FALSE),"") -> Tres Toques | F3: =IFERROR(VLOOKUP(D3,Clientes_PDV!$A$2:$J$250,3,FALSE),"") -> HORECA | G3: =IFERROR(VLOOKUP(D3,Clientes_PDV!$A$2:$J$250,4,FALSE),"") -> Tres Toques Vitacura | H3: NUVA-BAR-CC-U-01 | I3: =IFERROR(VLOOKUP(H3,Maestro_SKU!$A$2:$P$500,2,FALSE),"") -> Barra Cacao Crispy unidad | J3: 4 | K3: 948 | L3: =IF(OR(J3="",K3=""),"",J3*K3) -> 3792 | M3: =IF(L3="","",L3*Inicio!$B$13) -> 720.48 | N3: =IF(L3="","",L3+M3) -> 4512.48 | O3: 46223 | P3: Vencida | Q3: 0 | R3: =IF(N3="","",MAX(N3-Q3,0)) -> 4512.48 | S3: =IF(A3="","",IF(OR(P3="Pagada",R3=0),"Pagada",IF(O3<TODAY(),"Vencida",IF(O3<=TODAY()+Inicio!$B$19,"Próxima a vencer","Vigente")))) -> Vigente | U3: =IF($B3="","",YEAR($B3)) -> 2026 | V3: =IF($B3="","",MONTH($B3)) -> 7 | W3: =IF($B3="","",DAY($B3)) -> 5 | X3: =IF($B3="","",YEAR($B3)&"-"&TEXT(MONTH($B3),"00")) -> 2026-07 | Y3: =IF(OR($H3="",$J3=""),"",$J3*IFERROR(VLOOKUP($H3,Maestro_SKU!$A$2:$P$500,12,FALSE),1)) -> 4 | Z3: =IF(OR($A3="",$O3="",$S3="Pagada"),"",$O3-TODAY()) -> 10
A4: V-0003 | B4: 46174 | C4: F-202607003 | D4: PDV-012 | E4: =IFERROR(VLOOKUP(D4,Clientes_PDV!$A$2:$J$250,2,FALSE),"") -> Mundo del Vino | F4: =IFERROR(VLOOKUP(D4,Clientes_PDV!$A$2:$J$250,3,FALSE),"") -> Especializadas | G4: =IFERROR(VLOOKUP(D4,Clientes_PDV!$A$2:$J$250,4,FALSE),"") -> Mundo del Vino Escuela Militar | H4: NUVA-BAR-CC-BX-04 | I4: =IFERROR(VLOOKUP(H4,Maestro_SKU!$A$2:$P$500,2,FALSE),"") -> Estuche Cacao Crispy 4 unidades | J4: 4 | K4: 3807 | L4: =IF(OR(J4="",K4=""),"",J4*K4) -> 15228 | M4: =IF(L4="","",L4*Inicio!$B$13) -> 2893.32 | N4: =IF(L4="","",L4+M4) -> 18121.32 | O4: 46204 | P4: Pagada | Q4: 18121.32 | R4: =IF(N4="","",MAX(N4-Q4,0)) -> 0 | S4: =IF(A4="","",IF(OR(P4="Pagada",R4=0),"Pagada",IF(O4<TODAY(),"Vencida",IF(O4<=TODAY()+Inicio!$B$19,"Próxima a vencer","Vigente")))) -> Pagada | U4: =IF($B4="","",YEAR($B4)) -> 2026 | V4: =IF($B4="","",MONTH($B4)) -> 6 | W4: =IF($B4="","",DAY($B4)) -> 1 | X4: =IF($B4="","",YEAR($B4)&"-"&TEXT(MONTH($B4),"00")) -> 2026-06 | Y4: =IF(OR($H4="",$J4=""),"",$J4*IFERROR(VLOOKUP($H4,Maestro_SKU!$A$2:$P$500,12,FALSE),1)) -> 16 | Z4: =IF(OR($A4="",$O4="",$S4="Pagada"),"",$O4-TODAY())
A5: V-0004 | B5: 46170 | C5: F-202607004 | D5: PDV-005 | E5: =IFERROR(VLOOKUP(D5,Clientes_PDV!$A$2:$J$250,2,FALSE),"") -> Get It | F5: =IFERROR(VLOOKUP(D5,Clientes_PDV!$A$2:$J$250,3,FALSE),"") -> Conveniencia | G5: =IFERROR(VLOOKUP(D5,Clientes_PDV!$A$2:$J$250,4,FALSE),"") -> Get It Vitacura | H5: NUVA-BAR-PB-BX-04 | I5: =IFERROR(VLOOKUP(H5,Maestro_SKU!$A$2:$P$500,2,FALSE),"") -> Estuche Peanut Boost 4 unidades | J5: 24 | K5: 3130 | L5: =IF(OR(J5="",K5=""),"",J5*K5) -> 75120 | M5: =IF(L5="","",L5*Inicio!$B$13) -> 14272.8 | N5: =IF(L5="","",L5+M5) -> 89392.8 | O5: 46200 | P5: Pagada | Q5: 89392.8 | R5: =IF(N5="","",MAX(N5-Q5,0)) -> 0 | S5: =IF(A5="","",IF(OR(P5="Pagada",R5=0),"Pagada",IF(O5<TODAY(),"Vencida",IF(O5<=TODAY()+Inicio!$B$19,"Próxima a vencer","Vigente")))) -> Pagada | U5: =IF($B5="","",YEAR($B5)) -> 2026 | V5: =IF($B5="","",MONTH($B5)) -> 5 | W5: =IF($B5="","",DAY($B5)) -> 28 | X5: =IF($B5="","",YEAR($B5)&"-"&TEXT(MONTH($B5),"00")) -> 2026-05 | Y5: =IF(OR($H5="",$J5=""),"",$J5*IFERROR(VLOOKUP($H5,Maestro_SKU!$A$2:$P$500,12,FALSE),1)) -> 96 | Z5: =IF(OR($A5="",$O5="",$S5="Pagada"),"",$O5-TODAY())
A6: V-0005 | B6: 46197 | C6: F-202607005 | D6: PDV-004 | E6: =IFERROR(VLOOKUP(D6,Clientes_PDV!$A$2:$J$250,2,FALSE),"") -> Get It | F6: =IFERROR(VLOOKUP(D6,Clientes_PDV!$A$2:$J$250,3,FALSE),"") -> Conveniencia | G6: =IFERROR(VLOOKUP(D6,Clientes_PDV!$A$2:$J$250,4,FALSE),"") -> Get It Apoquindo | H6: NUVA-BAR-PB-CS-24 | I6: =IFERROR(VLOOKUP(H6,Maestro_SKU!$A$2:$P$500,2,FALSE),"") -> Caja master Peanut Boost 24 unidades | J6: 20 | K6: 17022 | L6: =IF(OR(J6="",K6=""),"",J6*K6) -> 340440 | M6: =IF(L6="","",L6*Inicio!$B$13) -> 64683.6 | N6: =IF(L6="","",L6+M6) -> 405123.6 | O6: 46212 | P6: Pagada | Q6: 405123.6 | R6: =IF(N6="","",MAX(N6-Q6,0)) -> 0 | S6: =IF(A6="","",IF(OR(P6="Pagada",R6=0),"Pagada",IF(O6<TODAY(),"Vencida",IF(O6<=TODAY()+Inicio!$B$19,"Próxima a vencer","Vigente")))) -> Pagada | U6: =IF($B6="","",YEAR($B6)) -> 2026 | V6: =IF($B6="","",MONTH($B6)) -> 6 | W6: =IF($B6="","",DAY($B6)) -> 24 | X6: =IF($B6="","",YEAR($B6)&"-"&TEXT(MONTH($B6),"00")) -> 2026-06 | Y6: =IF(OR($H6="",$J6=""),"",$J6*IFERROR(VLOOKUP($H6,Maestro_SKU!$A$2:$P$500,12,FALSE),1)) -> 480 | Z6: =IF(OR($A6="",$O6="",$S6="Pagada"),"",$O6-TODAY())
A7: V-0006 | B7: 46177 | C7: F-202607006 | D7: PDV-005 | E7: =IFERROR(VLOOKUP(D7,Clientes_PDV!$A$2:$J$250,2,FALSE),"") -> Get It | F7: =IFERROR(VLOOKUP(D7,Clientes_PDV!$A$2:$J$250,3,FALSE),"") -> Conveniencia | G7: =IFERROR(VLOOKUP(D7,Clientes_PDV!$A$2:$J$250,4,FALSE),"") -> Get It Vitacura | H7: NUVA-BAR-CC-CS-24 | I7: =IFERROR(VLOOKUP(H7,Maestro_SKU!$A$2:$P$500,2,FALSE),"") -> Caja master Cacao Crispy 24 unidades | J7: 15 | K7: 17698 | L7: =IF(OR(J7="",K7=""),"",J7*K7) -> 265470 | M7: =IF(L7="","",L7*Inicio!$B$13) -> 50439.3 | N7: =IF(L7="","",L7+M7) -> 315909.3 | O7: 46222 | P7: Pagada | Q7: 315909.3 | R7: =IF(N7="","",MAX(N7-Q7,0)) -> 0 | S7: =IF(A7="","",IF(OR(P7="Pagada",R7=0),"Pagada",IF(O7<TODAY(),"Vencida",IF(O7<=TODAY()+Inicio!$B$19,"Próxima a vencer","Vigente")))) -> Pagada | U7: =IF($B7="","",YEAR($B7)) -> 2026 | V7: =IF($B7="","",MONTH($B7)) -> 6 | W7: =IF($B7="","",DAY($B7)) -> 4 | X7: =IF($B7="","",YEAR($B7)&"-"&TEXT(MONTH($B7),"00")) -> 2026-06 | Y7: =IF(OR($H7="",$J7=""),"",$J7*IFERROR(VLOOKUP($H7,Maestro_SKU!$A$2:$P$500,12,FALSE),1)) -> 360 | Z7: =IF(OR($A7="",$O7="",$S7="Pagada"),"",$O7-TODAY())
A8: V-0007 | B8: 46197 | C8: F-202607007 | D8: PDV-002 | E8: =IFERROR(VLOOKUP(D8,Clientes_PDV!$A$2:$J$250,2,FALSE),"") -> Jumbo | F8: =IFERROR(VLOOKUP(D8,Clientes_PDV!$A$2:$J$250,3,FALSE),"") -> Retail | G8: =IFERROR(VLOOKUP(D8,Clientes_PDV!$A$2:$J$250,4,FALSE),"") -> Jumbo Kennedy | H8: NUVA-BAR-CC-BX-04 | I8: =IFERROR(VLOOKUP(H8,Maestro_SKU!$A$2:$P$500,2,FALSE),"") -> Estuche Cacao Crispy 4 unidades | J8: 8 | K8: 3268 | L8: =IF(OR(J8="",K8=""),"",J8*K8) -> 26144 | M8: =IF(L8="","",L8*Inicio!$B$13) -> 4967.36 | N8: =IF(L8="","",L8+M8) -> 31111.36 | O8: 46197 | P8: Pagada | Q8: 31111.36 | R8: =IF(N8="","",MAX(N8-Q8,0)) -> 0 | S8: =IF(A8="","",IF(OR(P8="Pagada",R8=0),"Pagada",IF(O8<TODAY(),"Vencida",IF(O8<=TODAY()+Inicio!$B$19,"Próxima a vencer","Vigente")))) -> Pagada | U8: =IF($B8="","",YEAR($B8)) -> 2026 | V8: =IF($B8="","",MONTH($B8)) -> 6 | W8: =IF($B8="","",DAY($B8)) -> 24 | X8: =IF($B8="","",YEAR($B8)&"-"&TEXT(MONTH($B8),"00")) -> 2026-06 | Y8: =IF(OR($H8="",$J8=""),"",$J8*IFERROR(VLOOKUP($H8,Maestro_SKU!$A$2:$P$500,12,FALSE),1)) -> 32 | Z8: =IF(OR($A8="",$O8="",$S8="Pagada"),"",$O8-TODAY())
A9: V-0008 | B9: 46152 | C9: F-202607008 | D9: PDV-005 | E9: =IFERROR(VLOOKUP(D9,Clientes_PDV!$A$2:$J$250,2,FALSE),"") -> Get It | F9: =IFERROR(VLOOKUP(D9,Clientes_PDV!$A$2:$J$250,3,FALSE),"") -> Conveniencia | G9: =IFERROR(VLOOKUP(D9,Clientes_PDV!$A$2:$J$250,4,FALSE),"") -> Get It Vitacura | H9: NUVA-BAR-PB-U-01 | I9: =IFERROR(VLOOKUP(H9,Maestro_SKU!$A$2:$P$500,2,FALSE),"") -> Barra Peanut Boost unidad | J9: 6 | K9: 745 | L9: =IF(OR(J9="",K9=""),"",J9*K9) -> 4470 | M9: =IF(L9="","",L9*Inicio!$B$13) -> 849.3 | N9: =IF(L9="","",L9+M9) -> 5319.3 | O9: 46182 | P9: Vencida | Q9: 0 | R9: =IF(N9="","",MAX(N9-Q9,0)) -> 5319.3 | S9: =IF(A9="","",IF(OR(P9="Pagada",R9=0),"Pagada",IF(O9<TODAY(),"Vencida",IF(O9<=TODAY()+Inicio!$B$19,"Próxima a vencer","Vigente")))) -> Vencida | U9: =IF($B9="","",YEAR($B9)) -> 2026 | V9: =IF($B9="","",MONTH($B9)) -> 5 | W9: =IF($B9="","",DAY($B9)) -> 10 | X9: =IF($B9="","",YEAR($B9)&"-"&TEXT(MONTH($B9),"00")) -> 2026-05 | Y9: =IF(OR($H9="",$J9=""),"",$J9*IFERROR(VLOOKUP($H9,Maestro_SKU!$A$2:$P$500,12,FALSE),1)) -> 6 | Z9: =IF(OR($A9="",$O9="",$S9="Pagada"),"",$O9-TODAY()) -> -31
A10: V-0009 | B10: 46161 | C10: F-202607009 | D10: PDV-003 | E10: =IFERROR(VLOOKUP(D10,Clientes_PDV!$A$2:$J$250,2,FALSE),"") -> Jumbo | F10: =IFERROR(VLOOKUP(D10,Clientes_PDV!$A$2:$J$250,3,FALSE),"") -> Retail | G10: =IFERROR(VLOOKUP(D10,Clientes_PDV!$A$2:$J$250,4,FALSE),"") -> Jumbo La Reina | H10: NUVA-BAR-PB-U-01 | I10: =IFERROR(VLOOKUP(H10,Maestro_SKU!$A$2:$P$500,2,FALSE),"") -> Barra Peanut Boost unidad | J10: 6 | K10: 851 | L10: =IF(OR(J10="",K10=""),"",J10*K10) -> 5106 | M10: =IF(L10="","",L10*Inicio!$B$13) -> 970.14 | N10: =IF(L10="","",L10+M10) -> 6076.14 | O10: 46176 | P10: Vencida | Q10: 0 | R10: =IF(N10="","",MAX(N10-Q10,0)) -> 6076.14 | S10: =IF(A10="","",IF(OR(P10="Pagada",R10=0),"Pagada",IF(O10<TODAY(),"Vencida",IF(O10<=TODAY()+Inicio!$B$19,"Próxima a vencer","Vigente")))) -> Vencida | U10: =IF($B10="","",YEAR($B10)) -> 2026 | V10: =IF($B10="","",MONTH($B10)) -> 5 | W10: =IF($B10="","",DAY($B10)) -> 19 | X10: =IF($B10="","",YEAR($B10)&"-"&TEXT(MONTH($B10),"00")) -> 2026-05 | Y10: =IF(OR($H10="",$J10=""),"",$J10*IFERROR(VLOOKUP($H10,Maestro_SKU!$A$2:$P$500,12,FALSE),1)) -> 6 | Z10: =IF(OR($A10="",$O10="",$S10="Pagada"),"",$O10-TODAY()) -> -37
A11: V-0010 | B11: 46203 | C11: F-202607010 | D11: PDV-007 | E11: =IFERROR(VLOOKUP(D11,Clientes_PDV!$A$2:$J$250,2,FALSE),"") -> All Nutrition | F11: =IFERROR(VLOOKUP(D11,Clientes_PDV!$A$2:$J$250,3,FALSE),"") -> Especializadas | G11: =IFERROR(VLOOKUP(D11,Clientes_PDV!$A$2:$J$250,4,FALSE),"") -> All Nutrition La Reina | H11: NUVA-BAR-BM-CS-24 | I11: =IFERROR(VLOOKUP(H11,Maestro_SKU!$A$2:$P$500,2,FALSE),"") -> Caja master Berry Mix 24 unidades | J11: 24 | K11: 18767 | L11: =IF(OR(J11="",K11=""),"",J11*K11) -> 450408 | M11: =IF(L11="","",L11*Inicio!$B$13) -> 85577.52 | N11: =IF(L11="","",L11+M11) -> 535985.52 | O11: 46218 | P11: Parcial | Q11: 205558 | R11: =IF(N11="","",MAX(N11-Q11,0)) -> 330427.52 | S11: =IF(A11="","",IF(OR(P11="Pagada",R11=0),"Pagada",IF(O11<TODAY(),"Vencida",IF(O11<=TODAY()+Inicio!$B$19,"Próxima a vencer","Vigente")))) -> Próxima a vencer | U11: =IF($B11="","",YEAR($B11)) -> 2026 | V11: =IF($B11="","",MONTH($B11)) -> 6 | W11: =IF($B11="","",DAY($B11)) -> 30 | X11: =IF($B11="","",YEAR($B11)&"-"&TEXT(MONTH($B11),"00")) -> 2026-06 | Y11: =IF(OR($H11="",$J11=""),"",$J11*IFERROR(VLOOKUP($H11,Maestro_SKU!$A$2:$P$500,12,FALSE),1)) -> 576 | Z11: =IF(OR($A11="",$O11="",$S11="Pagada"),"",$O11-TODAY()) -> 5
A12: V-0011 | B12: 46190 | C12: F-202607011 | D12: PDV-005 | E12: =IFERROR(VLOOKUP(D12,Clientes_PDV!$A$2:$J$250,2,FALSE),"") -> Get It | F12: =IFERROR(VLOOKUP(D12,Clientes_PDV!$A$2:$J$250,3,FALSE),"") -> Conveniencia | G12: =IFERROR(VLOOKUP(D12,Clientes_PDV!$A$2:$J$250,4,FALSE),"") -> Get It Vitacura | H12: NUVA-BAR-CC-U-01 | I12: =IFERROR(VLOOKUP(H12,Maestro_SKU!$A$2:$P$500,2,FALSE),"") -> Barra Cacao Crispy unidad | J12: 8 | K12: 757 | L12: =IF(OR(J12="",K12=""),"",J12*K12) -> 6056 | M12: =IF(L12="","",L12*Inicio!$B$13) -> 1150.64 | N12: =IF(L12="","",L12+M12) -> 7206.64 | O12: 46220 | P12: Pagada | Q12: 7206.64 | R12: =IF(N12="","",MAX(N12-Q12,0)) -> 9.094947e-13 | S12: =IF(A12="","",IF(OR(P12="Pagada",R12=0),"Pagada",IF(O12<TODAY(),"Vencida",IF(O12<=TODAY()+Inicio!$B$19,"Próxima a vencer","Vigente")))) -> Pagada | U12: =IF($B12="","",YEAR($B12)) -> 2026 | V12: =IF($B12="","",MONTH($B12)) -> 6 | W12: =IF($B12="","",DAY($B12)) -> 17 | X12: =IF($B12="","",YEAR($B12)&"-"&TEXT(MONTH($B12),"00")) -> 2026-06 | Y12: =IF(OR($H12="",$J12=""),"",$J12*IFERROR(VLOOKUP($H12,Maestro_SKU!$A$2:$P$500,12,FALSE),1)) -> 8 | Z12: =IF(OR($A12="",$O12="",$S12="Pagada"),"",$O12-TODAY())
A13: V-0012 | B13: 46197 | C13: F-202607012 | D13: PDV-001 | E13: =IFERROR(VLOOKUP(D13,Clientes_PDV!$A$2:$J$250,2,FALSE),"") -> Jumbo | F13: =IFERROR(VLOOKUP(D13,Clientes_PDV!$A$2:$J$250,3,FALSE),"") -> Retail | G13: =IFERROR(VLOOKUP(D13,Clientes_PDV!$A$2:$J$250,4,FALSE),"") -> Jumbo Bilbao | H13: NUVA-BAR-CC-CS-24 | I13: =IFERROR(VLOOKUP(H13,Maestro_SKU!$A$2:$P$500,2,FALSE),"") -> Caja master Cacao Crispy 24 unidades | J13: 4 | K13: 20929 | L13: =IF(OR(J13="",K13=""),"",J13*K13) -> 83716 | M13: =IF(L13="","",L13*Inicio!$B$13) -> 15906.04 | N13: =IF(L13="","",L13+M13) -> 99622.04 | O13: 46197 | P13: Pagada | Q13: 99622.04 | R13: =IF(N13="","",MAX(N13-Q13,0)) -> 1.4551915e-11 | S13: =IF(A13="","",IF(OR(P13="Pagada",R13=0),"Pagada",IF(O13<TODAY(),"Vencida",IF(O13<=TODAY()+Inicio!$B$19,"Próxima a vencer","Vigente")))) -> Pagada | U13: =IF($B13="","",YEAR($B13)) -> 2026 | V13: =IF($B13="","",MONTH($B13)) -> 6 | W13: =IF($B13="","",DAY($B13)) -> 24 | X13: =IF($B13="","",YEAR($B13)&"-"&TEXT(MONTH($B13),"00")) -> 2026-06 | Y13: =IF(OR($H13="",$J13=""),"",$J13*IFERROR(VLOOKUP($H13,Maestro_SKU!$A$2:$P$500,12,FALSE),1)) -> 96 | Z13: =IF(OR($A13="",$O13="",$S13="Pagada"),"",$O13-TODAY())
... A46: V-0045 | B46: 46170 | C46: F-202607045 | D46: PDV-009 | E46: =IFERROR(VLOOKUP(D46,Clientes_PDV!$A$2:$J$250,2,FALSE),"") -> Cruz Verde | F46: =IFERROR(VLOOKUP(D46,Clientes_PDV!$A$2:$J$250,3,FALSE),"") -> Farmacias | G46: =IFERROR(VLOOKUP(D46,Clientes_PDV!$A$2:$J$250,4,FALSE),"") -> Cruz Verde Vitacura | H46: NUVA-BAR-PB-CS-24 | I46: =IFERROR(VLOOKUP(H46,Maestro_SKU!$A$2:$P$500,2,FALSE),"") -> Caja master Peanut Boost 24 unidades | J46: 10 | K46: 22036 | L46: =IF(OR(J46="",K46=""),"",J46*K46) -> 220360 | M46: =IF(L46="","",L46*Inicio!$B$13) -> 41868.4 | N46: =IF(L46="","",L46+M46) -> 262228.4 | O46: 46185 | P46: Vencida | Q46: 0 | R46: =IF(N46="","",MAX(N46-Q46,0)) -> 262228.4 | S46: =IF(A46="","",IF(OR(P46="Pagada",R46=0),"Pagada",IF(O46<TODAY(),"Vencida",IF(O46<=TODAY()+Inicio!$B$19,"Próxima a vencer","Vigente")))) -> Vencida | U46: =IF($B46="","",YEAR($B46)) -> 2026 | V46: =IF($B46="","",MONTH($B46)) -> 5 | W46: =IF($B46="","",DAY($B46)) -> 28 | X46: =IF($B46="","",YEAR($B46)&"-"&TEXT(MONTH($B46),"00")) -> 2026-05 | Y46: =IF(OR($H46="",$J46=""),"",$J46*IFERROR(VLOOKUP($H46,Maestro_SKU!$A$2:$P$500,12,FALSE),1)) -> 240 | Z46: =IF(OR($A46="",$O46="",$S46="Pagada"),"",$O46-TODAY()) -> -28
E47: =IFERROR(VLOOKUP(D47,Clientes_PDV!$A$2:$J$250,2,FALSE),"") | F47: =IFERROR(VLOOKUP(D47,Clientes_PDV!$A$2:$J$250,3,FALSE),"") | G47: =IFERROR(VLOOKUP(D47,Clientes_PDV!$A$2:$J$250,4,FALSE),"") | I47: =IFERROR(VLOOKUP(H47,Maestro_SKU!$A$2:$P$500,2,FALSE),"") | L47: =IF(OR(J47="",K47=""),"",J47*K47) | M47: =IF(L47="","",L47*Inicio!$B$13) | N47: =IF(L47="","",L47+M47) | R47: =IF(N47="","",MAX(N47-Q47,0)) | S47: =IF(A47="","",IF(OR(P47="Pagada",R47=0),"Pagada",IF(O47<TODAY(),"Vencida",IF(O47<=TODAY()+Inicio!$B$19,"Próxima a vencer","Vigente")))) | U47: =IF($B47="","",YEAR($B47)) | V47: =IF($B47="","",MONTH($B47)) | W47: =IF($B47="","",DAY($B47)) | X47: =IF($B47="","",YEAR($B47)&"-"&TEXT(MONTH($B47),"00")) | Y47: =IF(OR($H47="",$J47=""),"",$J47*IFERROR(VLOOKUP($H47,Maestro_SKU!$A$2:$P$500,12,FALSE),1)) | Z47: =IF(OR($A47="",$O47="",$S47="Pagada"),"",$O47-TODAY())
E48: =IFERROR(VLOOKUP(D48,Clientes_PDV!$A$2:$J$250,2,FALSE),"") | F48: =IFERROR(VLOOKUP(D48,Clientes_PDV!$A$2:$J$250,3,FALSE),"") | G48: =IFERROR(VLOOKUP(D48,Clientes_PDV!$A$2:$J$250,4,FALSE),"") | I48: =IFERROR(VLOOKUP(H48,Maestro_SKU!$A$2:$P$500,2,FALSE),"") | L48: =IF(OR(J48="",K48=""),"",J48*K48) | M48: =IF(L48="","",L48*Inicio!$B$13) | N48: =IF(L48="","",L48+M48) | R48: =IF(N48="","",MAX(N48-Q48,0)) | S48: =IF(A48="","",IF(OR(P48="Pagada",R48=0),"Pagada",IF(O48<TODAY(),"Vencida",IF(O48<=TODAY()+Inicio!$B$19,"Próxima a vencer","Vigente")))) | U48: =IF($B48="","",YEAR($B48)) | V48: =IF($B48="","",MONTH($B48)) | W48: =IF($B48="","",DAY($B48)) | X48: =IF($B48="","",YEAR($B48)&"-"&TEXT(MONTH($B48),"00")) | Y48: =IF(OR($H48="",$J48=""),"",$J48*IFERROR(VLOOKUP($H48,Maestro_SKU!$A$2:$P$500,12,FALSE),1)) | Z48: =IF(OR($A48="",$O48="",$S48="Pagada"),"",$O48-TODAY())
E49: =IFERROR(VLOOKUP(D49,Clientes_PDV!$A$2:$J$250,2,FALSE),"") | F49: =IFERROR(VLOOKUP(D49,Clientes_PDV!$A$2:$J$250,3,FALSE),"") | G49: =IFERROR(VLOOKUP(D49,Clientes_PDV!$A$2:$J$250,4,FALSE),"") | I49: =IFERROR(VLOOKUP(H49,Maestro_SKU!$A$2:$P$500,2,FALSE),"") | L49: =IF(OR(J49="",K49=""),"",J49*K49) | M49: =IF(L49="","",L49*Inicio!$B$13) | N49: =IF(L49="","",L49+M49) | R49: =IF(N49="","",MAX(N49-Q49,0)) | S49: =IF(A49="","",IF(OR(P49="Pagada",R49=0),"Pagada",IF(O49<TODAY(),"Vencida",IF(O49<=TODAY()+Inicio!$B$19,"Próxima a vencer","Vigente")))) | U49: =IF($B49="","",YEAR($B49)) | V49: =IF($B49="","",MONTH($B49)) | W49: =IF($B49="","",DAY($B49)) | X49: =IF($B49="","",YEAR($B49)&"-"&TEXT(MONTH($B49),"00")) | Y49: =IF(OR($H49="",$J49=""),"",$J49*IFERROR(VLOOKUP($H49,Maestro_SKU!$A$2:$P$500,12,FALSE),1)) | Z49: =IF(OR($A49="",$O49="",$S49="Pagada"),"",$O49-TODAY())
E50: =IFERROR(VLOOKUP(D50,Clientes_PDV!$A$2:$J$250,2,FALSE),"") | F50: =IFERROR(VLOOKUP(D50,Clientes_PDV!$A$2:$J$250,3,FALSE),"") | G50: =IFERROR(VLOOKUP(D50,Clientes_PDV!$A$2:$J$250,4,FALSE),"") | I50: =IFERROR(VLOOKUP(H50,Maestro_SKU!$A$2:$P$500,2,FALSE),"") | L50: =IF(OR(J50="",K50=""),"",J50*K50) | M50: =IF(L50="","",L50*Inicio!$B$13) | N50: =IF(L50="","",L50+M50) | R50: =IF(N50="","",MAX(N50-Q50,0)) | S50: =IF(A50="","",IF(OR(P50="Pagada",R50=0),"Pagada",IF(O50<TODAY(),"Vencida",IF(O50<=TODAY()+Inicio!$B$19,"Próxima a vencer","Vigente")))) | U50: =IF($B50="","",YEAR($B50)) | V50: =IF($B50="","",MONTH($B50)) | W50: =IF($B50="","",DAY($B50)) | X50: =IF($B50="","",YEAR($B50)&"-"&TEXT(MONTH($B50),"00")) | Y50: =IF(OR($H50="",$J50=""),"",$J50*IFERROR(VLOOKUP($H50,Maestro_SKU!$A$2:$P$500,12,FALSE),1)) | Z50: =IF(OR($A50="",$O50="",$S50="Pagada"),"",$O50-TODAY())
E51: =IFERROR(VLOOKUP(D51,Clientes_PDV!$A$2:$J$250,2,FALSE),"") | F51: =IFERROR(VLOOKUP(D51,Clientes_PDV!$A$2:$J$250,3,FALSE),"") | G51: =IFERROR(VLOOKUP(D51,Clientes_PDV!$A$2:$J$250,4,FALSE),"") | I51: =IFERROR(VLOOKUP(H51,Maestro_SKU!$A$2:$P$500,2,FALSE),"") | L51: =IF(OR(J51="",K51=""),"",J51*K51) | M51: =IF(L51="","",L51*Inicio!$B$13) | N51: =IF(L51="","",L51+M51) | R51: =IF(N51="","",MAX(N51-Q51,0)) | S51: =IF(A51="","",IF(OR(P51="Pagada",R51=0),"Pagada",IF(O51<TODAY(),"Vencida",IF(O51<=TODAY()+Inicio!$B$19,"Próxima a vencer","Vigente")))) | U51: =IF($B51="","",YEAR($B51)) | V51: =IF($B51="","",MONTH($B51)) | W51: =IF($B51="","",DAY($B51)) | X51: =IF($B51="","",YEAR($B51)&"-"&TEXT(MONTH($B51),"00")) | Y51: =IF(OR($H51="",$J51=""),"",$J51*IFERROR(VLOOKUP($H51,Maestro_SKU!$A$2:$P$500,12,FALSE),1)) | Z51: =IF(OR($A51="",$O51="",$S51="Pagada"),"",$O51-TODAY())
E52: =IFERROR(VLOOKUP(D52,Clientes_PDV!$A$2:$J$250,2,FALSE),"") | F52: =IFERROR(VLOOKUP(D52,Clientes_PDV!$A$2:$J$250,3,FALSE),"") | G52: =IFERROR(VLOOKUP(D52,Clientes_PDV!$A$2:$J$250,4,FALSE),"") | I52: =IFERROR(VLOOKUP(H52,Maestro_SKU!$A$2:$P$500,2,FALSE),"") | L52: =IF(OR(J52="",K52=""),"",J52*K52) | M52: =IF(L52="","",L52*Inicio!$B$13) | N52: =IF(L52="","",L52+M52) | R52: =IF(N52="","",MAX(N52-Q52,0)) | S52: =IF(A52="","",IF(OR(P52="Pagada",R52=0),"Pagada",IF(O52<TODAY(),"Vencida",IF(O52<=TODAY()+Inicio!$B$19,"Próxima a vencer","Vigente")))) | U52: =IF($B52="","",YEAR($B52)) | V52: =IF($B52="","",MONTH($B52)) | W52: =IF($B52="","",DAY($B52)) | X52: =IF($B52="","",YEAR($B52)&"-"&TEXT(MONTH($B52),"00")) | Y52: =IF(OR($H52="",$J52=""),"",$J52*IFERROR(VLOOKUP($H52,Maestro_SKU!$A$2:$P$500,12,FALSE),1)) | Z52: =IF(OR($A52="",$O52="",$S52="Pagada"),"",$O52-TODAY())
E53: =IFERROR(VLOOKUP(D53,Clientes_PDV!$A$2:$J$250,2,FALSE),"") | F53: =IFERROR(VLOOKUP(D53,Clientes_PDV!$A$2:$J$250,3,FALSE),"") | G53: =IFERROR(VLOOKUP(D53,Clientes_PDV!$A$2:$J$250,4,FALSE),"") | I53: =IFERROR(VLOOKUP(H53,Maestro_SKU!$A$2:$P$500,2,FALSE),"") | L53: =IF(OR(J53="",K53=""),"",J53*K53) | M53: =IF(L53="","",L53*Inicio!$B$13) | N53: =IF(L53="","",L53+M53) | R53: =IF(N53="","",MAX(N53-Q53,0)) | S53: =IF(A53="","",IF(OR(P53="Pagada",R53=0),"Pagada",IF(O53<TODAY(),"Vencida",IF(O53<=TODAY()+Inicio!$B$19,"Próxima a vencer","Vigente")))) | U53: =IF($B53="","",YEAR($B53)) | V53: =IF($B53="","",MONTH($B53)) | W53: =IF($B53="","",DAY($B53)) | X53: =IF($B53="","",YEAR($B53)&"-"&TEXT(MONTH($B53),"00")) | Y53: =IF(OR($H53="",$J53=""),"",$J53*IFERROR(VLOOKUP($H53,Maestro_SKU!$A$2:$P$500,12,FALSE),1)) | Z53: =IF(OR($A53="",$O53="",$S53="Pagada"),"",$O53-TODAY())
E54: =IFERROR(VLOOKUP(D54,Clientes_PDV!$A$2:$J$250,2,FALSE),"") | F54: =IFERROR(VLOOKUP(D54,Clientes_PDV!$A$2:$J$250,3,FALSE),"") | G54: =IFERROR(VLOOKUP(D54,Clientes_PDV!$A$2:$J$250,4,FALSE),"") | I54: =IFERROR(VLOOKUP(H54,Maestro_SKU!$A$2:$P$500,2,FALSE),"") | L54: =IF(OR(J54="",K54=""),"",J54*K54) | M54: =IF(L54="","",L54*Inicio!$B$13) | N54: =IF(L54="","",L54+M54) | R54: =IF(N54="","",MAX(N54-Q54,0)) | S54: =IF(A54="","",IF(OR(P54="Pagada",R54=0),"Pagada",IF(O54<TODAY(),"Vencida",IF(O54<=TODAY()+Inicio!$B$19,"Próxima a vencer","Vigente")))) | U54: =IF($B54="","",YEAR($B54)) | V54: =IF($B54="","",MONTH($B54)) | W54: =IF($B54="","",DAY($B54)) | X54: =IF($B54="","",YEAR($B54)&"-"&TEXT(MONTH($B54),"00")) | Y54: =IF(OR($H54="",$J54=""),"",$J54*IFERROR(VLOOKUP($H54,Maestro_SKU!$A$2:$P$500,12,FALSE),1)) | Z54: =IF(OR($A54="",$O54="",$S54="Pagada"),"",$O54-TODAY())
E55: =IFERROR(VLOOKUP(D55,Clientes_PDV!$A$2:$J$250,2,FALSE),"") | F55: =IFERROR(VLOOKUP(D55,Clientes_PDV!$A$2:$J$250,3,FALSE),"") | G55: =IFERROR(VLOOKUP(D55,Clientes_PDV!$A$2:$J$250,4,FALSE),"") | I55: =IFERROR(VLOOKUP(H55,Maestro_SKU!$A$2:$P$500,2,FALSE),"") | L55: =IF(OR(J55="",K55=""),"",J55*K55) | M55: =IF(L55="","",L55*Inicio!$B$13) | N55: =IF(L55="","",L55+M55) | R55: =IF(N55="","",MAX(N55-Q55,0)) | S55: =IF(A55="","",IF(OR(P55="Pagada",R55=0),"Pagada",IF(O55<TODAY(),"Vencida",IF(O55<=TODAY()+Inicio!$B$19,"Próxima a vencer","Vigente")))) | U55: =IF($B55="","",YEAR($B55)) | V55: =IF($B55="","",MONTH($B55)) | W55: =IF($B55="","",DAY($B55)) | X55: =IF($B55="","",YEAR($B55)&"-"&TEXT(MONTH($B55),"00")) | Y55: =IF(OR($H55="",$J55=""),"",$J55*IFERROR(VLOOKUP($H55,Maestro_SKU!$A$2:$P$500,12,FALSE),1)) | Z55: =IF(OR($A55="",$O55="",$S55="Pagada"),"",$O55-TODAY())
E56: =IFERROR(VLOOKUP(D56,Clientes_PDV!$A$2:$J$250,2,FALSE),"") | F56: =IFERROR(VLOOKUP(D56,Clientes_PDV!$A$2:$J$250,3,FALSE),"") | G56: =IFERROR(VLOOKUP(D56,Clientes_PDV!$A$2:$J$250,4,FALSE),"") | I56: =IFERROR(VLOOKUP(H56,Maestro_SKU!$A$2:$P$500,2,FALSE),"") | L56: =IF(OR(J56="",K56=""),"",J56*K56) | M56: =IF(L56="","",L56*Inicio!$B$13) | N56: =IF(L56="","",L56+M56) | R56: =IF(N56="","",MAX(N56-Q56,0)) | S56: =IF(A56="","",IF(OR(P56="Pagada",R56=0),"Pagada",IF(O56<TODAY(),"Vencida",IF(O56<=TODAY()+Inicio!$B$19,"Próxima a vencer","Vigente")))) | U56: =IF($B56="","",YEAR($B56)) | V56: =IF($B56="","",MONTH($B56)) | W56: =IF($B56="","",DAY($B56)) | X56: =IF($B56="","",YEAR($B56)&"-"&TEXT(MONTH($B56),"00")) | Y56: =IF(OR($H56="",$J56=""),"",$J56*IFERROR(VLOOKUP($H56,Maestro_SKU!$A$2:$P$500,12,FALSE),1)) | Z56: =IF(OR($A56="",$O56="",$S56="Pagada"),"",$O56-TODAY())
E57: =IFERROR(VLOOKUP(D57,Clientes_PDV!$A$2:$J$250,2,FALSE),"") | F57: =IFERROR(VLOOKUP(D57,Clientes_PDV!$A$2:$J$250,3,FALSE),"") | G57: =IFERROR(VLOOKUP(D57,Clientes_PDV!$A$2:$J$250,4,FALSE),"") | I57: =IFERROR(VLOOKUP(H57,Maestro_SKU!$A$2:$P$500,2,FALSE),"") | L57: =IF(OR(J57="",K57=""),"",J57*K57) | M57: =IF(L57="","",L57*Inicio!$B$13) | N57: =IF(L57="","",L57+M57) | R57: =IF(N57="","",MAX(N57-Q57,0)) | S57: =IF(A57="","",IF(OR(P57="Pagada",R57=0),"Pagada",IF(O57<TODAY(),"Vencida",IF(O57<=TODAY()+Inicio!$B$19,"Próxima a vencer","Vigente")))) | U57: =IF($B57="","",YEAR($B57)) | V57: =IF($B57="","",MONTH($B57)) | W57: =IF($B57="","",DAY($B57)) | X57: =IF($B57="","",YEAR($B57)&"-"&TEXT(MONTH($B57),"00")) | Y57: =IF(OR($H57="",$J57=""),"",$J57*IFERROR(VLOOKUP($H57,Maestro_SKU!$A$2:$P$500,12,FALSE),1)) | Z57: =IF(OR($A57="",$O57="",$S57="Pagada"),"",$O57-TODAY())
E58: =IFERROR(VLOOKUP(D58,Clientes_PDV!$A$2:$J$250,2,FALSE),"") | F58: =IFERROR(VLOOKUP(D58,Clientes_PDV!$A$2:$J$250,3,FALSE),"") | G58: =IFERROR(VLOOKUP(D58,Clientes_PDV!$A$2:$J$250,4,FALSE),"") | I58: =IFERROR(VLOOKUP(H58,Maestro_SKU!$A$2:$P$500,2,FALSE),"") | L58: =IF(OR(J58="",K58=""),"",J58*K58) | M58: =IF(L58="","",L58*Inicio!$B$13) | N58: =IF(L58="","",L58+M58) | R58: =IF(N58="","",MAX(N58-Q58,0)) | S58: =IF(A58="","",IF(OR(P58="Pagada",R58=0),"Pagada",IF(O58<TODAY(),"Vencida",IF(O58<=TODAY()+Inicio!$B$19,"Próxima a vencer","Vigente")))) | U58: =IF($B58="","",YEAR($B58)) | V58: =IF($B58="","",MONTH($B58)) | W58: =IF($B58="","",DAY($B58)) | X58: =IF($B58="","",YEAR($B58)&"-"&TEXT(MONTH($B58),"00")) | Y58: =IF(OR($H58="",$J58=""),"",$J58*IFERROR(VLOOKUP($H58,Maestro_SKU!$A$2:$P$500,12,FALSE),1)) | Z58: =IF(OR($A58="",$O58="",$S58="Pagada"),"",$O58-TODAY())
... E800: =IFERROR(VLOOKUP(D800,Clientes_PDV!$A$2:$J$250,2,FALSE),"") | F800: =IFERROR(VLOOKUP(D800,Clientes_PDV!$A$2:$J$250,3,FALSE),"") | G800: =IFERROR(VLOOKUP(D800,Clientes_PDV!$A$2:$J$250,4,FALSE),"") | I800: =IFERROR(VLOOKUP(H800,Maestro_SKU!$A$2:$P$500,2,FALSE),"") | L800: =IF(OR(J800="",K800=""),"",J800*K800) | M800: =IF(L800="","",L800*Inicio!$B$13) | N800: =IF(L800="","",L800+M800) | R800: =IF(N800="","",MAX(N800-Q800,0)) | S800: =IF(A800="","",IF(OR(P800="Pagada",R800=0),"Pagada",IF(O800<TODAY(),"Vencida",IF(O800<=TODAY()+Inicio!$B$19,"Próxima a vencer","Vigente")))) | U800: =IF($B800="","",YEAR($B800)) | V800: =IF($B800="","",MONTH($B800)) | W800: =IF($B800="","",DAY($B800)) | X800: =IF($B800="","",YEAR($B800)&"-"&TEXT(MONTH($B800),"00")) | Y800: =IF(OR($H800="",$J800=""),"",$J800*IFERROR(VLOOKUP($H800,Maestro_SKU!$A$2:$P$500,12,FALSE),1)) | Z800: =IF(OR($A800="",$O800="",$S800="Pagada"),"",$O800-TODAY())

Sheet Condiciones Clientes
A1: Margen frontal | Simulador separado de ventas | L1: ⚙ Configuración
A2: Esta hoja NO modifica Ventas_SellIn ni Cobertura. Sirve para preparar negociación de precio antes de facturar.
A4: 1) Calcular precio sugerido desde PVP pensado y margen objetivo
A5: Cliente | B5: Canal | C5: SKU opcional | D5: PVP bruto pensado | E5: Margen frontal objetivo | F5: PVP neto calculado | G5: Precio neto sugerido | H5: Precio bruto equivalente | I5: Margen calculado | J5: Comentario
A6: Get It | B6: Conveniencia | C6: NUVA-BAR-CC-U-01 | D6: 1990 | E6: 0.4 | F6: =IF(D6="","",D6/(1+Inicio!$B$13)) -> 1672.2689 | G6: =IF(OR(F6="",E6=""),"",F6*(1-E6)) -> 1003.3613 | H6: =IF(G6="","",G6*(1+Inicio!$B$13)) -> 1194 | I6: =IF(OR(F6="",G6=""),"",(F6-G6)/F6) -> 0.4 | J6: Ejemplo: si Get It pide 40% de margen frontal
A7: Jumbo | B7: Retail | C7: NUVA-BAR-BM-BX-04 | D7: 5990 | E7: 0.45 | F7: =IF(D7="","",D7/(1+Inicio!$B$13)) -> 5033.6134 | G7: =IF(OR(F7="",E7=""),"",F7*(1-E7)) -> 2768.4874 | H7: =IF(G7="","",G7*(1+Inicio!$B$13)) -> 3294.5 | I7: =IF(OR(F7="",G7=""),"",(F7-G7)/F7) -> 0.45 | J7: Ejemplo retail estuche x4
A8: Farmacia Ahumada | B8: Farmacias | C8: NUVA-BAR-PB-U-01 | D8: 1990 | E8: 0.4 | F8: =IF(D8="","",D8/(1+Inicio!$B$13)) -> 1672.2689 | G8: =IF(OR(F8="",E8=""),"",F8*(1-E8)) -> 1003.3613 | H8: =IF(G8="","",G8*(1+Inicio!$B$13)) -> 1194 | I8: =IF(OR(F8="",G8=""),"",(F8-G8)/F8) -> 0.4 | J8: Ejemplo farmacias
F9: =IF(D9="","",D9/(1+Inicio!$B$13)) | G9: =IF(OR(F9="",E9=""),"",F9*(1-E9)) | H9: =IF(G9="","",G9*(1+Inicio!$B$13)) | I9: =IF(OR(F9="",G9=""),"",(F9-G9)/F9)
F10: =IF(D10="","",D10/(1+Inicio!$B$13)) | G10: =IF(OR(F10="",E10=""),"",F10*(1-E10)) | H10: =IF(G10="","",G10*(1+Inicio!$B$13)) | I10: =IF(OR(F10="",G10=""),"",(F10-G10)/F10)
F11: =IF(D11="","",D11/(1+Inicio!$B$13)) | G11: =IF(OR(F11="",E11=""),"",F11*(1-E11)) | H11: =IF(G11="","",G11*(1+Inicio!$B$13)) | I11: =IF(OR(F11="",G11=""),"",(F11-G11)/F11)
F12: =IF(D12="","",D12/(1+Inicio!$B$13)) | G12: =IF(OR(F12="",E12=""),"",F12*(1-E12)) | H12: =IF(G12="","",G12*(1+Inicio!$B$13)) | I12: =IF(OR(F12="",G12=""),"",(F12-G12)/F12)
F13: =IF(D13="","",D13/(1+Inicio!$B$13)) | G13: =IF(OR(F13="",E13=""),"",F13*(1-E13)) | H13: =IF(G13="","",G13*(1+Inicio!$B$13)) | I13: =IF(OR(F13="",G13=""),"",(F13-G13)/F13)
F14: =IF(D14="","",D14/(1+Inicio!$B$13)) | G14: =IF(OR(F14="",E14=""),"",F14*(1-E14)) | H14: =IF(G14="","",G14*(1+Inicio!$B$13)) | I14: =IF(OR(F14="",G14=""),"",(F14-G14)/F14)
F15: =IF(D15="","",D15/(1+Inicio!$B$13)) | G15: =IF(OR(F15="",E15=""),"",F15*(1-E15)) | H15: =IF(G15="","",G15*(1+Inicio!$B$13)) | I15: =IF(OR(F15="",G15=""),"",(F15-G15)/F15)
F16: =IF(D16="","",D16/(1+Inicio!$B$13)) | G16: =IF(OR(F16="",E16=""),"",F16*(1-E16)) | H16: =IF(G16="","",G16*(1+Inicio!$B$13)) | I16: =IF(OR(F16="",G16=""),"",(F16-G16)/F16)
F17: =IF(D17="","",D17/(1+Inicio!$B$13)) | G17: =IF(OR(F17="",E17=""),"",F17*(1-E17)) | H17: =IF(G17="","",G17*(1+Inicio!$B$13)) | I17: =IF(OR(F17="",G17=""),"",(F17-G17)/F17)
F18: =IF(D18="","",D18/(1+Inicio!$B$13)) | G18: =IF(OR(F18="",E18=""),"",F18*(1-E18)) | H18: =IF(G18="","",G18*(1+Inicio!$B$13)) | I18: =IF(OR(F18="",G18=""),"",(F18-G18)/F18)
F19: =IF(D19="","",D19/(1+Inicio!$B$13)) | G19: =IF(OR(F19="",E19=""),"",F19*(1-E19)) | H19: =IF(G19="","",G19*(1+Inicio!$B$13)) | I19: =IF(OR(F19="",G19=""),"",(F19-G19)/F19)
F20: =IF(D20="","",D20/(1+Inicio!$B$13)) | G20: =IF(OR(F20="",E20=""),"",F20*(1-E20)) | H20: =IF(G20="","",G20*(1+Inicio!$B$13)) | I20: =IF(OR(F20="",G20=""),"",(F20-G20)/F20)
... F55: =IF(D55="","",D55/(1+Inicio!$B$13)) | G55: =IF(OR(F55="",E55=""),"",F55*(1-E55)) | H55: =IF(G55="","",G55*(1+Inicio!$B$13)) | I55: =IF(OR(F55="",G55=""),"",(F55-G55)/F55)
A60: 2) Evaluar margen real desde un precio neto que tú decidas ofrecer
A61: Cliente | B61: Canal | C61: SKU opcional | D61: PVP bruto pensado | E61: Precio neto ofrecido | F61: Precio bruto equivalente | G61: PVP neto calculado | H61: Margen frontal real | I61: Margen objetivo referencial | J61: Resultado
A62: Get It | B62: Conveniencia | C62: NUVA-BAR-CC-U-01 | D62: 1990 | E62: 1000 | F62: =IF(E62="","",E62*(1+Inicio!$B$13)) -> 1190 | G62: =IF(D62="","",D62/(1+Inicio!$B$13)) -> 1672.2689 | H62: =IF(OR(G62="",E62=""),"",(G62-E62)/G62) -> 0.40201005 | I62: 0.4 | J62: =IF(OR(H62="",I62=""),"",IF(H62>=I62,"Cumple","Bajo objetivo")) -> Cumple
A63: Jumbo | B63: Retail | C63: NUVA-BAR-BM-BX-04 | D63: 5990 | E63: 2800 | F63: =IF(E63="","",E63*(1+Inicio!$B$13)) -> 3332 | G63: =IF(D63="","",D63/(1+Inicio!$B$13)) -> 5033.6134 | H63: =IF(OR(G63="",E63=""),"",(G63-E63)/G63) -> 0.44373957 | I63: 0.45 | J63: =IF(OR(H63="",I63=""),"",IF(H63>=I63,"Cumple","Bajo objetivo")) -> Bajo objetivo
F64: =IF(E64="","",E64*(1+Inicio!$B$13)) | G64: =IF(D64="","",D64/(1+Inicio!$B$13)) | H64: =IF(OR(G64="",E64=""),"",(G64-E64)/G64) | J64: =IF(OR(H64="",I64=""),"",IF(H64>=I64,"Cumple","Bajo objetivo"))
F65: =IF(E65="","",E65*(1+Inicio!$B$13)) | G65: =IF(D65="","",D65/(1+Inicio!$B$13)) | H65: =IF(OR(G65="",E65=""),"",(G65-E65)/G65) | J65: =IF(OR(H65="",I65=""),"",IF(H65>=I65,"Cumple","Bajo objetivo"))
F66: =IF(E66="","",E66*(1+Inicio!$B$13)) | G66: =IF(D66="","",D66/(1+Inicio!$B$13)) | H66: =IF(OR(G66="",E66=""),"",(G66-E66)/G66) | J66: =IF(OR(H66="",I66=""),"",IF(H66>=I66,"Cumple","Bajo objetivo"))
F67: =IF(E67="","",E67*(1+Inicio!$B$13)) | G67: =IF(D67="","",D67/(1+Inicio!$B$13)) | H67: =IF(OR(G67="",E67=""),"",(G67-E67)/G67) | J67: =IF(OR(H67="",I67=""),"",IF(H67>=I67,"Cumple","Bajo objetivo"))
F68: =IF(E68="","",E68*(1+Inicio!$B$13)) | G68: =IF(D68="","",D68/(1+Inicio!$B$13)) | H68: =IF(OR(G68="",E68=""),"",(G68-E68)/G68) | J68: =IF(OR(H68="",I68=""),"",IF(H68>=I68,"Cumple","Bajo objetivo"))
F69: =IF(E69="","",E69*(1+Inicio!$B$13)) | G69: =IF(D69="","",D69/(1+Inicio!$B$13)) | H69: =IF(OR(G69="",E69=""),"",(G69-E69)/G69) | J69: =IF(OR(H69="",I69=""),"",IF(H69>=I69,"Cumple","Bajo objetivo"))
F70: =IF(E70="","",E70*(1+Inicio!$B$13)) | G70: =IF(D70="","",D70/(1+Inicio!$B$13)) | H70: =IF(OR(G70="",E70=""),"",(G70-E70)/G70) | J70: =IF(OR(H70="",I70=""),"",IF(H70>=I70,"Cumple","Bajo objetivo"))
F71: =IF(E71="","",E71*(1+Inicio!$B$13)) | G71: =IF(D71="","",D71/(1+Inicio!$B$13)) | H71: =IF(OR(G71="",E71=""),"",(G71-E71)/G71) | J71: =IF(OR(H71="",I71=""),"",IF(H71>=I71,"Cumple","Bajo objetivo"))
F72: =IF(E72="","",E72*(1+Inicio!$B$13)) | G72: =IF(D72="","",D72/(1+Inicio!$B$13)) | H72: =IF(OR(G72="",E72=""),"",(G72-E72)/G72) | J72: =IF(OR(H72="",I72=""),"",IF(H72>=I72,"Cumple","Bajo objetivo"))
F73: =IF(E73="","",E73*(1+Inicio!$B$13)) | G73: =IF(D73="","",D73/(1+Inicio!$B$13)) | H73: =IF(OR(G73="",E73=""),"",(G73-E73)/G73) | J73: =IF(OR(H73="",I73=""),"",IF(H73>=I73,"Cumple","Bajo objetivo"))
F74: =IF(E74="","",E74*(1+Inicio!$B$13)) | G74: =IF(D74="","",D74/(1+Inicio!$B$13)) | H74: =IF(OR(G74="",E74=""),"",(G74-E74)/G74) | J74: =IF(OR(H74="",I74=""),"",IF(H74>=I74,"Cumple","Bajo objetivo"))
F75: =IF(E75="","",E75*(1+Inicio!$B$13)) | G75: =IF(D75="","",D75/(1+Inicio!$B$13)) | H75: =IF(OR(G75="",E75=""),"",(G75-E75)/G75) | J75: =IF(OR(H75="",I75=""),"",IF(H75>=I75,"Cumple","Bajo objetivo"))
... F111: =IF(E111="","",E111*(1+Inicio!$B$13)) | G111: =IF(D111="","",D111/(1+Inicio!$B$13)) | H111: =IF(OR(G111="",E111=""),"",(G111-E111)/G111) | J111: =IF(OR(H111="",I111=""),"",IF(H111>=I111,"Cumple","Bajo objetivo"))

Sheet SellOut_Jumbo
A1: Fecha | B1: Cliente | C1: PDV | D1: SKU | E1: Descripción SKU | F1: Unidades sell-out | G1: Venta pública bruta | H1: Stock informado | I1: Fuente/archivo | J1: Observaciones | K1: Año | L1: Mes | M1: Día | N1: Periodo | O1: Barras equiv | P1: ⚙ Configuración
A2: 46200 | B2: Jumbo | C2: Jumbo La Reina | D2: NUVA-BAR-PB-U-01 | E2: =IFERROR(VLOOKUP(D2,Maestro_SKU!$A$2:$P$500,2,FALSE),"") -> Barra Peanut Boost unidad | F2: 2 | G2: 35940 | H2: 16 | I2: Ejemplo exportación Cencosud | K2: =IF($A2="","",YEAR($A2)) -> 2026 | L2: =IF($A2="","",MONTH($A2)) -> 6 | M2: =IF($A2="","",DAY($A2)) -> 27 | N2: =IF($A2="","",YEAR($A2)&"-"&TEXT(MONTH($A2),"00")) -> 2026-06 | O2: =IF(OR($D2="",$F2=""),"",$F2*IFERROR(VLOOKUP($D2,Maestro_SKU!$A$2:$P$500,12,FALSE),1)) -> 2
A3: 46209 | B3: Jumbo | C3: Jumbo La Reina | D3: NUVA-BAR-BM-BX-04 | E3: =IFERROR(VLOOKUP(D3,Maestro_SKU!$A$2:$P$500,2,FALSE),"") -> Estuche Berry Mix 4 unidades | F3: 12 | G3: 11980 | H3: 8 | I3: Ejemplo exportación Cencosud | K3: =IF($A3="","",YEAR($A3)) -> 2026 | L3: =IF($A3="","",MONTH($A3)) -> 7 | M3: =IF($A3="","",DAY($A3)) -> 6 | N3: =IF($A3="","",YEAR($A3)&"-"&TEXT(MONTH($A3),"00")) -> 2026-07 | O3: =IF(OR($D3="",$F3=""),"",$F3*IFERROR(VLOOKUP($D3,Maestro_SKU!$A$2:$P$500,12,FALSE),1)) -> 48
A4: 46201 | B4: Jumbo | C4: Jumbo Bilbao | D4: NUVA-BAR-PB-U-01 | E4: =IFERROR(VLOOKUP(D4,Maestro_SKU!$A$2:$P$500,2,FALSE),"") -> Barra Peanut Boost unidad | F4: 12 | G4: 35940 | H4: 32 | I4: Ejemplo exportación Cencosud | K4: =IF($A4="","",YEAR($A4)) -> 2026 | L4: =IF($A4="","",MONTH($A4)) -> 6 | M4: =IF($A4="","",DAY($A4)) -> 28 | N4: =IF($A4="","",YEAR($A4)&"-"&TEXT(MONTH($A4),"00")) -> 2026-06 | O4: =IF(OR($D4="",$F4=""),"",$F4*IFERROR(VLOOKUP($D4,Maestro_SKU!$A$2:$P$500,12,FALSE),1)) -> 12
A5: 46212 | B5: Jumbo | C5: Jumbo Bilbao | D5: NUVA-BAR-BM-BX-04 | E5: =IFERROR(VLOOKUP(D5,Maestro_SKU!$A$2:$P$500,2,FALSE),"") -> Estuche Berry Mix 4 unidades | F5: 2 | G5: 5990 | H5: 16 | I5: Ejemplo exportación Cencosud | K5: =IF($A5="","",YEAR($A5)) -> 2026 | L5: =IF($A5="","",MONTH($A5)) -> 7 | M5: =IF($A5="","",DAY($A5)) -> 9 | N5: =IF($A5="","",YEAR($A5)&"-"&TEXT(MONTH($A5),"00")) -> 2026-07 | O5: =IF(OR($D5="",$F5=""),"",$F5*IFERROR(VLOOKUP($D5,Maestro_SKU!$A$2:$P$500,12,FALSE),1)) -> 8
A6: 46202 | B6: Jumbo | C6: Jumbo Bilbao | D6: NUVA-BAR-CC-BX-04 | E6: =IFERROR(VLOOKUP(D6,Maestro_SKU!$A$2:$P$500,2,FALSE),"") -> Estuche Cacao Crispy 4 unidades | F6: 2 | G6: 17970 | H6: 8 | I6: Ejemplo exportación Cencosud | K6: =IF($A6="","",YEAR($A6)) -> 2026 | L6: =IF($A6="","",MONTH($A6)) -> 6 | M6: =IF($A6="","",DAY($A6)) -> 29 | N6: =IF($A6="","",YEAR($A6)&"-"&TEXT(MONTH($A6),"00")) -> 2026-06 | O6: =IF(OR($D6="",$F6=""),"",$F6*IFERROR(VLOOKUP($D6,Maestro_SKU!$A$2:$P$500,12,FALSE),1)) -> 8
A7: 46192 | B7: Jumbo | C7: Jumbo Kennedy | D7: NUVA-BAR-PB-U-01 | E7: =IFERROR(VLOOKUP(D7,Maestro_SKU!$A$2:$P$500,2,FALSE),"") -> Barra Peanut Boost unidad | F7: 2 | G7: 11980 | H7: 4 | I7: Ejemplo exportación Cencosud | K7: =IF($A7="","",YEAR($A7)) -> 2026 | L7: =IF($A7="","",MONTH($A7)) -> 6 | M7: =IF($A7="","",DAY($A7)) -> 19 | N7: =IF($A7="","",YEAR($A7)&"-"&TEXT(MONTH($A7),"00")) -> 2026-06 | O7: =IF(OR($D7="",$F7=""),"",$F7*IFERROR(VLOOKUP($D7,Maestro_SKU!$A$2:$P$500,12,FALSE),1)) -> 2
A8: 46203 | B8: Jumbo | C8: Jumbo Bilbao | D8: NUVA-BAR-PB-U-01 | E8: =IFERROR(VLOOKUP(D8,Maestro_SKU!$A$2:$P$500,2,FALSE),"") -> Barra Peanut Boost unidad | F8: 4 | G8: 23960 | H8: 32 | I8: Ejemplo exportación Cencosud | K8: =IF($A8="","",YEAR($A8)) -> 2026 | L8: =IF($A8="","",MONTH($A8)) -> 6 | M8: =IF($A8="","",DAY($A8)) -> 30 | N8: =IF($A8="","",YEAR($A8)&"-"&TEXT(MONTH($A8),"00")) -> 2026-06 | O8: =IF(OR($D8="",$F8=""),"",$F8*IFERROR(VLOOKUP($D8,Maestro_SKU!$A$2:$P$500,12,FALSE),1)) -> 4
A9: 46195 | B9: Jumbo | C9: Jumbo La Reina | D9: NUVA-BAR-PB-BX-04 | E9: =IFERROR(VLOOKUP(D9,Maestro_SKU!$A$2:$P$500,2,FALSE),"") -> Estuche Peanut Boost 4 unidades | F9: 8 | G9: 35940 | H9: 0 | I9: Ejemplo exportación Cencosud | K9: =IF($A9="","",YEAR($A9)) -> 2026 | L9: =IF($A9="","",MONTH($A9)) -> 6 | M9: =IF($A9="","",DAY($A9)) -> 22 | N9: =IF($A9="","",YEAR($A9)&"-"&TEXT(MONTH($A9),"00")) -> 2026-06 | O9: =IF(OR($D9="",$F9=""),"",$F9*IFERROR(VLOOKUP($D9,Maestro_SKU!$A$2:$P$500,12,FALSE),1)) -> 32
A10: 46208 | B10: Jumbo | C10: Jumbo Bilbao | D10: NUVA-BAR-BM-U-01 | E10: =IFERROR(VLOOKUP(D10,Maestro_SKU!$A$2:$P$500,2,FALSE),"") -> Barra Berry Mix unidad | F10: 2 | G10: 5990 | H10: 4 | I10: Ejemplo exportación Cencosud | K10: =IF($A10="","",YEAR($A10)) -> 2026 | L10: =IF($A10="","",MONTH($A10)) -> 7 | M10: =IF($A10="","",DAY($A10)) -> 5 | N10: =IF($A10="","",YEAR($A10)&"-"&TEXT(MONTH($A10),"00")) -> 2026-07 | O10: =IF(OR($D10="",$F10=""),"",$F10*IFERROR(VLOOKUP($D10,Maestro_SKU!$A$2:$P$500,12,FALSE),1)) -> 2
A11: 46209 | B11: Jumbo | C11: Jumbo La Reina | D11: NUVA-BAR-BM-BX-04 | E11: =IFERROR(VLOOKUP(D11,Maestro_SKU!$A$2:$P$500,2,FALSE),"") -> Estuche Berry Mix 4 unidades | F11: 2 | G11: 5990 | H11: 16 | I11: Ejemplo exportación Cencosud | K11: =IF($A11="","",YEAR($A11)) -> 2026 | L11: =IF($A11="","",MONTH($A11)) -> 7 | M11: =IF($A11="","",DAY($A11)) -> 6 | N11: =IF($A11="","",YEAR($A11)&"-"&TEXT(MONTH($A11),"00")) -> 2026-07 | O11: =IF(OR($D11="",$F11=""),"",$F11*IFERROR(VLOOKUP($D11,Maestro_SKU!$A$2:$P$500,12,FALSE),1)) -> 8
A12: 46189 | B12: Jumbo | C12: Jumbo La Reina | D12: NUVA-BAR-PB-U-01 | E12: =IFERROR(VLOOKUP(D12,Maestro_SKU!$A$2:$P$500,2,FALSE),"") -> Barra Peanut Boost unidad | F12: 12 | G12: 23960 | H12: 0 | I12: Ejemplo exportación Cencosud | K12: =IF($A12="","",YEAR($A12)) -> 2026 | L12: =IF($A12="","",MONTH($A12)) -> 6 | M12: =IF($A12="","",DAY($A12)) -> 16 | N12: =IF($A12="","",YEAR($A12)&"-"&TEXT(MONTH($A12),"00")) -> 2026-06 | O12: =IF(OR($D12="",$F12=""),"",$F12*IFERROR(VLOOKUP($D12,Maestro_SKU!$A$2:$P$500,12,FALSE),1)) -> 12
A13: 46195 | B13: Jumbo | C13: Jumbo Bilbao | D13: NUVA-BAR-BM-U-01 | E13: =IFERROR(VLOOKUP(D13,Maestro_SKU!$A$2:$P$500,2,FALSE),"") -> Barra Berry Mix unidad | F13: 15 | G13: 23960 | H13: 32 | I13: Ejemplo exportación Cencosud | K13: =IF($A13="","",YEAR($A13)) -> 2026 | L13: =IF($A13="","",MONTH($A13)) -> 6 | M13: =IF($A13="","",DAY($A13)) -> 22 | N13: =IF($A13="","",YEAR($A13)&"-"&TEXT(MONTH($A13),"00")) -> 2026-06 | O13: =IF(OR($D13="",$F13=""),"",$F13*IFERROR(VLOOKUP($D13,Maestro_SKU!$A$2:$P$500,12,FALSE),1)) -> 15
... A19: 46187 | B19: Jumbo | C19: Jumbo Kennedy | D19: NUVA-BAR-BM-U-01 | E19: =IFERROR(VLOOKUP(D19,Maestro_SKU!$A$2:$P$500,2,FALSE),"") -> Barra Berry Mix unidad | F19: 12 | G19: 17970 | H19: 32 | I19: Ejemplo exportación Cencosud | K19: =IF($A19="","",YEAR($A19)) -> 2026 | L19: =IF($A19="","",MONTH($A19)) -> 6 | M19: =IF($A19="","",DAY($A19)) -> 14 | N19: =IF($A19="","",YEAR($A19)&"-"&TEXT(MONTH($A19),"00")) -> 2026-06 | O19: =IF(OR($D19="",$F19=""),"",$F19*IFERROR(VLOOKUP($D19,Maestro_SKU!$A$2:$P$500,12,FALSE),1)) -> 12
E20: =IFERROR(VLOOKUP(D20,Maestro_SKU!$A$2:$P$500,2,FALSE),"") | K20: =IF($A20="","",YEAR($A20)) | L20: =IF($A20="","",MONTH($A20)) | M20: =IF($A20="","",DAY($A20)) | N20: =IF($A20="","",YEAR($A20)&"-"&TEXT(MONTH($A20),"00")) | O20: =IF(OR($D20="",$F20=""),"",$F20*IFERROR(VLOOKUP($D20,Maestro_SKU!$A$2:$P$500,12,FALSE),1))
E21: =IFERROR(VLOOKUP(D21,Maestro_SKU!$A$2:$P$500,2,FALSE),"") | K21: =IF($A21="","",YEAR($A21)) | L21: =IF($A21="","",MONTH($A21)) | M21: =IF($A21="","",DAY($A21)) | N21: =IF($A21="","",YEAR($A21)&"-"&TEXT(MONTH($A21),"00")) | O21: =IF(OR($D21="",$F21=""),"",$F21*IFERROR(VLOOKUP($D21,Maestro_SKU!$A$2:$P$500,12,FALSE),1))
E22: =IFERROR(VLOOKUP(D22,Maestro_SKU!$A$2:$P$500,2,FALSE),"") | K22: =IF($A22="","",YEAR($A22)) | L22: =IF($A22="","",MONTH($A22)) | M22: =IF($A22="","",DAY($A22)) | N22: =IF($A22="","",YEAR($A22)&"-"&TEXT(MONTH($A22),"00")) | O22: =IF(OR($D22="",$F22=""),"",$F22*IFERROR(VLOOKUP($D22,Maestro_SKU!$A$2:$P$500,12,FALSE),1))
E23: =IFERROR(VLOOKUP(D23,Maestro_SKU!$A$2:$P$500,2,FALSE),"") | K23: =IF($A23="","",YEAR($A23)) | L23: =IF($A23="","",MONTH($A23)) | M23: =IF($A23="","",DAY($A23)) | N23: =IF($A23="","",YEAR($A23)&"-"&TEXT(MONTH($A23),"00")) | O23: =IF(OR($D23="",$F23=""),"",$F23*IFERROR(VLOOKUP($D23,Maestro_SKU!$A$2:$P$500,12,FALSE),1))
E24: =IFERROR(VLOOKUP(D24,Maestro_SKU!$A$2:$P$500,2,FALSE),"") | K24: =IF($A24="","",YEAR($A24)) | L24: =IF($A24="","",MONTH($A24)) | M24: =IF($A24="","",DAY($A24)) | N24: =IF($A24="","",YEAR($A24)&"-"&TEXT(MONTH($A24),"00")) | O24: =IF(OR($D24="",$F24=""),"",$F24*IFERROR(VLOOKUP($D24,Maestro_SKU!$A$2:$P$500,12,FALSE),1))
E25: =IFERROR(VLOOKUP(D25,Maestro_SKU!$A$2:$P$500,2,FALSE),"") | K25: =IF($A25="","",YEAR($A25)) | L25: =IF($A25="","",MONTH($A25)) | M25: =IF($A25="","",DAY($A25)) | N25: =IF($A25="","",YEAR($A25)&"-"&TEXT(MONTH($A25),"00")) | O25: =IF(OR($D25="",$F25=""),"",$F25*IFERROR(VLOOKUP($D25,Maestro_SKU!$A$2:$P$500,12,FALSE),1))
E26: =IFERROR(VLOOKUP(D26,Maestro_SKU!$A$2:$P$500,2,FALSE),"") | K26: =IF($A26="","",YEAR($A26)) | L26: =IF($A26="","",MONTH($A26)) | M26: =IF($A26="","",DAY($A26)) | N26: =IF($A26="","",YEAR($A26)&"-"&TEXT(MONTH($A26),"00")) | O26: =IF(OR($D26="",$F26=""),"",$F26*IFERROR(VLOOKUP($D26,Maestro_SKU!$A$2:$P$500,12,FALSE),1))
E27: =IFERROR(VLOOKUP(D27,Maestro_SKU!$A$2:$P$500,2,FALSE),"") | K27: =IF($A27="","",YEAR($A27)) | L27: =IF($A27="","",MONTH($A27)) | M27: =IF($A27="","",DAY($A27)) | N27: =IF($A27="","",YEAR($A27)&"-"&TEXT(MONTH($A27),"00")) | O27: =IF(OR($D27="",$F27=""),"",$F27*IFERROR(VLOOKUP($D27,Maestro_SKU!$A$2:$P$500,12,FALSE),1))
E28: =IFERROR(VLOOKUP(D28,Maestro_SKU!$A$2:$P$500,2,FALSE),"") | K28: =IF($A28="","",YEAR($A28)) | L28: =IF($A28="","",MONTH($A28)) | M28: =IF($A28="","",DAY($A28)) | N28: =IF($A28="","",YEAR($A28)&"-"&TEXT(MONTH($A28),"00")) | O28: =IF(OR($D28="",$F28=""),"",$F28*IFERROR(VLOOKUP($D28,Maestro_SKU!$A$2:$P$500,12,FALSE),1))
E29: =IFERROR(VLOOKUP(D29,Maestro_SKU!$A$2:$P$500,2,FALSE),"") | K29: =IF($A29="","",YEAR($A29)) | L29: =IF($A29="","",MONTH($A29)) | M29: =IF($A29="","",DAY($A29)) | N29: =IF($A29="","",YEAR($A29)&"-"&TEXT(MONTH($A29),"00")) | O29: =IF(OR($D29="",$F29=""),"",$F29*IFERROR(VLOOKUP($D29,Maestro_SKU!$A$2:$P$500,12,FALSE),1))
E30: =IFERROR(VLOOKUP(D30,Maestro_SKU!$A$2:$P$500,2,FALSE),"") | K30: =IF($A30="","",YEAR($A30)) | L30: =IF($A30="","",MONTH($A30)) | M30: =IF($A30="","",DAY($A30)) | N30: =IF($A30="","",YEAR($A30)&"-"&TEXT(MONTH($A30),"00")) | O30: =IF(OR($D30="",$F30=""),"",$F30*IFERROR(VLOOKUP($D30,Maestro_SKU!$A$2:$P$500,12,FALSE),1))
E31: =IFERROR(VLOOKUP(D31,Maestro_SKU!$A$2:$P$500,2,FALSE),"") | K31: =IF($A31="","",YEAR($A31)) | L31: =IF($A31="","",MONTH($A31)) | M31: =IF($A31="","",DAY($A31)) | N31: =IF($A31="","",YEAR($A31)&"-"&TEXT(MONTH($A31),"00")) | O31: =IF(OR($D31="",$F31=""),"",$F31*IFERROR(VLOOKUP($D31,Maestro_SKU!$A$2:$P$500,12,FALSE),1))
... E800: =IFERROR(VLOOKUP(D800,Maestro_SKU!$A$2:$P$500,2,FALSE),"") | K800: =IF($A800="","",YEAR($A800)) | L800: =IF($A800="","",MONTH($A800)) | M800: =IF($A800="","",DAY($A800)) | N800: =IF($A800="","",YEAR($A800)&"-"&TEXT(MONTH($A800),"00")) | O800: =IF(OR($D800="",$F800=""),"",$F800*IFERROR(VLOOKUP($D800,Maestro_SKU!$A$2:$P$500,12,FALSE),1))

Sheet Stock_PDV
A1: PDV_ID | B1: Cliente | C1: Canal | D1: Punto de venta | E1: SKU | F1: Descripción SKU | G1: Stock unidades | H1: Barras equivalentes | I1: Fecha conteo | J1: Estado stock | K1: Observaciones | M1: ⚙ Configuración
A2: PDV-001 | B2: =IFERROR(VLOOKUP(A2,Clientes_PDV!$A$2:$J$250,2,FALSE),"") -> Jumbo | C2: =IFERROR(VLOOKUP(A2,Clientes_PDV!$A$2:$J$250,3,FALSE),"") -> Retail | D2: =IFERROR(VLOOKUP(A2,Clientes_PDV!$A$2:$J$250,4,FALSE),"") -> Jumbo Bilbao | E2: NUVA-BAR-BM-U-01 | F2: =IFERROR(VLOOKUP(E2,Maestro_SKU!$A$2:$P$500,2,FALSE),"") -> Barra Berry Mix unidad | G2: 5 | H2: =IF(OR(G2="",E2=""),"",G2*IFERROR(VLOOKUP(E2,Maestro_SKU!$A$2:$P$500,12,FALSE),1)) -> 5 | I2: 46201 | J2: =IF(A2="","",IF(H2<=Inicio!$B$16,"Crítico",IF(H2<=Inicio!$B$17,"Observar","OK"))) -> Crítico
A3: PDV-001 | B3: =IFERROR(VLOOKUP(A3,Clientes_PDV!$A$2:$J$250,2,FALSE),"") -> Jumbo | C3: =IFERROR(VLOOKUP(A3,Clientes_PDV!$A$2:$J$250,3,FALSE),"") -> Retail | D3: =IFERROR(VLOOKUP(A3,Clientes_PDV!$A$2:$J$250,4,FALSE),"") -> Jumbo Bilbao | E3: NUVA-BAR-PB-U-01 | F3: =IFERROR(VLOOKUP(E3,Maestro_SKU!$A$2:$P$500,2,FALSE),"") -> Barra Peanut Boost unidad | G3: 0 | H3: =IF(OR(G3="",E3=""),"",G3*IFERROR(VLOOKUP(E3,Maestro_SKU!$A$2:$P$500,12,FALSE),1)) -> 0 | I3: 46203 | J3: =IF(A3="","",IF(H3<=Inicio!$B$16,"Crítico",IF(H3<=Inicio!$B$17,"Observar","OK"))) -> Crítico
A4: PDV-001 | B4: =IFERROR(VLOOKUP(A4,Clientes_PDV!$A$2:$J$250,2,FALSE),"") -> Jumbo | C4: =IFERROR(VLOOKUP(A4,Clientes_PDV!$A$2:$J$250,3,FALSE),"") -> Retail | D4: =IFERROR(VLOOKUP(A4,Clientes_PDV!$A$2:$J$250,4,FALSE),"") -> Jumbo Bilbao | E4: NUVA-BAR-CC-U-01 | F4: =IFERROR(VLOOKUP(E4,Maestro_SKU!$A$2:$P$500,2,FALSE),"") -> Barra Cacao Crispy unidad | G4: 8 | H4: =IF(OR(G4="",E4=""),"",G4*IFERROR(VLOOKUP(E4,Maestro_SKU!$A$2:$P$500,12,FALSE),1)) -> 8 | I4: 46204 | J4: =IF(A4="","",IF(H4<=Inicio!$B$16,"Crítico",IF(H4<=Inicio!$B$17,"Observar","OK"))) -> Crítico
A5: PDV-001 | B5: =IFERROR(VLOOKUP(A5,Clientes_PDV!$A$2:$J$250,2,FALSE),"") -> Jumbo | C5: =IFERROR(VLOOKUP(A5,Clientes_PDV!$A$2:$J$250,3,FALSE),"") -> Retail | D5: =IFERROR(VLOOKUP(A5,Clientes_PDV!$A$2:$J$250,4,FALSE),"") -> Jumbo Bilbao | E5: NUVA-BAR-BM-BX-04 | F5: =IFERROR(VLOOKUP(E5,Maestro_SKU!$A$2:$P$500,2,FALSE),"") -> Estuche Berry Mix 4 unidades | G5: 5 | H5: =IF(OR(G5="",E5=""),"",G5*IFERROR(VLOOKUP(E5,Maestro_SKU!$A$2:$P$500,12,FALSE),1)) -> 20 | I5: 46208 | J5: =IF(A5="","",IF(H5<=Inicio!$B$16,"Crítico",IF(H5<=Inicio!$B$17,"Observar","OK"))) -> Observar
A6: PDV-002 | B6: =IFERROR(VLOOKUP(A6,Clientes_PDV!$A$2:$J$250,2,FALSE),"") -> Jumbo | C6: =IFERROR(VLOOKUP(A6,Clientes_PDV!$A$2:$J$250,3,FALSE),"") -> Retail | D6: =IFERROR(VLOOKUP(A6,Clientes_PDV!$A$2:$J$250,4,FALSE),"") -> Jumbo Kennedy | E6: NUVA-BAR-BM-U-01 | F6: =IFERROR(VLOOKUP(E6,Maestro_SKU!$A$2:$P$500,2,FALSE),"") -> Barra Berry Mix unidad | G6: 0 | H6: =IF(OR(G6="",E6=""),"",G6*IFERROR(VLOOKUP(E6,Maestro_SKU!$A$2:$P$500,12,FALSE),1)) -> 0 | I6: 46207 | J6: =IF(A6="","",IF(H6<=Inicio!$B$16,"Crítico",IF(H6<=Inicio!$B$17,"Observar","OK"))) -> Crítico
A7: PDV-003 | B7: =IFERROR(VLOOKUP(A7,Clientes_PDV!$A$2:$J$250,2,FALSE),"") -> Jumbo | C7: =IFERROR(VLOOKUP(A7,Clientes_PDV!$A$2:$J$250,3,FALSE),"") -> Retail | D7: =IFERROR(VLOOKUP(A7,Clientes_PDV!$A$2:$J$250,4,FALSE),"") -> Jumbo La Reina | E7: NUVA-BAR-PB-U-01 | F7: =IFERROR(VLOOKUP(E7,Maestro_SKU!$A$2:$P$500,2,FALSE),"") -> Barra Peanut Boost unidad | G7: 30 | H7: =IF(OR(G7="",E7=""),"",G7*IFERROR(VLOOKUP(E7,Maestro_SKU!$A$2:$P$500,12,FALSE),1)) -> 30 | I7: 46203 | J7: =IF(A7="","",IF(H7<=Inicio!$B$16,"Crítico",IF(H7<=Inicio!$B$17,"Observar","OK"))) -> OK
A8: PDV-003 | B8: =IFERROR(VLOOKUP(A8,Clientes_PDV!$A$2:$J$250,2,FALSE),"") -> Jumbo | C8: =IFERROR(VLOOKUP(A8,Clientes_PDV!$A$2:$J$250,3,FALSE),"") -> Retail | D8: =IFERROR(VLOOKUP(A8,Clientes_PDV!$A$2:$J$250,4,FALSE),"") -> Jumbo La Reina | E8: NUVA-BAR-CC-U-01 | F8: =IFERROR(VLOOKUP(E8,Maestro_SKU!$A$2:$P$500,2,FALSE),"") -> Barra Cacao Crispy unidad | G8: 5 | H8: =IF(OR(G8="",E8=""),"",G8*IFERROR(VLOOKUP(E8,Maestro_SKU!$A$2:$P$500,12,FALSE),1)) -> 5 | I8: 46207 | J8: =IF(A8="","",IF(H8<=Inicio!$B$16,"Crítico",IF(H8<=Inicio!$B$17,"Observar","OK"))) -> Crítico
A9: PDV-003 | B9: =IFERROR(VLOOKUP(A9,Clientes_PDV!$A$2:$J$250,2,FALSE),"") -> Jumbo | C9: =IFERROR(VLOOKUP(A9,Clientes_PDV!$A$2:$J$250,3,FALSE),"") -> Retail | D9: =IFERROR(VLOOKUP(A9,Clientes_PDV!$A$2:$J$250,4,FALSE),"") -> Jumbo La Reina | E9: NUVA-BAR-CC-BX-04 | F9: =IFERROR(VLOOKUP(E9,Maestro_SKU!$A$2:$P$500,2,FALSE),"") -> Estuche Cacao Crispy 4 unidades | G9: 30 | H9: =IF(OR(G9="",E9=""),"",G9*IFERROR(VLOOKUP(E9,Maestro_SKU!$A$2:$P$500,12,FALSE),1)) -> 120 | I9: 46210 | J9: =IF(A9="","",IF(H9<=Inicio!$B$16,"Crítico",IF(H9<=Inicio!$B$17,"Observar","OK"))) -> OK
A10: PDV-004 | B10: =IFERROR(VLOOKUP(A10,Clientes_PDV!$A$2:$J$250,2,FALSE),"") -> Get It | C10: =IFERROR(VLOOKUP(A10,Clientes_PDV!$A$2:$J$250,3,FALSE),"") -> Conveniencia | D10: =IFERROR(VLOOKUP(A10,Clientes_PDV!$A$2:$J$250,4,FALSE),"") -> Get It Apoquindo | E10: NUVA-BAR-PB-U-01 | F10: =IFERROR(VLOOKUP(E10,Maestro_SKU!$A$2:$P$500,2,FALSE),"") -> Barra Peanut Boost unidad | G10: 8 | H10: =IF(OR(G10="",E10=""),"",G10*IFERROR(VLOOKUP(E10,Maestro_SKU!$A$2:$P$500,12,FALSE),1)) -> 8 | I10: 46205 | J10: =IF(A10="","",IF(H10<=Inicio!$B$16,"Crítico",IF(H10<=Inicio!$B$17,"Observar","OK"))) -> Crítico
A11: PDV-005 | B11: =IFERROR(VLOOKUP(A11,Clientes_PDV!$A$2:$J$250,2,FALSE),"") -> Get It | C11: =IFERROR(VLOOKUP(A11,Clientes_PDV!$A$2:$J$250,3,FALSE),"") -> Conveniencia | D11: =IFERROR(VLOOKUP(A11,Clientes_PDV!$A$2:$J$250,4,FALSE),"") -> Get It Vitacura | E11: NUVA-BAR-PB-U-01 | F11: =IFERROR(VLOOKUP(E11,Maestro_SKU!$A$2:$P$500,2,FALSE),"") -> Barra Peanut Boost unidad | G11: 20 | H11: =IF(OR(G11="",E11=""),"",G11*IFERROR(VLOOKUP(E11,Maestro_SKU!$A$2:$P$500,12,FALSE),1)) -> 20 | I11: 46201 | J11: =IF(A11="","",IF(H11<=Inicio!$B$16,"Crítico",IF(H11<=Inicio!$B$17,"Observar","OK"))) -> Observar
A12: PDV-005 | B12: =IFERROR(VLOOKUP(A12,Clientes_PDV!$A$2:$J$250,2,FALSE),"") -> Get It | C12: =IFERROR(VLOOKUP(A12,Clientes_PDV!$A$2:$J$250,3,FALSE),"") -> Conveniencia | D12: =IFERROR(VLOOKUP(A12,Clientes_PDV!$A$2:$J$250,4,FALSE),"") -> Get It Vitacura | E12: NUVA-BAR-BM-BX-04 | F12: =IFERROR(VLOOKUP(E12,Maestro_SKU!$A$2:$P$500,2,FALSE),"") -> Estuche Berry Mix 4 unidades | G12: 45 | H12: =IF(OR(G12="",E12=""),"",G12*IFERROR(VLOOKUP(E12,Maestro_SKU!$A$2:$P$500,12,FALSE),1)) -> 180 | I12: 46212 | J12: =IF(A12="","",IF(H12<=Inicio!$B$16,"Crítico",IF(H12<=Inicio!$B$17,"Observar","OK"))) -> OK
A13: PDV-006 | B13: =IFERROR(VLOOKUP(A13,Clientes_PDV!$A$2:$J$250,2,FALSE),"") -> Aldea Nativa | C13: =IFERROR(VLOOKUP(A13,Clientes_PDV!$A$2:$J$250,3,FALSE),"") -> Especializadas | D13: =IFERROR(VLOOKUP(A13,Clientes_PDV!$A$2:$J$250,4,FALSE),"") -> Aldea Nativa Providencia | E13: NUVA-BAR-PB-U-01 | F13: =IFERROR(VLOOKUP(E13,Maestro_SKU!$A$2:$P$500,2,FALSE),"") -> Barra Peanut Boost unidad | G13: 3 | H13: =IF(OR(G13="",E13=""),"",G13*IFERROR(VLOOKUP(E13,Maestro_SKU!$A$2:$P$500,12,FALSE),1)) -> 3 | I13: 46198 | J13: =IF(A13="","",IF(H13<=Inicio!$B$16,"Crítico",IF(H13<=Inicio!$B$17,"Observar","OK"))) -> Crítico
... A29: PDV-012 | B29: =IFERROR(VLOOKUP(A29,Clientes_PDV!$A$2:$J$250,2,FALSE),"") -> Mundo del Vino | C29: =IFERROR(VLOOKUP(A29,Clientes_PDV!$A$2:$J$250,3,FALSE),"") -> Especializadas | D29: =IFERROR(VLOOKUP(A29,Clientes_PDV!$A$2:$J$250,4,FALSE),"") -> Mundo del Vino Escuela Militar | E29: NUVA-BAR-CC-BX-04 | F29: =IFERROR(VLOOKUP(E29,Maestro_SKU!$A$2:$P$500,2,FALSE),"") -> Estuche Cacao Crispy 4 unidades | G29: 5 | H29: =IF(OR(G29="",E29=""),"",G29*IFERROR(VLOOKUP(E29,Maestro_SKU!$A$2:$P$500,12,FALSE),1)) -> 20 | I29: 46198 | J29: =IF(A29="","",IF(H29<=Inicio!$B$16,"Crítico",IF(H29<=Inicio!$B$17,"Observar","OK"))) -> Observar
B30: =IFERROR(VLOOKUP(A30,Clientes_PDV!$A$2:$J$250,2,FALSE),"") | C30: =IFERROR(VLOOKUP(A30,Clientes_PDV!$A$2:$J$250,3,FALSE),"") | D30: =IFERROR(VLOOKUP(A30,Clientes_PDV!$A$2:$J$250,4,FALSE),"") | F30: =IFERROR(VLOOKUP(E30,Maestro_SKU!$A$2:$P$500,2,FALSE),"") | H30: =IF(OR(G30="",E30=""),"",G30*IFERROR(VLOOKUP(E30,Maestro_SKU!$A$2:$P$500,12,FALSE),1)) | J30: =IF(A30="","",IF(H30<=Inicio!$B$16,"Crítico",IF(H30<=Inicio!$B$17,"Observar","OK")))
B31: =IFERROR(VLOOKUP(A31,Clientes_PDV!$A$2:$J$250,2,FALSE),"") | C31: =IFERROR(VLOOKUP(A31,Clientes_PDV!$A$2:$J$250,3,FALSE),"") | D31: =IFERROR(VLOOKUP(A31,Clientes_PDV!$A$2:$J$250,4,FALSE),"") | F31: =IFERROR(VLOOKUP(E31,Maestro_SKU!$A$2:$P$500,2,FALSE),"") | H31: =IF(OR(G31="",E31=""),"",G31*IFERROR(VLOOKUP(E31,Maestro_SKU!$A$2:$P$500,12,FALSE),1)) | J31: =IF(A31="","",IF(H31<=Inicio!$B$16,"Crítico",IF(H31<=Inicio!$B$17,"Observar","OK")))
B32: =IFERROR(VLOOKUP(A32,Clientes_PDV!$A$2:$J$250,2,FALSE),"") | C32: =IFERROR(VLOOKUP(A32,Clientes_PDV!$A$2:$J$250,3,FALSE),"") | D32: =IFERROR(VLOOKUP(A32,Clientes_PDV!$A$2:$J$250,4,FALSE),"") | F32: =IFERROR(VLOOKUP(E32,Maestro_SKU!$A$2:$P$500,2,FALSE),"") | H32: =IF(OR(G32="",E32=""),"",G32*IFERROR(VLOOKUP(E32,Maestro_SKU!$A$2:$P$500,12,FALSE),1)) | J32: =IF(A32="","",IF(H32<=Inicio!$B$16,"Crítico",IF(H32<=Inicio!$B$17,"Observar","OK")))
B33: =IFERROR(VLOOKUP(A33,Clientes_PDV!$A$2:$J$250,2,FALSE),"") | C33: =IFERROR(VLOOKUP(A33,Clientes_PDV!$A$2:$J$250,3,FALSE),"") | D33: =IFERROR(VLOOKUP(A33,Clientes_PDV!$A$2:$J$250,4,FALSE),"") | F33: =IFERROR(VLOOKUP(E33,Maestro_SKU!$A$2:$P$500,2,FALSE),"") | H33: =IF(OR(G33="",E33=""),"",G33*IFERROR(VLOOKUP(E33,Maestro_SKU!$A$2:$P$500,12,FALSE),1)) | J33: =IF(A33="","",IF(H33<=Inicio!$B$16,"Crítico",IF(H33<=Inicio!$B$17,"Observar","OK")))
B34: =IFERROR(VLOOKUP(A34,Clientes_PDV!$A$2:$J$250,2,FALSE),"") | C34: =IFERROR(VLOOKUP(A34,Clientes_PDV!$A$2:$J$250,3,FALSE),"") | D34: =IFERROR(VLOOKUP(A34,Clientes_PDV!$A$2:$J$250,4,FALSE),"") | F34: =IFERROR(VLOOKUP(E34,Maestro_SKU!$A$2:$P$500,2,FALSE),"") | H34: =IF(OR(G34="",E34=""),"",G34*IFERROR(VLOOKUP(E34,Maestro_SKU!$A$2:$P$500,12,FALSE),1)) | J34: =IF(A34="","",IF(H34<=Inicio!$B$16,"Crítico",IF(H34<=Inicio!$B$17,"Observar","OK")))
B35: =IFERROR(VLOOKUP(A35,Clientes_PDV!$A$2:$J$250,2,FALSE),"") | C35: =IFERROR(VLOOKUP(A35,Clientes_PDV!$A$2:$J$250,3,FALSE),"") | D35: =IFERROR(VLOOKUP(A35,Clientes_PDV!$A$2:$J$250,4,FALSE),"") | F35: =IFERROR(VLOOKUP(E35,Maestro_SKU!$A$2:$P$500,2,FALSE),"") | H35: =IF(OR(G35="",E35=""),"",G35*IFERROR(VLOOKUP(E35,Maestro_SKU!$A$2:$P$500,12,FALSE),1)) | J35: =IF(A35="","",IF(H35<=Inicio!$B$16,"Crítico",IF(H35<=Inicio!$B$17,"Observar","OK")))
B36: =IFERROR(VLOOKUP(A36,Clientes_PDV!$A$2:$J$250,2,FALSE),"") | C36: =IFERROR(VLOOKUP(A36,Clientes_PDV!$A$2:$J$250,3,FALSE),"") | D36: =IFERROR(VLOOKUP(A36,Clientes_PDV!$A$2:$J$250,4,FALSE),"") | F36: =IFERROR(VLOOKUP(E36,Maestro_SKU!$A$2:$P$500,2,FALSE),"") | H36: =IF(OR(G36="",E36=""),"",G36*IFERROR(VLOOKUP(E36,Maestro_SKU!$A$2:$P$500,12,FALSE),1)) | J36: =IF(A36="","",IF(H36<=Inicio!$B$16,"Crítico",IF(H36<=Inicio!$B$17,"Observar","OK")))
B37: =IFERROR(VLOOKUP(A37,Clientes_PDV!$A$2:$J$250,2,FALSE),"") | C37: =IFERROR(VLOOKUP(A37,Clientes_PDV!$A$2:$J$250,3,FALSE),"") | D37: =IFERROR(VLOOKUP(A37,Clientes_PDV!$A$2:$J$250,4,FALSE),"") | F37: =IFERROR(VLOOKUP(E37,Maestro_SKU!$A$2:$P$500,2,FALSE),"") | H37: =IF(OR(G37="",E37=""),"",G37*IFERROR(VLOOKUP(E37,Maestro_SKU!$A$2:$P$500,12,FALSE),1)) | J37: =IF(A37="","",IF(H37<=Inicio!$B$16,"Crítico",IF(H37<=Inicio!$B$17,"Observar","OK")))
B38: =IFERROR(VLOOKUP(A38,Clientes_PDV!$A$2:$J$250,2,FALSE),"") | C38: =IFERROR(VLOOKUP(A38,Clientes_PDV!$A$2:$J$250,3,FALSE),"") | D38: =IFERROR(VLOOKUP(A38,Clientes_PDV!$A$2:$J$250,4,FALSE),"") | F38: =IFERROR(VLOOKUP(E38,Maestro_SKU!$A$2:$P$500,2,FALSE),"") | H38: =IF(OR(G38="",E38=""),"",G38*IFERROR(VLOOKUP(E38,Maestro_SKU!$A$2:$P$500,12,FALSE),1)) | J38: =IF(A38="","",IF(H38<=Inicio!$B$16,"Crítico",IF(H38<=Inicio!$B$17,"Observar","OK")))
B39: =IFERROR(VLOOKUP(A39,Clientes_PDV!$A$2:$J$250,2,FALSE),"") | C39: =IFERROR(VLOOKUP(A39,Clientes_PDV!$A$2:$J$250,3,FALSE),"") | D39: =IFERROR(VLOOKUP(A39,Clientes_PDV!$A$2:$J$250,4,FALSE),"") | F39: =IFERROR(VLOOKUP(E39,Maestro_SKU!$A$2:$P$500,2,FALSE),"") | H39: =IF(OR(G39="",E39=""),"",G39*IFERROR(VLOOKUP(E39,Maestro_SKU!$A$2:$P$500,12,FALSE),1)) | J39: =IF(A39="","",IF(H39<=Inicio!$B$16,"Crítico",IF(H39<=Inicio!$B$17,"Observar","OK")))
B40: =IFERROR(VLOOKUP(A40,Clientes_PDV!$A$2:$J$250,2,FALSE),"") | C40: =IFERROR(VLOOKUP(A40,Clientes_PDV!$A$2:$J$250,3,FALSE),"") | D40: =IFERROR(VLOOKUP(A40,Clientes_PDV!$A$2:$J$250,4,FALSE),"") | F40: =IFERROR(VLOOKUP(E40,Maestro_SKU!$A$2:$P$500,2,FALSE),"") | H40: =IF(OR(G40="",E40=""),"",G40*IFERROR(VLOOKUP(E40,Maestro_SKU!$A$2:$P$500,12,FALSE),1)) | J40: =IF(A40="","",IF(H40<=Inicio!$B$16,"Crítico",IF(H40<=Inicio!$B$17,"Observar","OK")))
B41: =IFERROR(VLOOKUP(A41,Clientes_PDV!$A$2:$J$250,2,FALSE),"") | C41: =IFERROR(VLOOKUP(A41,Clientes_PDV!$A$2:$J$250,3,FALSE),"") | D41: =IFERROR(VLOOKUP(A41,Clientes_PDV!$A$2:$J$250,4,FALSE),"") | F41: =IFERROR(VLOOKUP(E41,Maestro_SKU!$A$2:$P$500,2,FALSE),"") | H41: =IF(OR(G41="",E41=""),"",G41*IFERROR(VLOOKUP(E41,Maestro_SKU!$A$2:$P$500,12,FALSE),1)) | J41: =IF(A41="","",IF(H41<=Inicio!$B$16,"Crítico",IF(H41<=Inicio!$B$17,"Observar","OK")))
... B800: =IFERROR(VLOOKUP(A800,Clientes_PDV!$A$2:$J$250,2,FALSE),"") | C800: =IFERROR(VLOOKUP(A800,Clientes_PDV!$A$2:$J$250,3,FALSE),"") | D800: =IFERROR(VLOOKUP(A800,Clientes_PDV!$A$2:$J$250,4,FALSE),"") | F800: =IFERROR(VLOOKUP(E800,Maestro_SKU!$A$2:$P$500,2,FALSE),"") | H800: =IF(OR(G800="",E800=""),"",G800*IFERROR(VLOOKUP(E800,Maestro_SKU!$A$2:$P$500,12,FALSE),1)) | J800: =IF(A800="","",IF(H800<=Inicio!$B$16,"Crítico",IF(H800<=Inicio!$B$17,"Observar","OK")))

Sheet Maestro_SKU
A1: SKU | B1: Descripción SKU | C1: Cód. barra | D1: Marca | E1: Categoría | F1: Código Categoría | G1: Subcategoría | H1: Sabor | I1: Código sabor | J1: Nivel logístico | K1: Formato | L1: Unidades por pack | M1: Mercado | N1: UM venta | O1: Estado | P1: Observación
A2: NUVA-BAR-BM-U-01 | B2: Barra Berry Mix unidad | D2: NUVA | E2: Barritas | F2: BAR | G2: Funcionales | H2: Berry Mix | I2: BM | J2: Unitario | K2: U | L2: 1 | M2: CL | N2: un | O2: Activo | P2: SKU de venta unitario
A3: NUVA-BAR-PB-U-01 | B3: Barra Peanut Boost unidad | D3: NUVA | E3: Barritas | F3: BAR | G3: Funcionales | H3: Peanut Boost | I3: PB | J3: Unitario | K3: U | L3: 1 | M3: CL | N3: un | O3: Activo | P3: SKU de venta unitario
A4: NUVA-BAR-CC-U-01 | B4: Barra Cacao Crispy unidad | D4: NUVA | E4: Barritas | F4: BAR | G4: Funcionales | H4: Cacao Crispy | I4: CC | J4: Unitario | K4: U | L4: 1 | M4: CL | N4: un | O4: Activo | P4: SKU de venta unitario
A5: NUVA-BAR-BM-BX-04 | B5: Estuche Berry Mix 4 unidades | D5: NUVA | E5: Barritas | F5: BAR | G5: Funcionales | H5: Berry Mix | I5: BM | J5: Estuche | K5: BX | L5: 4 | M5: CL | N5: un | O5: Activo | P5: SKU pack comercial
A6: NUVA-BAR-PB-BX-04 | B6: Estuche Peanut Boost 4 unidades | D6: NUVA | E6: Barritas | F6: BAR | G6: Funcionales | H6: Peanut Boost | I6: PB | J6: Estuche | K6: BX | L6: 4 | M6: CL | N6: un | O6: Activo | P6: SKU pack comercial
A7: NUVA-BAR-CC-BX-04 | B7: Estuche Cacao Crispy 4 unidades | D7: NUVA | E7: Barritas | F7: BAR | G7: Funcionales | H7: Cacao Crispy | I7: CC | J7: Estuche | K7: BX | L7: 4 | M7: CL | N7: un | O7: Activo | P7: SKU pack comercial
A8: NUVA-BAR-BM-CS-24 | B8: Caja master Berry Mix 24 unidades | D8: NUVA | E8: Barritas | F8: BAR | G8: Funcionales | H8: Berry Mix | I8: BM | J8: Caja master | K8: CS | L8: 24 | M8: CL | N8: un | O8: Activo | P8: SKU pack comercial
A9: NUVA-BAR-PB-CS-24 | B9: Caja master Peanut Boost 24 unidades | D9: NUVA | E9: Barritas | F9: BAR | G9: Funcionales | H9: Peanut Boost | I9: PB | J9: Caja master | K9: CS | L9: 24 | M9: CL | N9: un | O9: Activo | P9: SKU pack comercial
A10: NUVA-BAR-CC-CS-24 | B10: Caja master Cacao Crispy 24 unidades | D10: NUVA | E10: Barritas | F10: BAR | G10: Funcionales | H10: Cacao Crispy | I10: CC | J10: Caja master | K10: CS | L10: 24 | M10: CL | N10: un | O10: Activo | P10: SKU pack comercial
A11: NUVA-BAR-BM-CS-60 | B11: Caja master Berry Mix 15x4 unidades | D11: NUVA | E11: Barritas | F11: BAR | G11: Funcionales | H11: Berry Mix | I11: BM | J11: Caja master | K11: CS | L11: 60 | M11: CL | N11: un | O11: Activo | P11: SKU logístico
A12: NUVA-BAR-PB-CS-60 | B12: Caja master Peanut Boost 15x4 unidades | D12: NUVA | E12: Barritas | F12: BAR | G12: Funcionales | H12: Peanut Boost | I12: PB | J12: Caja master | K12: CS | L12: 60 | M12: CL | N12: un | O12: Activo | P12: SKU logístico
A13: NUVA-BAR-CC-CS-60 | B13: Caja master Cacao Crispy 15x4 unidades | D13: NUVA | E13: Barritas | F13: BAR | G13: Funcionales | H13: Cacao Crispy | I13: CC | J13: Caja master | K13: CS | L13: 60 | M13: CL | N13: un | O13: Activo | P13: SKU logístico
