Workbook
Name DatosExternos_1: datos_ventas!$A$1:$D$7

Sheet ESTADO_RESULTADOS
A1: ESTADO DE RESULTADOS - Piloto Ago-Oct 2026 (NUVA OXI)
A2: Alimentado por el sell-in del CRM (Datos > Actualizar todo). Gastos = supuestos editables (azul).
A4: Ingresos por ventas (neto) | B4: =SUM(datos_ventas!A:A) -> 358656
A5: (-) Costo de ventas | B5: =-SUM(datos_ventas!B:B) -> -70250
A6: =Margen bruto -> #NAME? | B6: =B4+B5 -> 288406
A7: % Margen bruto | B7: =IFERROR(B6/B4,0) -> 0.80412986
A9: Gastos operativos
A10: (-) Marketing / POP | B10: -120000
A11: (-) Logistica / despacho | B11: -45000
A12: (-) Comercial / ruta | B12: -80000
A13: (-) Administracion | B13: -30000
A14: =Total gastos operativos -> #NAME? | B14: =SUM(B10:B13) -> -275000
A16: =RESULTADO OPERATIVO -> #NAME? | B16: =B6+B14 -> 13406
A17: % sobre ventas | B17: =IFERROR(B16/B4,0) -> 0.037378435

Sheet BALANCE
A1: BALANCE SIMPLIFICADO (NUVA OXI)
A3: ACTIVOS
A4: Caja (flujo cobrado) | B4: =FLUJO_CAJA!B9 -> -288527
A5: Cuentas por cobrar (CxC) | B5: =SUMIF(datos_ventas!D:D,"Emitida",datos_ventas!A:A) -> 301933
A6: Inventario valorizado (supuesto) | B6: 150000
A7: =Total ACTIVOS -> #NAME? | B7: =SUM(B4:B6) -> 163406
A9: PASIVOS + PATRIMONIO
A10: Proveedores por pagar (supuesto) | B10: 60000
A11: Patrimonio / resultado acumulado | B11: =B7-B10 -> 103406
A12: =Total PASIVO+PATRIMONIO -> #NAME? | B12: =B10+B11 -> 163406

Sheet FLUJO_CAJA
A1: FLUJO DE CAJA - Piloto (NUVA OXI)
A4: Cobros (facturas Pagadas) | B4: =SUMIF(datos_ventas!D:D,"Pagada",datos_ventas!A:A) -> 56723
A5: (+) CxC por cobrar (Emitidas) | B5: =SUMIF(datos_ventas!D:D,"Emitida",datos_ventas!A:A) -> 301933
A6: (-) Pago costo de ventas | B6: =-SUM(datos_ventas!B:B) -> -70250
A7: (-) Pago gastos operativos | B7: =ESTADO_RESULTADOS!B14 -> -275000
A8: =Flujo neto (si se cobra todo) -> #NAME? | B8: =B4+B5+B6+B7 -> 13406
A9: =Flujo neto de CAJA HOY (solo Pagadas) -> #NAME? | B9: =B4+B6+B7 -> -288527
A11: Nota: Jumbo paga a 30 dias; HoReCa contado. CxC Emitida = caja en riesgo hasta cobro.

Sheet datos_ventas
A1: Venta_Neta | B1: Costo_Total | C1: Margen | D1: Estado_Factura
A2: 19160 | B2: 3000 | C2: 16160 | D2: Pagada
A3: 12773 | B3: 2000 | C3: 10773 | D3: Pagada
A4: 14370 | B4: 2250 | C4: 12120 | D4: Emitida
A5: 24790 | B5: 5000 | C5: 19790 | D5: Pagada
A6: 39664 | B6: 8000 | C6: 31664 | D6: Emitida
A7: 247899 | B7: 50000 | C7: 197899 | D7: Emitida
