Workbook

Sheet PANEL
A1: 🎯 NUVA OXI — Panel Operacional 2026 | Filtrar col A=Segmento · B=Cadena · C=SubCanal
A2: 💡 AZUL = ingresar manualmente | NEGRO = fórmula automática | VERDE = jalado desde otra hoja | Metas en fila 5 — editarlas aquí directamente
A3: Ventas Neto ($) | D3: Margen Aprox. ($) | G3: Uds Vendidas | J3: CxC Pendiente ($) | M3: PDVs Activos | P3: Stock Alertas 🔴
A4: =IFERROR(SUM(VENTAS!J4:J10000),0) -> 221514 | D4: =IFERROR(SUM(VENTAS!L4:L10000),0) -> 200514 | G4: =IFERROR(SUM(VENTAS!G4:G10000),0) -> 92 | J4: =IFERROR(SUMIF(VENTAS!M4:M10000,"Emitida",VENTAS!J4:J10000),0) -> 301933 | M4: =IFERROR(COUNTIF(PANEL!G5:G200,"Activo"),0) -> 22 | P4: =IFERROR(COUNTIF(INVENTARIO!K4:K100,"🔴 Sin stock"),0) -> 1
A5: ⚠️ Jumbo: reunión pendiente confirmación definitiva. Costo $250 NO validado — margen aprox. NO real. Sell-out disponible solo para Jumbo (EDI Cencosud).
A6: IDENTIFICACIÓN PDV | H6: METAS MENSUALES (uds) ← EDITAR AQUÍ DIRECTAMENTE | T6: RESULTADOS ACUMULADOS | W6: OPERACIONAL
A7: Segmento | B7: Cadena | C7: Sub Canal | D7: ID | E7: Nombre PDV | F7: Resp | G7: Estado | H7: Meta Ene | I7: Meta Feb | J7: Meta Mar | K7: Meta Abr | L7: Meta May | M7: Meta Jun | N7: Meta Jul | O7: Meta Ago | P7: Meta Sep | Q7: Meta Oct | R7: Meta Nov | S7: Meta Dic | T7: Vtas Acum. ($) | U7: Uds Vendidas | V7: Semáforo Meta | W7: Últ. Visita | X7: Estado Stock
A8: Retail Moderno | B8: Cencosud | C8: Jumbo | D8: J001 | E8: Jumbo Parque Arauco | F8: JI | G8: Activo | H8: 0 | I8: 0 | J8: 0 | K8: 0 | L8: 0 | M8: 0 | N8: 0 | O8: 0 | P8: 0 | Q8: 10 | R8: 12 | S8: 14 | T8: =IFERROR(SUMIF(VENTAS!D4:D10000,D8,VENTAS!J4:J10000),0) -> 0 | U8: =IFERROR(SUMIF(VENTAS!D4:D10000,D8,VENTAS!G4:G10000),0) -> 0 | V8: =IF(SUM(H8:S8)=0,"—",IF(U8/SUM(H8:S8)>=1,"✅ Logrado",IF(U8/SUM(H8:S8)>=0.6,"🟡 En curso","🔴 Bajo"))) -> 🔴 Bajo | X8: =IFERROR(VLOOKUP(D8,INVENTARIO!C4:K27,9,0),"Sin dato") -> 🔴 Sin stock
A9: Retail Moderno | B9: Cencosud | C9: Jumbo | D9: J002 | E9: Jumbo Costanera Center | F9: JI | G9: Activo | H9: 0 | I9: 0 | J9: 0 | K9: 0 | L9: 0 | M9: 0 | N9: 0 | O9: 0 | P9: 0 | Q9: 10 | R9: 12 | S9: 14 | T9: =IFERROR(SUMIF(VENTAS!D4:D10000,D9,VENTAS!J4:J10000),0) -> 0 | U9: =IFERROR(SUMIF(VENTAS!D4:D10000,D9,VENTAS!G4:G10000),0) -> 0 | V9: =IF(SUM(H9:S9)=0,"—",IF(U9/SUM(H9:S9)>=1,"✅ Logrado",IF(U9/SUM(H9:S9)>=0.6,"🟡 En curso","🔴 Bajo"))) -> 🔴 Bajo | X9: =IFERROR(VLOOKUP(D9,INVENTARIO!C4:K27,9,0),"Sin dato") -> ✅ OK
A10: Retail Moderno | B10: Cencosud | C10: Jumbo | D10: J003 | E10: Jumbo Mall Vespucio | F10: Ana | G10: Activo | H10: 0 | I10: 0 | J10: 0 | K10: 0 | L10: 0 | M10: 0 | N10: 0 | O10: 0 | P10: 0 | Q10: 8 | R10: 10 | S10: 12 | T10: =IFERROR(SUMIF(VENTAS!D4:D10000,D10,VENTAS!J4:J10000),0) -> 0 | U10: =IFERROR(SUMIF(VENTAS!D4:D10000,D10,VENTAS!G4:G10000),0) -> 0 | V10: =IF(SUM(H10:S10)=0,"—",IF(U10/SUM(H10:S10)>=1,"✅ Logrado",IF(U10/SUM(H10:S10)>=0.6,"🟡 En curso","🔴 Bajo"))) -> 🔴 Bajo | X10: =IFERROR(VLOOKUP(D10,INVENTARIO!C4:K27,9,0),"Sin dato") -> ✅ OK
A11: Retail Moderno | B11: Cencosud | C11: Jumbo | D11: J004 | E11: Jumbo Maipú | F11: JI | G11: Activo | H11: 0 | I11: 0 | J11: 0 | K11: 0 | L11: 0 | M11: 0 | N11: 0 | O11: 0 | P11: 0 | Q11: 8 | R11: 10 | S11: 12 | T11: =IFERROR(SUMIF(VENTAS!D4:D10000,D11,VENTAS!J4:J10000),0) -> 0 | U11: =IFERROR(SUMIF(VENTAS!D4:D10000,D11,VENTAS!G4:G10000),0) -> 0 | V11: =IF(SUM(H11:S11)=0,"—",IF(U11/SUM(H11:S11)>=1,"✅ Logrado",IF(U11/SUM(H11:S11)>=0.6,"🟡 En curso","🔴 Bajo"))) -> 🔴 Bajo | X11: =IFERROR(VLOOKUP(D11,INVENTARIO!C4:K27,9,0),"Sin dato") -> ✅ OK
A12: Retail Moderno | B12: Cencosud | C12: Jumbo | D12: J005 | E12: Jumbo La Florida | F12: JI | G12: Activo | H12: 0 | I12: 0 | J12: 0 | K12: 0 | L12: 0 | M12: 0 | N12: 0 | O12: 0 | P12: 0 | Q12: 6 | R12: 8 | S12: 10 | T12: =IFERROR(SUMIF(VENTAS!D4:D10000,D12,VENTAS!J4:J10000),0) -> 0 | U12: =IFERROR(SUMIF(VENTAS!D4:D10000,D12,VENTAS!G4:G10000),0) -> 0 | V12: =IF(SUM(H12:S12)=0,"—",IF(U12/SUM(H12:S12)>=1,"✅ Logrado",IF(U12/SUM(H12:S12)>=0.6,"🟡 En curso","🔴 Bajo"))) -> 🔴 Bajo | X12: =IFERROR(VLOOKUP(D12,INVENTARIO!C4:K27,9,0),"Sin dato") -> ✅ OK
A13: Retail Moderno | B13: Cencosud | C13: Jumbo | D13: J006 | E13: Jumbo Quilicura | F13: JI | G13: Activo | H13: 0 | I13: 0 | J13: 0 | K13: 0 | L13: 0 | M13: 0 | N13: 0 | O13: 0 | P13: 0 | Q13: 6 | R13: 8 | S13: 10 | T13: =IFERROR(SUMIF(VENTAS!D4:D10000,D13,VENTAS!J4:J10000),0) -> 0 | U13: =IFERROR(SUMIF(VENTAS!D4:D10000,D13,VENTAS!G4:G10000),0) -> 0 | V13: =IF(SUM(H13:S13)=0,"—",IF(U13/SUM(H13:S13)>=1,"✅ Logrado",IF(U13/SUM(H13:S13)>=0.6,"🟡 En curso","🔴 Bajo"))) -> 🔴 Bajo | X13: =IFERROR(VLOOKUP(D13,INVENTARIO!C4:K27,9,0),"Sin dato") -> ✅ OK
A14: Retail Moderno | B14: Cencosud | C14: Jumbo | D14: J007 | E14: Jumbo Puente Alto | F14: JI | G14: Activo | H14: 0 | I14: 0 | J14: 0 | K14: 0 | L14: 0 | M14: 0 | N14: 0 | O14: 0 | P14: 0 | Q14: 6 | R14: 8 | S14: 10 | T14: =IFERROR(SUMIF(VENTAS!D4:D10000,D14,VENTAS!J4:J10000),0) -> 0 | U14: =IFERROR(SUMIF(VENTAS!D4:D10000,D14,VENTAS!G4:G10000),0) -> 0 | V14: =IF(SUM(H14:S14)=0,"—",IF(U14/SUM(H14:S14)>=1,"✅ Logrado",IF(U14/SUM(H14:S14)>=0.6,"🟡 En curso","🔴 Bajo"))) -> 🔴 Bajo | X14: =IFERROR(VLOOKUP(D14,INVENTARIO!C4:K27,9,0),"Sin dato") -> ✅ OK
A15: Retail Moderno | B15: Cencosud | C15: Jumbo | D15: J008 | E15: Jumbo San Bernardo | F15: Ana | G15: Activo | H15: 0 | I15: 0 | J15: 0 | K15: 0 | L15: 0 | M15: 0 | N15: 0 | O15: 0 | P15: 0 | Q15: 6 | R15: 8 | S15: 10 | T15: =IFERROR(SUMIF(VENTAS!D4:D10000,D15,VENTAS!J4:J10000),0) -> 0 | U15: =IFERROR(SUMIF(VENTAS!D4:D10000,D15,VENTAS!G4:G10000),0) -> 0 | V15: =IF(SUM(H15:S15)=0,"—",IF(U15/SUM(H15:S15)>=1,"✅ Logrado",IF(U15/SUM(H15:S15)>=0.6,"🟡 En curso","🔴 Bajo"))) -> 🔴 Bajo | X15: =IFERROR(VLOOKUP(D15,INVENTARIO!C4:K27,9,0),"Sin dato") -> ✅ OK
A16: Retail Moderno | B16: Cencosud | C16: Jumbo | D16: J009 | E16: Jumbo Ñuñoa | F16: Ana | G16: Activo | H16: 0 | I16: 0 | J16: 0 | K16: 0 | L16: 0 | M16: 0 | N16: 0 | O16: 0 | P16: 0 | Q16: 6 | R16: 8 | S16: 10 | T16: =IFERROR(SUMIF(VENTAS!D4:D10000,D16,VENTAS!J4:J10000),0) -> 0 | U16: =IFERROR(SUMIF(VENTAS!D4:D10000,D16,VENTAS!G4:G10000),0) -> 0 | V16: =IF(SUM(H16:S16)=0,"—",IF(U16/SUM(H16:S16)>=1,"✅ Logrado",IF(U16/SUM(H16:S16)>=0.6,"🟡 En curso","🔴 Bajo"))) -> 🔴 Bajo | X16: =IFERROR(VLOOKUP(D16,INVENTARIO!C4:K27,9,0),"Sin dato") -> ✅ OK
A17: Retail Moderno | B17: Cencosud | C17: Jumbo | D17: J010 | E17: Jumbo Macul | F17: JI | G17: Activo | H17: 0 | I17: 0 | J17: 0 | K17: 0 | L17: 0 | M17: 0 | N17: 0 | O17: 0 | P17: 0 | Q17: 5 | R17: 7 | S17: 9 | T17: =IFERROR(SUMIF(VENTAS!D4:D10000,D17,VENTAS!J4:J10000),0) -> 0 | U17: =IFERROR(SUMIF(VENTAS!D4:D10000,D17,VENTAS!G4:G10000),0) -> 0 | V17: =IF(SUM(H17:S17)=0,"—",IF(U17/SUM(H17:S17)>=1,"✅ Logrado",IF(U17/SUM(H17:S17)>=0.6,"🟡 En curso","🔴 Bajo"))) -> 🔴 Bajo | X17: =IFERROR(VLOOKUP(D17,INVENTARIO!C4:K27,9,0),"Sin dato") -> ✅ OK | Z17: estado podria tener tambien mas opciones, como perdido o stand by
A18: Retail Moderno | B18: Cencosud | C18: Jumbo | D18: J011 | E18: Jumbo Independencia | F18: JI | G18: Activo | H18: 0 | I18: 0 | J18: 0 | K18: 0 | L18: 0 | M18: 0 | N18: 0 | O18: 0 | P18: 0 | Q18: 5 | R18: 7 | S18: 9 | T18: =IFERROR(SUMIF(VENTAS!D4:D10000,D18,VENTAS!J4:J10000),0) -> 0 | U18: =IFERROR(SUMIF(VENTAS!D4:D10000,D18,VENTAS!G4:G10000),0) -> 0 | V18: =IF(SUM(H18:S18)=0,"—",IF(U18/SUM(H18:S18)>=1,"✅ Logrado",IF(U18/SUM(H18:S18)>=0.6,"🟡 En curso","🔴 Bajo"))) -> 🔴 Bajo | X18: =IFERROR(VLOOKUP(D18,INVENTARIO!C4:K27,9,0),"Sin dato") -> ✅ OK | Z18: mencionar que estamos a 06.07.26 y que cuando modifico algo los formatos no me permiten copiar pegar formato.
A19: Retail Moderno | B19: Cencosud | C19: Jumbo | D19: J012 | E19: Jumbo Las Rejas | F19: Ana | G19: Activo | H19: 0 | I19: 0 | J19: 0 | K19: 0 | L19: 0 | M19: 0 | N19: 0 | O19: 0 | P19: 0 | Q19: 5 | R19: 7 | S19: 9 | T19: =IFERROR(SUMIF(VENTAS!D4:D10000,D19,VENTAS!J4:J10000),0) -> 0 | U19: =IFERROR(SUMIF(VENTAS!D4:D10000,D19,VENTAS!G4:G10000),0) -> 0 | V19: =IF(SUM(H19:S19)=0,"—",IF(U19/SUM(H19:S19)>=1,"✅ Logrado",IF(U19/SUM(H19:S19)>=0.6,"🟡 En curso","🔴 Bajo"))) -> 🔴 Bajo | X19: =IFERROR(VLOOKUP(D19,INVENTARIO!C4:K27,9,0),"Sin dato") -> ✅ OK
A20: Retail Moderno | B20: Cencosud | C20: Jumbo | D20: J013 | E20: Jumbo Renca | F20: JI | G20: Activo | H20: 0 | I20: 0 | J20: 0 | K20: 0 | L20: 0 | M20: 0 | N20: 0 | O20: 0 | P20: 0 | Q20: 5 | R20: 7 | S20: 9 | T20: =IFERROR(SUMIF(VENTAS!D4:D10000,D20,VENTAS!J4:J10000),0) -> 0 | U20: =IFERROR(SUMIF(VENTAS!D4:D10000,D20,VENTAS!G4:G10000),0) -> 0 | V20: =IF(SUM(H20:S20)=0,"—",IF(U20/SUM(H20:S20)>=1,"✅ Logrado",IF(U20/SUM(H20:S20)>=0.6,"🟡 En curso","🔴 Bajo"))) -> 🔴 Bajo | X20: =IFERROR(VLOOKUP(D20,INVENTARIO!C4:K27,9,0),"Sin dato") -> ✅ OK
A21: Retail Moderno | B21: Cencosud | C21: Jumbo | D21: J014 | E21: Jumbo Peñalolén | F21: Ana | G21: Activo | H21: 0 | I21: 0 | J21: 0 | K21: 0 | L21: 0 | M21: 0 | N21: 0 | O21: 0 | P21: 0 | Q21: 5 | R21: 7 | S21: 9 | T21: =IFERROR(SUMIF(VENTAS!D4:D10000,D21,VENTAS!J4:J10000),0) -> 0 | U21: =IFERROR(SUMIF(VENTAS!D4:D10000,D21,VENTAS!G4:G10000),0) -> 0 | V21: =IF(SUM(H21:S21)=0,"—",IF(U21/SUM(H21:S21)>=1,"✅ Logrado",IF(U21/SUM(H21:S21)>=0.6,"🟡 En curso","🔴 Bajo"))) -> 🔴 Bajo | X21: =IFERROR(VLOOKUP(D21,INVENTARIO!C4:K27,9,0),"Sin dato") -> ✅ OK
A22: Retail Moderno | B22: Cencosud | C22: Jumbo | D22: J015 | E22: Jumbo Pudahuel | F22: JI | G22: Activo | H22: 0 | I22: 0 | J22: 0 | K22: 0 | L22: 0 | M22: 0 | N22: 0 | O22: 0 | P22: 0 | Q22: 5 | R22: 7 | S22: 9 | T22: =IFERROR(SUMIF(VENTAS!D4:D10000,D22,VENTAS!J4:J10000),0) -> 0 | U22: =IFERROR(SUMIF(VENTAS!D4:D10000,D22,VENTAS!G4:G10000),0) -> 0 | V22: =IF(SUM(H22:S22)=0,"—",IF(U22/SUM(H22:S22)>=1,"✅ Logrado",IF(U22/SUM(H22:S22)>=0.6,"🟡 En curso","🔴 Bajo"))) -> 🔴 Bajo | X22: =IFERROR(VLOOKUP(D22,INVENTARIO!C4:K27,9,0),"Sin dato") -> ✅ OK
A23: Canal Especializado | B23: Dellanatura | C23: Dellanatura | D23: D001 | E23: Dellanatura Las Condes | F23: JI | G23: Activo | H23: 0 | I23: 0 | J23: 0 | K23: 0 | L23: 0 | M23: 0 | N23: 0 | O23: 10 | P23: 10 | Q23: 11 | R23: 12 | S23: 13 | T23: =IFERROR(SUMIF(VENTAS!D4:D10000,D23,VENTAS!J4:J10000),0) -> 0 | U23: =IFERROR(SUMIF(VENTAS!D4:D10000,D23,VENTAS!G4:G10000),0) -> 0 | V23: =IF(SUM(H23:S23)=0,"—",IF(U23/SUM(H23:S23)>=1,"✅ Logrado",IF(U23/SUM(H23:S23)>=0.6,"🟡 En curso","🔴 Bajo"))) -> 🔴 Bajo | X23: =IFERROR(VLOOKUP(D23,INVENTARIO!C4:K27,9,0),"Sin dato") -> ✅ OK
A24: Canal Especializado | B24: Dellanatura | C24: Dellanatura | D24: D002 | E24: Dellanatura Providencia | F24: Ana | G24: Activo | H24: 0 | I24: 0 | J24: 0 | K24: 0 | L24: 0 | M24: 0 | N24: 0 | O24: 9 | P24: 9 | Q24: 10 | R24: 11 | S24: 12 | T24: =IFERROR(SUMIF(VENTAS!D4:D10000,D24,VENTAS!J4:J10000),0) -> 0 | U24: =IFERROR(SUMIF(VENTAS!D4:D10000,D24,VENTAS!G4:G10000),0) -> 0 | V24: =IF(SUM(H24:S24)=0,"—",IF(U24/SUM(H24:S24)>=1,"✅ Logrado",IF(U24/SUM(H24:S24)>=0.6,"🟡 En curso","🔴 Bajo"))) -> 🔴 Bajo | X24: =IFERROR(VLOOKUP(D24,INVENTARIO!C4:K27,9,0),"Sin dato") -> ✅ OK
A25: Canal Especializado | B25: Central Orgánica | C25: Central Orgánica | D25: CO01 | E25: Central Orgánica Ñuñoa | F25: Ana | G25: Activo | H25: 0 | I25: 0 | J25: 0 | K25: 0 | L25: 0 | M25: 0 | N25: 0 | O25: 8 | P25: 8 | Q25: 9 | R25: 10 | S25: 11 | T25: =IFERROR(SUMIF(VENTAS!D4:D10000,D25,VENTAS!J4:J10000),0) -> 0 | U25: =IFERROR(SUMIF(VENTAS!D4:D10000,D25,VENTAS!G4:G10000),0) -> 0 | V25: =IF(SUM(H25:S25)=0,"—",IF(U25/SUM(H25:S25)>=1,"✅ Logrado",IF(U25/SUM(H25:S25)>=0.6,"🟡 En curso","🔴 Bajo"))) -> 🔴 Bajo | X25: =IFERROR(VLOOKUP(D25,INVENTARIO!C4:K27,9,0),"Sin dato") -> ✅ OK
A26: Canal Especializado | B26: All Nutrition | C26: All Nutrition | D26: AN01 | E26: All Nutrition Vitacura | F26: JI | G26: Activo | H26: 0 | I26: 0 | J26: 0 | K26: 0 | L26: 0 | M26: 0 | N26: 0 | O26: 11 | P26: 11 | Q26: 12 | R26: 13 | S26: 14 | T26: =IFERROR(SUMIF(VENTAS!D4:D10000,D26,VENTAS!J4:J10000),0) -> 0 | U26: =IFERROR(SUMIF(VENTAS!D4:D10000,D26,VENTAS!G4:G10000),0) -> 0 | V26: =IF(SUM(H26:S26)=0,"—",IF(U26/SUM(H26:S26)>=1,"✅ Logrado",IF(U26/SUM(H26:S26)>=0.6,"🟡 En curso","🔴 Bajo"))) -> 🔴 Bajo | X26: =IFERROR(VLOOKUP(D26,INVENTARIO!C4:K27,9,0),"Sin dato") -> ✅ OK
A27: Canal Conveniencia | B27: Fork | C27: Fork | D27: F001 | E27: Fork Apoquindo | F27: JI | G27: Activo | H27: 0 | I27: 0 | J27: 0 | K27: 0 | L27: 0 | M27: 0 | N27: 0 | O27: 12 | P27: 14 | Q27: 16 | R27: 18 | S27: 20 | T27: =IFERROR(SUMIF(VENTAS!D4:D10000,D27,VENTAS!J4:J10000),0) -> 0 | U27: =IFERROR(SUMIF(VENTAS!D4:D10000,D27,VENTAS!G4:G10000),0) -> 0 | V27: =IF(SUM(H27:S27)=0,"—",IF(U27/SUM(H27:S27)>=1,"✅ Logrado",IF(U27/SUM(H27:S27)>=0.6,"🟡 En curso","🔴 Bajo"))) -> 🔴 Bajo | X27: =IFERROR(VLOOKUP(D27,INVENTARIO!C4:K27,9,0),"Sin dato") -> ✅ OK
A28: Canal Conveniencia | B28: Fork | C28: Fork | D28: F002 | E28: Fork El Bosque | F28: Ana | G28: Activo | H28: 0 | I28: 0 | J28: 0 | K28: 0 | L28: 0 | M28: 0 | N28: 0 | O28: 10 | P28: 12 | Q28: 14 | R28: 16 | S28: 18 | T28: =IFERROR(SUMIF(VENTAS!D4:D10000,D28,VENTAS!J4:J10000),0) -> 0 | U28: =IFERROR(SUMIF(VENTAS!D4:D10000,D28,VENTAS!G4:G10000),0) -> 0 | V28: =IF(SUM(H28:S28)=0,"—",IF(U28/SUM(H28:S28)>=1,"✅ Logrado",IF(U28/SUM(H28:S28)>=0.6,"🟡 En curso","🔴 Bajo"))) -> 🔴 Bajo | X28: =IFERROR(VLOOKUP(D28,INVENTARIO!C4:K27,9,0),"Sin dato") -> ✅ OK
A29: Canal Turístico | B29: Pirque CDV | C29: Pirque CDV | D29: P001 | E29: Pirque Centro del Vino | F29: JI | G29: Activo | H29: 0 | I29: 0 | J29: 0 | K29: 0 | L29: 0 | M29: 0 | N29: 0 | O29: 5 | P29: 5 | Q29: 4 | R29: 4 | S29: 5 | T29: =IFERROR(SUMIF(VENTAS!D4:D10000,D29,VENTAS!J4:J10000),0) -> 0 | U29: =IFERROR(SUMIF(VENTAS!D4:D10000,D29,VENTAS!G4:G10000),0) -> 0 | V29: =IF(SUM(H29:S29)=0,"—",IF(U29/SUM(H29:S29)>=1,"✅ Logrado",IF(U29/SUM(H29:S29)>=0.6,"🟡 En curso","🔴 Bajo"))) -> 🔴 Bajo | X29: =IFERROR(VLOOKUP(D29,INVENTARIO!C4:K27,9,0),"Sin dato") -> ✅ OK
A30: HoReCa | B30: Ritz-Carlton | C30: Ritz-Carlton | D30: H001 | E30: Ritz-Carlton Santiago | F30: JI | G30: Prospecto | H30: 0 | I30: 0 | J30: 0 | K30: 0 | L30: 0 | M30: 0 | N30: 0 | O30: 0 | P30: 0 | Q30: 8 | R30: 10 | S30: 12 | T30: =IFERROR(SUMIF(VENTAS!D4:D10000,D30,VENTAS!J4:J10000),0) -> 0 | U30: =IFERROR(SUMIF(VENTAS!D4:D10000,D30,VENTAS!G4:G10000),0) -> 0 | V30: =IF(SUM(H30:S30)=0,"—",IF(U30/SUM(H30:S30)>=1,"✅ Logrado",IF(U30/SUM(H30:S30)>=0.6,"🟡 En curso","🔴 Bajo"))) -> 🔴 Bajo | X30: =IFERROR(VLOOKUP(D30,INVENTARIO!C4:K27,9,0),"Sin dato") -> ✅ OK | Z30: cambiar segmentacion
A31: TOTAL PERÍODO | T31: =SUBTOTAL(9,T8:T30) -> 0 | U31: =SUBTOTAL(9,U8:U30) -> 0
A33: ➕ AGREGAR PDV: insertar fila en esta tabla, completar cols A-G y metas H-S. Las fórmulas T,U,V,X se copian solos. ⚠️ Las celdas de meta en 0 aparecen grises = canal inactivo ese mes (editar si cambia la fecha de entrada).

Sheet CONFIG
A1: ⚙️ CONFIG — Parámetros del Modelo 2026 | Solo editar celdas AZUL
A3: ▸ Parámetros Globales
A4: IVA Chile | B4: 0.19 | C4: Tasa IVA aplicada al PVP para calcular precio neto
A5: PVP Unitaria (c/IVA) | B5: 1900 | C5: Precio consumidor barra 40g
A6: PVP Estuche x4 (c/IVA) | B6: 5900 | C6: Precio consumidor estuche 4 barras
A7: Costo Unit. Neto ($) | B7: 250 | C7: ⚠️ SUPUESTO — reemplazar con costo real urgente
A8: Año operación | B8: 2026 | C8: Año del modelo
A9: ⚠️ MARGEN NO REAL: Costo $250 implica margen bruto ~84% sobre PVP neto ($1.597). Inverosímil para alimentos. Actualizar celda B7 con costo real.
A11: ▸ SKUs (6 códigos activos — 3 sabores × 2 formatos)
A12: Código | B12: Descripción | C12: Sabor | D12: Formato | E12: PVP c/IVA | F12: PVP Neto
A13: SKU-CAC-U | B13: Barra Cacao 40g | C13: Cacao | D13: Unitaria | E13: 1900 | F13: =ROUND(E13/(1+CONFIG!$B$4),0) -> 1597 | H13: voy a cambiar los sku posteriormente y tambien existira un terper precio para la barra unitaria y estuche de 4, unitaria aun nose el valor pero estuch puede ser que este a 6490 y que aveces trabajemos con descuentos de aprox 20-30% durante 30% del año
A14: SKU-MAN-U | B14: Barra Maní 40g | C14: Maní | D14: Unitaria | E14: 1900 | F14: =ROUND(E14/(1+CONFIG!$B$4),0) -> 1597
A15: SKU-FRU-U | B15: Barra Frutal 40g | C15: Frutal | D15: Unitaria | E15: 1900 | F15: =ROUND(E15/(1+CONFIG!$B$4),0) -> 1597
A16: SKU-CAC-4 | B16: Estuche Cacao x4 | C16: Cacao | D16: Estuche x4 | E16: 5900 | F16: =ROUND(E16/(1+CONFIG!$B$4),0) -> 4958
A17: SKU-MAN-4 | B17: Estuche Maní x4 | C17: Maní | D17: Estuche x4 | E17: 5900 | F17: =ROUND(E17/(1+CONFIG!$B$4),0) -> 4958
A18: SKU-FRU-4 | B18: Estuche Frutal x4 | C18: Frutal | D18: Estuche x4 | E18: 5900 | F18: =ROUND(E18/(1+CONFIG!$B$4),0) -> 4958

Sheet VENTAS
A1: 📋 VENTAS | Agregar fila con Tab en última fila — fórmulas se copian solas | 2026
A2: 💡 CÓMO USAR: Tab en la última fila de la tabla genera nueva fila automáticamente. Ingresar: Fecha, Segmento, Cadena, ID_PDV, SKU, Sabor, Uds_Vendidas, PVP, Factura, Plazo, Resp.
A3: # | B3: Fecha | C3: Segmento | D3: Cadena | E3: ID_PDV | F3: Nombre_PDV | G3: Uds Vendidas | H3: Uds Sell-out | I3: PVP c/IVA ($) | J3: Venta Neta ($) | K3: Costo Total ($) | L3: Margen ($) | M3: Estado Factura | N3: Plazo (días) | O3: Fecha Vencim. | P3: Resp
A4: 1 | B4: 05/01/2026 | C4: Canal Especializado | D4: Dellanatura | E4: D001 | F4: Dellanatura Las Condes | G4: 12 | H4: 10 | I4: 1900 | J4: =ROUND(G4*I4/(1+CONFIG!$B$4),0) -> 19160 | K4: =G4*CONFIG!$B$7 -> 3000 | L4: =J4-K4 -> 16160 | M4: Pagada | N4: 30 | O4: =IFERROR(DATEVALUE(B4)+N4,"") -> 46057 | P4: Ana Barra
A5: 2 | B5: 06/01/2026 | C5: Canal Especializado | D5: Dellanatura | E5: D002 | F5: Dellanatura Providencia | G5: 8 | H5: 6 | I5: 1900 | J5: =ROUND(G5*I5/(1+CONFIG!$B$4),0) -> 12773 | K5: =G5*CONFIG!$B$7 -> 2000 | L5: =J5-K5 -> 10773 | M5: Pagada | N5: 30 | O5: =IFERROR(DATEVALUE(B5)+N5,"") -> 46058 | P5: Ana Barra | R5: si pongo vencida en el estado de factura, las acciones en la data estan alineadas? Asegurar que todo este correctamente alineado.
A6: 3 | B6: 07/01/2026 | C6: Canal Especializado | D6: All Nutrition | E6: AN01 | F6: All Nutrition Vitacura | G6: 9 | I6: 1900 | J6: =ROUND(G6*I6/(1+CONFIG!$B$4),0) -> 14370 | K6: =G6*CONFIG!$B$7 -> 2250 | L6: =J6-K6 -> 12120 | M6: Emitida | N6: 30 | O6: =IFERROR(DATEVALUE(B6)+N6,"") -> 46059 | P6: José Ignacio
A7: 4 | B7: 09/01/2026 | C7: Canal Turístico | D7: Pirque CDV | E7: P001 | F7: Pirque Centro del Vino | G7: 5 | H7: 4 | I7: 5900 | J7: =ROUND(G7*I7/(1+CONFIG!$B$4),0) -> 24790 | K7: =G7*CONFIG!$B$7 -> 1250 | L7: =J7-K7 -> 23540 | M7: Pagada | N7: 30 | O7: =IFERROR(DATEVALUE(B7)+N7,"") -> 46061 | P7: José Ignacio
A8: 5 | B8: 12/01/2026 | C8: HoReCa | D8: Ritz-Carlton | E8: H001 | F8: Ritz-Carlton Santiago | G8: 8 | H8: 8 | I8: 5900 | J8: =ROUND(G8*I8/(1+CONFIG!$B$4),0) -> 39664 | K8: =G8*CONFIG!$B$7 -> 2000 | L8: =J8-K8 -> 37664 | M8: Emitida | N8: 30 | O8: =IFERROR(DATEVALUE(B8)+N8,"") -> 46064 | P8: José Ignacio
A9: 6 | B9: 46179 | C9: Retail Moderno | D9: Cencosud | E9: J001 | F9: Jumbo Parque Arauco | G9: 50 | H9: 5 | I9: 5900 | J9: =ROUND(G9*I9/(1+CONFIG!$B$4),0) -> 247899 | K9: =G9*CONFIG!$B$7 -> 12500 | L9: =J9-K9 -> 235399 | M9: Emitida | N9: 30 | O9: =IFERROR(DATEVALUE(B9)+N9,"")
A10: TOTAL (SUBTOTAL — se recalcula al filtrar) | J10: =SUBTOTAL(9,J4:J10000) -> 110757 | K10: =SUBTOTAL(9,K4:K10000) -> 10500 | L10: =SUBTOTAL(9,L4:L10000) -> 100257
A13: : Arreglar fecha, no me deja copiar y pegar el formato de fecha para que luego se calcule la fecha de vencimiento.
B14: y hacer 2 vistas de venta.. Una como la actual y otra que pueda hacer seguimiento de la gestion completa por ejemplo con cencosud, OC, Facturacion, status pago etc.

Sheet INVENTARIO
A1: 📦 INVENTARIO | Stock por PDV · Rotación · Alertas de reposición
A2: 🔴 CONCENTRACIÓN: Jumbo absorbe ~60% del stock. Rotación <50% por 3 semanas = riesgo de retiro de góndola. Stock disponible se descuenta automáticamente desde VENTAS.
A3: Segmento | B3: Cadena | C3: ID_PDV | D3: Nombre_PDV | E3: Resp | F3: Stock Inicial | G3: Vendido Acum. | H3: Stock Disp. | I3: Stock Mínimo | J3: Rotación (so/si) | K3: Alerta
A4: Retail Moderno | B4: Cencosud | C4: J001 | D4: Jumbo Parque Arauco | E4: JI | F4: 50 | G4: =IFERROR(SUMIF(VENTAS!E4:E10000,C4,VENTAS!G4:G10000),0) -> 50 | H4: =F4-G4 -> 0 | I4: 15 | J4: =IF(G4=0,"Sin dato",IFERROR(SUMIF(VENTAS!E4:E10000,C4,VENTAS!H4:H10000)/G4,0)) -> 0.1 | K4: =IF(H4<=0,"🔴 Sin stock",IF(H4<=I4,"🟡 Stock bajo","✅ OK")) -> 🔴 Sin stock | N4: la rotacion parece que esta mal calculada
A5: Retail Moderno | B5: Cencosud | C5: J002 | D5: Jumbo Costanera Center | E5: JI | F5: 50 | G5: =IFERROR(SUMIF(VENTAS!E4:E10000,C5,VENTAS!G4:G10000),0) -> 0 | H5: =F5-G5 -> 50 | I5: 15 | J5: =IF(G5=0,"Sin dato",IFERROR(SUMIF(VENTAS!E4:E10000,C5,VENTAS!H4:H10000)/G5,0)) -> Sin dato | K5: =IF(H5<=0,"🔴 Sin stock",IF(H5<=I5,"🟡 Stock bajo","✅ OK")) -> ✅ OK
A6: Retail Moderno | B6: Cencosud | C6: J003 | D6: Jumbo Mall Vespucio | E6: Ana | F6: 40 | G6: =IFERROR(SUMIF(VENTAS!E4:E10000,C6,VENTAS!G4:G10000),0) -> 0 | H6: =F6-G6 -> 40 | I6: 12 | J6: =IF(G6=0,"Sin dato",IFERROR(SUMIF(VENTAS!E4:E10000,C6,VENTAS!H4:H10000)/G6,0)) -> Sin dato | K6: =IF(H6<=0,"🔴 Sin stock",IF(H6<=I6,"🟡 Stock bajo","✅ OK")) -> ✅ OK
A7: Retail Moderno | B7: Cencosud | C7: J004 | D7: Jumbo Maipú | E7: JI | F7: 40 | G7: =IFERROR(SUMIF(VENTAS!E4:E10000,C7,VENTAS!G4:G10000),0) -> 0 | H7: =F7-G7 -> 40 | I7: 12 | J7: =IF(G7=0,"Sin dato",IFERROR(SUMIF(VENTAS!E4:E10000,C7,VENTAS!H4:H10000)/G7,0)) -> Sin dato | K7: =IF(H7<=0,"🔴 Sin stock",IF(H7<=I7,"🟡 Stock bajo","✅ OK")) -> ✅ OK
A8: Retail Moderno | B8: Cencosud | C8: J005 | D8: Jumbo La Florida | E8: JI | F8: 35 | G8: =IFERROR(SUMIF(VENTAS!E4:E10000,C8,VENTAS!G4:G10000),0) -> 0 | H8: =F8-G8 -> 35 | I8: 10 | J8: =IF(G8=0,"Sin dato",IFERROR(SUMIF(VENTAS!E4:E10000,C8,VENTAS!H4:H10000)/G8,0)) -> Sin dato | K8: =IF(H8<=0,"🔴 Sin stock",IF(H8<=I8,"🟡 Stock bajo","✅ OK")) -> ✅ OK
A9: Retail Moderno | B9: Cencosud | C9: J006 | D9: Jumbo Quilicura | E9: JI | F9: 35 | G9: =IFERROR(SUMIF(VENTAS!E4:E10000,C9,VENTAS!G4:G10000),0) -> 0 | H9: =F9-G9 -> 35 | I9: 10 | J9: =IF(G9=0,"Sin dato",IFERROR(SUMIF(VENTAS!E4:E10000,C9,VENTAS!H4:H10000)/G9,0)) -> Sin dato | K9: =IF(H9<=0,"🔴 Sin stock",IF(H9<=I9,"🟡 Stock bajo","✅ OK")) -> ✅ OK
A10: Retail Moderno | B10: Cencosud | C10: J007 | D10: Jumbo Puente Alto | E10: JI | F10: 35 | G10: =IFERROR(SUMIF(VENTAS!E4:E10000,C10,VENTAS!G4:G10000),0) -> 0 | H10: =F10-G10 -> 35 | I10: 10 | J10: =IF(G10=0,"Sin dato",IFERROR(SUMIF(VENTAS!E4:E10000,C10,VENTAS!H4:H10000)/G10,0)) -> Sin dato | K10: =IF(H10<=0,"🔴 Sin stock",IF(H10<=I10,"🟡 Stock bajo","✅ OK")) -> ✅ OK
A11: Retail Moderno | B11: Cencosud | C11: J008 | D11: Jumbo San Bernardo | E11: Ana | F11: 35 | G11: =IFERROR(SUMIF(VENTAS!E4:E10000,C11,VENTAS!G4:G10000),0) -> 0 | H11: =F11-G11 -> 35 | I11: 10 | J11: =IF(G11=0,"Sin dato",IFERROR(SUMIF(VENTAS!E4:E10000,C11,VENTAS!H4:H10000)/G11,0)) -> Sin dato | K11: =IF(H11<=0,"🔴 Sin stock",IF(H11<=I11,"🟡 Stock bajo","✅ OK")) -> ✅ OK
A12: Retail Moderno | B12: Cencosud | C12: J009 | D12: Jumbo Ñuñoa | E12: Ana | F12: 35 | G12: =IFERROR(SUMIF(VENTAS!E4:E10000,C12,VENTAS!G4:G10000),0) -> 0 | H12: =F12-G12 -> 35 | I12: 10 | J12: =IF(G12=0,"Sin dato",IFERROR(SUMIF(VENTAS!E4:E10000,C12,VENTAS!H4:H10000)/G12,0)) -> Sin dato | K12: =IF(H12<=0,"🔴 Sin stock",IF(H12<=I12,"🟡 Stock bajo","✅ OK")) -> ✅ OK
A13: Retail Moderno | B13: Cencosud | C13: J010 | D13: Jumbo Macul | E13: JI | F13: 30 | G13: =IFERROR(SUMIF(VENTAS!E4:E10000,C13,VENTAS!G4:G10000),0) -> 0 | H13: =F13-G13 -> 30 | I13: 9 | J13: =IF(G13=0,"Sin dato",IFERROR(SUMIF(VENTAS!E4:E10000,C13,VENTAS!H4:H10000)/G13,0)) -> Sin dato | K13: =IF(H13<=0,"🔴 Sin stock",IF(H13<=I13,"🟡 Stock bajo","✅ OK")) -> ✅ OK
A14: Retail Moderno | B14: Cencosud | C14: J011 | D14: Jumbo Independencia | E14: JI | F14: 30 | G14: =IFERROR(SUMIF(VENTAS!E4:E10000,C14,VENTAS!G4:G10000),0) -> 0 | H14: =F14-G14 -> 30 | I14: 9 | J14: =IF(G14=0,"Sin dato",IFERROR(SUMIF(VENTAS!E4:E10000,C14,VENTAS!H4:H10000)/G14,0)) -> Sin dato | K14: =IF(H14<=0,"🔴 Sin stock",IF(H14<=I14,"🟡 Stock bajo","✅ OK")) -> ✅ OK
A15: Retail Moderno | B15: Cencosud | C15: J012 | D15: Jumbo Las Rejas | E15: Ana | F15: 30 | G15: =IFERROR(SUMIF(VENTAS!E4:E10000,C15,VENTAS!G4:G10000),0) -> 0 | H15: =F15-G15 -> 30 | I15: 9 | J15: =IF(G15=0,"Sin dato",IFERROR(SUMIF(VENTAS!E4:E10000,C15,VENTAS!H4:H10000)/G15,0)) -> Sin dato | K15: =IF(H15<=0,"🔴 Sin stock",IF(H15<=I15,"🟡 Stock bajo","✅ OK")) -> ✅ OK
A16: Retail Moderno | B16: Cencosud | C16: J013 | D16: Jumbo Renca | E16: JI | F16: 30 | G16: =IFERROR(SUMIF(VENTAS!E4:E10000,C16,VENTAS!G4:G10000),0) -> 0 | H16: =F16-G16 -> 30 | I16: 9 | J16: =IF(G16=0,"Sin dato",IFERROR(SUMIF(VENTAS!E4:E10000,C16,VENTAS!H4:H10000)/G16,0)) -> Sin dato | K16: =IF(H16<=0,"🔴 Sin stock",IF(H16<=I16,"🟡 Stock bajo","✅ OK")) -> ✅ OK
A17: Retail Moderno | B17: Cencosud | C17: J014 | D17: Jumbo Peñalolén | E17: Ana | F17: 30 | G17: =IFERROR(SUMIF(VENTAS!E4:E10000,C17,VENTAS!G4:G10000),0) -> 0 | H17: =F17-G17 -> 30 | I17: 9 | J17: =IF(G17=0,"Sin dato",IFERROR(SUMIF(VENTAS!E4:E10000,C17,VENTAS!H4:H10000)/G17,0)) -> Sin dato | K17: =IF(H17<=0,"🔴 Sin stock",IF(H17<=I17,"🟡 Stock bajo","✅ OK")) -> ✅ OK
A18: Retail Moderno | B18: Cencosud | C18: J015 | D18: Jumbo Pudahuel | E18: JI | F18: 30 | G18: =IFERROR(SUMIF(VENTAS!E4:E10000,C18,VENTAS!G4:G10000),0) -> 0 | H18: =F18-G18 -> 30 | I18: 9 | J18: =IF(G18=0,"Sin dato",IFERROR(SUMIF(VENTAS!E4:E10000,C18,VENTAS!H4:H10000)/G18,0)) -> Sin dato | K18: =IF(H18<=0,"🔴 Sin stock",IF(H18<=I18,"🟡 Stock bajo","✅ OK")) -> ✅ OK
A19: Canal Especializado | B19: Dellanatura | C19: D001 | D19: Dellanatura Las Condes | E19: JI | F19: 40 | G19: =IFERROR(SUMIF(VENTAS!E4:E10000,C19,VENTAS!G4:G10000),0) -> 12 | H19: =F19-G19 -> 28 | I19: 12 | J19: =IF(G19=0,"Sin dato",IFERROR(SUMIF(VENTAS!E4:E10000,C19,VENTAS!H4:H10000)/G19,0)) -> 0.83333333 | K19: =IF(H19<=0,"🔴 Sin stock",IF(H19<=I19,"🟡 Stock bajo","✅ OK")) -> ✅ OK
A20: Canal Especializado | B20: Dellanatura | C20: D002 | D20: Dellanatura Providencia | E20: Ana | F20: 40 | G20: =IFERROR(SUMIF(VENTAS!E4:E10000,C20,VENTAS!G4:G10000),0) -> 8 | H20: =F20-G20 -> 32 | I20: 12 | J20: =IF(G20=0,"Sin dato",IFERROR(SUMIF(VENTAS!E4:E10000,C20,VENTAS!H4:H10000)/G20,0)) -> 0.75 | K20: =IF(H20<=0,"🔴 Sin stock",IF(H20<=I20,"🟡 Stock bajo","✅ OK")) -> ✅ OK
A21: Canal Especializado | B21: Central Orgánica | C21: CO01 | D21: Central Orgánica Ñuñoa | E21: Ana | F21: 30 | G21: =IFERROR(SUMIF(VENTAS!E4:E10000,C21,VENTAS!G4:G10000),0) -> 0 | H21: =F21-G21 -> 30 | I21: 9 | J21: =IF(G21=0,"Sin dato",IFERROR(SUMIF(VENTAS!E4:E10000,C21,VENTAS!H4:H10000)/G21,0)) -> Sin dato | K21: =IF(H21<=0,"🔴 Sin stock",IF(H21<=I21,"🟡 Stock bajo","✅ OK")) -> ✅ OK
A22: Canal Especializado | B22: All Nutrition | C22: AN01 | D22: All Nutrition Vitacura | E22: JI | F22: 40 | G22: =IFERROR(SUMIF(VENTAS!E4:E10000,C22,VENTAS!G4:G10000),0) -> 9 | H22: =F22-G22 -> 31 | I22: 12 | J22: =IF(G22=0,"Sin dato",IFERROR(SUMIF(VENTAS!E4:E10000,C22,VENTAS!H4:H10000)/G22,0)) -> 0 | K22: =IF(H22<=0,"🔴 Sin stock",IF(H22<=I22,"🟡 Stock bajo","✅ OK")) -> ✅ OK
A23: Canal Conveniencia | B23: Fork | C23: F001 | D23: Fork Apoquindo | E23: JI | F23: 30 | G23: =IFERROR(SUMIF(VENTAS!E4:E10000,C23,VENTAS!G4:G10000),0) -> 0 | H23: =F23-G23 -> 30 | I23: 9 | J23: =IF(G23=0,"Sin dato",IFERROR(SUMIF(VENTAS!E4:E10000,C23,VENTAS!H4:H10000)/G23,0)) -> Sin dato | K23: =IF(H23<=0,"🔴 Sin stock",IF(H23<=I23,"🟡 Stock bajo","✅ OK")) -> ✅ OK
A24: Canal Conveniencia | B24: Fork | C24: F002 | D24: Fork El Bosque | E24: Ana | F24: 30 | G24: =IFERROR(SUMIF(VENTAS!E4:E10000,C24,VENTAS!G4:G10000),0) -> 0 | H24: =F24-G24 -> 30 | I24: 9 | J24: =IF(G24=0,"Sin dato",IFERROR(SUMIF(VENTAS!E4:E10000,C24,VENTAS!H4:H10000)/G24,0)) -> Sin dato | K24: =IF(H24<=0,"🔴 Sin stock",IF(H24<=I24,"🟡 Stock bajo","✅ OK")) -> ✅ OK
A25: Canal Turístico | B25: Pirque CDV | C25: P001 | D25: Pirque Centro del Vino | E25: JI | F25: 20 | G25: =IFERROR(SUMIF(VENTAS!E4:E10000,C25,VENTAS!G4:G10000),0) -> 5 | H25: =F25-G25 -> 15 | I25: 6 | J25: =IF(G25=0,"Sin dato",IFERROR(SUMIF(VENTAS!E4:E10000,C25,VENTAS!H4:H10000)/G25,0)) -> 0.8 | K25: =IF(H25<=0,"🔴 Sin stock",IF(H25<=I25,"🟡 Stock bajo","✅ OK")) -> ✅ OK
A26: HoReCa | B26: Ritz-Carlton | C26: H001 | D26: Ritz-Carlton Santiago | E26: JI | F26: 30 | G26: =IFERROR(SUMIF(VENTAS!E4:E10000,C26,VENTAS!G4:G10000),0) -> 8 | H26: =F26-G26 -> 22 | I26: 9 | J26: =IF(G26=0,"Sin dato",IFERROR(SUMIF(VENTAS!E4:E10000,C26,VENTAS!H4:H10000)/G26,0)) -> 1 | K26: =IF(H26<=0,"🔴 Sin stock",IF(H26<=I26,"🟡 Stock bajo","✅ OK")) -> ✅ OK
A28: ➕ Agregar PDV: insertar fila en la tabla. Copiar fórmulas G,H,J,K. Stock Inicial y Mínimo: editar en azul. Reposición: sumar al Stock Inicial (no reemplazar si aún queda stock).

Sheet GRÁFICO
A1: 📊 AVANCE vs META — Por Canal | Actualizado automáticamente
A2: 💡 Este gráfico se actualiza solo cuando registras ventas en VENTAS. El dato de Meta es la suma de metas anuales de cada PDV del segmento.
A4: Segmento | B4: Meta Anual (uds) | C4: Vendido (uds) | D4: % Cumplimiento | E4: Estado
A5: Retail Moderno | B5: =IFERROR(SUMPRODUCT((PANEL!A8:A30=A5)*(PANEL!H8:S30)),0) -> 378 | C5: =IFERROR(SUMIF(VENTAS!C4:C10000,A5,VENTAS!G4:G10000),0) -> 50 | D5: =IFERROR(C5/B5,0) -> 0.13227513 | E5: =IF(B5=0,"Sin meta",IF(D5>=1,"✅ Logrado",IF(D5>=0.6,"🟡 En curso","🔴 Bajo"))) -> 🔴 Bajo
A6: Canal Especializado | B6: =IFERROR(SUMPRODUCT((PANEL!A8:A30=A6)*(PANEL!H8:S30)),0) -> 214 | C6: =IFERROR(SUMIF(VENTAS!C4:C10000,A6,VENTAS!G4:G10000),0) -> 29 | D6: =IFERROR(C6/B6,0) -> 0.13551402 | E6: =IF(B6=0,"Sin meta",IF(D6>=1,"✅ Logrado",IF(D6>=0.6,"🟡 En curso","🔴 Bajo"))) -> 🔴 Bajo
A7: Canal Conveniencia | B7: =IFERROR(SUMPRODUCT((PANEL!A8:A30=A7)*(PANEL!H8:S30)),0) -> 150 | C7: =IFERROR(SUMIF(VENTAS!C4:C10000,A7,VENTAS!G4:G10000),0) -> 0 | D7: =IFERROR(C7/B7,0) -> 0 | E7: =IF(B7=0,"Sin meta",IF(D7>=1,"✅ Logrado",IF(D7>=0.6,"🟡 En curso","🔴 Bajo"))) -> 🔴 Bajo
A8: Canal Turístico | B8: =IFERROR(SUMPRODUCT((PANEL!A8:A30=A8)*(PANEL!H8:S30)),0) -> 23 | C8: =IFERROR(SUMIF(VENTAS!C4:C10000,A8,VENTAS!G4:G10000),0) -> 5 | D8: =IFERROR(C8/B8,0) -> 0.2173913 | E8: =IF(B8=0,"Sin meta",IF(D8>=1,"✅ Logrado",IF(D8>=0.6,"🟡 En curso","🔴 Bajo"))) -> 🔴 Bajo
A9: HoReCa | B9: =IFERROR(SUMPRODUCT((PANEL!A8:A30=A9)*(PANEL!H8:S30)),0) -> 30 | C9: =IFERROR(SUMIF(VENTAS!C4:C10000,A9,VENTAS!G4:G10000),0) -> 8 | D9: =IFERROR(C9/B9,0) -> 0.26666667 | E9: =IF(B9=0,"Sin meta",IF(D9>=1,"✅ Logrado",IF(D9>=0.6,"🟡 En curso","🔴 Bajo"))) -> 🔴 Bajo
H13: me gusto el resumen pero el grafico podria verse por cliente tambien y despues tambien poder evaluar la tendencia que hace el sabor para futuros forecast
H14: otra pregunta para hacer es como vamos a seguir si llegamos al 2027 para no perder lectura, solo dime si se podra.

Sheet POP
A1: 🎯 MATERIAL POP Y ACTIVACIONES 2026 | Filtrable por Canal / Cliente
A2: 💡 Registrar todo el material asignado y su estado de instalación. El costo total se jalará al DASHBOARD automáticamente.
A4: ▸ Tipos de Material (editar costos en col D)
A5: Código | B5: Tipo | C5: Descripción | D5: Costo Ref ($) | E5: Duración
A6: POP-EXH | B6: Exhibidor piso | C6: Estructura display 60×40cm | D6: 85000 | E6: Permanente
A7: POP-STO | B7: Stopper góndola | C7: Señalética lateral | D7: 8500 | E7: 6 meses
A8: POP-CEN | B8: Cenefa | C8: Franja frontal góndola | D8: 4500 | E8: 3 meses
A9: POP-CAR | B9: Cartel precio | C9: Tarjeta precio destacado | D9: 1200 | E9: 3 meses
A10: POP-PRO | B10: Promotora (día) | C10: Activación promotora | D10: 35000 | E10: 1 día
A11: POP-DEG | B11: Degustación | C11: Kit muestras + insumos | D11: 25000 | E11: 1 día
A12: POP-SEÑ | B12: Señalética vitrina | C12: Vinilo adhesivo | D12: 12000 | E12: 12 meses
A14: ▸ Registro de Activaciones | Agregar fila dentro de la tabla
A15: Canal | B15: Cadena | C15: Cliente | D15: ID_PDV | E15: Nombre_PDV | F15: Resp | G15: Tipo_Mat | H15: Descripción | I15: Fecha_Prog | J15: Fecha_Ejec | K15: Cant_Asig | L15: Cant_Inst | M15: Pct_Inst | N15: Costo_Unit ($) | O15: Costo_Total ($) | P15: Estado | Q15: Resultado
A16: Canal Especializado | B16: Dellanatura | C16: Dellanatura | D16: D001 | E16: Dellanatura Las Condes | F16: JI | G16: POP-STO | H16: Stopper góndola | I16: 05/01/2026 | K16: 2 | L16: 0 | M16: =IFERROR(L16/K16,0) -> 0 | N16: 8500 | O16: =K16*N16 -> 17000 | P16: Pendiente
A17: Canal Especializado | B17: Dellanatura | C17: Dellanatura | D17: D001 | E17: Dellanatura Las Condes | F17: JI | G17: POP-DEG | H17: Degustación apertura | I17: 12/01/2026 | K17: 1 | L17: 0 | M17: =IFERROR(L17/K17,0) -> 0 | N17: 25000 | O17: =K17*N17 -> 25000 | P17: Pendiente
A18: Canal Especializado | B18: All Nutrition | C18: All Nutrition | D18: AN01 | E18: All Nutrition Vitacura | F18: JI | G18: POP-CEN | H18: Cenefa lineal nutrición | I18: 07/01/2026 | K18: 2 | L18: 0 | M18: =IFERROR(L18/K18,0) -> 0 | N18: 4500 | O18: =K18*N18 -> 9000 | P18: Pendiente
A19: Canal Conveniencia | B19: Fork | C19: Fork | D19: F001 | E19: Fork Apoquindo | F19: JI | G19: POP-CAR | H19: Cartel precio x3 | I19: 01/06/2026 | K19: 3 | L19: 0 | M19: =IFERROR(L19/K19,0) -> 0 | N19: 1200 | O19: =K19*N19 -> 3600 | P19: Programado
A20: Canal Especializado | B20: Pirque CDV | C20: Pirque CDV | D20: P001 | E20: Pirque Centro del Vino | F20: JI | G20: POP-SEÑ | H20: Señalética vitrina | I20: 09/01/2026 | K20: 1 | L20: 0 | M20: =IFERROR(L20/K20,0) -> 0 | N20: 12000 | O20: =K20*N20 -> 12000 | P20: Pendiente
A21: HoReCa | B21: Ritz-Carlton | C21: Ritz-Carlton | D21: H001 | E21: Ritz-Carlton Santiago | F21: JI | G21: POP-DEG | H21: Presentación F&B Manager | I21: 15/10/2026 | K21: 1 | L21: 0 | M21: =IFERROR(L21/K21,0) -> 0 | N21: 25000 | O21: =K21*N21 -> 25000 | P21: Programado
A22: Retail Moderno | B22: Cencosud | C22: Jumbo | D22: J001 | E22: Jumbo Parque Arauco | F22: JI | G22: POP-EXH | H22: Exhibidor piso | I22: 01/10/2026 | K22: 1 | L22: 0 | M22: =IFERROR(L22/K22,0) -> 0 | N22: 85000 | O22: =K22*N22 -> 85000 | P22: Programado
A23: Retail Moderno | B23: Cencosud | C23: Jumbo | D23: J001 | E23: Jumbo Parque Arauco | F23: JI | G23: POP-PRO | H23: Promotora lanzamiento | I23: 04/10/2026 | K23: 2 | L23: 0 | M23: =IFERROR(L23/K23,0) -> 0 | N23: 35000 | O23: =K23*N23 -> 70000 | P23: Programado
A25: INVERSIÓN TOTAL POP (SUBTOTAL — se ajusta al filtrar) | O25: =SUBTOTAL(9,O16:O24) -> 246600

Sheet DASHBOARD
A1: 📊 DASHBOARD EJECUTIVO 2026 | CxC Aging · Stock Agotamiento · Rentabilidad
A2: Solo lectura — se alimenta automáticamente desde VENTAS, INVENTARIO y POP.
A4: Ventas Neto ($) | E4: Margen Aprox. ($) | I4: CxC Total Emitida ($) | M4: CxC Vencida ($) | Q4: Alertas Stock 🔴
A5: =IFERROR(SUM(VENTAS!K4:K10000),0) -> 0 | E5: =IFERROR(SUM(VENTAS!M4:M10000),0) -> 0 | I5: =IFERROR(SUMIF(VENTAS!N4:N10000,"Emitida",VENTAS!K4:K10000),0) -> 0 | M5: =IFERROR(SUMIFS(VENTAS!K4:K10000,VENTAS!N4:N10000,"Vencida"),0) -> 0 | Q5: =IFERROR(COUNTIF(INVENTARIO!K4:K100,"🔴 Sin stock"),0) -> 1
A8: ▸ CxC Aging — Antigüedad de Cartera Emitida | Clave para Jumbo (30 días)
A9: ⚠️ Jumbo paga 30 días desde despacho. Tramo 31-60 días = cobro en riesgo. >60 días = gestionar urgente con buyer Cencosud.
A10: Tramo | B10: Criterio | C10: Monto CxC ($) | D10: N° Movimientos | E10: % del Total | F10: Acción Recomendada
A11: 0–15 días | B11: Recién emitida | C11: =IFERROR(SUMIFS(VENTAS!K4:K10000,VENTAS!N4:N10000,"Emitida",VENTAS!S4:S10000,">="&TODAY()-15),0) -> 0 | D11: =IFERROR(COUNTIFS(VENTAS!N4:N10000,"Emitida",VENTAS!S4:S10000,">="&TODAY()-15),0) -> 0 | E11: =IFERROR(C11/SUM(C11:C14),0) -> 0 | F11: Monitorear
A12: 16–30 días | B12: Próxima a vencer | C12: =IFERROR(SUMIFS(VENTAS!K4:K10000,VENTAS!N4:N10000,"Emitida",VENTAS!S4:S10000,">="&TODAY()-30,VENTAS!S4:S10000,"<"&TODAY()-15),0) -> 0 | D12: =IFERROR(COUNTIFS(VENTAS!N4:N10000,"Emitida",VENTAS!S4:S10000,">="&TODAY()-30,VENTAS!S4:S10000,"<"&TODAY()-15),0) -> 0 | E12: =IFERROR(C12/SUM(C11:C14),0) -> 0 | F12: Confirmar recepción buyer
A13: 31–60 días | B13: Vencida — gestionar | C13: =IFERROR(SUMIFS(VENTAS!K4:K10000,VENTAS!N4:N10000,"Emitida",VENTAS!S4:S10000,">="&TODAY()-60,VENTAS!S4:S10000,"<"&TODAY()-30),0) -> 0 | D13: =IFERROR(COUNTIFS(VENTAS!N4:N10000,"Emitida",VENTAS!S4:S10000,">="&TODAY()-60,VENTAS!S4:S10000,"<"&TODAY()-30),0) -> 0 | E13: =IFERROR(C13/SUM(C11:C14),0) -> 0 | F13: 🟡 Contactar buyer
A14: +60 días | B14: Crítica | C14: =IFERROR(SUMIFS(VENTAS!K4:K10000,VENTAS!N4:N10000,"Emitida",VENTAS!S4:S10000,"<"&TODAY()-60),0) -> 0 | D14: =IFERROR(COUNTIFS(VENTAS!N4:N10000,"Emitida",VENTAS!S4:S10000,"<"&TODAY()-60),0) -> 0 | E14: =IFERROR(C14/SUM(C11:C14),0) -> 0 | F14: 🔴 Escalar KAM urgente
A15: TOTAL CxC EMITIDA | C15: =IFERROR(SUMIF(VENTAS!N4:N10000,"Emitida",VENTAS!K4:K10000),0) -> 0
A18: ▸ Proyección Agotamiento de Stock | Semanas disponibles por PDV
A19: 💡 Semanas disponibles = Stock Disp. ÷ Velocidad de venta (uds/semana). <2 semanas = reponer urgente esta semana.
A20: Canal | B20: Cliente | C20: ID_PDV | D20: PDV | E20: Stock Disp. | F20: Vendido Acum. | G20: Vel. Venta (uds/sem) | H20: Semanas Restantes | I20: Fecha Agotamiento | J20: Alerta | L20: velocidad venta deberia ser uds/sem i uds/mes?
A21: Retail Moderno | B21: Jumbo | C21: J001 | D21: Jumbo Parque Arauco | E21: =IFERROR(VLOOKUP(C21,INVENTARIO!C4:H100,6,0),0) -> 0 | F21: =IFERROR(SUMIFS(VENTAS!H4:H10000,VENTAS!E4:E10000,C21,VENTAS!J4:J10000,"Venta"),0) -> 0 | G21: =IF(F21=0,0,IFERROR(F21/MAX(1,ROUND((TODAY()-DATE(2026,1,1))/7,1)),0)) -> 0 | H21: =IF(G21=0,"Sin venta",IFERROR(ROUND(E21/G21,1),0)) -> Sin venta | I21: =IF(G21=0,"—",IFERROR(TODAY()+H21*7,"—")) -> — | J21: =IF(G21=0,"📊 Sin datos",IF(E21<=0,"🔴 Agotado",IF(ISNUMBER(H21)*H21<=2,"🔴 <2 sem",IF(ISNUMBER(H21)*H21<=4,"🟡 2-4 sem","✅ +4 sem")))) -> 📊 Sin datos
A22: Retail Moderno | B22: Jumbo | C22: J002 | D22: Jumbo Costanera Center | E22: =IFERROR(VLOOKUP(C22,INVENTARIO!C4:H100,6,0),0) -> 50 | F22: =IFERROR(SUMIFS(VENTAS!H4:H10000,VENTAS!E4:E10000,C22,VENTAS!J4:J10000,"Venta"),0) -> 0 | G22: =IF(F22=0,0,IFERROR(F22/MAX(1,ROUND((TODAY()-DATE(2026,1,1))/7,1)),0)) -> 0 | H22: =IF(G22=0,"Sin venta",IFERROR(ROUND(E22/G22,1),0)) -> Sin venta | I22: =IF(G22=0,"—",IFERROR(TODAY()+H22*7,"—")) -> — | J22: =IF(G22=0,"📊 Sin datos",IF(E22<=0,"🔴 Agotado",IF(ISNUMBER(H22)*H22<=2,"🔴 <2 sem",IF(ISNUMBER(H22)*H22<=4,"🟡 2-4 sem","✅ +4 sem")))) -> 📊 Sin datos
A23: Retail Moderno | B23: Jumbo | C23: J003 | D23: Jumbo Mall Vespucio | E23: =IFERROR(VLOOKUP(C23,INVENTARIO!C4:H100,6,0),0) -> 40 | F23: =IFERROR(SUMIFS(VENTAS!H4:H10000,VENTAS!E4:E10000,C23,VENTAS!J4:J10000,"Venta"),0) -> 0 | G23: =IF(F23=0,0,IFERROR(F23/MAX(1,ROUND((TODAY()-DATE(2026,1,1))/7,1)),0)) -> 0 | H23: =IF(G23=0,"Sin venta",IFERROR(ROUND(E23/G23,1),0)) -> Sin venta | I23: =IF(G23=0,"—",IFERROR(TODAY()+H23*7,"—")) -> — | J23: =IF(G23=0,"📊 Sin datos",IF(E23<=0,"🔴 Agotado",IF(ISNUMBER(H23)*H23<=2,"🔴 <2 sem",IF(ISNUMBER(H23)*H23<=4,"🟡 2-4 sem","✅ +4 sem")))) -> 📊 Sin datos
A24: Retail Moderno | B24: Jumbo | C24: J004 | D24: Jumbo Maipú | E24: =IFERROR(VLOOKUP(C24,INVENTARIO!C4:H100,6,0),0) -> 40 | F24: =IFERROR(SUMIFS(VENTAS!H4:H10000,VENTAS!E4:E10000,C24,VENTAS!J4:J10000,"Venta"),0) -> 0 | G24: =IF(F24=0,0,IFERROR(F24/MAX(1,ROUND((TODAY()-DATE(2026,1,1))/7,1)),0)) -> 0 | H24: =IF(G24=0,"Sin venta",IFERROR(ROUND(E24/G24,1),0)) -> Sin venta | I24: =IF(G24=0,"—",IFERROR(TODAY()+H24*7,"—")) -> — | J24: =IF(G24=0,"📊 Sin datos",IF(E24<=0,"🔴 Agotado",IF(ISNUMBER(H24)*H24<=2,"🔴 <2 sem",IF(ISNUMBER(H24)*H24<=4,"🟡 2-4 sem","✅ +4 sem")))) -> 📊 Sin datos | N24: deberia ir ingresando en otra parte las condiciones de entrada para cada cliente?
A25: Retail Moderno | B25: Jumbo | C25: J005 | D25: Jumbo La Florida | E25: =IFERROR(VLOOKUP(C25,INVENTARIO!C4:H100,6,0),0) -> 35 | F25: =IFERROR(SUMIFS(VENTAS!H4:H10000,VENTAS!E4:E10000,C25,VENTAS!J4:J10000,"Venta"),0) -> 0 | G25: =IF(F25=0,0,IFERROR(F25/MAX(1,ROUND((TODAY()-DATE(2026,1,1))/7,1)),0)) -> 0 | H25: =IF(G25=0,"Sin venta",IFERROR(ROUND(E25/G25,1),0)) -> Sin venta | I25: =IF(G25=0,"—",IFERROR(TODAY()+H25*7,"—")) -> — | J25: =IF(G25=0,"📊 Sin datos",IF(E25<=0,"🔴 Agotado",IF(ISNUMBER(H25)*H25<=2,"🔴 <2 sem",IF(ISNUMBER(H25)*H25<=4,"🟡 2-4 sem","✅ +4 sem")))) -> 📊 Sin datos
A26: Canal Especializado | B26: Dellanatura | C26: D001 | D26: Dellanatura Las Condes | E26: =IFERROR(VLOOKUP(C26,INVENTARIO!C4:H100,6,0),0) -> 28 | F26: =IFERROR(SUMIFS(VENTAS!H4:H10000,VENTAS!E4:E10000,C26,VENTAS!J4:J10000,"Venta"),0) -> 0 | G26: =IF(F26=0,0,IFERROR(F26/MAX(1,ROUND((TODAY()-DATE(2026,1,1))/7,1)),0)) -> 0 | H26: =IF(G26=0,"Sin venta",IFERROR(ROUND(E26/G26,1),0)) -> Sin venta | I26: =IF(G26=0,"—",IFERROR(TODAY()+H26*7,"—")) -> — | J26: =IF(G26=0,"📊 Sin datos",IF(E26<=0,"🔴 Agotado",IF(ISNUMBER(H26)*H26<=2,"🔴 <2 sem",IF(ISNUMBER(H26)*H26<=4,"🟡 2-4 sem","✅ +4 sem")))) -> 📊 Sin datos
A27: Canal Especializado | B27: Dellanatura | C27: D002 | D27: Dellanatura Providencia | E27: =IFERROR(VLOOKUP(C27,INVENTARIO!C4:H100,6,0),0) -> 32 | F27: =IFERROR(SUMIFS(VENTAS!H4:H10000,VENTAS!E4:E10000,C27,VENTAS!J4:J10000,"Venta"),0) -> 0 | G27: =IF(F27=0,0,IFERROR(F27/MAX(1,ROUND((TODAY()-DATE(2026,1,1))/7,1)),0)) -> 0 | H27: =IF(G27=0,"Sin venta",IFERROR(ROUND(E27/G27,1),0)) -> Sin venta | I27: =IF(G27=0,"—",IFERROR(TODAY()+H27*7,"—")) -> — | J27: =IF(G27=0,"📊 Sin datos",IF(E27<=0,"🔴 Agotado",IF(ISNUMBER(H27)*H27<=2,"🔴 <2 sem",IF(ISNUMBER(H27)*H27<=4,"🟡 2-4 sem","✅ +4 sem")))) -> 📊 Sin datos
A28: Canal Especializado | B28: Central Orgánica | C28: CO01 | D28: Central Orgánica Ñuñoa | E28: =IFERROR(VLOOKUP(C28,INVENTARIO!C4:H100,6,0),0) -> 30 | F28: =IFERROR(SUMIFS(VENTAS!H4:H10000,VENTAS!E4:E10000,C28,VENTAS!J4:J10000,"Venta"),0) -> 0 | G28: =IF(F28=0,0,IFERROR(F28/MAX(1,ROUND((TODAY()-DATE(2026,1,1))/7,1)),0)) -> 0 | H28: =IF(G28=0,"Sin venta",IFERROR(ROUND(E28/G28,1),0)) -> Sin venta | I28: =IF(G28=0,"—",IFERROR(TODAY()+H28*7,"—")) -> — | J28: =IF(G28=0,"📊 Sin datos",IF(E28<=0,"🔴 Agotado",IF(ISNUMBER(H28)*H28<=2,"🔴 <2 sem",IF(ISNUMBER(H28)*H28<=4,"🟡 2-4 sem","✅ +4 sem")))) -> 📊 Sin datos
A29: Canal Especializado | B29: All Nutrition | C29: AN01 | D29: All Nutrition Vitacura | E29: =IFERROR(VLOOKUP(C29,INVENTARIO!C4:H100,6,0),0) -> 31 | F29: =IFERROR(SUMIFS(VENTAS!H4:H10000,VENTAS!E4:E10000,C29,VENTAS!J4:J10000,"Venta"),0) -> 0 | G29: =IF(F29=0,0,IFERROR(F29/MAX(1,ROUND((TODAY()-DATE(2026,1,1))/7,1)),0)) -> 0 | H29: =IF(G29=0,"Sin venta",IFERROR(ROUND(E29/G29,1),0)) -> Sin venta | I29: =IF(G29=0,"—",IFERROR(TODAY()+H29*7,"—")) -> — | J29: =IF(G29=0,"📊 Sin datos",IF(E29<=0,"🔴 Agotado",IF(ISNUMBER(H29)*H29<=2,"🔴 <2 sem",IF(ISNUMBER(H29)*H29<=4,"🟡 2-4 sem","✅ +4 sem")))) -> 📊 Sin datos
A30: Canal Especializado | B30: Pirque CDV | C30: P001 | D30: Pirque Centro del Vino | E30: =IFERROR(VLOOKUP(C30,INVENTARIO!C4:H100,6,0),0) -> 15 | F30: =IFERROR(SUMIFS(VENTAS!H4:H10000,VENTAS!E4:E10000,C30,VENTAS!J4:J10000,"Venta"),0) -> 0 | G30: =IF(F30=0,0,IFERROR(F30/MAX(1,ROUND((TODAY()-DATE(2026,1,1))/7,1)),0)) -> 0 | H30: =IF(G30=0,"Sin venta",IFERROR(ROUND(E30/G30,1),0)) -> Sin venta | I30: =IF(G30=0,"—",IFERROR(TODAY()+H30*7,"—")) -> — | J30: =IF(G30=0,"📊 Sin datos",IF(E30<=0,"🔴 Agotado",IF(ISNUMBER(H30)*H30<=2,"🔴 <2 sem",IF(ISNUMBER(H30)*H30<=4,"🟡 2-4 sem","✅ +4 sem")))) -> 📊 Sin datos
A31: Canal Conveniencia | B31: Fork | C31: F001 | D31: Fork Apoquindo | E31: =IFERROR(VLOOKUP(C31,INVENTARIO!C4:H100,6,0),0) -> 30 | F31: =IFERROR(SUMIFS(VENTAS!H4:H10000,VENTAS!E4:E10000,C31,VENTAS!J4:J10000,"Venta"),0) -> 0 | G31: =IF(F31=0,0,IFERROR(F31/MAX(1,ROUND((TODAY()-DATE(2026,1,1))/7,1)),0)) -> 0 | H31: =IF(G31=0,"Sin venta",IFERROR(ROUND(E31/G31,1),0)) -> Sin venta | I31: =IF(G31=0,"—",IFERROR(TODAY()+H31*7,"—")) -> — | J31: =IF(G31=0,"📊 Sin datos",IF(E31<=0,"🔴 Agotado",IF(ISNUMBER(H31)*H31<=2,"🔴 <2 sem",IF(ISNUMBER(H31)*H31<=4,"🟡 2-4 sem","✅ +4 sem")))) -> 📊 Sin datos
A32: Canal Conveniencia | B32: Fork | C32: F002 | D32: Fork El Bosque | E32: =IFERROR(VLOOKUP(C32,INVENTARIO!C4:H100,6,0),0) -> 30 | F32: =IFERROR(SUMIFS(VENTAS!H4:H10000,VENTAS!E4:E10000,C32,VENTAS!J4:J10000,"Venta"),0) -> 0 | G32: =IF(F32=0,0,IFERROR(F32/MAX(1,ROUND((TODAY()-DATE(2026,1,1))/7,1)),0)) -> 0 | H32: =IF(G32=0,"Sin venta",IFERROR(ROUND(E32/G32,1),0)) -> Sin venta | I32: =IF(G32=0,"—",IFERROR(TODAY()+H32*7,"—")) -> — | J32: =IF(G32=0,"📊 Sin datos",IF(E32<=0,"🔴 Agotado",IF(ISNUMBER(H32)*H32<=2,"🔴 <2 sem",IF(ISNUMBER(H32)*H32<=4,"🟡 2-4 sem","✅ +4 sem")))) -> 📊 Sin datos
A33: HoReCa | B33: Ritz-Carlton | C33: H001 | D33: Ritz-Carlton Santiago | E33: =IFERROR(VLOOKUP(C33,INVENTARIO!C4:H100,6,0),0) -> 22 | F33: =IFERROR(SUMIFS(VENTAS!H4:H10000,VENTAS!E4:E10000,C33,VENTAS!J4:J10000,"Venta"),0) -> 0 | G33: =IF(F33=0,0,IFERROR(F33/MAX(1,ROUND((TODAY()-DATE(2026,1,1))/7,1)),0)) -> 0 | H33: =IF(G33=0,"Sin venta",IFERROR(ROUND(E33/G33,1),0)) -> Sin venta | I33: =IF(G33=0,"—",IFERROR(TODAY()+H33*7,"—")) -> — | J33: =IF(G33=0,"📊 Sin datos",IF(E33<=0,"🔴 Agotado",IF(ISNUMBER(H33)*H33<=2,"🔴 <2 sem",IF(ISNUMBER(H33)*H33<=4,"🟡 2-4 sem","✅ +4 sem")))) -> 📊 Sin datos
A37: ▸ Rentabilidad Neta por Canal | Margen ajustado por CxC pendiente
A38: Canal | B38: Ventas ($) | C38: Margen Bruto ($) | D38: % Margen | E38: CxC Pend. ($) | F38: Margen Ajust. ($) | G38: Plazo Pago | H38: Nota
A39: Retail Moderno | B39: =IFERROR(SUMIFS(VENTAS!K4:K10000,VENTAS!C4:C10000,A39,VENTAS!J4:J10000,"Venta"),0) -> 0 | C39: =IFERROR(SUMIFS(VENTAS!M4:M10000,VENTAS!C4:C10000,A39,VENTAS!J4:J10000,"Venta"),0) -> 0 | D39: =IFERROR(C39/B39,0) -> 0 | E39: =IFERROR(SUMIFS(VENTAS!K4:K10000,VENTAS!C4:C10000,A39,VENTAS!N4:N10000,"Emitida"),0) -> 0 | F39: =C39-E39 -> 0 | G39: 30 días | H39: Mayor volumen, cobro diferido. Margen real < aparente.
A40: Canal Especializado | B40: =IFERROR(SUMIFS(VENTAS!K4:K10000,VENTAS!C4:C10000,A40,VENTAS!J4:J10000,"Venta"),0) -> 0 | C40: =IFERROR(SUMIFS(VENTAS!M4:M10000,VENTAS!C4:C10000,A40,VENTAS!J4:J10000,"Venta"),0) -> 0 | D40: =IFERROR(C40/B40,0) -> 0 | E40: =IFERROR(SUMIFS(VENTAS!K4:K10000,VENTAS!C4:C10000,A40,VENTAS!N4:N10000,"Emitida"),0) -> 0 | F40: =C40-E40 -> 0 | G40: Contado | H40: Cobro inmediato. Mejor flujo de caja.
A41: Canal Conveniencia | B41: =IFERROR(SUMIFS(VENTAS!K4:K10000,VENTAS!C4:C10000,A41,VENTAS!J4:J10000,"Venta"),0) -> 0 | C41: =IFERROR(SUMIFS(VENTAS!M4:M10000,VENTAS!C4:C10000,A41,VENTAS!J4:J10000,"Venta"),0) -> 0 | D41: =IFERROR(C41/B41,0) -> 0 | E41: =IFERROR(SUMIFS(VENTAS!K4:K10000,VENTAS!C4:C10000,A41,VENTAS!N4:N10000,"Emitida"),0) -> 0 | F41: =C41-E41 -> 0 | G41: Contado | H41: Ticket bajo, alta rotación. Evaluar margen neto.
A42: HoReCa | B42: =IFERROR(SUMIFS(VENTAS!K4:K10000,VENTAS!C4:C10000,A42,VENTAS!J4:J10000,"Venta"),0) -> 0 | C42: =IFERROR(SUMIFS(VENTAS!M4:M10000,VENTAS!C4:C10000,A42,VENTAS!J4:J10000,"Venta"),0) -> 0 | D42: =IFERROR(C42/B42,0) -> 0 | E42: =IFERROR(SUMIFS(VENTAS!K4:K10000,VENTAS!C4:C10000,A42,VENTAS!N4:N10000,"Emitida"),0) -> 0 | F42: =C42-E42 -> 0 | G42: Contado | H42: Mejor canal por caja real. Sin CxC. Priorizar desarrollo.
A44: 💡 Margen Ajust. = Margen Bruto − CxC pendiente = caja real disponible hoy. HoReCa contado = mejor flujo aunque menor volumen. Jumbo: margen aparente > margen real de caja.
